Workbook
Name aa: #REF!
Name aa: #REF!
Name aa: #REF!
Name aa: #REF!
Name aa: #REF!
Name aa: #REF!
Name aa: #REF!
Name aa: #REF!
Name aa: #REF!
Name Civil4: #REF!
Name Civil4: #REF!
Name Civil4: #REF!
Name Civil4: #REF!
Name Civil4: #REF!
Name Civil4: #REF!
Name Civil4: #REF!
Name Civil4: #REF!
Name Civil4: #REF!
Name d: #REF!
Name d: #REF!
Name d: #REF!
Name d: #REF!
Name d: #REF!
Name d: #REF!
Name d: #REF!
Name d: #REF!
Name d: #REF!
Name date: #REF!
Name date: #REF!
Name date: #REF!
Name date: #REF!
Name date: #REF!
Name date: #REF!
Name date: #REF!
Name date: #REF!
Name date: #REF!
Name daz: #REF!
Name daz: #REF!
Name daz: #REF!
Name daz: #REF!
Name daz: #REF!
Name daz: #REF!
Name daz: #REF!
Name daz: #REF!
Name ddd: #REF!
Name ddd: #REF!
Name ddd: #REF!
Name ddd: #REF!
Name ddd: #REF!
Name ddd: #REF!
Name ddd: #REF!
Name ddd: #REF!
Name for: #REF!
Name for: #REF!
Name for: #REF!
Name for: #REF!
Name for: #REF!
Name for: #REF!
Name for: #REF!
Name for: #REF!

Sheet TCS $ Sched
B6: SUMMARY | V6: BIG TICKET ITEMS
B8: JOB DESCRIPTION: | I8: ROK Sports Precinct | N8: DATE: | O8: 26/07/2026 | V8: Club house (NBC )
B9: SITE ADDRESS: | I9: 554-700 Yaamba Rd, Norman Gardens QLD 4701 | N9: TPS-TEN16699-V2
R10: Cost | S10: (Cost + O/H) + Profit | V10: 1500 Liters Git Viking Panel TIm in Ground ( grease trap ) | Y10: Hot Water Pump set to suit Rheem Hot Water Unit | AB10: Rheem HWU
N11: TOTALS | V11: Purchase Cost Total | W11: =6110+2413.28 -> 8523.28 | Y11: Purchase Cost Total | Z11: 6775.83 | AB11: Purchase Cost Total | AC11: 3438.29
AB12: Safe Tray | AC12: 52.8
V13: TPS Markup | W13: 1.15 | Y13: TPS Markup | Z13: 1.15 | AB13: TPS Markup | AC13: 1.15
V14: Qty | W14: 1 | Y14: Qty | Z14: 1 | AB14: Qty | AC14: 2
I15: N16 rewired = S16+W17+Z17+AC17 - NBC Rheem HWU block was orphaned (never reached summary) | V15: Freight | W15: 250 | Y15: Freight | Z15: 150 | AB15: Freight | AC15: 300
I16: CLUBHOUSE | N16: =S16+W17+Z17+AC17 -> 692573.54 | R16: ='ClubHouse (NBC )'!F943 -> 470848.1 | S16: =((R16/$R$39)*($R$49-$R$39))+R16 -> 666250.06 | V16: Installation_MH | W16: 0 | X16: RULE 4: token $250 set to $0 26/07/26 - installation labour is priced in Phase 7 activity T1-08: NBC trade waste 110 HDPE + Geberit 50 + 1500L Viking GIT install (8 crew-days, Crew 1; rate basis explicitly includes 'GIT excavation/set'; plant 3-5T exc 4d + crane truck 1d). Commissioning in T5-02. Retaining the token would DOUBLE-COUNT. Supply, freight, safe tray and mounting are priced separately - see EQUIPMENT_TEST_TPS.md. | Y16: Installation_MH | Z16: 0 | AA16: RULE 4: token $200 set to $0 26/07/26 - installation labour is priced in Phase 7 activity T4-03: 2x Rheem 315L HWU + HW circulating pump + flow/return loop (3 crew-days, Crew 4). Commissioning in T5-06. Retaining the token would DOUBLE-COUNT. Supply, freight, safe tray and mounting are priced separately - see EQUIPMENT_TEST_TPS.md. | AB16: Installation_MH | AC16: 0 | AD16: RULE 4: token $600 set to $0 26/07/26 - installation labour is priced in Phase 7 activity T4-03: 2x Rheem 315L HWU + HW circulating pump + flow/return loop (3 crew-days, Crew 4; crane truck 0.5d for HWU delivery/set). Commissioning in T5-06 ('HWU'). Retaining the token would DOUBLE-COUNT. Supply, freight, safe tray and mounting are priced separately - see EQUIPMENT_TEST_TPS.md.
V17: TOTAL | W17: =W11*W13*W14+W15+W16 -> 10051.772 | Y17: TOTAL | Z17: =Z11*Z13*Z14+Z15+Z16 -> 7942.2045 | AB17: TOTAL | AC17: =(AC11+AC12)*AC13*AC14+AC15+AC16 -> 8329.507
AB18: HWU qty 2 adopted (QUANTITY_RECONCILIATION TPS_NBC - take-off double-count removed; 2 drawn H-NBC-200/202)
V21: Public Amenities Block
I23: PUBLIC AMENITIES | N23: =S23+W31 -> 157680.56 | R23: ='Public Amenities (PAM)'!F864 -> 109647.6 | S23: =((R23/$R$39)*($R$49-$R$39))+R23 -> 155151.35
V24: Rheem HWU | X24: PAM HWU is Rheem 50L 613/050 (H-PAM-200) - rate corrected from $3,438.29 (315L model) to $2,016.08 (Reece Q-459014431)
V25: Purchase Cost Total | W25: 2016.08
V26: Safe Tray | W26: 52.8
V27: TPS Markup | W27: 1.15
V28: Qty | W28: 1
I29: SITEWORKS | N29: =S29 -> 641445.4 | R29: ='Siteworks '!F874 -> 453318.3 | S29: =((R29/$R$39)*($R$49-$R$39))+R29 -> 641445.4 | V29: Freight | W29: 150
V30: Installation_MH | W30: 0 | X30: RULE 4: token $200 set to $0 26/07/26 - installation labour is priced in Phase 7 activity T4-06: PAM Rheem 50L HWU + TMV + O32 check-meter assembly (1 crew-day, Crew 4). Commissioning in T5-06. Retaining the token would DOUBLE-COUNT. Supply, freight, safe tray and mounting are priced separately - see EQUIPMENT_TEST_TPS.md.
V31: TOTAL | W31: =(W25+W26)*W27*W28+W29+W30 -> 2529.212
I32: ACCOMMODATION - FIFO Option A (apartments + LH nightly) | N32: =S32 -> 124117.25 | R32: =14*'LabourProject Rates_Master'!E103+225*'LabourProject Rates_Master'!E109 -> 87715.368 | S32: =((R32/$R$39)*($R$49-$R$39))+R32 -> 124117.25 | T32: Phase 7 Accommodation TPS: 14 apt-months x $4,606.06 (crew of 3/apt) + LH 225 nights x $103.2468 = $87,715 (Option A recommended). Option B all-individual = 1,275 nights x $103.2468 = $131,640 - premium $43,925 not taken. No sharing with TCS (SS5.2).
I33: FLIGHTS - FIFO roster (return every 2nd w/e) | N33: =S33 -> 63505.2 | R33: =51*2*2*220 -> 44880 | S33: =((R33/$R$39)*($R$49-$R$39))+R33 -> 63505.2 | T33: 51 person-months (Phase 7) x 2 returns/person-month x 2 legs x $220/leg = $44,880 - assumption stated (Misc Rates flight basis)
V34: Sewer pump station EXCLUDED - installed by Council per Addendum 2 (10 Jul 2026); interfaces per interface ledger L6; add-price held in EBC register (APS 14065 basis) - see EBC_Alternates. Prior orphaned block W37 $468,000 -> W43 $545,700 removed (fed no roll-up; never in N64).
R39: =SUM(R13:R38) -> 1166409.4
P42: Prelim | Q42: 0.055 | R42: =R39*Q42 -> 64152.515 | S42: of total cost
P43: O/H | Q43: 0.18 | R43: =R39*Q43 -> 209953.69 | S43: of total cost
P45: Sub Total | R45: =SUM(R39:R44) -> 1440515.6 | S45: total cost + Prelim + O/H
P47: Gross Profit | Q47: 0.18 | R47: =R39*Q47 -> 209953.69 | S47: of total cost (SS5.4 re-base 26/07/26; was =R45*Q47 -> effective 45.73%)
R49: =SUM(R45:R47) -> 1650469.3
P51: Total Markup | Q51: =SUM(Q42:Q50) -> 0.415
P53: Net Profit Incl Equip | R53: =R48 -> 0
M64: TOTAL - TPS BASE SELL ex GST (excl PC Sums) | N64: =SUM(N16:N63) -> 1679321.9
M66: GST rows removed - ALL PRICING EX GST per SS5.4
P67: Prelim | Q67: =R42/R39 -> 0.055
P68: O/H | Q68: =R43/R39 -> 0.18
Q69: .
M70: PC SUMS - separate identified lines (ex GST) | P70: Sub Total | R70: Fixtures PC build (ex GST)
M71: PC-1A Fixtures supply - Tradelink 1066143 adjusted + 15% | N71: =(S71+S72+S73+S74)*1.15 -> 207268.84 | O71: Quote validity 13/08/26 vs 2027 start - escalation/validity qualification carried; Phase 4 line-by-line reconciliation mandatory | R71: Tradelink 1066143 quote total | S71: 252694.77
M72: PC-1A Drinking fountains - 2x CF400 chilled (NBC) + 15% | N72: =2*11050*1.15 -> 25415 | P72: Profit | Q72: 0.18 | R72: less 4x CF400 chilled fountains (moved to DF PC lines) | S72: -44200
M73: PC-1A Provisional connection fees - as directed, NO markup | N73: 20000 | O73: 1A 5.0 / 1B 4.6: $20,000 actual-cost reimbursement carried in BOTH stages exactly as directed (SS5.4) - no markup | P73: Total Markup | Q73: =SUM(Q67:Q72) -> 0.415 | R73: less 5x Billi Quadra 4180 - SUPPLIED BY RCC per FF&E VOL25 (install labour retained in base) | S73: -38261
M74: PC-1B Fixtures supply - PAM adopted-count extension + 15% | N74: =S75*1.15 -> 17250 | P74: Grand Total | R74: plus NBC adopted-count extension allowance | S74: 10000
M75: PC-1B Drinking fountains - 2x CF400 non-chilled (PAM, benchmark) + 15% | N75: =2*S78*1.15 -> 16560 | R75: plus PAM adopted-count extension allowance (PAM set never counted: 8 s/s WC + cisterns, trough, CSK, taps, 2 TR) | S75: 15000
M76: PC-1B Water bubbler stations - 4x site DF (H003, benchmark) + 15% | N76: =4*S78*1.15 -> 33120 | R76: Adjusted PC base (1A+1B) | S76: =SUM(S71:S75) -> 195233.77
M77: PC-1B Provisional connection fees - as directed, NO markup | N77: 20000 | R77: Extension deltas are stated allowances: quote quantities unfinalised; only 25 of ~108 adopted fixtures were counted when quote was assembled (Fixtures sheet). Where adopted counts exceed known quote lines they extend at quote-rate family; delta = +$25,000 total. Phase 4 reconciliation governs before award.
M78: PC SUMS TOTAL ex GST | N78: =SUM(N71:N77) -> 339613.84 | R78: Non-chilled CF400 benchmark rate (chilled $11,050 less ~35% chiller premium; Gap #6 pending re-quote) | S78: 7200
M80: STAGE SPLIT (SCOPE_MATRIX: mains-through-1B in 1A; PAM/bubblers/1B connections in 1B)
M81: 1A base sell: NBC + Siteworks + accom/flights share (146/166 crew-days) | N81: =N16+N29+(N32+N33)*146/166 -> 1499036.3
M82: 1A PC sums | N82: =N71+N72+N73 -> 252683.84
M83: STAGE 1A TOTAL ex GST | N83: =N81+N82 -> 1751720.1
M84: 1B base sell: PAM sheet (incl 1B site branches T2-09) + accom/flights share (20/166) | N84: =N23+(N32+N33)*20/166 -> 180285.68
M85: 1B PC sums | N85: =SUM(N74:N77) -> 86930
M86: STAGE 1B TOTAL ex GST | N86: =N84+N85 -> 267215.68
M87: GRAND TOTAL ex GST (1A + 1B incl PC sums) | N87: =N83+N86 -> 2018935.8
M88: Tie check (N64 + N78 - N87) = 0 | N88: =N64+N78-N87 -> 0

Sheet 00_ TCS Prelim & OH
B1: Project:
B2: Tricore -
B3: Stage 1 Version 1
A4: Item | K4: Source
A7: A | B7: PRELIMINARIES
B8: SUMMARY (Not added in prelim$)
C9: TOTAL Days Mobilized On Site | D9: 285 | G9: Re-based from Phase 7 TPS_Programme (link [1] severed): 197 work days across 3 discrete site windows; 10 months elapsed less inter-window demob = 285 calendar days on site | K9: frozen from [1] CQU ROK_PROGRAM - MASTER.V1 (SharePoint) - link severed 26/07/26; re-based from Phase 7 TPS_Programme
C10: Months Mobilized | D10: 9.4 | K10: frozen from [1] CQU ROK_PROGRAM - MASTER.V1 (SharePoint) - link severed 26/07/26; re-based from Phase 7 TPS_Programme
C11: Work Weeks' Mobilized On Site | D11: 40 | K11: frozen from [1] CQU ROK_PROGRAM - MASTER.V1 (SharePoint) - link severed 26/07/26; re-based from Phase 7 TPS_Programme
C12: Work Days | D12: 197 | G12: 197 work days = Phase 7 programme finish (T5-07 as-cons) | K12: frozen from [1] CQU ROK_PROGRAM - MASTER.V1 (SharePoint) - link severed 26/07/26; re-based from Phase 7 TPS_Programme
C13: Breakdown as per program
B14: ='LabourProject Rates_Master'!$B$14 -> TRADESMAN_LEADING HAND | C14: Day | E14: =E36 -> 1329.6343 | F14: =D14*E14 -> 0
B15: ='LabourProject Rates_Master'!$B$23 -> TRADESMAN_PLUMBER_OPERATOR | C15: Day | E15: =E37 -> 1016.4579 | F15: =D15*E15 -> 0
B16: ='LabourProject Rates_Master'!$B$30 -> T/A & Apprentice | C16: Day | E16: =E38 -> 829.51029 | F16: =D16*E16 -> 0
B17: ='LabourProject Rates_Master'!$B$36 -> Crew #1 - InGround Drainage | C17: Day | E17: =E39 -> 2862.4261 | F17: =D17*E17 -> 0
B18: ='LabourProject Rates_Master'!$B$43 -> Crew #2 - InGround Water/Fire | C18: Day | E18: =E40 -> 2862.4261 | F18: =D18*E18 -> 0
E19: Total Labour | F19: =SUM(F14:F18) -> 0
C20: Total as per stage boq
E21: Total Part A Labour | F21: 0
E22: Total Stage 1 Labour | F22: 0
E23: Total Stage 2 Labour | F23: 0
E24: Total Stage 3 Labour | F24: 0
E25: Total Stage 4 Labour | F25: 0
F26: =SUM(F21:F25) -> 0
E27: Difference | F27: =F26-F19 -> 0
C29: Unit | D29: REQ | E29: Cost ex GST | F29: Total ex GST
B30: Labour
B33: Contingencies; Wet Weather ?
B35: Superviser; Return Trip, 2 day stay - Inclusive | C35: item | E35: 2423.831 | F35: =D35*E35 -> 0
B36: ='LabourProject Rates_Master'!$B$14 -> TRADESMAN_LEADING HAND | C36: Day | D36: 0 | E36: ='LabourProject Rates_Master'!$E$15 -> 1329.6343 | F36: =E36*D36 -> 0 | G36: MEMO ONLY - 140 LH supervision days (1,400 hr) are priced IN the three work-area labour blocks per Phase 7 (Siteworks 489.2 + NBC 742.1 + PAM 168.5 = 1,399.8 hr). Not repeated here - double-count control.
B37: ='LabourProject Rates_Master'!$B$23 -> TRADESMAN_PLUMBER_OPERATOR | C37: Day | E37: ='LabourProject Rates_Master'!$E$22 -> 1016.4579 | F37: =E37*D37 -> 0
B38: ='LabourProject Rates_Master'!$B$30 -> T/A & Apprentice | C38: Day | E38: ='LabourProject Rates_Master'!$E$29 -> 829.51029 | F38: =E38*D38 -> 0
B39: ='LabourProject Rates_Master'!$B$36 -> Crew #1 - InGround Drainage | C39: Day | E39: ='LabourProject Rates_Master'!$E$37 -> 2862.4261 | F39: =E39*D39 -> 0
B40: ='LabourProject Rates_Master'!$B$43 -> Crew #2 - InGround Water/Fire | C40: Day | E40: ='LabourProject Rates_Master'!$E$44 -> 2862.4261 | F40: =E40*D40 -> 0
B42: Management Labour
B44: ='LabourProject Rates_Master'!$B$14 -> TRADESMAN_LEADING HAND | C44: Day | E44: ='LabourProject Rates_Master'!$E$15 -> 1329.6343 | F44: =E44*D44 -> 0 | G44: Included within stages?
B45: MH / DQ | C45: Day | E45: 120 | F45: =E45*D45 -> 0 | G45: Refer Program for approx attendance on site. Technically covered in overheads. E/O for meals etc?
B46: MH / DQ - FLIGHTS | C46: ea | E46: 200 | F46: =E46*D46 -> 0
B51: ACCOMODATION (Refer Program)
B52: Per Month - Full Project (6 Persons)
B53: ='LabourProject Rates_Master'!B100 -> Full Apartment / TownHouse / Unit - VIA AGENT | C53: Month | D53: 0 | E53: ='LabourProject Rates_Master'!E103 -> 4606.0606 | F53: =D53*E53 -> 0 | G53: ** 1 x 4Bed House (@650/Wk) fully kitted, +Consumable, +Cleaner etc | H53: MEMO - accommodation Option A (14 apt-months + LH 225 nights = $87,715) carried as a cost row on 'TCS $ Sched' R32; not repeated here
B54: ='LabourProject Rates_Master'!B100 -> Full Apartment / TownHouse / Unit - VIA AGENT | C54: Month | D54: 0 | E54: ='LabourProject Rates_Master'!E103 -> 4606.0606 | F54: =D54*E54 -> 0 | G54: ** 1 x 4Bed House (@650/Wk) fully kitted, +Consumable, +Cleaner etc
B56: Individual Night Stay - Private Room/Suite | H56: Avrg Nightly Book (LONG STAY)
B57: ='LabourProject Rates_Master'!$B$14 -> TRADESMAN_LEADING HAND | G57: =D14 -> 0 | H57: ='LabourProject Rates_Master'!$E$109 -> 103.24675 | I57: =H57*G57 -> 0
B58: ='LabourProject Rates_Master'!$B$23 -> TRADESMAN_PLUMBER_OPERATOR | G58: =D15 -> 0 | H58: ='LabourProject Rates_Master'!$E$109 -> 103.24675 | I58: =H58*G58 -> 0
B59: ='LabourProject Rates_Master'!$B$30 -> T/A & Apprentice | G59: =D16 -> 0 | H59: ='LabourProject Rates_Master'!$E$109 -> 103.24675 | I59: =H59*G59 -> 0
B60: ='LabourProject Rates_Master'!$B$36 -> Crew #1 - InGround Drainage | G60: =D17*3 -> 0 | H60: ='LabourProject Rates_Master'!$E$109 -> 103.24675 | I60: =H60*G60 -> 0
B62: Per Night - Extra-Over, Per Person.
B63: ='LabourProject Rates_Master'!B110 -> TCS Cost Per Person - Private Unit - NO SHARE - Nightly Booking (average allowance) | C63: item | E63: =Accomodation_Master!$F$343 -> 112.85714 | F63: =D63*E63 -> 0
B65: MH / DQ | C65: item | E65: 140 | F65: =D65*E65 -> 0 | G65: TOTAL ACCOM ALLOWANCE
G66: =SUM(F53:F66) -> 0 | I66: =SUM(I57:I65) -> 0
B68: Equipment, Hire, Subbies
B70: Vehicle - UTE - SUPERVISER | C70: Day | D70: 140 | E70: 90 | F70: =D70*E70 -> 12600 | G70: Supervisor ute - 140 LH days on site @ $90/d
B71: Vehicle - UTE - TRADESMAN | C71: Day | D71: 166 | E71: 60 | F71: =D71*E71 -> 9960 | G71: One crew ute per crew-day - 166 base crew-days @ $60/d (Phase 7 roll-up)
B72: Vehicle - UTE - TRADESMAN / TA | C72: Day | D72: 0 | E72: 40 | F72: =D72*E72 -> 0 | G72: nil - second crew ute is inside the $60/d crew allowance above
B74: Site Vehicle - Ute/Buggy | C74: Day | E74: 90 | F74: =D74*E74 -> 0
B75: Genset hire + fuel - TPS compound (no site power, ITT S17.3) | C75: Day | D75: =$D$9 -> 285 | E75: 45 | F75: =D75*E75 -> 12825 | G75: Allowance $45/d single-phase genset + fuel, full 285-day site duration
B76: Temporary potable water storage pods + site distribution (no site water, ITT S17.3) | C76: item | D76: 1 | E76: 5000 | F76: =D76*E76 -> 5000 | G76: 2 pods over ~10 months + fittings/stands. Test/flush water PURCHASE is priced separately on Siteworks r148 - no overlap
B77: ='Equip&HIRE_Master'!A40 -> Porta Loo_No Tank | C77: Day | D77: =$D$9 -> 285 | E77: ='Equip&HIRE_Master'!D40 -> 5.46 | F77: =D77*E77 -> 1556.1 | G77: Portable toilet - full site duration (TPS own; no shared compound - interface L5)
B78: ='Equip&HIRE_Master'!A41 -> 6*3m Demantable Lunchroom - COMPLETE | C78: Day | D78: =$D$9 -> 285 | E78: ='Equip&HIRE_Master'!D41 -> 23 | F78: =D78*E78 -> 6555
B79: ='Equip&HIRE_Master'!A42 -> 6*3m Demantable Office - COMPLETE | C79: Day | D79: =$D$9 -> 285 | E79: ='Equip&HIRE_Master'!D42 -> 23 | F79: =D79*E79 -> 6555
B80: ='Equip&HIRE_Master'!A43 -> 20Ft Shipping Container | C80: BUY | D80: 1 | E80: 1800 | F80: =D80*E80 -> 1800 | G80: 20 ft container - purchase, TPS site store
B81: Skip Bin | C81: Changeover | D81: =$D$10 -> 9.4 | E81: ='Equip&HIRE_Master'!D59 -> 239.8 | F81: =D81*E81 -> 2254.12 | G81: Skip changeovers = months mobilised
B83: Three-mobilisation allowance - plant float (3 discrete site windows per Phase 7 programme) | C83: mob | D83: 3 | E83: 1440 | F83: =D83*E83 -> 4320 | G83: 3 mob x 2 loads x 4 hr x $180/hr ex-ROK transport (Equip&HIRE D66). Crew remobilisation LABOUR is Phase 7 T1-12, priced in Siteworks - no overlap
B85: Misc.
B87: INSURANCE | C87: item | D87: 1 | E87: 20000 | F87: =D87*E87 -> 20000 | G87: Project-specific insurances (contract works + project PL/PI excess) - allowance; review against corporate cover before close
E89: Total TCS Prelims | F89: =SUM(F32:F88) -> 83425.22 | G89: CROSS-CHECK: 5.5% prelims markup allowance ('TCS $ Sched' R42) | H89: ='TCS $ Sched'!R42 -> 64152.515
G90: Variance $ (bottom-up F89 less 5.5% allowance) | H90: =F89-H89 -> 19272.705
G91: Variance % of the 5.5% allowance | H91: =IF(H89=0,0,H90/H89) -> 0.3004201
A92: A | B92: OverHeads | G92: Bottom-up prelims are the DIRECT establishment / temp-services / vehicle / mobilisation costs TPS must carry standalone (SS5.2 - no shared compound). Where bottom-up exceeds the 5.5% margin allowance the difference is a real exposure: lift the prelims % or carry the delta as a priced line before close.
C93: Unit | D93: REQ | E93: Cost ex GST | F93: Total ex GST | G93: Percentage across Project COST
B94: TriCore Overheads - COMPLETE…PER MONTH | C94: item | D94: 9.4 | E94: 40000 | F94: =D94*E94 -> 376000 | G94: ='TCS $ Sched'!$Q$68 -> 0.18 | H94: 9.4 months mobilised x $40,000/month TriCore corporate overhead (full corporate rate)
B95: less share attributable to concurrent TriCore projects (TPS carries 45% of corporate O/H over this window) | C95: item | D95: 1 | E95: =-F94*0.55 -> -206800 | F95: =D95*E95 -> -206800 | H95: STATED ASSUMPTION: charging 100% of corporate overhead to one project would over-recover. A 45% allocation is adopted for a project of this duration and value against expected concurrent workload - Director to confirm before close.
E96: Total TCS O/H | F96: =SUM(F94:F95) -> 169200 | G96: CROSS-CHECK: 18% O/H markup allowance ('TCS $ Sched' R43) | H96: ='TCS $ Sched'!R43 -> 209953.69
G97: Variance $ (bottom-up F96 less 18% allowance) | H97: =F96-H96 -> -40753.686
G98: Variance % of the 18% allowance | H98: =IF(H96=0,0,H97/H96) -> -0.19410798
G100: COMBINED bottom-up prelims + O/H | H100: =F89+F96 -> 252625.22
G101: COMBINED 5.5% + 18% margin allowance | H101: =H89+H96 -> 274106.2
G102: Combined variance $ / % | H102: =H100-H101 -> -21480.981 | I102: =IF(H101=0,0,H102/H101) -> -0.078367367

Sheet ClubHouse (NBC )
B1: Project:
B2: Tricore -
B3: Stage 1 Version 1
A4: Item
A9: 1 | B9: Complete -
B12: Labour
G13: Denis qty | H13: Qty / rate source note
B14: DAY | J14: april 2026 direct impact Increase % (not contigency)
B15: ='LabourProject Rates_Master'!$B$14 -> TRADESMAN_LEADING HAND | C15: Day | E15: ='LabourProject Rates_Master'!$E$15 -> 1329.6343 | F15: =E15*D15 -> 0
B16: ='LabourProject Rates_Master'!$B$23 -> TRADESMAN_PLUMBER_OPERATOR | C16: Day | E16: ='LabourProject Rates_Master'!$E$22 -> 1016.4579 | F16: =E16*D16 -> 0 | K16: PE Pipe & Fitting | L16: 0.38 | M16: 1.38
B17: ='LabourProject Rates_Master'!$B$30 -> T/A & Apprentice | C17: Day | E17: ='LabourProject Rates_Master'!$E$29 -> 829.51029 | F17: =E17*D17 -> 0 | K17: PVC Pipe & Fittings | L17: 0.38 | M17: 1.38
B18: ='LabourProject Rates_Master'!$B$36 -> Crew #1 - InGround Drainage | C18: Day | D18: 26 | E18: ='LabourProject Rates_Master'!$E$37 -> 2862.4261 | F18: =E18*D18 -> 74423.079 | H18: Phase 7 crew-days: T1-07 14 + T1-08 8 + T1-10 4 (DP stubs NBC+PAM) | K18: Subby Rates | L18: 0.15 | M18: 1.15
B19: ='LabourProject Rates_Master'!$B$43 -> Crew #2 - InGround Water/Fire | C19: Day | E19: ='LabourProject Rates_Master'!$E$44 -> 2862.4261 | F19: =E19*D19 -> 0 | K19: Delivey Rate | L19: 0.2 | M19: 1.2
B20: ='LabourProject Rates_Master'!B51 -> Crew #3 - Above Ground Drainage | C20: Day | D20: 14 | E20: ='LabourProject Rates_Master'!E52 -> 2862.4261 | F20: =E20*D20 -> 40073.965 | H20: Phase 7 crew-days: T3-01 6 + T3-02 5 + T3-04 3
B21: ='LabourProject Rates_Master'!B59 -> Crew #4 - Above Ground WATER/FIRE | C21: Day | D21: 21 | E21: ='LabourProject Rates_Master'!E60 -> 2862.4261 | F21: =E21*D21 -> 60110.948 | H21: Phase 7 crew-days: T4-01 12 + T4-02 3 + T4-03 3 + T4-04 1 + T4-07 2
B22: ='LabourProject Rates_Master'!B67 -> Crew #5 - Above Ground FitOff / Misc | C22: Day | D22: 27 | E22: ='LabourProject Rates_Master'!E68 -> 2862.4261 | F22: =E22*D22 -> 77285.505 | H22: Phase 7 crew-days: T5-01 13 + T5-02 3 + T5-04a 1 + T5-05 3 + T5-06 4 + T5-07 3
B23: ='LabourProject Rates_Master'!B75 -> Crew #6 - DEMO | C23: Day | E23: ='LabourProject Rates_Master'!E76 -> 1845.9682 | F23: =E23*D23 -> 0
B27: HOUR
B28: ='LabourProject Rates_Master'!$B$14 -> TRADESMAN_LEADING HAND | C28: HR | D28: 742.1 | E28: ='LabourProject Rates_Master'!$E$14 -> 132.96343 | F28: =E28*D28 -> 98672.16 | H28: Phase 7 LH supervision - NBC activities 742.1 hr
B29: ='LabourProject Rates_Master'!$B$23 -> TRADESMAN_PLUMBER_OPERATOR | C29: HR | D29: 0 | E29: ='LabourProject Rates_Master'!$E$21 -> 101.64579 | F29: =E29*D29 -> 0
B30: ='LabourProject Rates_Master'!$B$30 -> T/A & Apprentice | C30: HR | D30: 0 | E30: ='LabourProject Rates_Master'!$E$28 -> 82.951029 | F30: =E30*D30 -> 0
B31: ='LabourProject Rates_Master'!$B$36 -> Crew #1 - InGround Drainage | C31: HR | D31: 0 | E31: ='LabourProject Rates_Master'!$E$36 -> 286.24261 | F31: =E31*D31 -> 0
B32: ='LabourProject Rates_Master'!$B$43 -> Crew #2 - InGround Water/Fire | C32: HR | D32: 0 | E32: ='LabourProject Rates_Master'!$E$43 -> 286.24261 | F32: =E32*D32 -> 0
B35: Demolition & Reinstatement
B36: DEMO
B37: ='Misc Subbie Rates_Master'!A49 -> Asphalt Cutting | C37: m | E37: ='Misc Subbie Rates_Master'!D49+('Misc Subbie Rates_Master'!D49*$L$18) -> 15.525 | F37: =E37*D37 -> 0
B38: ='Misc Subbie Rates_Master'!A50 -> Concrete Cutting | C38: m | E38: ='Misc Subbie Rates_Master'!D50+('Misc Subbie Rates_Master'!D50*$L$18) -> 18.4 | F38: =E38*D38 -> 0
B39: Con Cut Establishemnt Fee | C39: ea | E39: ='Misc Subbie Rates_Master'!D51+('Misc Subbie Rates_Master'!D51*$L$18) -> 92 | F39: =E39*D39 -> 0
B40: REINSTATE - CONCRETE
B41: ='Misc Subbie Rates_Master'!A56 -> Road/Drveway Reinstate; 1mW x 150 Thck, N25/20/80, Incl Reinforcement | C41: m | E41: ='Misc Subbie Rates_Master'!D56 -> 145 | F41: =E41*D41 -> 0
B42: ='Misc Subbie Rates_Master'!A57 -> Kerb & Channel - 1m Wide | C42: ea | E42: ='Misc Subbie Rates_Master'!D57 -> 155 | F42: =E42*D42 -> 0
B43: ='Misc Subbie Rates_Master'!A58 -> Footpath - 1.5mW, N25/20/80, Incl Reinforcement | C43: lm | E43: ='Misc Subbie Rates_Master'!D58 -> 180 | F43: =E43*D43 -> 0
B44: ='Misc Subbie Rates_Master'!A59 -> Footpath - 1.5mW, EXPOSED AGG, N25/20/80, Incl Reinforcement | C44: lm | E44: ='Misc Subbie Rates_Master'!D59 -> 185 | F44: =E44*D44 -> 0
B45: REINSTATE - ASPHALT
B46: ='Misc Subbie Rates_Master'!A64 -> 50mm Thck - Trench Reinstatement Through Road/Driveway | C46: m2 | E46: ='Misc Subbie Rates_Master'!D64 -> 97 | F46: =E46*D46 -> 0
B47: ='Misc Subbie Rates_Master'!A65 -> 50mm Thck - 1.5-2m Wide Footpath reinstatements | C47: m2 | E47: ='Misc Subbie Rates_Master'!D65 -> 97 | F47: =E47*D47 -> 0
B48: ='Misc Subbie Rates_Master'!A66 -> Establishment Fee (1 per stage) | C48: Ea | E48: ='Misc Subbie Rates_Master'!D66 -> 5500 | F48: =E48*D48 -> 0
B50: Equipment & Hire - INCL WET PLANT HIRE
A52: HIDDEN | B52: PLANT HIRE - WET
B53: 1.8T Excavator | C53: Hr | E53: ='Misc Subbie Rates_Master'!D10 -> 100 | F53: =E53*D53 -> 0
B54: 3-5 ton Excavator | C54: Hr | E54: ='Misc Subbie Rates_Master'!D11 -> 115 | F54: =E54*D54 -> 0
B55: 3-5T Combo | C55: Hr | E55: ='Misc Subbie Rates_Master'!D12 -> 154 | F55: =E55*D55 -> 0
B56: Hammer attachment 3.5-4T | C56: Hr | E56: ='Misc Subbie Rates_Master'!D13 -> 21 | F56: =E56*D56 -> 0
B57: Ripper 3.5-4T | C57: Hr | E57: ='Misc Subbie Rates_Master'!D14 -> 10 | F57: =E57*D57 -> 0
B58: 5t Excavator | C58: Hr | E58: ='Misc Subbie Rates_Master'!D15 -> 150 | F58: =E58*D58 -> 0
B59: Hammer attachment 5T | C59: Hr | E59: ='Misc Subbie Rates_Master'!D16 -> 50 | F59: =E59*D59 -> 0
B60: Skid steer | C60: Hr | E60: ='Misc Subbie Rates_Master'!D17 -> 140 | F60: =E60*D60 -> 0
B61: 8T Excavator | C61: Hr | E61: ='Misc Subbie Rates_Master'!D18 -> 128 | F61: =E61*D61 -> 0
B62: Hammer attachment 8T | C62: Hr | E62: ='Misc Subbie Rates_Master'!D19 -> 26 | F62: =E62*D62 -> 0
B63: Ripper 8T | C63: Hr | E63: ='Misc Subbie Rates_Master'!D20 -> 10 | F63: =E63*D63 -> 0
B64: 13-15T Excavator | C64: Hr | E64: ='Misc Subbie Rates_Master'!D21 -> 153 | F64: =E64*D64 -> 0
... B71: 12t Body Truck Tipper | C71: Hr | E71: ='Misc Subbie Rates_Master'!D28 -> 110 | F71: =E71*D71 -> 0
B73: HIRE - DRY
B74: Skid Steer Loader_Tracked (CAT249+) | C74: Day | E74: ='Equip&HIRE_Master'!D4 -> 225.43333 | F74: =E74*D74 -> 0
B75: Skid Steer Loader_Wheeled (CAT226+) | C75: Day | E75: ='Equip&HIRE_Master'!D5 -> 163.96667 | F75: =E75*D75 -> 0
B76: Mini Loader, Stand-on Type | C76: Day | E76: ='Equip&HIRE_Master'!D6 -> 180 | F76: =E76*D76 -> 0
E77: ='Equip&HIRE_Master'!D7 -> 0 | F77: =E77*D77 -> 0
B78: 1.5-1.8 Ton_Excavator | C78: Day | D78: 14 | E78: ='Equip&HIRE_Master'!D8 -> 137.14286 | F78: =E78*D78 -> 1920 | H78: Phase 7 plant: T1-07 10 + T1-10 4
B79: 1.7-2Ton_Excavator | C79: Day | E79: ='Equip&HIRE_Master'!D9 -> 0 | F79: =E79*D79 -> 0
B80: 3-5Ton_Excavator | C80: Day | D80: 8 | E80: ='Equip&HIRE_Master'!D10 -> 238.66667 | F80: =E80*D80 -> 1909.3333 | H80: Phase 7 plant: T1-08 4 + T1-07 combo 4 (combo classed as 3-5T)
B81: 8Ton_Excavator | C81: Day | E81: ='Equip&HIRE_Master'!D11 -> 261.16667 | F81: =E81*D81 -> 0
B82: 10-12Ton_Excavator | C82: Day | E82: ='Equip&HIRE_Master'!D12 -> 0 | F82: =E82*D82 -> 0
B83: 13-16Ton_Excavator | C83: Day | E83: ='Equip&HIRE_Master'!D13 -> 317.2 | F83: =E83*D83 -> 0
B84: 20-24Ton_Excavator | C84: Day | E84: ='Equip&HIRE_Master'!D14 -> 314.28571 | F84: =E84*D84 -> 0
E85: ='Equip&HIRE_Master'!D15 -> 0 | F85: =E85*D85 -> 0
B86: Ripper_1.7-2T | C86: Day | E86: ='Equip&HIRE_Master'!D16 -> 0 | F86: =E86*D86 -> 0
B87: Ripper_1.5-4T | C87: Day | E87: ='Equip&HIRE_Master'!D17 -> 32.74 | F87: =E87*D87 -> 0
B88: Ripper_3-5T | C88: Day | E88: ='Equip&HIRE_Master'!D18 -> 0 | F88: =E88*D88 -> 0
B89: Ripper_8T | C89: Day | E89: ='Equip&HIRE_Master'!D19 -> 40.38 | F89: =E89*D89 -> 0
B90: Breaker_1.7-2T | C90: Day | E90: ='Equip&HIRE_Master'!D20 -> 123.33 | F90: =E90*D90 -> 0
B91: Breaker_3-5T | C91: Day | E91: ='Equip&HIRE_Master'!D21 -> 165.89 | F91: =E91*D91 -> 0
B92: Breaker_8T | C92: Day | E92: ='Equip&HIRE_Master'!D22 -> 165.89 | F92: =E92*D92 -> 0
B93: Breaker_10-12T | C93: Day | E93: ='Equip&HIRE_Master'!D23 -> 0 | F93: =E93*D93 -> 0
B94: Breaker_13-15T | C94: Day | E94: ='Equip&HIRE_Master'!D24 -> 203 | F94: =E94*D94 -> 0
B95: Auger Drive_10-12T | E95: ='Equip&HIRE_Master'!D25 -> 0 | F95: =E95*D95 -> 0
B96: 300Dia Auger Drill | E96: ='Equip&HIRE_Master'!D26 -> 0 | F96: =E96*D96 -> 0
E97: ='Equip&HIRE_Master'!D27 -> 0 | F97: =E97*D97 -> 0
B98: 1.25T_Tipper Truck | C98: Day | E98: ='Equip&HIRE_Master'!D28 -> 205 | F98: =E98*D98 -> 0
B99: 2-4T_Tipper Truck | C99: Day | E99: ='Equip&HIRE_Master'!D29 -> 166.98 | F99: =E99*D99 -> 0
B100: <6T_Tipper Truck | C100: Day | E100: ='Equip&HIRE_Master'!D30 -> 171.42857 | F100: =E100*D100 -> 0
E101: ='Equip&HIRE_Master'!D31 -> 0 | F101: =E101*D101 -> 0
B102: <10T_Articulated Site Tipper | C102: Day | E102: ='Equip&HIRE_Master'!D32 -> 0 | F102: =E102*D102 -> 0
B103: Upright Rammer_Wacker | C103: Day | D103: 10 | E103: ='Equip&HIRE_Master'!D33 -> 34.285714 | F103: =E103*D103 -> 342.85714 | H103: Phase 7 plant: T1-07 10
B104: Trench Roller_Dbl Drum_Remote | C104: Day | E104: ='Equip&HIRE_Master'!D34 -> 165 | F104: =E104*D104 -> 0
B105: <26Ft_Scissor Lift - Diesel | C105: Day | E105: 300 | F105: =E105*D105 -> 0
B106: <26Ft_Scissor Lift - Elec | C106: Day | D106: 13 | E106: 30 | F106: =E106*D106 -> 390 | H106: Phase 7: 13 d (T3-01 4 + T3-04 3 + T4-01 4 + T4-07 2); rate $150/wk (Civ Equip_HIRE weekly)/5 = $30/d - confirm Phase 6
B107: <34Ft_Boom Lift - Diesel | C107: Day | E107: ='Equip&HIRE_Master'!D37 -> 0 | F107: =E107*D107 -> 0
B108: <34Ft_Boom Lift - Elec | C108: Day | E108: ='Equip&HIRE_Master'!D38 -> 0 | F108: =E108*D108 -> 0
E109: ='Equip&HIRE_Master'!D39 -> 0 | F109: =E109*D109 -> 0
B110: Porta Loo_No Tank | C110: Day | E110: ='Equip&HIRE_Master'!D40 -> 5.46 | F110: =E110*D110 -> 0
B111: 6*3m Demantable Lunchroom - COMPLETE | C111: Day | E111: ='Equip&HIRE_Master'!D41 -> 23 | F111: =E111*D111 -> 0
B112: 6*3m Demantable Office - COMPLETE | C112: Day | E112: ='Equip&HIRE_Master'!D42 -> 23 | F112: =E112*D112 -> 0
B113: 20Ft Shipping Container | C113: Day | E113: ='Equip&HIRE_Master'!D43 -> 0 | F113: =E113*D113 -> 0
B114: Quick Cut Demo Saw | C114: Day | E114: ='Equip&HIRE_Master'!D44 -> 0 | F114: =E114*D114 -> 0
B115: Sngl Ph_6KVA Genset | C115: Day | E115: ='Equip&HIRE_Master'!D45 -> 0 | F115: =E115*D115 -> 0
B116: Diesel Air Compressor_Trailer | C116: Day | E116: ='Equip&HIRE_Master'!D46 -> 0 | F116: =E116*D116 -> 0
B117: Air Breaker - Heavy | C117: Day | E117: ='Equip&HIRE_Master'!D47 -> 0 | F117: =E117*D117 -> 0
B118: Air Hose <10m | C118: Day | E118: ='Equip&HIRE_Master'!D48 -> 0 | F118: =E118*D118 -> 0
B119: Elec Breaker/Jachammer | C119: Day | E119: ='Equip&HIRE_Master'!D49 -> 0 | F119: =E119*D119 -> 0
B120: Flexdrive Motor Unit | C120: Day | E120: ='Equip&HIRE_Master'!D50 -> 0 | F120: =E120*D120 -> 0
...

Sheet Public Amenities (PAM)
B1: Project:
B2: Tricore -
B3: Stage 1 Version 1
A4: Item
A9: 1 | B9: Complete -
B12: Labour
G13: Denis qty | H13: Qty / rate source note
B14: DAY | J14: april 2026 direct impact Increase % (not contigency)
B15: ='LabourProject Rates_Master'!$B$14 -> TRADESMAN_LEADING HAND | C15: Day | E15: ='LabourProject Rates_Master'!$E$15 -> 1329.6343 | F15: =E15*D15 -> 0
B16: ='LabourProject Rates_Master'!$B$23 -> TRADESMAN_PLUMBER_OPERATOR | C16: Day | E16: ='LabourProject Rates_Master'!$E$22 -> 1016.4579 | F16: =E16*D16 -> 0 | K16: PE Pipe & Fitting | L16: 0.38 | M16: 1.38
B17: ='LabourProject Rates_Master'!$B$30 -> T/A & Apprentice | C17: Day | E17: ='LabourProject Rates_Master'!$E$29 -> 829.51029 | F17: =E17*D17 -> 0 | K17: PVC Pipe & Fittings | L17: 0.38 | M17: 1.38
B18: ='LabourProject Rates_Master'!$B$36 -> Crew #1 - InGround Drainage | C18: Day | D18: 4 | E18: ='LabourProject Rates_Master'!$E$37 -> 2862.4261 | F18: =E18*D18 -> 11449.704 | H18: Phase 7 crew-days (1B): T1-09 PAM UG drainage 4 | K18: Subby Rates | L18: 0.15 | M18: 1.15
B19: ='LabourProject Rates_Master'!$B$43 -> Crew #2 - InGround Water/Fire | C19: Day | D19: 4 | E19: ='LabourProject Rates_Master'!$E$44 -> 2862.4261 | F19: =E19*D19 -> 11449.704 | H19: Phase 7 crew-days (1B): T2-09 1B site branch take-offs 4 (1B scope carried on PAM sheet as 1B roll-up collector - interface L9) | K19: Delivey Rate | L19: 0.2 | M19: 1.2
B20: ='LabourProject Rates_Master'!B51 -> Crew #3 - Above Ground Drainage | C20: Day | D20: 2 | E20: ='LabourProject Rates_Master'!E52 -> 2862.4261 | F20: =E20*D20 -> 5724.8522 | H20: Phase 7 crew-days (1B): T3-03 PAM vent + AG waste 2
B21: ='LabourProject Rates_Master'!B59 -> Crew #4 - Above Ground WATER/FIRE | C21: Day | D21: 5 | E21: ='LabourProject Rates_Master'!E60 -> 2862.4261 | F21: =E21*D21 -> 14312.13 | H21: Phase 7 crew-days (1B): T4-05 4 + T4-06 1
B22: ='LabourProject Rates_Master'!B67 -> Crew #5 - Above Ground FitOff / Misc | C22: Day | D22: 5 | E22: ='LabourProject Rates_Master'!E68 -> 2862.4261 | F22: =E22*D22 -> 14312.13 | H22: Phase 7 crew-days (1B): T5-03 4 + T5-04b 1 (bubbler install)
B23: ='LabourProject Rates_Master'!B75 -> Crew #6 - DEMO | C23: Day | E23: ='LabourProject Rates_Master'!E76 -> 1845.9682 | F23: =E23*D23 -> 0
B25: HOUR
B26: ='LabourProject Rates_Master'!$B$14 -> TRADESMAN_LEADING HAND | C26: HR | D26: 168.5 | E26: ='LabourProject Rates_Master'!$E$14 -> 132.96343 | F26: =E26*D26 -> 22404.338 | H26: Phase 7 LH supervision - 1B activities 168.5 hr
B27: ='LabourProject Rates_Master'!$B$23 -> TRADESMAN_PLUMBER_OPERATOR | C27: HR | D27: 0 | E27: ='LabourProject Rates_Master'!$E$21 -> 101.64579 | F27: =E27*D27 -> 0
B28: ='LabourProject Rates_Master'!$B$30 -> T/A & Apprentice | C28: HR | D28: 0 | E28: ='LabourProject Rates_Master'!$E$28 -> 82.951029 | F28: =E28*D28 -> 0
B29: ='LabourProject Rates_Master'!$B$36 -> Crew #1 - InGround Drainage | C29: HR | D29: 0 | E29: ='LabourProject Rates_Master'!$E$36 -> 286.24261 | F29: =E29*D29 -> 0
B30: ='LabourProject Rates_Master'!$B$43 -> Crew #2 - InGround Water/Fire | C30: HR | D30: 0 | E30: ='LabourProject Rates_Master'!$E$43 -> 286.24261 | F30: =E30*D30 -> 0
B33: Demolition & Reinstatement
B34: DEMO
B35: ='Misc Subbie Rates_Master'!A49 -> Asphalt Cutting | C35: m | E35: ='Misc Subbie Rates_Master'!D49+('Misc Subbie Rates_Master'!D49*$L$18) -> 15.525 | F35: =E35*D35 -> 0
B36: ='Misc Subbie Rates_Master'!A50 -> Concrete Cutting | C36: m | E36: ='Misc Subbie Rates_Master'!D50+('Misc Subbie Rates_Master'!D50*$L$18) -> 18.4 | F36: =E36*D36 -> 0
B37: Con Cut Establishemnt Fee | C37: ea | E37: ='Misc Subbie Rates_Master'!D51+('Misc Subbie Rates_Master'!D51*$L$18) -> 92 | F37: =E37*D37 -> 0
B38: REINSTATE - CONCRETE
B39: ='Misc Subbie Rates_Master'!A56 -> Road/Drveway Reinstate; 1mW x 150 Thck, N25/20/80, Incl Reinforcement | C39: m | E39: ='Misc Subbie Rates_Master'!D56 -> 145 | F39: =E39*D39 -> 0
B40: ='Misc Subbie Rates_Master'!A57 -> Kerb & Channel - 1m Wide | C40: ea | E40: ='Misc Subbie Rates_Master'!D57 -> 155 | F40: =E40*D40 -> 0
B41: ='Misc Subbie Rates_Master'!A58 -> Footpath - 1.5mW, N25/20/80, Incl Reinforcement | C41: lm | E41: ='Misc Subbie Rates_Master'!D58 -> 180 | F41: =E41*D41 -> 0
B42: ='Misc Subbie Rates_Master'!A59 -> Footpath - 1.5mW, EXPOSED AGG, N25/20/80, Incl Reinforcement | C42: lm | E42: ='Misc Subbie Rates_Master'!D59 -> 185 | F42: =E42*D42 -> 0
B43: REINSTATE - ASPHALT
B44: ='Misc Subbie Rates_Master'!A64 -> 50mm Thck - Trench Reinstatement Through Road/Driveway | C44: m2 | E44: ='Misc Subbie Rates_Master'!D64 -> 97 | F44: =E44*D44 -> 0
B45: ='Misc Subbie Rates_Master'!A65 -> 50mm Thck - 1.5-2m Wide Footpath reinstatements | C45: m2 | E45: ='Misc Subbie Rates_Master'!D65 -> 97 | F45: =E45*D45 -> 0
B46: ='Misc Subbie Rates_Master'!A66 -> Establishment Fee (1 per stage) | C46: Ea | E46: ='Misc Subbie Rates_Master'!D66 -> 5500 | F46: =E46*D46 -> 0
B48: Equipment & Hire - INCL WET PLANT HIRE
B50: PLANT HIRE - WET
B51: 1.8T Excavator | C51: Hr | E51: ='Misc Subbie Rates_Master'!D10 -> 100 | F51: =E51*D51 -> 0
B52: 3-5 ton Excavator | C52: Hr | E52: ='Misc Subbie Rates_Master'!D11 -> 115 | F52: =E52*D52 -> 0
B53: 3-5T Combo | C53: Hr | E53: ='Misc Subbie Rates_Master'!D12 -> 154 | F53: =E53*D53 -> 0
B54: Hammer attachment 3.5-4T | C54: Hr | E54: ='Misc Subbie Rates_Master'!D13 -> 21 | F54: =E54*D54 -> 0
B55: Ripper 3.5-4T | C55: Hr | E55: ='Misc Subbie Rates_Master'!D14 -> 10 | F55: =E55*D55 -> 0
B56: 5t Excavator | C56: Hr | E56: ='Misc Subbie Rates_Master'!D15 -> 150 | F56: =E56*D56 -> 0
B57: Hammer attachment 5T | C57: Hr | E57: ='Misc Subbie Rates_Master'!D16 -> 50 | F57: =E57*D57 -> 0
B58: Skid steer | C58: Hr | E58: ='Misc Subbie Rates_Master'!D17 -> 140 | F58: =E58*D58 -> 0
B59: 8T Excavator | C59: Hr | E59: ='Misc Subbie Rates_Master'!D18 -> 128 | F59: =E59*D59 -> 0
B60: Hammer attachment 8T | C60: Hr | E60: ='Misc Subbie Rates_Master'!D19 -> 26 | F60: =E60*D60 -> 0
B61: Ripper 8T | C61: Hr | E61: ='Misc Subbie Rates_Master'!D20 -> 10 | F61: =E61*D61 -> 0
B62: 13-15T Excavator | C62: Hr | E62: ='Misc Subbie Rates_Master'!D21 -> 153 | F62: =E62*D62 -> 0
... B69: 12t Body Truck Tipper | C69: Hr | E69: ='Misc Subbie Rates_Master'!D28 -> 110 | F69: =E69*D69 -> 0
B71: HIRE - DRY
B72: Skid Steer Loader_Tracked (CAT249+) | C72: Day | E72: ='Equip&HIRE_Master'!D4 -> 225.43333 | F72: =E72*D72 -> 0
B73: Skid Steer Loader_Wheeled (CAT226+) | C73: Day | E73: ='Equip&HIRE_Master'!D5 -> 163.96667 | F73: =E73*D73 -> 0
B74: Mini Loader, Stand-on Type | C74: Day | E74: ='Equip&HIRE_Master'!D6 -> 180 | F74: =E74*D74 -> 0
E75: ='Equip&HIRE_Master'!D7 -> 0 | F75: =E75*D75 -> 0
B76: 1.5-1.8 Ton_Excavator | C76: Day | D76: 8 | E76: ='Equip&HIRE_Master'!D8 -> 137.14286 | F76: =E76*D76 -> 1097.1429 | H76: Phase 7 plant (1B): T1-09 4 + T2-09 4
B77: 1.7-2Ton_Excavator | C77: Day | E77: ='Equip&HIRE_Master'!D9 -> 0 | F77: =E77*D77 -> 0
B78: 3-5Ton_Excavator | C78: Day | E78: ='Equip&HIRE_Master'!D10 -> 238.66667 | F78: =E78*D78 -> 0
B79: 8Ton_Excavator | C79: Day | E79: ='Equip&HIRE_Master'!D11 -> 261.16667 | F79: =E79*D79 -> 0
B80: 10-12Ton_Excavator | C80: Day | E80: ='Equip&HIRE_Master'!D12 -> 0 | F80: =E80*D80 -> 0
B81: 13-16Ton_Excavator | C81: Day | E81: ='Equip&HIRE_Master'!D13 -> 317.2 | F81: =E81*D81 -> 0
B82: 20-24Ton_Excavator | C82: Day | E82: ='Equip&HIRE_Master'!D14 -> 314.28571 | F82: =E82*D82 -> 0
E83: ='Equip&HIRE_Master'!D15 -> 0 | F83: =E83*D83 -> 0
B84: Ripper_1.7-2T | C84: Day | E84: ='Equip&HIRE_Master'!D16 -> 0 | F84: =E84*D84 -> 0
B85: Ripper_1.5-4T | C85: Day | E85: ='Equip&HIRE_Master'!D17 -> 32.74 | F85: =E85*D85 -> 0
B86: Ripper_3-5T | C86: Day | E86: ='Equip&HIRE_Master'!D18 -> 0 | F86: =E86*D86 -> 0
B87: Ripper_8T | C87: Day | E87: ='Equip&HIRE_Master'!D19 -> 40.38 | F87: =E87*D87 -> 0
B88: Breaker_1.7-2T | C88: Day | E88: ='Equip&HIRE_Master'!D20 -> 123.33 | F88: =E88*D88 -> 0
B89: Breaker_3-5T | C89: Day | E89: ='Equip&HIRE_Master'!D21 -> 165.89 | F89: =E89*D89 -> 0
B90: Breaker_8T | C90: Day | E90: ='Equip&HIRE_Master'!D22 -> 165.89 | F90: =E90*D90 -> 0
B91: Breaker_10-12T | C91: Day | E91: ='Equip&HIRE_Master'!D23 -> 0 | F91: =E91*D91 -> 0
B92: Breaker_13-15T | C92: Day | E92: ='Equip&HIRE_Master'!D24 -> 203 | F92: =E92*D92 -> 0
B93: Auger Drive_10-12T | E93: ='Equip&HIRE_Master'!D25 -> 0 | F93: =E93*D93 -> 0
B94: 300Dia Auger Drill | E94: ='Equip&HIRE_Master'!D26 -> 0 | F94: =E94*D94 -> 0
E95: ='Equip&HIRE_Master'!D27 -> 0 | F95: =E95*D95 -> 0
B96: 1.25T_Tipper Truck | C96: Day | E96: ='Equip&HIRE_Master'!D28 -> 205 | F96: =E96*D96 -> 0
B97: 2-4T_Tipper Truck | C97: Day | E97: ='Equip&HIRE_Master'!D29 -> 166.98 | F97: =E97*D97 -> 0
B98: <6T_Tipper Truck | C98: Day | E98: ='Equip&HIRE_Master'!D30 -> 171.42857 | F98: =E98*D98 -> 0
E99: ='Equip&HIRE_Master'!D31 -> 0 | F99: =E99*D99 -> 0
B100: <10T_Articulated Site Tipper | C100: Day | E100: ='Equip&HIRE_Master'!D32 -> 0 | F100: =E100*D100 -> 0
B101: Upright Rammer_Wacker | C101: Day | D101: 4 | E101: ='Equip&HIRE_Master'!D33 -> 34.285714 | F101: =E101*D101 -> 137.14286 | H101: Phase 7 plant (1B): T1-09 4
B102: Trench Roller_Dbl Drum_Remote | C102: Day | E102: ='Equip&HIRE_Master'!D34 -> 165 | F102: =E102*D102 -> 0
B103: <26Ft_Scissor Lift - Diesel | C103: Day | E103: ='Equip&HIRE_Master'!D35 -> 0 | F103: =E103*D103 -> 0
B104: <26Ft_Scissor Lift - Elec | C104: Day | E104: ='Equip&HIRE_Master'!D36 -> 0 | F104: =E104*D104 -> 0
B105: <34Ft_Boom Lift - Diesel | C105: Day | E105: ='Equip&HIRE_Master'!D37 -> 0 | F105: =E105*D105 -> 0
B106: <34Ft_Boom Lift - Elec | C106: Day | E106: ='Equip&HIRE_Master'!D38 -> 0 | F106: =E106*D106 -> 0
E107: ='Equip&HIRE_Master'!D39 -> 0 | F107: =E107*D107 -> 0
B108: Porta Loo_No Tank | C108: Day | E108: ='Equip&HIRE_Master'!D40 -> 5.46 | F108: =E108*D108 -> 0
B109: 6*3m Demantable Lunchroom - COMPLETE | C109: Day | E109: ='Equip&HIRE_Master'!D41 -> 23 | F109: =E109*D109 -> 0
B110: 6*3m Demantable Office - COMPLETE | C110: Day | E110: ='Equip&HIRE_Master'!D42 -> 23 | F110: =E110*D110 -> 0
B111: 20Ft Shipping Container | C111: Day | E111: ='Equip&HIRE_Master'!D43 -> 0 | F111: =E111*D111 -> 0
B112: Quick Cut Demo Saw | C112: Day | E112: ='Equip&HIRE_Master'!D44 -> 0 | F112: =E112*D112 -> 0
B113: Sngl Ph_6KVA Genset | C113: Day | E113: ='Equip&HIRE_Master'!D45 -> 0 | F113: =E113*D113 -> 0
B114: Diesel Air Compressor_Trailer | C114: Day | E114: ='Equip&HIRE_Master'!D46 -> 0 | F114: =E114*D114 -> 0
B115: Air Breaker - Heavy | C115: Day | E115: ='Equip&HIRE_Master'!D47 -> 0 | F115: =E115*D115 -> 0
B116: Air Hose <10m | C116: Day | E116: ='Equip&HIRE_Master'!D48 -> 0 | F116: =E116*D116 -> 0
B117: Elec Breaker/Jachammer | C117: Day | E117: ='Equip&HIRE_Master'!D49 -> 0 | F117: =E117*D117 -> 0
B118: Flexdrive Motor Unit | C118: Day | E118: ='Equip&HIRE_Master'!D50 -> 0 | F118: =E118*D118 -> 0
...

Sheet Siteworks 
B1: Project:
B2: Tricore -
B3: Stage 1 Version 1
A4: Item
A9: 1 | B9: Complete -
B12: Labour
G13: Denis qty | H13: Qty / rate source note
B14: DAY | J14: april 2026 direct impact Increase % (not contigency)
B15: ='LabourProject Rates_Master'!$B$14 -> TRADESMAN_LEADING HAND | C15: Day | E15: ='LabourProject Rates_Master'!$E$15 -> 1329.6343 | F15: =E15*D15 -> 0
B16: ='LabourProject Rates_Master'!$B$23 -> TRADESMAN_PLUMBER_OPERATOR | C16: Day | E16: ='LabourProject Rates_Master'!$E$22 -> 1016.4579 | F16: =E16*D16 -> 0 | K16: PE Pipe & Fitting | L16: 0.38 | M16: 1.38
B17: ='LabourProject Rates_Master'!$B$30 -> T/A & Apprentice | C17: Day | E17: ='LabourProject Rates_Master'!$E$29 -> 829.51029 | F17: =E17*D17 -> 0 | K17: PVC Pipe & Fittings | L17: 0.38 | M17: 1.38
B18: ='LabourProject Rates_Master'!$B$36 -> Crew #1 - InGround Drainage | C18: Day | D18: 23 | E18: ='LabourProject Rates_Master'!$E$37 -> 2862.4261 | F18: =E18*D18 -> 65835.8 | H18: Phase 7 Crew 1 site: T1-01..T1-05 + T1-11 + T1-12 = 23 crew-days (T1-06 rising main EBC excluded) | K18: Subby Rates | L18: 0.15 | M18: 1.15
B19: ='LabourProject Rates_Master'!$B$43 -> Crew #2 - InGround Water/Fire | C19: Day | D19: 35 | E19: ='LabourProject Rates_Master'!$E$44 -> 2862.4261 | F19: =E19*D19 -> 100184.91 | H19: Phase 7 Crew 2 site: T2-01..T2-08 + T2-10 = 35 crew-days | K19: Delivey Rate | L19: 0.2 | M19: 1.2
B20: ='LabourProject Rates_Master'!B51 -> Crew #3 - Above Ground Drainage | C20: Day | E20: ='LabourProject Rates_Master'!E52 -> 2862.4261 | F20: =E20*D20 -> 0
B21: ='LabourProject Rates_Master'!B59 -> Crew #4 - Above Ground WATER/FIRE | C21: Day | E21: ='LabourProject Rates_Master'!E60 -> 2862.4261 | F21: =E21*D21 -> 0
B22: ='LabourProject Rates_Master'!B67 -> Crew #5 - Above Ground FitOff / Misc | C22: Day | E22: ='LabourProject Rates_Master'!E68 -> 2862.4261 | F22: =E22*D22 -> 0
B23: ='LabourProject Rates_Master'!B75 -> Crew #6 - DEMO | C23: Day | E23: ='LabourProject Rates_Master'!E76 -> 1845.9682 | F23: =E23*D23 -> 0
B25: HOUR
B26: ='LabourProject Rates_Master'!$B$14 -> TRADESMAN_LEADING HAND | C26: HR | D26: 489.2 | E26: ='LabourProject Rates_Master'!$E$14 -> 132.96343 | F26: =E26*D26 -> 65045.709 | H26: Phase 7 LH supervision - site activities 489.2 hr (of 1,400 hr / 140 d total)
B27: ='LabourProject Rates_Master'!$B$23 -> TRADESMAN_PLUMBER_OPERATOR | C27: HR | D27: 0 | E27: ='LabourProject Rates_Master'!$E$21 -> 101.64579 | F27: =E27*D27 -> 0
B28: ='LabourProject Rates_Master'!$B$30 -> T/A & Apprentice | C28: HR | D28: 0 | E28: ='LabourProject Rates_Master'!$E$28 -> 82.951029 | F28: =E28*D28 -> 0
B29: ='LabourProject Rates_Master'!$B$36 -> Crew #1 - InGround Drainage | C29: HR | D29: 0 | E29: ='LabourProject Rates_Master'!$E$36 -> 286.24261 | F29: =E29*D29 -> 0
B30: ='LabourProject Rates_Master'!$B$43 -> Crew #2 - InGround Water/Fire | C30: HR | D30: 0 | E30: ='LabourProject Rates_Master'!$E$43 -> 286.24261 | F30: =E30*D30 -> 0
B33: Demolition & Reinstatement
B34: DEMO
B35: ='Misc Subbie Rates_Master'!A49 -> Asphalt Cutting | C35: m | E35: ='Misc Subbie Rates_Master'!D49+('Misc Subbie Rates_Master'!D49*$L$18) -> 15.525 | F35: =E35*D35 -> 0
B36: ='Misc Subbie Rates_Master'!A50 -> Concrete Cutting | C36: m | E36: ='Misc Subbie Rates_Master'!D50+('Misc Subbie Rates_Master'!D50*$L$18) -> 18.4 | F36: =E36*D36 -> 0
B37: Con Cut Establishemnt Fee | C37: ea | E37: ='Misc Subbie Rates_Master'!D51+('Misc Subbie Rates_Master'!D51*$L$18) -> 92 | F37: =E37*D37 -> 0
B38: REINSTATE - CONCRETE
B39: ='Misc Subbie Rates_Master'!A56 -> Road/Drveway Reinstate; 1mW x 150 Thck, N25/20/80, Incl Reinforcement | C39: m | E39: ='Misc Subbie Rates_Master'!D56 -> 145 | F39: =E39*D39 -> 0
B40: ='Misc Subbie Rates_Master'!A57 -> Kerb & Channel - 1m Wide | C40: ea | E40: ='Misc Subbie Rates_Master'!D57 -> 155 | F40: =E40*D40 -> 0
B41: ='Misc Subbie Rates_Master'!A58 -> Footpath - 1.5mW, N25/20/80, Incl Reinforcement | C41: lm | E41: ='Misc Subbie Rates_Master'!D58 -> 180 | F41: =E41*D41 -> 0
B42: ='Misc Subbie Rates_Master'!A59 -> Footpath - 1.5mW, EXPOSED AGG, N25/20/80, Incl Reinforcement | C42: lm | E42: ='Misc Subbie Rates_Master'!D59 -> 185 | F42: =E42*D42 -> 0
B43: REINSTATE - ASPHALT
B44: ='Misc Subbie Rates_Master'!A64 -> 50mm Thck - Trench Reinstatement Through Road/Driveway | C44: m2 | E44: ='Misc Subbie Rates_Master'!D64 -> 97 | F44: =E44*D44 -> 0
B45: ='Misc Subbie Rates_Master'!A65 -> 50mm Thck - 1.5-2m Wide Footpath reinstatements | C45: m2 | E45: ='Misc Subbie Rates_Master'!D65 -> 97 | F45: =E45*D45 -> 0
B46: ='Misc Subbie Rates_Master'!A66 -> Establishment Fee (1 per stage) | C46: Ea | E46: ='Misc Subbie Rates_Master'!D66 -> 5500 | F46: =E46*D46 -> 0
B48: Equipment & Hire - INCL WET PLANT HIRE
B50: PLANT HIRE - WET
B51: 1.8T Excavator | C51: Hr | E51: ='Misc Subbie Rates_Master'!D10 -> 100 | F51: =E51*D51 -> 0
B52: 3-5 ton Excavator | C52: Hr | E52: ='Misc Subbie Rates_Master'!D11 -> 115 | F52: =E52*D52 -> 0
B53: 3-5T Combo | C53: Hr | E53: ='Misc Subbie Rates_Master'!D12 -> 154 | F53: =E53*D53 -> 0
B54: Hammer attachment 3.5-4T | C54: Hr | E54: ='Misc Subbie Rates_Master'!D13 -> 21 | F54: =E54*D54 -> 0
B55: Ripper 3.5-4T | C55: Hr | E55: ='Misc Subbie Rates_Master'!D14 -> 10 | F55: =E55*D55 -> 0
B56: 5t Excavator | C56: Hr | E56: ='Misc Subbie Rates_Master'!D15 -> 150 | F56: =E56*D56 -> 0
B57: Hammer attachment 5T | C57: Hr | E57: ='Misc Subbie Rates_Master'!D16 -> 50 | F57: =E57*D57 -> 0
B58: Skid steer | C58: Hr | E58: ='Misc Subbie Rates_Master'!D17 -> 140 | F58: =E58*D58 -> 0
B59: 8T Excavator | C59: Hr | E59: ='Misc Subbie Rates_Master'!D18 -> 128 | F59: =E59*D59 -> 0
B60: Hammer attachment 8T | C60: Hr | E60: ='Misc Subbie Rates_Master'!D19 -> 26 | F60: =E60*D60 -> 0
B61: Ripper 8T | C61: Hr | E61: ='Misc Subbie Rates_Master'!D20 -> 10 | F61: =E61*D61 -> 0
B62: 13-15T Excavator | C62: Hr | E62: ='Misc Subbie Rates_Master'!D21 -> 153 | F62: =E62*D62 -> 0
... B64: Ripper 14T | C64: Hr | E64: ='Misc Subbie Rates_Master'!D23 -> 10 | F64: =E64*D64 -> 0
B65: 3000L Hydro Excavation Truck | C65: Hr | D65: 20 | E65: ='Misc Subbie Rates_Master'!D24 -> 190 | F65: =E65*D65 -> 3800 | H65: Hydro-ex 3000L: T1-04 1 d + T2-02 1 d = 20 hr wet @ $190
B66: 4500L Hydro Excavation Truck | C66: Hr | E66: ='Misc Subbie Rates_Master'!D25 -> 220 | F66: =E66*D66 -> 0
B67: 6300L Hydro Excavation Truck | C67: Hr | E67: ='Misc Subbie Rates_Master'!D26 -> 250 | F67: =E67*D67 -> 0
B68: Water Truck allow for water at cost | C68: Hr | D68: 30 | E68: ='Misc Subbie Rates_Master'!D27 -> 110 | F68: =E68*D68 -> 3300 | H68: Water truck: T1-11 1 d + T2-10 2 d = 30 hr wet @ $110 (test/flush cartage)
B69: 12t Body Truck Tipper | C69: Hr | E69: ='Misc Subbie Rates_Master'!D28 -> 110 | F69: =E69*D69 -> 0
B71: HIRE - DRY
B72: Skid Steer Loader_Tracked (CAT249+) | C72: Day | E72: ='Equip&HIRE_Master'!D4 -> 225.43333 | F72: =E72*D72 -> 0
B73: Skid Steer Loader_Wheeled (CAT226+) | C73: Day | E73: ='Equip&HIRE_Master'!D5 -> 163.96667 | F73: =E73*D73 -> 0
B74: Mini Loader, Stand-on Type | C74: Day | E74: ='Equip&HIRE_Master'!D6 -> 180 | F74: =E74*D74 -> 0
E75: ='Equip&HIRE_Master'!D7 -> 0 | F75: =E75*D75 -> 0
B76: 1.5-1.8 Ton_Excavator | C76: Day | D76: 2 | E76: ='Equip&HIRE_Master'!D8 -> 137.14286 | F76: =E76*D76 -> 274.28571 | H76: Phase 7 plant: 1.8T: T2-06 2
B77: 1.7-2Ton_Excavator | C77: Day | E77: ='Equip&HIRE_Master'!D9 -> 0 | F77: =E77*D77 -> 0
B78: 3-5Ton_Excavator | C78: Day | D78: 11 | E78: ='Equip&HIRE_Master'!D10 -> 238.66667 | F78: =E78*D78 -> 2625.3333 | H78: Phase 7 plant: 3-5T: T1-03 6 + T1-04 3 + T1-05 2
B79: 8Ton_Excavator | C79: Day | D79: 6 | E79: ='Equip&HIRE_Master'!D11 -> 261.16667 | F79: =E79*D79 -> 1567 | H79: Phase 7 plant: 8T: T2-02 3 + T2-03 2 + T2-08 1
B80: 10-12Ton_Excavator | C80: Day | E80: ='Equip&HIRE_Master'!D12 -> 0 | F80: =E80*D80 -> 0
B81: 13-16Ton_Excavator | C81: Day | D81: 16 | E81: ='Equip&HIRE_Master'!D13 -> 317.2 | F81: =E81*D81 -> 5075.2 | H81: Phase 7 plant: 13-16T: T2-01 5 + T2-04 6 + T2-07 5
B82: 20-24Ton_Excavator | C82: Day | E82: ='Equip&HIRE_Master'!D14 -> 314.28571 | F82: =E82*D82 -> 0
E83: ='Equip&HIRE_Master'!D15 -> 0 | F83: =E83*D83 -> 0
B84: Ripper_1.7-2T | C84: Day | E84: ='Equip&HIRE_Master'!D16 -> 0 | F84: =E84*D84 -> 0
B85: Ripper_1.5-4T | C85: Day | E85: ='Equip&HIRE_Master'!D17 -> 32.74 | F85: =E85*D85 -> 0
B86: Ripper_3-5T | C86: Day | E86: ='Equip&HIRE_Master'!D18 -> 0 | F86: =E86*D86 -> 0
B87: Ripper_8T | C87: Day | E87: ='Equip&HIRE_Master'!D19 -> 40.38 | F87: =E87*D87 -> 0
B88: Breaker_1.7-2T | C88: Day | E88: ='Equip&HIRE_Master'!D20 -> 123.33 | F88: =E88*D88 -> 0
B89: Breaker_3-5T | C89: Day | E89: ='Equip&HIRE_Master'!D21 -> 165.89 | F89: =E89*D89 -> 0
B90: Breaker_8T | C90: Day | E90: ='Equip&HIRE_Master'!D22 -> 165.89 | F90: =E90*D90 -> 0
B91: Breaker_10-12T | C91: Day | E91: ='Equip&HIRE_Master'!D23 -> 0 | F91: =E91*D91 -> 0
B92: Breaker_13-15T | C92: Day | E92: ='Equip&HIRE_Master'!D24 -> 203 | F92: =E92*D92 -> 0
B93: Auger Drive_10-12T | E93: ='Equip&HIRE_Master'!D25 -> 0 | F93: =E93*D93 -> 0
B94: 300Dia Auger Drill | E94: ='Equip&HIRE_Master'!D26 -> 0 | F94: =E94*D94 -> 0
E95: ='Equip&HIRE_Master'!D27 -> 0 | F95: =E95*D95 -> 0
B96: 1.25T_Tipper Truck | C96: Day | E96: ='Equip&HIRE_Master'!D28 -> 205 | F96: =E96*D96 -> 0
B97: 2-4T_Tipper Truck | C97: Day | E97: ='Equip&HIRE_Master'!D29 -> 166.98 | F97: =E97*D97 -> 0
B98: <6T_Tipper Truck | C98: Day | D98: 18 | E98: ='Equip&HIRE_Master'!D30 -> 171.42857 | F98: =E98*D98 -> 3085.7143 | H98: Phase 7 plant: <6T tipper - Phase 7 roll-up 18 d
E99: ='Equip&HIRE_Master'!D31 -> 0 | F99: =E99*D99 -> 0
B100: <10T_Articulated Site Tipper | C100: Day | E100: ='Equip&HIRE_Master'!D32 -> 0 | F100: =E100*D100 -> 0
B101: Upright Rammer_Wacker | C101: Day | D101: 14 | E101: ='Equip&HIRE_Master'!D33 -> 34.285714 | F101: =E101*D101 -> 480 | H101: Phase 7 plant: Wacker - site share of Phase 7 roll-up 28 d
B102: Trench Roller_Dbl Drum_Remote | C102: Day | D102: 22 | E102: ='Equip&HIRE_Master'!D34 -> 165 | F102: =E102*D102 -> 3630 | H102: Phase 7 plant: Trench roller: T1-03 6 + T2-01 5 + T2-04 6 + T2-07 5
B103: <26Ft_Scissor Lift - Diesel | C103: Day | E103: ='Equip&HIRE_Master'!D35 -> 0 | F103: =E103*D103 -> 0
B104: <26Ft_Scissor Lift - Elec | C104: Day | E104: 300 | F104: =E104*D104 -> 0
B105: <34Ft_Boom Lift - Diesel | C105: Day | E105: ='Equip&HIRE_Master'!D37 -> 0 | F105: =E105*D105 -> 0
B106: <34Ft_Boom Lift - Elec | C106: Day | E106: ='Equip&HIRE_Master'!D38 -> 0 | F106: =E106*D106 -> 0
E107: ='Equip&HIRE_Master'!D39 -> 0 | F107: =E107*D107 -> 0
B108: Porta Loo_No Tank | C108: Day | E108: ='Equip&HIRE_Master'!D40 -> 5.46 | F108: =E108*D108 -> 0
B109: 6*3m Demantable Lunchroom - COMPLETE | C109: Day | E109: ='Equip&HIRE_Master'!D41 -> 23 | F109: =E109*D109 -> 0
B110: 6*3m Demantable Office - COMPLETE | C110: Day | E110: ='Equip&HIRE_Master'!D42 -> 23 | F110: =E110*D110 -> 0
B111: 20Ft Shipping Container | C111: Day | E111: ='Equip&HIRE_Master'!D43 -> 0 | F111: =E111*D111 -> 0
B112: Quick Cut Demo Saw | C112: Day | E112: ='Equip&HIRE_Master'!D44 -> 0 | F112: =E112*D112 -> 0
B113: Sngl Ph_6KVA Genset | C113: Day | E113: ='Equip&HIRE_Master'!D45 -> 0 | F113: =E113*D113 -> 0
...

Sheet LabourProject Rates_Master
B1: Project:
B2: Tricore -
B3: Stage 1 Version 1
A4: Item | I4: Source
B6: BASED ON:
B7: Work ROSTER Example #3 - 6-Day Week, 10Hr Days, Stay @ Rocky for W/E, Return Every 2nd W/E. (FLY) | I7: frozen from [2] CQU ROK_Staff Costing.V1_Steph (2024 FIFO build) - link severed 26/07/26; re-based x1.08 below
B8: Working Days/Month | C8: 21 | I8: frozen from [2] CQU ROK_Staff Costing.V1_Steph (2024 FIFO build) - link severed 26/07/26; re-based x1.08 below
B9: No-Work Days/Month | C9: 7 | I9: frozen from [2] CQU ROK_Staff Costing.V1_Steph (2024 FIFO build) - link severed 26/07/26; re-based x1.08 below
B10: Avrg Hours / Month | C10: 210 | I10: frozen from [2] CQU ROK_Staff Costing.V1_Steph (2024 FIFO build) - link severed 26/07/26; re-based x1.08 below
B12: STAFF
C13: Unit | D13: REQ | E13: Cost ex GST | F13: Total ex GST
B14: TRADESMAN_LEADING HAND | C14: HR | D14: 1 | E14: =E17/$C$10 -> 132.96343 | F14: =D14*E14 -> 132.96343 | I14: frozen from [2] CQU ROK_Staff Costing.V1_Steph (2024 FIFO build) - link severed 26/07/26; re-based x1.08 below
B15: ** for Roster Examples # 3 | C15: DAY | D15: 1 | E15: =E17/$C$8 -> 1329.6343 | F15: =D15*E15 -> 1329.6343
B16: =B14 -> TRADESMAN_LEADING HAND | C16: WEEK | D16: 1 | E16: =E17/4 -> 6980.58 | F16: =D16*E16 -> 6980.58
C17: MONTH | D17: 1 | E17: 27922.32 | F17: =D17*E17 -> 27922.32 | I17: LH monthly: $25,854 (frozen [2]) x 1.08 ROK uplift = $27,922.32 literal; hr/day/week formula-derived (/210, /21, /4) -> $132.9634/hr
B19: QTY Staff in Crew | C19: =COUNTA(B16,B17,B18) -> 1
B21: TRADESMAN_PLUMBER_OPERATOR | C21: HR | D21: 1 | E21: =E24/$C$10 -> 101.64579 | F21: =D21*E21 -> 101.64579 | I21: frozen from [2] CQU ROK_Staff Costing.V1_Steph (2024 FIFO build) - link severed 26/07/26; re-based x1.08 below
B22: ** for Roster Examples # 3 | C22: DAY | D22: 1 | E22: =E24/$C$8 -> 1016.4579 | F22: =D22*E22 -> 1016.4579
B23: =B21 -> TRADESMAN_PLUMBER_OPERATOR | C23: WEEK | D23: 1 | E23: =E24/4 -> 5336.404 | F23: =D23*E23 -> 5336.404
C24: MONTH | D24: 1 | E24: 21345.616 | F24: =D24*E24 -> 21345.616 | I24: Trades monthly: $19,764.4593 (frozen [2]) x 1.08 = $21,345.6160 literal -> $101.6458/hr
B26: QTY Staff in Crew | C26: =COUNTA(B23,B24,B25) -> 1
B28: T/A & Apprentice | C28: HR | D28: 1 | E28: =E31/$C$10 -> 82.951029 | F28: =D28*E28 -> 82.951029 | I28: frozen from [2] CQU ROK_Staff Costing.V1_Steph (2024 FIFO build) - link severed 26/07/26; re-based x1.08 below
B29: ** for Roster Examples # 3 | C29: DAY | D29: 1 | E29: =E31/$C$8 -> 829.51029 | F29: =D29*E29 -> 829.51029
B30: =B28 -> T/A & Apprentice | C30: WEEK | D30: 1 | E30: =E31/4 -> 4354.929 | F30: =D30*E30 -> 4354.929
C31: MONTH | D31: 1 | E31: 17419.716 | F31: =D31*E31 -> 17419.716 | I31: T/A monthly: $16,129.3667 (frozen [2]) x 1.08 = $17,419.7160 literal -> $82.9510/hr
B33: QTY Staff in Crew | C33: =COUNTA(B30,B31,B32) -> 1
B36: Crew #1 - InGround Drainage | C36: HR | D36: 1 | E36: =E39/$C$10 -> 286.24261 | F36: =D36*E36 -> 286.24261
B37: ** for Roster Examples # 3 | C37: DAY | D37: 1 | E37: =E39/$C$8 -> 2862.4261 | F37: =D37*E37 -> 2862.4261
B38: =B21 -> TRADESMAN_PLUMBER_OPERATOR | C38: WEEK | D38: 1 | E38: =E39/4 -> 15027.737 | F38: =D38*E38 -> 15027.737
B39: =B21 -> TRADESMAN_PLUMBER_OPERATOR | C39: MONTH | D39: 1 | E39: =(E24*2)+E31 -> 60110.948 | F39: =D39*E39 -> 60110.948
B40: =B28 -> T/A & Apprentice
B41: QTY Staff in Crew | C41: =COUNTA(B38,B39,B40) -> 3
B43: Crew #2 - InGround Water/Fire | C43: HR | D43: 1 | E43: =E46/$C$10 -> 286.24261 | F43: =D43*E43 -> 286.24261
B44: ** for Roster Examples # 3 | C44: DAY | D44: 1 | E44: =E46/$C$8 -> 2862.4261 | F44: =D44*E44 -> 2862.4261
B45: =B21 -> TRADESMAN_PLUMBER_OPERATOR | C45: WEEK | D45: 1 | E45: =E46/4 -> 15027.737 | F45: =D45*E45 -> 15027.737
B46: =B21 -> TRADESMAN_PLUMBER_OPERATOR | C46: MONTH | D46: 1 | E46: =(E24*2)+E31 -> 60110.948 | F46: =D46*E46 -> 60110.948
B47: =B28 -> T/A & Apprentice
B48: QTY Staff in Crew | C48: =COUNTA(B45,B46,B47) -> 3
B51: Crew #3 - Above Ground Drainage | C51: HR | D51: 1 | E51: =E43 -> 286.24261 | F51: =D51*E51 -> 286.24261
B52: =B44 -> ** for Roster Examples # 3 | C52: DAY | D52: 1 | E52: =E44 -> 2862.4261 | F52: =D52*E52 -> 2862.4261
B53: =B45 -> TRADESMAN_PLUMBER_OPERATOR | C53: WEEK | D53: 1 | E53: =E45 -> 15027.737 | F53: =D53*E53 -> 15027.737
B54: =B46 -> TRADESMAN_PLUMBER_OPERATOR | C54: MONTH | D54: 1 | E54: =E46 -> 60110.948 | F54: =D54*E54 -> 60110.948
B55: =B47 -> T/A & Apprentice
B56: QTY Staff in Crew | C56: =COUNTA(B53,B54,B55) -> 3
B59: Crew #4 - Above Ground WATER/FIRE | C59: HR | D59: 1 | E59: =E51 -> 286.24261 | F59: =D59*E59 -> 286.24261
B60: =B52 -> ** for Roster Examples # 3 | C60: DAY | D60: 1 | E60: =E52 -> 2862.4261 | F60: =D60*E60 -> 2862.4261
B61: =B53 -> TRADESMAN_PLUMBER_OPERATOR | C61: WEEK | D61: 1 | E61: =E53 -> 15027.737 | F61: =D61*E61 -> 15027.737
B62: =B54 -> TRADESMAN_PLUMBER_OPERATOR | C62: MONTH | D62: 1 | E62: =E54 -> 60110.948 | F62: =D62*E62 -> 60110.948
B63: =B55 -> T/A & Apprentice
B64: QTY Staff in Crew | C64: =COUNTA(B61,B62,B63) -> 3
B67: Crew #5 - Above Ground FitOff / Misc | C67: HR | D67: 1 | E67: =E59 -> 286.24261 | F67: =D67*E67 -> 286.24261
B68: =B60 -> ** for Roster Examples # 3 | C68: DAY | D68: 1 | E68: =E60 -> 2862.4261 | F68: =D68*E68 -> 2862.4261
B69: =B61 -> TRADESMAN_PLUMBER_OPERATOR | C69: WEEK | D69: 1 | E69: =E61 -> 15027.737 | F69: =D69*E69 -> 15027.737
B70: =B62 -> TRADESMAN_PLUMBER_OPERATOR | C70: MONTH | D70: 1 | E70: =E62 -> 60110.948 | F70: =D70*E70 -> 60110.948
B71: =B63 -> T/A & Apprentice
B72: QTY Staff in Crew | C72: =COUNTA(B69,B70,B71) -> 3
B75: Crew #6 - DEMO | C75: HR | D75: 1 | E75: =E78/$C$10 -> 184.59682 | F75: =D75*E75 -> 184.59682
B76: =B68 -> ** for Roster Examples # 3 | C76: DAY | D76: 1 | E76: =E78/$C$8 -> 1845.9682 | F76: =D76*E76 -> 1845.9682
B77: =B69 -> TRADESMAN_PLUMBER_OPERATOR | C77: WEEK | D77: 1 | E77: =E78/4 -> 9691.333 | F77: =D77*E77 -> 9691.333
B78: =B71 -> T/A & Apprentice | C78: MONTH | D78: 1 | E78: =(E24)+E31 -> 38765.332 | F78: =D78*E78 -> 38765.332
B80: QTY Staff in Crew | C80: =COUNTA(B77,B78) -> 2
A85: `
B87: FULL team, FULL Duration, as per Program | C87: HR | D87: 0 | E87: =E90/$C$10 -> 705.44865 | F87: =D87*E87 -> 0
B88: ** for Roster Examples # 3 | C88: DAY | D88: 0 | E88: =E90/$C$8 -> 7054.4865 | F88: =D88*E88 -> 0
B89: =B36 -> Crew #1 - InGround Drainage | C89: WEEK | D89: 0 | E89: =E90/4 -> 37036.054 | F89: =D89*E89 -> 0
B90: =B43 -> Crew #2 - InGround Water/Fire | C90: MONTH | D90: 4 | E90: =E46+E39+E17 -> 148144.22 | F90: =D90*E90 -> 592576.86
B91: =B14 -> TRADESMAN_LEADING HAND
B92: QTY Staff in Crew | C92: =C48+C41+C19 -> 7
A94: `
B97: ACCOMODATION
C98: Unit | D98: REQ | E98: Cost | F98: Total EX GST
B100: =Accomodation_Master!B266 -> Full Apartment / TownHouse / Unit - VIA AGENT | E100: *Changed to ex GST | G100: 11
B101: ** for Roster Examples # 3 | C101: NIGHT | D101: 0 | E101: =E102/7 -> 164.50216 | F101: =D101*E101 -> 0
C102: WEEK | D102: 0 | E102: =E103/4 -> 1151.5152 | F102: =D102*E102 -> 0
B103: =B21 -> TRADESMAN_PLUMBER_OPERATOR | C103: MONTH | D103: 0 | E103: =(Accomodation_Master!E308)-(Accomodation_Master!E308/G100) -> 4606.0606 | F103: =D103*E103 -> 0
B104: =B21 -> TRADESMAN_PLUMBER_OPERATOR
B105: =B28 -> T/A & Apprentice
B106: QTY Staff in Crew | C106: =COUNTA(B103,B104,B105) -> 3
B108: Individual - PER PERSON | E108: *Changed to ex GST | G108: 11
B109: ** for Roster Examples # 3 | C109: NIGHT | D109: 0 | E109: =(Accomodation_Master!F364)-(Accomodation_Master!F364/G108) -> 103.24675 | F109: =D109*E109 -> 0
B110: =Accomodation_Master!$B$364 -> TCS Cost Per Person - Private Unit - NO SHARE - Nightly Booking (average allowance) | C110: WEEK | D110: 0 | E110: =E109*7 -> 722.72727 | F110: =D110*E110 -> 0
C111: MONTH | D111: 0 | E111: =E110*4 -> 2890.9091 | F111: =D111*E111 -> 0

Sheet Material Rates_Master
A3: FIRE SERVICES - IN GROUND
A4: Description | B4: Unit | D4: Rate | F4: Total | I4: Qty | N4: Source
A5: 200 HDPE PN16 SDR11 - REDLINE | B5: m | D5: 33.920833 | F5: =I5*D5 -> 16282 | G5: COMPLETED don’t edit | I5: 480 | N5: frozen from [3] 240614 Pipe & Fittings Price Comparison (Jun-2024 cache) - link severed 26/07/26; >=2yr old at 2027 start - Phase 5 re-source pending
A6: 180 HDPE PN16 SDR11 - REDLINE | B6: m | D6: 25.466667 | F6: =I6*D6 -> 128657.6 | I6: 5052 | N6: frozen from [3] 240614 Pipe & Fittings Price Comparison (Jun-2024 cache) - link severed 26/07/26; >=2yr old at 2027 start - Phase 5 re-source pending
A7: 125 HDPE PN16 SDR11 - REDLINE | B7: m | D7: 12.314167 | F7: =I7*D7 -> 13151.53 | I7: 1068 | N7: frozen from [3] 240614 Pipe & Fittings Price Comparison (Jun-2024 cache) - link severed 26/07/26; >=2yr old at 2027 start - Phase 5 re-source pending
A8: 32 HDPE PN16 SDR11 - BLUELINE | B8: m | D8: 1.2159 | F8: =I8*D8 -> 121.59 | I8: 100 | N8: frozen from [3] 240614 Pipe & Fittings Price Comparison (Jun-2024 cache) - link severed 26/07/26; >=2yr old at 2027 start - Phase 5 re-source pending
A10: 200 EF Coupler | B10: ea | D10: 44.06 | F10: =I10*D10 -> 1321.8 | G10: COMPLETED don’t edit | I10: 30 | N10: frozen from [3] 240614 Pipe & Fittings Price Comparison (Jun-2024 cache) - link severed 26/07/26; >=2yr old at 2027 start - Phase 5 re-source pending
A11: 180 EF Coupler | B11: ea | D11: 25.72 | F11: =I11*D11 -> 5144 | I11: 200 | N11: frozen from [3] 240614 Pipe & Fittings Price Comparison (Jun-2024 cache) - link severed 26/07/26; >=2yr old at 2027 start - Phase 5 re-source pending
A12: 125 EF Coupler | B12: ea | D12: 14.11 | F12: =I12*D12 -> 1411 | I12: 100 | N12: frozen from [3] 240614 Pipe & Fittings Price Comparison (Jun-2024 cache) - link severed 26/07/26; >=2yr old at 2027 start - Phase 5 re-source pending
A13: 200 EF 45DFeg Bend | B13: ea | D13: 109.16 | F13: =I13*D13 -> 218.32 | I13: 2 | N13: frozen from [3] 240614 Pipe & Fittings Price Comparison (Jun-2024 cache) - link severed 26/07/26; >=2yr old at 2027 start - Phase 5 re-source pending
A14: 180 EF 45DFeg Bend | B14: ea | D14: 97.97 | F14: =I14*D14 -> 12736.1 | I14: 130 | N14: frozen from [3] 240614 Pipe & Fittings Price Comparison (Jun-2024 cache) - link severed 26/07/26; >=2yr old at 2027 start - Phase 5 re-source pending
A15: 125 EF 45DFeg Bend | B15: ea | D15: 44.69 | F15: =I15*D15 -> 1117.25 | G15: COMPLETED don’t edit | I15: 25 | N15: frozen from [3] 240614 Pipe & Fittings Price Comparison (Jun-2024 cache) - link severed 26/07/26; >=2yr old at 2027 start - Phase 5 re-source pending
A16: 200 EF 90DFeg Bend | B16: ea | D16: 109.16 | F16: =I16*D16 -> 654.96 | I16: 6 | N16: frozen from [3] 240614 Pipe & Fittings Price Comparison (Jun-2024 cache) - link severed 26/07/26; >=2yr old at 2027 start - Phase 5 re-source pending
A17: 180 EF 90DFeg Bend | B17: ea | D17: 97.81 | F17: =I17*D17 -> 7824.8 | I17: 80 | N17: frozen from [3] 240614 Pipe & Fittings Price Comparison (Jun-2024 cache) - link severed 26/07/26; >=2yr old at 2027 start - Phase 5 re-source pending
A18: 125 EF 90DFeg Bend | B18: ea | D18: 44.65 | F18: =I18*D18 -> 3572 | I18: 80 | N18: frozen from [3] 240614 Pipe & Fittings Price Comparison (Jun-2024 cache) - link severed 26/07/26; >=2yr old at 2027 start - Phase 5 re-source pending
A19: 200 EF TEE | B19: ea | D19: 109.75 | F19: =I19*D19 -> 329.25 | I19: 3 | N19: frozen from [3] 240614 Pipe & Fittings Price Comparison (Jun-2024 cache) - link severed 26/07/26; >=2yr old at 2027 start - Phase 5 re-source pending
A20: 180 EF TEE | B20: ea | D20: 114.28 | F20: =I20*D20 -> 4571.2 | G20: COMPLETED don’t edit | I20: 40 | N20: frozen from [3] 240614 Pipe & Fittings Price Comparison (Jun-2024 cache) - link severed 26/07/26; >=2yr old at 2027 start - Phase 5 re-source pending
A21: 125 EF TEE | B21: ea | D21: 49.25 | F21: =I21*D21 -> 49.25 | I21: 1 | N21: frozen from [3] 240614 Pipe & Fittings Price Comparison (Jun-2024 cache) - link severed 26/07/26; >=2yr old at 2027 start - Phase 5 re-source pending
A22: 200*180 EF TEE | B22: ea | D22: 209.47 | F22: =I22*D22 -> 418.94 | I22: 2 | N22: frozen from [3] 240614 Pipe & Fittings Price Comparison (Jun-2024 cache) - link severed 26/07/26; >=2yr old at 2027 start - Phase 5 re-source pending
A23: 200*125 EF TEE | B23: ea | D23: 218.42 | F23: =I23*D23 -> 436.84 | I23: 2 | N23: frozen from [3] 240614 Pipe & Fittings Price Comparison (Jun-2024 cache) - link severed 26/07/26; >=2yr old at 2027 start - Phase 5 re-source pending
A24: 180*125 EF TEE | B24: ea | D24: 122.13 | F24: =I24*D24 -> 4885.2 | I24: 40 | N24: frozen from [3] 240614 Pipe & Fittings Price Comparison (Jun-2024 cache) - link severed 26/07/26; >=2yr old at 2027 start - Phase 5 re-source pending
A25: 200*180 EF Reducer | B25: ea | D25: 125.62 | F25: =I25*D25 -> 502.48 | G25: COMPLETED don’t edit | I25: 4 | N25: frozen from [3] 240614 Pipe & Fittings Price Comparison (Jun-2024 cache) - link severed 26/07/26; >=2yr old at 2027 start - Phase 5 re-source pending
A26: 180*125 EF Reducer | B26: ea | D26: 60.1 | F26: =I26*D26 -> 1202 | I26: 20 | N26: frozen from [3] 240614 Pipe & Fittings Price Comparison (Jun-2024 cache) - link severed 26/07/26; >=2yr old at 2027 start - Phase 5 re-source pending
A27: 200PE*8"(200m) - MaxiStub W/Backing Ring | B27: ea | D27: 342.35 | F27: =I27*D27 -> 3423.5 | I27: 10 | N27: frozen from [3] 240614 Pipe & Fittings Price Comparison (Jun-2024 cache) - link severed 26/07/26; >=2yr old at 2027 start - Phase 5 re-source pending
A28: 180PE*6"(150mm) - MaxiStub W/Backing Ring | B28: ea | D28: 129.77 | F28: =I28*D28 -> 7786.2 | I28: 60 | N28: frozen from [3] 240614 Pipe & Fittings Price Comparison (Jun-2024 cache) - link severed 26/07/26; >=2yr old at 2027 start - Phase 5 re-source pending
A29: 125PE*4" (100mm) - MaxiStub W/Backing Ring | B29: ea | D29: 92.67 | F29: =I29*D29 -> 1853.4 | I29: 20 | N29: frozen from [3] 240614 Pipe & Fittings Price Comparison (Jun-2024 cache) - link severed 26/07/26; >=2yr old at 2027 start - Phase 5 re-source pending
A30: 180mm PE x 150mm GALV ADAPTER - PLASSON Brand | B30: ea | D30: 313.19 | F30: =I30*D30 -> 3131.9 | G30: COMPLETED don’t edit | I30: 10 | N30: frozen from [3] 240614 Pipe & Fittings Price Comparison (Jun-2024 cache) - link severed 26/07/26; >=2yr old at 2027 start - Phase 5 re-source pending
A31: 125mm PE x 100mm GALV ADAPTER - PLASSON Brand | B31: ea | D31: 204.11 | F31: =I31*D31 -> 10205.5 | I31: 50 | N31: frozen from [3] 240614 Pipe & Fittings Price Comparison (Jun-2024 cache) - link severed 26/07/26; >=2yr old at 2027 start - Phase 5 re-source pending
A33: 180mm PE x 150mm GALV ADAPTER | B33: ea | D33: 315.71 | F33: =I33*D33 -> 3157.1 | I33: 10 | N33: frozen from [3] 240614 Pipe & Fittings Price Comparison (Jun-2024 cache) - link severed 26/07/26; >=2yr old at 2027 start - Phase 5 re-source pending
A34: 125mm PE x 100mm GALV ADAPTER | B34: ea | D34: 201.43 | F34: =I34*D34 -> 10071.5 | I34: 50 | N34: frozen from [3] 240614 Pipe & Fittings Price Comparison (Jun-2024 cache) - link severed 26/07/26; >=2yr old at 2027 start - Phase 5 re-source pending
A35: 200 Long SPIG 45DFeg Bend | B35: ea | D35: 68.54 | F35: =I35*D35 -> 137.08 | G35: COMPLETED don’t edit | I35: 2 | N35: frozen from [3] 240614 Pipe & Fittings Price Comparison (Jun-2024 cache) - link severed 26/07/26; >=2yr old at 2027 start - Phase 5 re-source pending
A36: 180 Long SPIG 45DFeg Bend | B36: ea | D36: 64.46 | F36: =I36*D36 -> 8379.8 | I36: 130 | N36: frozen from [3] 240614 Pipe & Fittings Price Comparison (Jun-2024 cache) - link severed 26/07/26; >=2yr old at 2027 start - Phase 5 re-source pending
A37: 125 Long SPIG 45DFeg Bend | B37: ea | D37: 38.76 | F37: =I37*D37 -> 969 | I37: 25 | N37: frozen from [3] 240614 Pipe & Fittings Price Comparison (Jun-2024 cache) - link severed 26/07/26; >=2yr old at 2027 start - Phase 5 re-source pending
A38: 200 Long SPIG 90DFeg Bend | B38: ea | D38: 86.17 | F38: =I38*D38 -> 517.02 | I38: 6 | N38: frozen from [3] 240614 Pipe & Fittings Price Comparison (Jun-2024 cache) - link severed 26/07/26; >=2yr old at 2027 start - Phase 5 re-source pending
A39: 180 Long SPIG 90DFeg Bend | B39: ea | D39: 68.11 | F39: =I39*D39 -> 5448.8 | I39: 80 | N39: frozen from [3] 240614 Pipe & Fittings Price Comparison (Jun-2024 cache) - link severed 26/07/26; >=2yr old at 2027 start - Phase 5 re-source pending
A40: 125 Long SPIG 90DFeg Bend | B40: ea | D40: 31.65 | F40: =I40*D40 -> 2532 | G40: COMPLETED don’t edit | I40: 80 | N40: frozen from [3] 240614 Pipe & Fittings Price Comparison (Jun-2024 cache) - link severed 26/07/26; >=2yr old at 2027 start - Phase 5 re-source pending
A41: 200 Long SPIG TEE | B41: ea | D41: 127.64 | F41: =I41*D41 -> 382.92 | I41: 3 | N41: frozen from [3] 240614 Pipe & Fittings Price Comparison (Jun-2024 cache) - link severed 26/07/26; >=2yr old at 2027 start - Phase 5 re-source pending
A42: 180 Long SPIG TEE | B42: ea | D42: 114.22 | F42: =I42*D42 -> 4568.8 | I42: 40 | N42: frozen from [3] 240614 Pipe & Fittings Price Comparison (Jun-2024 cache) - link severed 26/07/26; >=2yr old at 2027 start - Phase 5 re-source pending
A43: 125 Long SPIG TEE | B43: ea | D43: 38.26 | F43: =I43*D43 -> 38.26 | I43: 1 | N43: frozen from [3] 240614 Pipe & Fittings Price Comparison (Jun-2024 cache) - link severed 26/07/26; >=2yr old at 2027 start - Phase 5 re-source pending
A44: 200*180 Long SPIG TEE | B44: ea | D44: 183.48 | F44: =I44*D44 -> 366.96 | I44: 2 | N44: frozen from [3] 240614 Pipe & Fittings Price Comparison (Jun-2024 cache) - link severed 26/07/26; >=2yr old at 2027 start - Phase 5 re-source pending
A45: 200*125 Long SPIG TEE | B45: ea | D45: 192.43 | F45: =I45*D45 -> 384.86 | G45: COMPLETED don’t edit | I45: 2 | N45: frozen from [3] 240614 Pipe & Fittings Price Comparison (Jun-2024 cache) - link severed 26/07/26; >=2yr old at 2027 start - Phase 5 re-source pending
A46: 180*125 Long SPIG TEE | B46: ea | D46: 185.71 | F46: =I46*D46 -> 7428.4 | I46: 40 | N46: frozen from [3] 240614 Pipe & Fittings Price Comparison (Jun-2024 cache) - link severed 26/07/26; >=2yr old at 2027 start - Phase 5 re-source pending
A47: 200*180 Long SPIG Reducer | B47: ea | D47: 55.84 | F47: =I47*D47 -> 223.36 | I47: 4 | N47: frozen from [3] 240614 Pipe & Fittings Price Comparison (Jun-2024 cache) - link severed 26/07/26; >=2yr old at 2027 start - Phase 5 re-source pending
A48: 180*125 Long SPIG Reducer | B48: ea | D48: 39.83 | F48: =I48*D48 -> 796.6 | I48: 20 | N48: frozen from [3] 240614 Pipe & Fittings Price Comparison (Jun-2024 cache) - link severed 26/07/26; >=2yr old at 2027 start - Phase 5 re-source pending
D49: 0 | N49: frozen from [3] 240614 Pipe & Fittings Price Comparison (Jun-2024 cache) - link severed 26/07/26; >=2yr old at 2027 start - Phase 5 re-source pending
A50: 200 FL DICL Sluice Valve | B50: ea | D50: 679.41 | F50: =I50*D50 -> 4076.46 | G50: COMPLETED don’t edit | I50: 6 | N50: frozen from [3] 240614 Pipe & Fittings Price Comparison (Jun-2024 cache) - link severed 26/07/26; >=2yr old at 2027 start - Phase 5 re-source pending
A51: 150 FL DICL Sluice Valve | B51: ea | D51: 323.53 | F51: =I51*D51 -> 19411.8 | I51: 60 | N51: frozen from [3] 240614 Pipe & Fittings Price Comparison (Jun-2024 cache) - link severed 26/07/26; >=2yr old at 2027 start - Phase 5 re-source pending
A52: 100 FL DICL Sluice Valve | B52: ea | D52: 202.94 | F52: =I52*D52 -> 6088.2 | I52: 30 | N52: frozen from [3] 240614 Pipe & Fittings Price Comparison (Jun-2024 cache) - link severed 26/07/26; >=2yr old at 2027 start - Phase 5 re-source pending
A53: Valve Spindle Riser - 600Long | B53: ea | D53: 136.94 | F53: =I53*D53 -> 13146.24 | I53: 96 | N53: frozen from [3] 240614 Pipe & Fittings Price Comparison (Jun-2024 cache) - link severed 26/07/26; >=2yr old at 2027 start - Phase 5 re-source pending
A54: Valve Box - Cast Iron Trafficable - Rectangle Type "V" | B54: ea | D54: 123.53 | F54: =I54*D54 -> 8647.1 | I54: 70 | N54: frozen from [3] 240614 Pipe & Fittings Price Comparison (Jun-2024 cache) - link severed 26/07/26; >=2yr old at 2027 start - Phase 5 re-source pending
A55: Valve Box - Non-Trafficable - Plastic Surround with CI Drop In "V" | B55: ea | D55: 98.82 | F55: =I55*D55 -> 2964.6 | G55: COMPLETED don’t edit | I55: 30 | N55: frozen from [3] 240614 Pipe & Fittings Price Comparison (Jun-2024 cache) - link severed 26/07/26; >=2yr old at 2027 start - Phase 5 re-source pending
A57: 200*150mm DICL FL Reducer | B57: ea | D57: 291.18 | F57: =I57*D57 -> 582.36 | I57: 2 | N57: frozen from [3] 240614 Pipe & Fittings Price Comparison (Jun-2024 cache) - link severed 26/07/26; >=2yr old at 2027 start - Phase 5 re-source pending
A58: 200*100mm DICL FL Reducer | B58: ea | D58: 330 | F58: =I58*D58 -> 660 | I58: 2 | N58: frozen from [3] 240614 Pipe & Fittings Price Comparison (Jun-2024 cache) - link severed 26/07/26; >=2yr old at 2027 start - Phase 5 re-source pending
A59: 150*100mm DICL FL Reducer | B59: ea | D59: 156 | F59: =I59*D59 -> 936 | I59: 6 | N59: frozen from [3] 240614 Pipe & Fittings Price Comparison (Jun-2024 cache) - link severed 26/07/26; >=2yr old at 2027 start - Phase 5 re-source pending
A60: 150mm DICL FL * SP Adapter | B60: ea | D60: 106.24 | F60: =I60*D60 -> 1274.88 | G60: COMPLETED don’t edit | I60: 12 | N60: frozen from [3] 240614 Pipe & Fittings Price Comparison (Jun-2024 cache) - link severed 26/07/26; >=2yr old at 2027 start - Phase 5 re-source pending
A61: 100mm DICL FL * SP Adapter | B61: ea | D61: 70.59 | F61: =I61*D61 -> 564.72 | I61: 8 | N61: frozen from [3] 240614 Pipe & Fittings Price Comparison (Jun-2024 cache) - link severed 26/07/26; >=2yr old at 2027 start - Phase 5 re-source pending
A62: 200mm DICL FL 90Deg Bend | B62: ea | D62: 516.35 | F62: =I62*D62 -> 1032.7 | I62: 2 | N62: frozen from [3] 240614 Pipe & Fittings Price Comparison (Jun-2024 cache) - link severed 26/07/26; >=2yr old at 2027 start - Phase 5 re-source pending
A63: 150mm DICL FL 90Deg Bend | B63: ea | D63: 198.88 | F63: =I63*D63 -> 1591.04 | I63: 8 | N63: frozen from [3] 240614 Pipe & Fittings Price Comparison (Jun-2024 cache) - link severed 26/07/26; >=2yr old at 2027 start - Phase 5 re-source pending
A64: 100mm DICL FL 90Deg Bend | B64: ea | D64: 108.71 | F64: =I64*D64 -> 434.84 | I64: 4 | N64: frozen from [3] 240614 Pipe & Fittings Price Comparison (Jun-2024 cache) - link severed 26/07/26; >=2yr old at 2027 start - Phase 5 re-source pending
A65: 200mm DICL FL TEE | B65: ea | D65: 672.65 | F65: =I65*D65 -> 1345.3 | G65: COMPLETED don’t edit | I65: 2 | N65: frozen from [3] 240614 Pipe & Fittings Price Comparison (Jun-2024 cache) - link severed 26/07/26; >=2yr old at 2027 start - Phase 5 re-source pending
A66: 150mm DICL FL TEE | B66: ea | D66: 228.24 | F66: =I66*D66 -> 3423.6 | I66: 15 | N66: frozen from [3] 240614 Pipe & Fittings Price Comparison (Jun-2024 cache) - link severed 26/07/26; >=2yr old at 2027 start - Phase 5 re-source pending
A67: 100mm DICL FL TEE | B67: ea | D67: 128.24 | F67: =I67*D67 -> 256.48 | I67: 2 | N67: frozen from [3] 240614 Pipe & Fittings Price Comparison (Jun-2024 cache) - link severed 26/07/26; >=2yr old at 2027 start - Phase 5 re-source pending
A68: 200*150*200 DICL FL TEE | B68: ea | D68: 536.76 | F68: =I68*D68 -> 1073.52 | I68: 2 | N68: frozen from [3] 240614 Pipe & Fittings Price Comparison (Jun-2024 cache) - link severed 26/07/26; >=2yr old at 2027 start - Phase 5 re-source pending
A69: 200*100*200 DICL FL TEE | B69: ea | D69: 576.47 | F69: =I69*D69 -> 576.47 | I69: 1 | N69: frozen from [3] 240614 Pipe & Fittings Price Comparison (Jun-2024 cache) - link severed 26/07/26; >=2yr old at 2027 start - Phase 5 re-source pending
A70: 150-100-150 DICL FL TEE | B70: ea | D70: 198.82 | F70: =I70*D70 -> 1192.92 | G70: COMPLETED don’t edit | I70: 6 | N70: frozen from [3] 240614 Pipe & Fittings Price Comparison (Jun-2024 cache) - link severed 26/07/26; >=2yr old at 2027 start - Phase 5 re-source pending
A71: 200mm DICL FL Pipe @ 1000 | B71: ea | D71: 898.82 | F71: =I71*D71 -> 898.82 | I71: 1 | N71: frozen from [3] 240614 Pipe & Fittings Price Comparison (Jun-2024 cache) - link severed 26/07/26; >=2yr old at 2027 start - Phase 5 re-source pending
A72: 200mm DICL FL Pipe @ 600 | B72: ea | D72: 640 | F72: =I72*D72 -> 640 | I72: 1 | N72: frozen from [3] 240614 Pipe & Fittings Price Comparison (Jun-2024 cache) - link severed 26/07/26; >=2yr old at 2027 start - Phase 5 re-source pending
A73: 200mm DICL FL Pipe @ 300 | B73: ea | D73: 355.29 | F73: =I73*D73 -> 355.29 | I73: 1 | N73: frozen from [3] 240614 Pipe & Fittings Price Comparison (Jun-2024 cache) - link severed 26/07/26; >=2yr old at 2027 start - Phase 5 re-source pending
A74: 150mm DICL FL Pipe @ 1000 | B74: ea | D74: 534.41 | F74: =I74*D74 -> 534.41 | I74: 1 | N74: frozen from [3] 240614 Pipe & Fittings Price Comparison (Jun-2024 cache) - link severed 26/07/26; >=2yr old at 2027 start - Phase 5 re-source pending
A75: 150mm DICL FL Pipe @ 600 | B75: ea | D75: 280 | F75: =I75*D75 -> 280 | G75: COMPLETED don’t edit | I75: 1 | N75: frozen from [3] 240614 Pipe & Fittings Price Comparison (Jun-2024 cache) - link severed 26/07/26; >=2yr old at 2027 start - Phase 5 re-source pending
A76: 150mm DICL FL Pipe @ 450 | B76: ea | D76: 236.47 | F76: =I76*D76 -> 236.47 | I76: 1 | N76: frozen from [3] 240614 Pipe & Fittings Price Comparison (Jun-2024 cache) - link severed 26/07/26; >=2yr old at 2027 start - Phase 5 re-source pending
A77: 150mm DICL FL Pipe @ 300 | B77: ea | D77: 178.8 | F77: =I77*D77 -> 1430.4 | I77: 8 | N77: frozen from [3] 240614 Pipe & Fittings Price Comparison (Jun-2024 cache) - link severed 26/07/26; >=2yr old at 2027 start - Phase 5 re-source pending
A78: 100mm DICL FL Pipe @ 1000 | B78: ea | D78: 362.35 | F78: =I78*D78 -> 362.35 | I78: 1 | N78: frozen from [3] 240614 Pipe & Fittings Price Comparison (Jun-2024 cache) - link severed 26/07/26; >=2yr old at 2027 start - Phase 5 re-source pending
A79: 100mm DICL FL Pipe @ 600 | B79: ea | D79: 144.71 | F79: =I79*D79 -> 144.71 | I79: 1 | N79: frozen from [3] 240614 Pipe & Fittings Price Comparison (Jun-2024 cache) - link severed 26/07/26; >=2yr old at 2027 start - Phase 5 re-source pending
A80: 100mm DICL FL Pipe @ 450 | B80: ea | D80: 135.88 | F80: =I80*D80 -> 135.88 | G80: COMPLETED don’t edit | I80: 1 | N80: frozen from [3] 240614 Pipe & Fittings Price Comparison (Jun-2024 cache) - link severed 26/07/26; >=2yr old at 2027 start - Phase 5 re-source pending
A81: 100mm DICL FL Pipe @ 300 | B81: ea | D81: 76.47 | F81: =I81*D81 -> 305.88 | I81: 4 | N81: frozen from [3] 240614 Pipe & Fittings Price Comparison (Jun-2024 cache) - link severed 26/07/26; >=2yr old at 2027 start - Phase 5 re-source pending
A82: 150mm DICL FL Deadplate | B82: ea | D82: 67.65 | F82: =I82*D82 -> 1691.25 | I82: 25 | N82: frozen from [3] 240614 Pipe & Fittings Price Comparison (Jun-2024 cache) - link severed 26/07/26; >=2yr old at 2027 start - Phase 5 re-source pending
A83: 100mm DICL FL Deadplate | B83: ea | D83: 43.53 | F83: =I83*D83 -> 1958.85 | I83: 45 | N83: frozen from [3] 240614 Pipe & Fittings Price Comparison (Jun-2024 cache) - link severed 26/07/26; >=2yr old at 2027 start - Phase 5 re-source pending
A85: 200mm PE*DI Gasket Kit Complete | B85: ea | D85: 67.06 | F85: =I85*D85 -> 804.72 | G85: COMPLETED don’t edit | I85: 12 | N85: frozen from [3] 240614 Pipe & Fittings Price Comparison (Jun-2024 cache) - link severed 26/07/26; >=2yr old at 2027 start - Phase 5 re-source pending
A86: 200mm DI*DI Gasket Kit Complete | B86: ea | D86: 46.71 | F86: =I86*D86 -> 560.52 | I86: 12 | N86: frozen from [3] 240614 Pipe & Fittings Price Comparison (Jun-2024 cache) - link severed 26/07/26; >=2yr old at 2027 start - Phase 5 re-source pending
A87: 150mm PE*DI Gasket Kit Complete | B87: ea | D87: 60 | F87: =I87*D87 -> 3600 | I87: 60 | N87: frozen from [3] 240614 Pipe & Fittings Price Comparison (Jun-2024 cache) - link severed 26/07/26; >=2yr old at 2027 start - Phase 5 re-source pending
A88: 150mm DI*DI Gasket Kit Complete | B88: ea | D88: 42.35 | F88: =I88*D88 -> 2541 | I88: 60 | N88: frozen from [3] 240614 Pipe & Fittings Price Comparison (Jun-2024 cache) - link severed 26/07/26; >=2yr old at 2027 start - Phase 5 re-source pending
A89: 100mm PE*DI Gasket Kit Complete | B89: ea | D89: 24.71 | F89: =I89*D89 -> 741.3 | I89: 30 | N89: frozen from [3] 240614 Pipe & Fittings Price Comparison (Jun-2024 cache) - link severed 26/07/26; >=2yr old at 2027 start - Phase 5 re-source pending
A90: 100mm DI*DI Gasket Kit Complete | B90: ea | D90: 20 | F90: =I90*D90 -> 600 | G90: COMPLETED don’t edit | I90: 30 | N90: frozen from [3] 240614 Pipe & Fittings Price Comparison (Jun-2024 cache) - link severed 26/07/26; >=2yr old at 2027 start - Phase 5 re-source pending
A92: 150mm SS Gibault Adapter Coupling | B92: ea | D92: 108.71 | F92: =I92*D92 -> 2174.2 | I92: 20 | N92: frozen from [3] 240614 Pipe & Fittings Price Comparison (Jun-2024 cache) - link severed 26/07/26; >=2yr old at 2027 start - Phase 5 re-source pending
A93: 100mm SS Gibault Adapter Coupling | B93: ea | D93: 87.06 | F93: =I93*D93 -> 1218.84 | I93: 14 | N93: frozen from [3] 240614 Pipe & Fittings Price Comparison (Jun-2024 cache) - link severed 26/07/26; >=2yr old at 2027 start - Phase 5 re-source pending
A94: 180mm PE GRIPPER Adapter Coupling | B94: ea | D94: 305.88 | F94: =I94*D94 -> 3670.56 | I94: 12 | N94: frozen from [3] 240614 Pipe & Fittings Price Comparison (Jun-2024 cache) - link severed 26/07/26; >=2yr old at 2027 start - Phase 5 re-source pending
A95: 125mm PE GRIPPER Adapter Coupling | B95: ea | D95: 182.35 | F95: =I95*D95 -> 1458.8 | G95: COMPLETED don’t edit | I95: 8 | N95: frozen from [3] 240614 Pipe & Fittings Price Comparison (Jun-2024 cache) - link severed 26/07/26; >=2yr old at 2027 start - Phase 5 re-source pending
A96: 180mm PE GRIPPER * 150FL Adapter Coupling | B96: ea | D96: 229.41 | F96: =I96*D96 -> 917.64 | I96: 4 | N96: frozen from [3] 240614 Pipe & Fittings Price Comparison (Jun-2024 cache) - link severed 26/07/26; >=2yr old at 2027 start - Phase 5 re-source pending
A97: 125mm PE GRIPPER * 100FL Adapter Coupling | B97: ea | D97: 152.94 | F97: =I97*D97 -> 611.76 | I97: 4 | N97: frozen from [3] 240614 Pipe & Fittings Price Comparison (Jun-2024 cache) - link severed 26/07/26; >=2yr old at 2027 start - Phase 5 re-source pending
A98: 180mm PE GRIPPER Sluice Valve | B98: ea | D98: 690 | F98: =I98*D98 -> 13800 | I98: 20 | N98: frozen from [3] 240614 Pipe & Fittings Price Comparison (Jun-2024 cache) - link severed 26/07/26; >=2yr old at 2027 start - Phase 5 re-source pending
A99: 125mm PE GRIPPER Sluice Valve | B99: ea | D99: 408.47 | F99: =I99*D99 -> 8169.4 | I99: 20 | N99: frozen from [3] 240614 Pipe & Fittings Price Comparison (Jun-2024 cache) - link severed 26/07/26; >=2yr old at 2027 start - Phase 5 re-source pending
G100: COMPLETED don’t edit
A101: Detectable Tape - Fire x 250m | B101: ea | D101: 90 | F101: =I101*D101 -> 2520 | I101: 28 | N101: frozen from [3] 240614 Pipe & Fittings Price Comparison (Jun-2024 cache) - link severed 26/07/26; >=2yr old at 2027 start - Phase 5 re-source pending
A102: Alcohol Weld Wipes | B102: ea | D102: 13.5 | F102: =I102*D102 -> 2025 | I102: 150 | N102: frozen from [3] 240614 Pipe & Fittings Price Comparison (Jun-2024 cache) - link severed 26/07/26; >=2yr old at 2027 start - Phase 5 re-source pending
A103: Denzo Tape 100mm roll | B103: ea | D103: 27.14 | F103: =I103*D103 -> 4071 | I103: 150 | N103: frozen from [3] 240614 Pipe & Fittings Price Comparison (Jun-2024 cache) - link severed 26/07/26; >=2yr old at 2027 start - Phase 5 re-source pending
A104: Black over-wrap tape - roll | B104: ea | D104: 27.14 | F104: =I104*D104 -> 4071 | I104: 150 | N104: frozen from [3] 240614 Pipe & Fittings Price Comparison (Jun-2024 cache) - link severed 26/07/26; >=2yr old at 2027 start - Phase 5 re-source pending
A106: FIRE SERVICES - ABOVE GROUND
A107: Description | B107: Unit | D107: Rate | F107: Total | G107: COMPLETED don’t edit | I107: Qty
A108: 150mm MED DUTY Galv Pipe | B108: m | D108: 43.846154 | F108: =I108*D108 -> 3946.1538 | I108: 90 | N108: frozen from [3] 240614 Pipe & Fittings Price Comparison (Jun-2024 cache) - link severed 26/07/26; >=2yr old at 2027 start - Phase 5 re-source pending
...

Sheet Equip&HIRE_Master
B2: TCS PROJECT USE | F2: COMPLETED don’t edit
A3: DESCRIPTION | B3: Unit | C3: Qty | D3: WEEKLY (5 day)
A4: Skid Steer Loader_Tracked (CAT249+) | B4: Day | D4: 225.43333 | G4: Source
A5: Skid Steer Loader_Wheeled (CAT226+) | B5: Day | D5: 163.96667 | G5: frozen from [4] 240614 Suppliers Subbies Price Comparison (Jun-2024 cache) - link severed 26/07/26; Phase 5 re-source pending
A6: Mini Loader, Stand-on Type | B6: Day | D6: 180 | G6: frozen from [4] 240614 Suppliers Subbies Price Comparison (Jun-2024 cache) - link severed 26/07/26; Phase 5 re-source pending
F7: COMPLETED don’t edit
A8: 1.5-1.8 Ton_Excavator | B8: Day | D8: 137.14286 | G8: frozen from [4] 240614 Suppliers Subbies Price Comparison (Jun-2024 cache) - link severed 26/07/26; Phase 5 re-source pending
A9: 1.7-2Ton_Excavator | B9: Day
A10: 3-5Ton_Excavator | B10: Day | D10: 238.66667 | G10: frozen from [4] 240614 Suppliers Subbies Price Comparison (Jun-2024 cache) - link severed 26/07/26; Phase 5 re-source pending
A11: 8Ton_Excavator | B11: Day | D11: 261.16667 | G11: frozen from [4] 240614 Suppliers Subbies Price Comparison (Jun-2024 cache) - link severed 26/07/26; Phase 5 re-source pending
A12: 10-12Ton_Excavator | B12: Day | F12: COMPLETED don’t edit
A13: 13-16Ton_Excavator | B13: Day | D13: 317.2 | G13: frozen from [4] 240614 Suppliers Subbies Price Comparison (Jun-2024 cache) - link severed 26/07/26; Phase 5 re-source pending
A14: 20-24Ton_Excavator | B14: Day | D14: 314.28571 | G14: frozen from [4] 240614 Suppliers Subbies Price Comparison (Jun-2024 cache) - link severed 26/07/26; Phase 5 re-source pending
A16: Ripper_1.7-2T | B16: Day
A17: Ripper_1.5-4T | B17: Day | D17: 32.74 | F17: COMPLETED don’t edit | G17: frozen from [4] 240614 Suppliers Subbies Price Comparison (Jun-2024 cache) - link severed 26/07/26; Phase 5 re-source pending
A18: Ripper_3-5T | B18: Day
A19: Ripper_8T | B19: Day | D19: 40.38 | G19: frozen from [4] 240614 Suppliers Subbies Price Comparison (Jun-2024 cache) - link severed 26/07/26; Phase 5 re-source pending
A20: Breaker_1.7-2T | B20: Day | D20: 123.33 | G20: frozen from [4] 240614 Suppliers Subbies Price Comparison (Jun-2024 cache) - link severed 26/07/26; Phase 5 re-source pending
A21: Breaker_3-5T | B21: Day | D21: 165.89 | G21: frozen from [4] 240614 Suppliers Subbies Price Comparison (Jun-2024 cache) - link severed 26/07/26; Phase 5 re-source pending
A22: Breaker_8T | B22: Day | D22: 165.89 | F22: COMPLETED don’t edit | G22: frozen from [4] 240614 Suppliers Subbies Price Comparison (Jun-2024 cache) - link severed 26/07/26; Phase 5 re-source pending
A23: Breaker_10-12T | B23: Day
A24: Breaker_13-15T | B24: Day | D24: 203 | G24: frozen from [4] 240614 Suppliers Subbies Price Comparison (Jun-2024 cache) - link severed 26/07/26; Phase 5 re-source pending
A25: Auger Drive_10-12T
A26: 300Dia Auger Drill
F27: COMPLETED don’t edit
A28: 1.25T_Tipper Truck | B28: Day | D28: 205 | G28: frozen from [4] 240614 Suppliers Subbies Price Comparison (Jun-2024 cache) - link severed 26/07/26; Phase 5 re-source pending
A29: 2-4T_Tipper Truck | B29: Day | D29: 166.98 | G29: frozen from [4] 240614 Suppliers Subbies Price Comparison (Jun-2024 cache) - link severed 26/07/26; Phase 5 re-source pending
A30: <6T_Tipper Truck | B30: Day | D30: 171.42857 | G30: frozen from [4] 240614 Suppliers Subbies Price Comparison (Jun-2024 cache) - link severed 26/07/26; Phase 5 re-source pending
A32: <10T_Articulated Site Tipper | B32: Day | F32: COMPLETED don’t edit
A33: Upright Rammer_Wacker | B33: Day | D33: 34.285714 | G33: frozen from [4] 240614 Suppliers Subbies Price Comparison (Jun-2024 cache) - link severed 26/07/26; Phase 5 re-source pending
A34: Trench Roller_Dbl Drum_Remote | B34: Day | D34: 165 | G34: frozen from [4] 240614 Suppliers Subbies Price Comparison (Jun-2024 cache) - link severed 26/07/26; Phase 5 re-source pending
A35: <26Ft_Scissor Lift - Diesel | B35: Day
A36: <26Ft_Scissor Lift - Elec | B36: Day
A37: <34Ft_Boom Lift - Diesel | B37: Day | F37: COMPLETED don’t edit
A38: <34Ft_Boom Lift - Elec | B38: Day
A40: Porta Loo_No Tank | B40: Day | D40: 5.46 | G40: frozen from [4] 240614 Suppliers Subbies Price Comparison (Jun-2024 cache) - link severed 26/07/26; Phase 5 re-source pending
A41: 6*3m Demantable Lunchroom - COMPLETE | B41: Day | D41: 23 | G41: frozen from [4] 240614 Suppliers Subbies Price Comparison (Jun-2024 cache) - link severed 26/07/26; Phase 5 re-source pending
A42: 6*3m Demantable Office - COMPLETE | B42: Day | D42: 23 | F42: COMPLETED don’t edit | G42: frozen from [4] 240614 Suppliers Subbies Price Comparison (Jun-2024 cache) - link severed 26/07/26; Phase 5 re-source pending
A43: 20Ft Shipping Container | B43: Day
A44: Quick Cut Demo Saw | B44: Day
A45: Sngl Ph_6KVA Genset | B45: Day
A46: Diesel Air Compressor_Trailer | B46: Day
A47: Air Breaker - Heavy | B47: Day | F47: COMPLETED don’t edit
A48: Air Hose <10m | B48: Day
A49: Elec Breaker/Jachammer | B49: Day
A50: Flexdrive Motor Unit | B50: Day
A51: Flexdrive_Pump Shaft | B51: Day
A52: Temporary Power Board | B52: Day | F52: COMPLETED don’t edit
A54: Dual CabUte | B54: Day
A55: 3m3 Skip Bbin | B55: per serive | D55: 230 | G55: frozen from [4] 240614 Suppliers Subbies Price Comparison (Jun-2024 cache) - link severed 26/07/26; Phase 5 re-source pending
A56: plus disposal | B56: Tonne | D56: 309 | G56: frozen from [4] 240614 Suppliers Subbies Price Comparison (Jun-2024 cache) - link severed 26/07/26; Phase 5 re-source pending
A57: site fee | B57: Week | D57: 35 | F57: COMPLETED don’t edit | G57: frozen from [4] 240614 Suppliers Subbies Price Comparison (Jun-2024 cache) - link severed 26/07/26; Phase 5 re-source pending
A58: ~4m3_Skip Bin | B58: per change over | D58: 229.9 | G58: frozen from [4] 240614 Suppliers Subbies Price Comparison (Jun-2024 cache) - link severed 26/07/26; Phase 5 re-source pending
A59: ~6m3_Skip Bin | B59: per change over | D59: 239.8 | G59: frozen from [4] 240614 Suppliers Subbies Price Comparison (Jun-2024 cache) - link severed 26/07/26; Phase 5 re-source pending
A60: Plus disposal | B60: Tonne | D60: 309 | G60: frozen from [4] 240614 Suppliers Subbies Price Comparison (Jun-2024 cache) - link severed 26/07/26; Phase 5 re-source pending
A61: Site fee | B61: Week | D61: 35 | G61: frozen from [4] 240614 Suppliers Subbies Price Comparison (Jun-2024 cache) - link severed 26/07/26; Phase 5 re-source pending
A62: Vacuum Excavator - Vermeer VT250D | B62: Day | D62: 295.77 | F62: COMPLETED don’t edit | G62: frozen from [4] 240614 Suppliers Subbies Price Comparison (Jun-2024 cache) - link severed 26/07/26; Phase 5 re-source pending
A63: Vac Trailer – Dry Hire | B63: Day | D63: 355 | G63: frozen from [4] 240614 Suppliers Subbies Price Comparison (Jun-2024 cache) - link severed 26/07/26; Phase 5 re-source pending
A65: TRANSPORT_Ex BRIS - Return | B65: Day
A66: TRANSPORT_Ex ROK - Return | B66: Hour | D66: 180 | G66: frozen from [4] 240614 Suppliers Subbies Price Comparison (Jun-2024 cache) - link severed 26/07/26; Phase 5 re-source pending
A67: 0-4T Per Hour Delivery Rate | B67: Hour | D67: 125 | F67: COMPLETED don’t edit | G67: frozen from [4] 240614 Suppliers Subbies Price Comparison (Jun-2024 cache) - link severed 26/07/26; Phase 5 re-source pending
A68: 5 - 9t Transport Hourly Rate | B68: Hour | D68: 160 | G68: frozen from [4] 240614 Suppliers Subbies Price Comparison (Jun-2024 cache) - link severed 26/07/26; Phase 5 re-source pending
A69: 10 - 19t Low Loader Hourly rate - Minimum 2 Hour Charge | B69: Hour | D69: 200 | G69: frozen from [4] 240614 Suppliers Subbies Price Comparison (Jun-2024 cache) - link severed 26/07/26; Phase 5 re-source pending

Sheet Misc Subbie Rates_Master
A4: DENIS - Cells highlighted GREEN are complete (By Me). | H4: Source
A8: PLANT HIRE - WET | D8: TCS PROJECT USE | G8: COMPLETED don’t edit
A9: DESCRIPTION | B9: Unit | D9: Hr Rate | E9: Total
A10: 1.8T Excavator | B10: Hr | D10: 100 | H10: frozen from [4] 240614 Suppliers Subbies Price Comparison (Jun-2024 cache) - link severed 26/07/26; Phase 5 re-source pending
A11: 3-5 ton Excavator | B11: Hr | D11: 115 | H11: frozen from [4] 240614 Suppliers Subbies Price Comparison (Jun-2024 cache) - link severed 26/07/26; Phase 5 re-source pending
A12: 3-5T Combo | B12: Hr | D12: 154 | H12: frozen from [4] 240614 Suppliers Subbies Price Comparison (Jun-2024 cache) - link severed 26/07/26; Phase 5 re-source pending
A13: Hammer attachment 3.5-4T | B13: Hr | D13: 21 | G13: COMPLETED don’t edit | H13: frozen from [4] 240614 Suppliers Subbies Price Comparison (Jun-2024 cache) - link severed 26/07/26; Phase 5 re-source pending
A14: Ripper 3.5-4T | B14: Hr | D14: 10 | H14: frozen from [4] 240614 Suppliers Subbies Price Comparison (Jun-2024 cache) - link severed 26/07/26; Phase 5 re-source pending
A15: 5t Excavator | B15: Hr | D15: 150 | H15: frozen from [4] 240614 Suppliers Subbies Price Comparison (Jun-2024 cache) - link severed 26/07/26; Phase 5 re-source pending
A16: Hammer attachment 5T | B16: Hr | D16: 50 | H16: frozen from [4] 240614 Suppliers Subbies Price Comparison (Jun-2024 cache) - link severed 26/07/26; Phase 5 re-source pending
A17: Skid steer | B17: Hr | D17: 140 | H17: frozen from [4] 240614 Suppliers Subbies Price Comparison (Jun-2024 cache) - link severed 26/07/26; Phase 5 re-source pending
A18: 8T Excavator | B18: Hr | D18: 128 | G18: COMPLETED don’t edit | H18: frozen from [4] 240614 Suppliers Subbies Price Comparison (Jun-2024 cache) - link severed 26/07/26; Phase 5 re-source pending
A19: Hammer attachment 8T | B19: Hr | D19: 26 | H19: frozen from [4] 240614 Suppliers Subbies Price Comparison (Jun-2024 cache) - link severed 26/07/26; Phase 5 re-source pending
A20: Ripper 8T | B20: Hr | D20: 10 | H20: frozen from [4] 240614 Suppliers Subbies Price Comparison (Jun-2024 cache) - link severed 26/07/26; Phase 5 re-source pending
A21: 13-15T Excavator | B21: Hr | D21: 153 | H21: frozen from [4] 240614 Suppliers Subbies Price Comparison (Jun-2024 cache) - link severed 26/07/26; Phase 5 re-source pending
A22: Hammer attachment 14T | B22: Hr | D22: 36 | H22: frozen from [4] 240614 Suppliers Subbies Price Comparison (Jun-2024 cache) - link severed 26/07/26; Phase 5 re-source pending
A23: Ripper 14T | B23: Hr | D23: 10 | G23: COMPLETED don’t edit | H23: frozen from [4] 240614 Suppliers Subbies Price Comparison (Jun-2024 cache) - link severed 26/07/26; Phase 5 re-source pending
A24: 3000L Hydro Excavation Truck | B24: Hr | D24: 190 | H24: frozen from [4] 240614 Suppliers Subbies Price Comparison (Jun-2024 cache) - link severed 26/07/26; Phase 5 re-source pending
A25: 4500L Hydro Excavation Truck | B25: Hr | D25: 220 | H25: frozen from [4] 240614 Suppliers Subbies Price Comparison (Jun-2024 cache) - link severed 26/07/26; Phase 5 re-source pending
A26: 6300L Hydro Excavation Truck | B26: Hr | D26: 250 | H26: frozen from [4] 240614 Suppliers Subbies Price Comparison (Jun-2024 cache) - link severed 26/07/26; Phase 5 re-source pending
A27: Water Truck allow for water at cost | B27: Hr | D27: 110 | H27: frozen from [4] 240614 Suppliers Subbies Price Comparison (Jun-2024 cache) - link severed 26/07/26; Phase 5 re-source pending
A28: 12t Body Truck Tipper | B28: Hr | D28: 110 | G28: COMPLETED don’t edit | H28: frozen from [4] 240614 Suppliers Subbies Price Comparison (Jun-2024 cache) - link severed 26/07/26; Phase 5 re-source pending
A33: SURVEYOR | D33: TCS PROJECT USE | G33: COMPLETED don’t edit
A34: DESCRIPTION | B34: QTY | D34: Hr Rate? | E34: Total
A35: Site Field Surveyor for all works preformed | B35: 0 | D35: 180 | E35: =B35*D35 -> 0 | H35: frozen from [4] 240614 Suppliers Subbies Price Comparison (Jun-2024 cache) - link severed 26/07/26; Phase 5 re-source pending
B36: 0 | D36: 0 | E36: =B36*D36 -> 0
B37: 0 | D37: 0 | E37: =B37*D37 -> 0
A40: SERVICES LOCATOR | D40: TCS PROJECT USE | G40: COMPLETED don’t edit
A41: DESCRIPTION | B41: QTY | D41: Hr Rate? | E41: Total
A42: Standard Rate (includes wand, GPR) | B42: 0 | D42: 130 | E42: =B42*D42 -> 0 | H42: frozen from [4] 240614 Suppliers Subbies Price Comparison (Jun-2024 cache) - link severed 26/07/26; Phase 5 re-source pending
B43: 0 | D43: 0 | E43: =B43*D43 -> 0
B44: 0 | D44: 0 | E44: =B44*D44 -> 0
A47: CONCRETE CUTTER | D47: TCS PROJECT USE | G47: COMPLETED don’t edit
A48: DESCRIPTION | B48: QTY | D48: Lm Rate | E48: Total
A49: Asphalt Cutting | B49: 0 | D49: 13.5 | E49: =B49*D49 -> 0 | H49: frozen from [4] 240614 Suppliers Subbies Price Comparison (Jun-2024 cache) - link severed 26/07/26; Phase 5 re-source pending
A50: Concrete Cutting | B50: 0 | D50: 16 | E50: =B50*D50 -> 0 | H50: frozen from [4] 240614 Suppliers Subbies Price Comparison (Jun-2024 cache) - link severed 26/07/26; Phase 5 re-source pending
A51: Site Establishment Fee (2 per stage) | B51: 0 | D51: 80 | E51: =B51*D51 -> 0 | H51: frozen from [4] 240614 Suppliers Subbies Price Comparison (Jun-2024 cache) - link severed 26/07/26; Phase 5 re-source pending
A54: CONCRETING SERVICES | D54: TCS PROJECT USE | G54: COMPLETED don’t edit
A55: DESCRIPTION | B55: QTY | D55: Rate | E55: Total
A56: Road/Drveway Reinstate; 1mW x 150 Thck, N25/20/80, Incl Reinforcement | B56: 0 | D56: 145 | E56: =B56*D56 -> 0 | H56: frozen from [4] 240614 Suppliers Subbies Price Comparison (Jun-2024 cache) - link severed 26/07/26; Phase 5 re-source pending
A57: Kerb & Channel - 1m Wide | B57: 0 | D57: 155 | E57: =B57*D57 -> 0 | H57: frozen from [4] 240614 Suppliers Subbies Price Comparison (Jun-2024 cache) - link severed 26/07/26; Phase 5 re-source pending
A58: Footpath - 1.5mW, N25/20/80, Incl Reinforcement | B58: 0 | D58: 180 | E58: =B58*D58 -> 0 | H58: frozen from [4] 240614 Suppliers Subbies Price Comparison (Jun-2024 cache) - link severed 26/07/26; Phase 5 re-source pending
A59: Footpath - 1.5mW, EXPOSED AGG, N25/20/80, Incl Reinforcement | B59: 0 | D59: 185 | E59: =B59*D59 -> 0 | H59: frozen from [4] 240614 Suppliers Subbies Price Comparison (Jun-2024 cache) - link severed 26/07/26; Phase 5 re-source pending
A62: ASPHALT SERVICES | D62: TCS PROJECT USE | G62: COMPLETED don’t edit
A63: DESCRIPTION | B63: QTY | D63: m2 | E63: Total
A64: 50mm Thck - Trench Reinstatement Through Road/Driveway | B64: 0 | D64: 97 | E64: =B64*D64 -> 0 | H64: frozen from [4] 240614 Suppliers Subbies Price Comparison (Jun-2024 cache) - link severed 26/07/26; Phase 5 re-source pending
A65: 50mm Thck - 1.5-2m Wide Footpath reinstatements | B65: 0 | D65: 97 | E65: =B65*D65 -> 0 | H65: frozen from [4] 240614 Suppliers Subbies Price Comparison (Jun-2024 cache) - link severed 26/07/26; Phase 5 re-source pending
A66: Establishment Fee (1 per stage) | B66: 0 | D66: 5500 | E66: =B66*D66 -> 0
A70: SOIL TESTING & GEO | D70: TCS PROJECT USE | G70: COMPLETED don’t edit
A71: DESCRIPTION | B71: QTY | D71: Rate | E71: Total
A72: Compaction Testing | B72: 0 | D72: 115 | E72: =B72*D72 -> 0 | H72: frozen from [4] 240614 Suppliers Subbies Price Comparison (Jun-2024 cache) - link severed 26/07/26; Phase 5 re-source pending
A73: Site Establishment (3 per stage) | B73: 0 | D73: 90 | E73: =B73*D73 -> 0
B74: 0 | D74: 0 | E74: =B74*D74 -> 0 | H74: frozen from [4] 240614 Suppliers Subbies Price Comparison (Jun-2024 cache) - link severed 26/07/26; Phase 5 re-source pending
A78: FIRE TESTING / CERTIFICATION | D78: TCS PROJECT USE | G78: COMPLETED don’t edit
A79: DESCRIPTION | B79: QTY | D79: Rate | E79: Total
A80: Sprinkler Fitter | B80: 0 | D80: 130 | E80: =B80*D80 -> 0 | H80: frozen from [4] 240614 Suppliers Subbies Price Comparison (Jun-2024 cache) - link severed 26/07/26; Phase 5 re-source pending
A81: Sprinkler Apprentice | B81: 0 | D81: 100 | E81: =B81*D81 -> 0 | H81: frozen from [4] 240614 Suppliers Subbies Price Comparison (Jun-2024 cache) - link severed 26/07/26; Phase 5 re-source pending
A82: Hydrostatic Test Equip | B82: 0 | D82: 450 | E82: =B82*D82 -> 0 | H82: frozen from [4] 240614 Suppliers Subbies Price Comparison (Jun-2024 cache) - link severed 26/07/26; Phase 5 re-source pending
A83: Booster Pump Appliance | B83: 0 | D83: 800 | E83: =B83*D83 -> 0 | G83: COMPLETED don’t edit | H83: frozen from [4] 240614 Suppliers Subbies Price Comparison (Jun-2024 cache) - link severed 26/07/26; Phase 5 re-source pending
A84: FULL Hydro Test - Per Test (6.5Hr 1 x fitter, 1 x apprentice, 1 day Test gear) | B84: 0 | D84: 1945 | E84: =B84*D84 -> 0 | H84: frozen from [4] 240614 Suppliers Subbies Price Comparison (Jun-2024 cache) - link severed 26/07/26; Phase 5 re-source pending
A85: FULL Boost Test - Per Test (8.5Hr - 2 x fitter, 1 x apprentice, 1 day Pump) | B85: 0 | D85: 3560 | E85: =B85*D85 -> 0 | H85: frozen from [4] 240614 Suppliers Subbies Price Comparison (Jun-2024 cache) - link severed 26/07/26; Phase 5 re-source pending
A86: Provision of Form 72 | B86: 0 | D86: 350 | E86: =B86*D86 -> 0 | H86: frozen from [4] 240614 Suppliers Subbies Price Comparison (Jun-2024 cache) - link severed 26/07/26; Phase 5 re-source pending
A95: Misc. Project Rates (ROCHAMPTON) - Master
B96: Unit | C96: REQ | D96: All EX GST | E96: Total EX GST
A97: Flight Costs; Qantas, 1-Way, No Check in Luggage | B97: Ea. | C97: 1 | D97: 220 | E97: =C97*D97 -> 220 | F97: Average $220 Incl GST per flight
A98: Hire Car; Budget, Airport Pick/Drop, NOT UTE, No Fuel | B98: Day | C98: 1 | D98: 190 | E98: =C98*D98 -> 190
A99: Transport (TCS Cost); Airport-Site/Accom, Cab/Staff Pickup | B99: Ea. | C99: 1 | D99: 65 | E99: =C99*D99 -> 65 | F99: Avg | G99: HD
A100: TCS Fuel; $/Km | B100: Km | C100: 1 | D100: 0.2 | E100: =C100*D100 -> 0.2 | G100: 0.16
A101: TCS Vehicle Running Costs; $/Km ($3,800/Yr, 35,000Kms/Yr) | B101: Km | C101: 1 | D101: 0.18 | E101: =C101*D101 -> 0.18 | G101: 0.11
B103: Ea. | C103: 1 | D103: 0 | E103: =C103*D103 -> 0
A104: Bris -> Rok - Courier - UTE | B104: Ea. | C104: 1 | D104: 0 | E104: =C104*D104 -> 0
A105: Bris -> Rok - Courier - Std Truck | B105: Ea. | C105: 1 | D105: 0 | E105: =C105*D105 -> 0
A106: Bris -> Rok - Courier - Flat Bed (Container/Machine) | B106: Ea. | C106: 1 | D106: 2500 | E106: =C106*D106 -> 2500

Sheet Accomodation_Master
B3: INCLUDING GST (UNLESS NOTED OTHERWISE)
B5: TCS Accomodation Rates & Costs
B6: Hotel / Motel | C6: Sngl Night | D6: Week | E6: Month | F6: Qtr
B7: 1 x Unit, 1 x Room | C7: Motel Unit | D7: Private Unit
A8: Hidden | B8: No. of persons stayng; | C8: 1
B9: Furnished | C9: YES
B10: *Serviced | C10: YES
B11: Individual/Private BATHROOM | C11: YES
B12: Individual/Private KITCHEN (Cooking) Faciliities Available - Microwave min. | C12: YES
B13: Individual/Private LAUNDRY Facilities Available | C13: YES
B14: Individual/Private LOUNGE ROOM Facilities Available | C14: YES
C16: Sngl Night | D16: Week | E16: Month | F16: Qtr
B17: Total Booking Cost | C17: =D17/7 -> 112.85714 | D17: 790 | E17: =D17*4 -> 3160 | F17: =E17*3 -> 9480
B19: TCS Housing Consumables; ….. | C19: =D19/7 -> 0 | D19: 0 | E19: =D19*4 -> 0 | F19: =E19*3 -> 0
B20: TCS Laundry Allowance..? | C20: =D20/7 -> 0 | D20: 0 | E20: =D20*4 -> 0 | F20: =E20*3 -> 0
B21: TCS Additional Meals Allowance (If no cooking Facilities?) | C21: =D21/7 -> 0 | D21: 0 | E21: =D21*4 -> 0 | F21: =E21*3 -> 0
B22: TCS Furnishings? | C22: =D22/7 -> 0 | D22: 0 | E22: =D22*4 -> 0 | F22: =E22*3 -> 0
B23: TCS Cleaning/Servincing Allowance? | C23: =D23/7 -> 0 | D23: 0 | E23: =D23*4 -> 0 | F23: =E23*3 -> 0
B25: Total TCS Cost | C25: =SUM(C17:C24) -> 112.85714 | D25: =SUM(D17:D24) -> 790 | E25: =SUM(E17:E24) -> 3160 | F25: =SUM(F17:F24) -> 9480
B26: Total Cost Per Person | C26: =D26/7 -> 112.85714 | D26: =D17/C8 -> 790 | E26: =D26*4 -> 3160 | F26: =E26*3 -> 9480
B28: 1 x Unit, 1 x Room | C28: Motel Unit | D28: Share Rooms
A29: Hidden | B29: No. of persons stayng; | C29: 2
B31: Furnished | C31: YES
B32: *Serviced | C32: YES
B33: Individual/Private BATHROOM | C33: NO | D33: Share with Unit
B34: Individual/Private KITCHEN (Cooking) Faciliities Available - Microwave min. | C34: NO | D34: Share with Unit
B35: Individual/Private LAUNDRY Facilities Available | C35: YES
B36: Individual/Private LOUNGE ROOM Facilities Available | C36: YES
C38: Sngl Night | D38: Week | E38: Month | F38: Qtr
B39: Total Booking Cost | C39: =D39/7 -> 101.42857 | D39: 710 | E39: =D39*4 -> 2840 | F39: =E39*3 -> 8520
B41: TCS Housing Consumables; ….. | C41: =D41/7 -> 0 | D41: 0 | E41: =D41*4 -> 0 | F41: =E41*3 -> 0
B42: TCS Laundry Allowance..? | C42: =D42/7 -> 0 | D42: 0 | E42: =D42*4 -> 0 | F42: =E42*3 -> 0
B43: TCS Additional Meals Allowance (If no cooking Facilities?) | C43: =D43/7 -> 0 | D43: 0 | E43: =D43*4 -> 0 | F43: =E43*3 -> 0
B44: TCS Furnishings? | C44: =D44/7 -> 0 | D44: 0 | E44: =D44*4 -> 0 | F44: =E44*3 -> 0
B45: TCS Cleaning/Servincing Allowance? | C45: =D45/7 -> 0 | D45: 0 | E45: =D45*4 -> 0 | F45: =E45*3 -> 0
B47: Total TCS Cost | C47: =SUM(C39:C46) -> 101.42857 | D47: =SUM(D39:D46) -> 710 | E47: =SUM(E39:E46) -> 2840 | F47: =SUM(F39:F46) -> 8520
B48: Total Cost Per Person | C48: =D48/7 -> 50.714286 | D48: =D39/C29 -> 355 | E48: =D48*4 -> 1420 | F48: =E48*3 -> 4260
B50: 1 x Unit, 1 x Room | C50: Motel Unit | D50: Share Rooms
A51: Hidden | B51: No. of persons stayng; | C51: 3
B53: Furnished | C53: YES
B54: *Serviced | C54: YES
B55: Individual/Private BATHROOM | C55: NO | D55: Share with Unit
B56: Individual/Private KITCHEN (Cooking) Faciliities Available - Microwave min. | C56: NO | D56: Share with Unit
B57: Individual/Private LAUNDRY Facilities Available | C57: YES
B58: Individual/Private LOUNGE ROOM Facilities Available | C58: YES
C60: Sngl Night | D60: Week | E60: Month | F60: Qtr
B61: Total Booking Cost | C61: =D61/7 -> 130.71429 | D61: 915 | E61: =D61*4 -> 3660 | F61: =E61*3 -> 10980
B63: TCS Housing Consumables; ….. | C63: =D63/7 -> 0 | D63: 0 | E63: =D63*4 -> 0 | F63: =E63*3 -> 0
B64: TCS Laundry Allowance..? | C64: =D64/7 -> 0 | D64: 0 | E64: =D64*4 -> 0 | F64: =E64*3 -> 0
B65: TCS Additional Meals Allowance (If no cooking Facilities?) | C65: =D65/7 -> 0 | D65: 0 | E65: =D65*4 -> 0 | F65: =E65*3 -> 0
B66: TCS Furnishings? | C66: =D66/7 -> 0 | D66: 0 | E66: =D66*4 -> 0 | F66: =E66*3 -> 0
B67: TCS Cleaning/Servincing Allowance? | C67: =D67/7 -> 0 | D67: 0 | E67: =D67*4 -> 0 | F67: =E67*3 -> 0
B69: Total TCS Cost | C69: =SUM(C61:C68) -> 130.71429 | D69: =SUM(D61:D68) -> 915 | E69: =SUM(E61:E68) -> 3660 | F69: =SUM(F61:F68) -> 10980
B70: Total Cost Per Person | C70: =D70/7 -> 43.571429 | D70: =D69/C51 -> 305 | E70: =D70*4 -> 1220 | F70: =E70*3 -> 3660
B72: 1 x Unit, 2 x Room | C72: Motel Unit | D72: Share House'
A73: Hidden | B73: No. of persons stayng; | C73: 2
B75: Furnished | C75: YES
B76: *Serviced | C76: YES
B77: Individual/Private BATHROOM | C77: NO | D77: Share with Unit
B78: Individual/Private KITCHEN (Cooking) Faciliities Available - Microwave min. | C78: NO | D78: Share with Unit
B79: Individual/Private LAUNDRY Facilities Available | C79: YES
B80: Individual/Private LOUNGE ROOM Facilities Available | C80: YES
C82: Sngl Night | D82: Week | E82: Month | F82: Qtr
B83: Total Booking Cost | C83: =D83/7 -> 254.28571 | D83: 1780 | E83: =D83*4 -> 7120 | F83: =E83*3 -> 21360
B85: TCS Housing Consumables; ….. | C85: =D85/7 -> 0 | D85: 0 | E85: =D85*4 -> 0 | F85: =E85*3 -> 0
B86: TCS Laundry Allowance..? | C86: =D86/7 -> 0 | D86: 0 | E86: =D86*4 -> 0 | F86: =E86*3 -> 0
B87: TCS Additional Meals Allowance (If no cooking Facilities?) | C87: =D87/7 -> 0 | D87: 0 | E87: =D87*4 -> 0 | F87: =E87*3 -> 0
B88: TCS Furnishings? | C88: =D88/7 -> 0 | D88: 0 | E88: =D88*4 -> 0 | F88: =E88*3 -> 0
B89: TCS Cleaning/Servincing Allowance? | C89: =D89/7 -> 0 | D89: 0 | E89: =D89*4 -> 0 | F89: =E89*3 -> 0
B91: Total TCS Cost | C91: =SUM(C83:C90) -> 254.28571 | D91: =SUM(D83:D90) -> 1780 | E91: =SUM(E83:E90) -> 7120 | F91: =SUM(F83:F90) -> 21360
B92: Total Cost Per Person | C92: =D92/7 -> 127.14286 | D92: =D91/C73 -> 890 | E92: =D92*4 -> 3560 | F92: =E92*3 -> 10680
B94: Full Apartment / Cabin / Villa (Tourist/Caravan Park) | C94: Sngl Night | D94: Week | E94: Month | F94: Qtr
B95: 1 x Unit, 1 x Room | C95: *CABIN | D95: Private Unit
A96: Hidden | B96: No. of persons stayng; | C96: 1
B97: Furnished | C97: YES
B98: *Serviced | C98: YES
B99: Individual/Private BATHROOM | C99: YES
B100: Individual/Private KITCHEN (Cooking) Faciliities Available - Microwave min. | C100: YES
B101: Individual/Private LAUNDRY Facilities Available | C101: YES
B102: Individual/Private LOUNGE ROOM Facilities Available | C102: YES
B103: ** Pool, BBQ, Games etc etc?
C104: Sngl Night | D104: Week | E104: Month | F104: Qtr
B105: Total Booking Cost | C105: =D105/7 -> 114.28571 | D105: 800 | E105: =D105*4 -> 3200 | F105: =E105*3 -> 9600
B107: TCS Housing Consumables; ….. | C107: =D107/7 -> 0 | D107: 0 | E107: =D107*4 -> 0 | F107: =E107*3 -> 0
B108: TCS Laundry Allowance..? | C108: =D108/7 -> 0 | D108: 0 | E108: =D108*4 -> 0 | F108: =E108*3 -> 0
B109: TCS Additional Meals Allowance (If no cooking Facilities?) | C109: =D109/7 -> 0 | D109: 0 | E109: =D109*4 -> 0 | F109: =E109*3 -> 0
B110: TCS Furnishings? | C110: =D110/7 -> 0 | D110: 0 | E110: =D110*4 -> 0 | F110: =E110*3 -> 0
B111: TCS Cleaning/Servincing Allowance? | C111: =D111/7 -> 0 | D111: 0 | E111: =D111*4 -> 0 | F111: =E111*3 -> 0
B113: Total TCS Cost | C113: =SUM(C105:C112) -> 114.28571 | D113: =SUM(D105:D112) -> 800 | E113: =SUM(E105:E112) -> 3200 | F113: =SUM(F105:F112) -> 9600
B114: Total Cost Per Person | C114: =D114/7 -> 114.28571 | D114: =D113/C96 -> 800 | E114: =D114*4 -> 3200 | F114: =E114*3 -> 9600
A116: Hidden | B116: 1 x Unit, 1 x Room | C116: *UNIT/VILLA | D116: Share Rooms
B117: No. of persons stayng; | C117: 2
B118: Furnished | C118: YES
B119: *Serviced | C119: YES
B120: Individual/Private BATHROOM | C120: NO | D120: Share with Unit
B121: Individual/Private KITCHEN (Cooking) Faciliities Available - Microwave min. | C121: NO | D121: Share with Unit
B122: Individual/Private LAUNDRY Facilities Available | C122: YES
B123: Individual/Private LOUNGE ROOM Facilities Available | C123: YES
B124: ** Pool, BBQ, Games etc etc?
C125: Sngl Night | D125: Week | E125: Month | F125: Qtr
...

Sheet EBC_Alternates
B1: TPS - EBC REGISTER & ALTERNATES - TEN16699 (all ex GST)
B2: NOTHING on this sheet feeds the base roll-up on 'TCS $ Sched'. Every figure is either an EXCLUDED-BUT-COSTED add-price held ready for reinstatement, or a labelled ALTERNATE to a base-offer item. The markup factor is referenced live from 'TCS $ Sched' Q51 (41.5% = 5.5% prelims + 18% O/H + 18% profit, each applied to total cost per SS5.4).
B4: SECTION A - EXCLUDED-BUT-COSTED (EBC) add-prices - formula-ready for reinstatement
B6: EBC-1 Sewer rising main O100/DN110, pumpwell to discharge - 110 m (SCOPE_MATRIX 2.1-x2; NewItems #1; RFI CL C4 discharge undefined)
B7: PE100 DN110 PN16 pressure pipe - benchmark (Reece Q-459014437 PE100 125 @ $31.1083/m x (110/125)^2 weight ratio x 1.38 escalation) | C7: m | D7: 110 | E7: =31.1083*(110/125)^2*1.38 -> 33.244569 | F7: =E7*D7 -> 3656.9026
B8: EF couplers / fittings allowance (15% of pipe value) | C8: item | D8: 1 | E8: =F7*0.15 -> 548.53539 | F8: =E8*D8 -> 548.53539
B9: Labour - Crew 1 in-ground, 2 crew-days (Phase 7 T1-06) | C9: day | D9: 2 | E9: ='LabourProject Rates_Master'!E37 -> 2862.4261 | F9: =E9*D9 -> 5724.8522
B10: Plant - 5T excavator 2 d + butt welder 2 d @ $350/d allowance | C10: item | D10: 1 | E10: =2*'Equip&HIRE_Master'!D10+2*350 -> 1177.3333 | F10: =E10*D10 -> 1177.3333
B11: EBC-1 cost subtotal | F11: =SUM(F7:F10) -> 11107.624
B12: EBC-1 ADD-PRICE (cost x 1.415) | F12: =F11*(1+'TCS $ Sched'!Q51) -> 15717.287
B13: Wording control: the exclusion must be worded so the builder cannot deem the rising main included inside 2.1-b gravity sewer. Ownership is ambiguous once Council installs the station (interface L6) - the reinstatement price is HELD, not offered.
B15: EBC-2 Trade waste application (grease arrestor) - excluded per locked SS5.3 / cross-cutting X3; add-price held (CL A2)
B16: Trade waste application / consultant fee allowance | C16: item | D16: 1 | E16: 1500 | F16: =E16*D16 -> 1500
B17: Attendance + documentation - 0.5 crew-day | C17: day | D17: 0.5 | E17: ='LabourProject Rates_Master'!E37 -> 2862.4261 | F17: =E17*D17 -> 1431.213
B18: EBC-2 cost subtotal | F18: =SUM(F16:F17) -> 2931.213
B19: EBC-2 ADD-PRICE (cost x 1.415) | F19: =F18*(1+'TCS $ Sched'!Q51) -> 4147.6665
B20: H002 n.25 makes the trade waste application TPS's; VOL 21 never mentions trade waste despite the canteen. Excluded per locked decision + RFI. The arrestor HARDWARE is priced in the NBC base (1500 L Viking GIT; size conflict 1500/2000/550-5000 L per CL B6).
B22: EBC-3 Fire extinguisher SUPPLY - NBC x8 + PAM x1 (drawn with no trade allocation - CL B8; matrix 4.11-d / 3.11-d)
B23: FE 2.5 kg ABE + bracket + location sign | C23: ea | D23: 9 | E23: 120 | F23: =E23*D23 -> 1080
B24: Install / mount labour - 0.25 crew-day | C24: day | D24: 0.25 | E24: ='LabourProject Rates_Master'!E37 -> 2862.4261 | F24: =E24*D24 -> 715.60652
B25: EBC-3 cost subtotal | F25: =SUM(F23:F24) -> 1795.6065
B26: EBC-3 ADD-PRICE (cost x 1.415) | F26: =F25*(1+'TCS $ Sched'!Q51) -> 2540.7832
B27: VOL38 s14.1 says the plumber prices extinguishers; the drawing note says the builder generally provides them. Carried EBC + RFI so the position is stated either way. AS1851 12-month maintenance of the fire services IS priced in the NBC base (r309).
B29: EBC-4 Sewer pump station - EXCLUDED, NO PRICE CARRIED (Addendum 2, 10 Jul 2026: 'Sewage Pump Station will be getting installed by Council')
B30: Interface per ledger L6: TPS carries the gravity sewer to and terminating at the station's inlet DICL pipe piece ('LIMIT OF Q-MAX WORKS'). Station supply, installation, excavation and slab by Council/others; electrical supply, controls and commissioning cabling by the electrical trade; the rising main is EBC-1 above. TPS states this interface list verbatim in its submission so 'pump station excluded' cannot be read as excluding the connecting works.
B31: Add-price EVIDENCE held (not offered): APS Quote 14065 as-specified QMax Fortis 3200 O x 6700 deep = $468,000 supply + install + commissioning - the basis to quote from if an add-price is requested (no validity stated - flag). Cross-references for the same station: Tradelink 1066334 pack ~$416,000 (incl. $115,000 M&E install labour) and Reece Q-459014431 $523,170.73 S+I. Spread of $107k across the three offers.
B32: REMOVED FROM THE MODEL 26/07/26: the prior workbook carried an orphaned block W37 $468,000 -> W43 = 468,000 x 1.15 + $2,500 freight + $5,000 install = $545,700 'sell'. That block fed NO roll-up cell - it was never inside the old $273,056.54 sub-total, so its deletion moves no headline number. D6 FLAG: any prior quote circulated off the old N68 grand total never included the pump station.
B34: SECTION B - ALTERNATES (clearly labelled; EXCLUDED from the base roll-up)
B36: ALT-1 O200 buried main - COPPER Type B alternate. BASE OFFER = HDPE PE100 SDR11 DN250 (locked SS5.5: no buried copper alternate is OFFERED)
B37: Kembla copper Type B DN200 - Tradelink 6595064, $2,015 per 6 m length (Jul-26; escalation not embedded) | C37: m | D37: 134.63 | E37: =2015/6 -> 335.83333 | F37: =E37*D37 -> 45213.242
B38: Base HDPE line as carried in the model ('Siteworks ' F349) | F38: ='Siteworks '!F349 -> 23118.388
B39: Material delta if copper were adopted (alternate less base) | F39: =F37-F38 -> 22094.854
B40: Sell delta if adopted (delta x 1.18 site contingency x 1.415 markup) | F40: =F39*1.18*(1+'TCS $ Sched'!Q51) -> 36891.777
B41: The copper build-up is retained here as a cost record only. The base offer sits inside the spec's own equivalence table (VOL38 s10.1, Cromford PN16 250 = O200 ID) so it is a CONFORMING offer, not a departure. The copper tapping-cluster FITTINGS (tees, bends, full-faced stubs, gasket kits, sluice valves) remain in the base at adopted counts - only the 134.63 m pipe run changes material.
B43: ALT-2 Building water >DN22 - COPPER alternate. BASE = 316 SS press-fit per WS2 (priced both ways per locked SS5.5 / CL C9)
B44: NBC copper Type B 32 mm (CQU 1057751 curve basis) | C44: m | D44: 17.86 | E44: 32 | F44: =E44*D44 -> 571.52
B45: NBC copper Type B 25 mm | C45: m | D45: 112.72 | E45: =129/6 -> 21.5 | F45: =E45*D45 -> 2423.48
B46: PAM copper Type B 32 mm | C46: m | D46: 9.56 | E46: =119.88/6 -> 19.98 | F46: =E46*D46 -> 191.0088
B47: PAM copper Type B 25 mm | C47: m | D47: 26.9 | E47: 17.52 | F47: =E47*D47 -> 471.288
B48: Copper pipe alternate - total | F48: =SUM(F44:F47) -> 3657.2968
B49: 316 SS press-fit pipe as carried in the base (NBC F420+F423, PAM F405+F407) | F49: ='ClubHouse (NBC )'!F420+'ClubHouse (NBC )'!F423+'Public Amenities (PAM)'!F405+'Public Amenities (PAM)'!F407 -> 2479.6372
B50: Base SS press FITTINGS total (these carry a +50% benchmark uplift over copper press) | F50: ='ClubHouse (NBC )'!F421+'ClubHouse (NBC )'!F422+'ClubHouse (NBC )'!F424+'ClubHouse (NBC )'!F425+'ClubHouse (NBC )'!F438+'ClubHouse (NBC )'!F439+'ClubHouse (NBC )'!F442+'ClubHouse (NBC )'!F443+'Public Amenities (PAM)'!F406+'Public Amenities (PAM)'!F408+'Public Amenities (PAM)'!F410+'Public Amenities (PAM)'!F419+'Public Amenities (PAM)'!F420+'Public Amenities (PAM)'!F423+'Public Amenities (PAM)'!F425 -> 1319.655
B51: Copper fitting reversion (base/1.5 less base = -base/3) | F51: =-F50/3 -> -439.885
B52: Material delta if copper adopted (copper pipe less SS pipe plus fitting reversion) | F52: =F48-F49+F51 -> 737.7746
B53: Sell delta if adopted (delta x 1.12 NBC contingency x 1.415 markup) | F53: =F52*1.12*(1+'TCS $ Sched'!Q51) -> 1169.2252
B54: Gap #2: Tradelink refused a 316 SS press-fit rate; Reece Q-459014431 priced 22/28/35 mm only - which covers every size needed here (NBC/PAM carry nothing above 35 mm), so the PIPE rate is a project quote, not a benchmark. The FITTING rates are benchmark-derived at copper press x1.5 (SS press fittings run 1.4-1.6x copper on supplier curves) and are tagged PENDING RFQ on every affected row. 316 SS long-lead 10-14 weeks is flagged in the programme.
B56: SUMMARY - held add-prices (EBC) and alternate deltas are STATED in the submission but are NOT in the tendered sum. Base-offer positions: O200 main = HDPE PE100 SDR11 DN250; building water >DN22 = 316 SS press-fit; <=DN22 = PEX / copper per WS2.
B57: TOTAL EBC add-prices held (EBC-1 + EBC-2 + EBC-3) | F57: =F12+F19+F26 -> 22405.737

Sheet Sched3_Extract
A1: TPS (Hydraulic) - Paynters Schedule 3 price extract - TEN16699 - ALL EX GST
A2: Maps the TPS cost model to the exact Schedule 3 line structure (schedule3_transcript.md / 01_SCOPE_MATRIX). Physical lump-sum lines are carried inside the stage lump sums; PC Sums, provisional fees and schedule-of-rates lines are separately identified as the schedule requires. Every Schedule 3 line allocated to TPS appears exactly once.
A4: Stage | B4: Sch ref | C4: Schedule 3 line | D4: TPS treatment | E4: Amount ex GST | F4: Basis / qualification
A5: 1A | B5: 1.1-1.7 | C5: Preliminaries & Documentation (TPS share of the Split lines) | D5: In 1A lump sum | F5: Own establishment/TC/ESC/plans/set-out/QC+ADAC/PM per SS5.2 - priced via Phase 7 activities T1-01, T1-02, T5-07 plus the Prelim & OH tab; no shared compound (L5)
A6: 1A | B6: 2.1-b | C6: Sewerage mains (incl. mains through 1B land serving 1A) | D6: In 1A lump sum | F6: Gravity sewer 207.53 m (29.29 O150 + 178.24 O100) + SMS x2 + O150 property connection. Terminates at the Council station inlet DICL piece (L6). FRW lodgement = Principal Contractor (X2)
A7: 1A | B7: 2.1-x1 | C7: -- Sewer pump station | D7: EXCLUDED (Addendum 2) | F7: Council-installed; interface list stated verbatim (L6); add-price evidence held on EBC_Alternates EBC-4 (APS 14065 basis)
A8: 1A | B8: 2.1-x2 | C8: -- Sewer rising main O100/DN110 | D8: EBC - add-price held | E8: =EBC_Alternates!F12 -> 15717.287 | F8: 110 m allowance, formula-ready reinstatement; RFI CL C4 (discharge location undefined); wording prevents it being deemed inside 2.1-b
A9: 1A | B9: 2.1-c | C9: Water mains - O200 tapping to meter slab (mains through 1B) | D9: In 1A lump sum | F9: BASE = O200 ID HDPE PE100 SDR11 DN250 per locked SS5.5 (VOL38 s10.1 equivalence); rate benchmark-derived PENDING RFQ (Gap #5). Copper alternate ALT-1. H002 n.26 diameter blank - RFI CL C3
A10: 1A | B10: 2.2-b | C10: Temporary site services (TPS own, in full) | D10: In 1A lump sum | F10: Own toilets/wash/genset/potable water storage + distribution (ITT S17.3 - no site power or water). Priced bottom-up on the Prelim & OH tab
A11: 1A | B11: 2.4-b | C11: Hydraulic services - site reticulation within 1A | D11: In 1A lump sum | F11: 125 PE CW spine 236.88 m + 6 take-off sets + 32/25 branches 111.51 m + capped future services + irrigation take-off capped at the E-type flange (L13)
A12: 1A | B12: 2.4-c | C12: Fire services - site | D12: In 1A lump sum | F12: 125 HDPE REDLINE 217.73 m + H-pattern booster + cabinet + 100 dual pillar hydrant. Extent qualified (CL C1/F3); AS2419.1 coverage + missing H004 = RFI
A13: 1A | B13: 3.5 | C13: Hydraulic - grated trench drains and pits | D13: EXCLUDED - TCS scope | F13: Locked SS5.1: priced by TCS despite the 'Hydraulic' heading (drawn on the civil sheets). TPS expressly excludes and cross-refers the TCS tender (L1)
A14: 1A | B14: 4.3 | C14: -- Roofing / roof plumbing / gutters / downpipes | D14: EXCLUDED (SS5.3) | F14: TPS scope starts at the DP 'CONNECT TO CIVIL' point in ground; the roofer owns everything above (L14). DP stub count adopted 19 EA, RFI on count (Opens #23)
A15: 1A | B15: 4.11-c | C15: NBC hydraulic services | D15: In 1A lump sum | F15: Sanitary 268.4 m + trade waste 54.78 m + 1500 L GIT (size RFI CL B6) + water (316 SS press-fit >DN22 conforming, PEX <=DN22; copper ALT-2) + 2x Rheem 315L HWU + RPZD/backflow + articulation + seismic (install + layout only, CL C7) + DP stubs to CONNECT TO CIVIL only (L2)
A16: 1A | B16: 4.11-d | C16: NBC fire compliance | D16: In 1A lump sum | F16: FHR x1 + FB x1 + AS1851 12-month maintenance & tagging. FE x8 supply = EBC-3 + RFI (CL B8)
A17: 1A | B17: 4.12-c | C17: NBC plumbing fixtures - SUPPLY | D17: PC SUM | E17: ='TCS $ Sched'!N71 -> 207268.84 | F17: Tradelink 1066143 adjusted for adopted counts + 15% (build-up on 'TCS $ Sched' R70:S78). Install labour is in Base. Validity 13/08/26 vs 2027 start + header defects qualified (CL F4)
A18: 1A | B18: 4.12-e | C18: NBC drinking fountain (chilled) | D18: PC SUM (calculated) | E18: ='TCS $ Sched'!N72 -> 25415 | F18: 2x CF400 chilled @ $11,050 + 15%; chilled/non-chilled same-SKU RFI (CL C10); signage explicitly extra on the quote. Rough-in connections in Base
A19: 1A | B19: 5.0 | C19: Provisional - plumbing, water & sewer connection fees | D19: PROVISIONAL as directed | E19: ='TCS $ Sched'!N73 -> 20000 | F19: $20,000 actual-cost reimbursement carried exactly as directed, NO markup (SS5.4). Schedule entry mechanics RFI (CL A3)
A20: 1A | B20: 7.0-a | C20: Rock removal rate - TPS trenches AND pits, soft AND hard | D20: SCHEDULE OF RATES | E20: see build-up below | F20: Four rates tendered per H002 n.24. Extra-over, payable on Superintendent written direction (ITT s18.2). TPS rates apply only to water/sewer/fire excavations - no overlap with TCS. Three-regime inconsistency RFI'd (CL B5/A5)
A21: 1A | B21: 7.0-b | C21: Unsuitable ground removal & reinstatement rate | D21: SCHEDULE OF RATES | E21: see build-up below | F21: Extra-over, Superintendent written direction only (ITT s18.1); same own-excavations boundary
A22: 1A | C22: STAGE 1A TOTAL ex GST (lump sum + PC sums + provisional) | E22: ='TCS $ Sched'!N83 -> 1751720.1 | F22: 1A base sell + 1A PC sums. Section 6.0 (electrical) is Not Ours; 1A 2.3 / 2.5 drainage is TCS
A23: 1B | B23: 1.1-1.7 | C23: Preliminaries & Documentation (TPS share) | D23: In 1B lump sum | F23: Standalone-viable 1B per SS5.2 - no reliance on any 1A establishment
A24: 1B | B24: 2.1-a | C24: Temporary site services (TPS own) | D24: In 1B lump sum | F24: As 1A 2.2-b, sized for a standalone 1B award
A25: 1B | B25: 2.2-b | C25: Hydraulic services - 1B's own connections and reticulation | D25: In 1B lump sum | F25: Branch take-offs from the 1A-priced mains; the branch fitting/valve IS the line (L9). PAM O25/O32 entries, O100 PAM sewer leg, bubbler/DF supplies + wastes, hose taps (Phase 7 T2-09, 4 crew-days carried on the PAM sheet)
A26: 1B | B26: 2.2-c | C26: Fire services - 1B extent | D26: In 1B lump sum | F26: Same extent-verification qualification as 1A 2.4-c (CL C1)
A27: 1B | B27: 3.11-c | C27: PAM hydraulic services | D27: In 1B lump sum | F27: Sanitary 68.09 m @1:60 + ORG + FWG x4 + Rheem 50L HWU + TMV in SS lockable cabinet + O32 check-meter (no PRV vs NBC 500 kPa - RFI CL C8) + 316 SS/PEX water + articulation + seismic. DP stubs only - PAM sheets carry NO 'connect to civil' note (RFI)
A28: 1B | B28: 3.11-d | C28: PAM fire compliance | D28: In 1B lump sum | F28: FE x1 supply = EBC-3 + RFI (CL B8)
A29: 1B | B29: 3.12-a | C29: PAM plumbing fixtures - SUPPLY | D29: PC SUM | E29: ='TCS $ Sched'!N74 -> 17250 | F29: PAM extension of the Tradelink 1066143 basis + 15%. The PAM fixture set was never counted by the take-off - adopted counts (8 s/s WC + in-wall cisterns, 1800 trough, PWD basin, CSK, timed taps, 2x TR) extended at the quote-rate family; delta stated
A30: 1B | B30: 3.12-b | C30: PAM drinking fountain (non-chilled) | D30: PC SUM (calculated) | E30: ='TCS $ Sched'!N75 -> 16560 | F30: 2x CF400 non-chilled benchmark $7,200 ea + 15% - the non-chilled variant is unpriced by anyone (Gap #6), re-quote pending; same SKU RFI (CL C10)
A31: 1B | B31: 4.5-c | C31: Water bubbler stations (recreational park) | D31: PC SUM (calculated) | E31: ='TCS $ Sched'!N76 -> 33120 | F31: 4x site DF/BT positions per H003 at the same benchmark + 15%; unit type undefined in the legend (RFI CL C10). Supply/waste connections priced in 1B 2.2-b Base; slabs/surrounds by others
A32: 1B | B32: 4.6 | C32: Provisional - connection fees | D32: PROVISIONAL as directed | E32: ='TCS $ Sched'!N77 -> 20000 | F32: $20,000 as directed, no markup - mirror of 1A 5.0. Carried in BOTH stages per the schedule and SS5.4
A33: 1B | B33: 5.0-a | C33: Rock removal rate - TPS trenches AND pits, soft AND hard | D33: SCHEDULE OF RATES | E33: see build-up below | F33: Identical rates and regime to 1A 7.0-a
A34: 1B | B34: 5.0-b | C34: Unsuitable ground removal & reinstatement rate | D34: SCHEDULE OF RATES | E34: see build-up below | F34: Identical to 1A 7.0-b
A35: 1B | B35: 2.3 / 4.x | C35: Stormwater drainage, landscaping, play equipment, park furniture | D35: Not Ours / TCS | F35: 1B 2.3-a stormwater = TCS; landscape/irrigation/play/furniture = other trades. Listed so no 1B line is silent
A36: 1B | C36: STAGE 1B TOTAL ex GST (lump sum + PC sums + provisional) | E36: ='TCS $ Sched'!N86 -> 267215.68 | F36: 1B base sell + 1B PC sums
C37: TPS GRAND TOTAL ex GST (1A + 1B) | E37: ='TCS $ Sched'!N87 -> 2018935.8 | F37: Tie check on 'TCS $ Sched' N88 must read 0
A39: SCHEDULE-OF-RATES BUILD-UP (1A 7.0 / 1B 5.0) - extra-over rates, TPS excavations only
A40: Extra-over $/m3 = (crew day rate + plant day rate) x (1/rock production - 1/normal production) + disposal or import premium. The crew rate is the re-based FIFO Crew 1 day rate; plant is 8T excavator + breaker. Productions are estimator judgement for Rockhampton siltstone/sandstone per geotech NQL2024-0320 s5.3.3 refusal depths.
A42: Rate line | B42: Rock prod (m3/d) | C42: Normal prod (m3/d) | D42: Crew+plant $/day | E42: Disposal/import $/m3 | F42: TENDERED RATE $/m3
A43: Soft rock - TRENCH (extra over) | B43: 18 | C43: 45 | D43: ='LabourProject Rates_Master'!E37+'Equip&HIRE_Master'!D11+'Equip&HIRE_Master'!D22 -> 3289.4828 | E43: 25 | F43: =D43*(1/B43-1/C43)+E43 -> 134.64943
A44: Hard rock - TRENCH (extra over) | B44: 7 | C44: 45 | D44: ='LabourProject Rates_Master'!E37+'Equip&HIRE_Master'!D11+'Equip&HIRE_Master'!D22 -> 3289.4828 | E44: 25 | F44: =D44*(1/B44-1/C44)+E44 -> 421.82649
A45: Soft rock - PIT / structure (extra over) | B45: 12 | C45: 45 | D45: ='LabourProject Rates_Master'!E37+'Equip&HIRE_Master'!D11+'Equip&HIRE_Master'!D22 -> 3289.4828 | E45: 25 | F45: =D45*(1/B45-1/C45)+E45 -> 226.02395
A46: Hard rock - PIT / structure (extra over) | B46: 4.5 | C46: 45 | D46: ='LabourProject Rates_Master'!E37+'Equip&HIRE_Master'!D11+'Equip&HIRE_Master'!D22 -> 3289.4828 | E46: 25 | F46: =D46*(1/B46-1/C46)+E46 -> 682.89655
A47: Unsuitable ground - removal & reinstatement (extra over) | B47: 25 | C47: 45 | D47: ='LabourProject Rates_Master'!E37+'Equip&HIRE_Master'!D11 -> 3123.5928 | E47: =15+'Material Rates_Master'!D185 -> 54.75 | F47: =D47*(1/B47-1/C47)+E47 -> 110.28054 | G47: Disposal $15/m3 (helper haulage rate) + imported select fill at the bedding-sand rate; compaction sits inside the crew production
A49: Rock 'reasonably anticipated' extent: the rates apply BELOW the bore-log rock horizons in NQL2024-0320; rock encountered above those horizons is deemed included. Three inconsistent regimes exist (ITT s18.2 written direction vs H002 n.24 four-way schedule vs VOL38 s7.7 deemed-included) - the priced regime is stated and the inconsistency RFI'd (CL B5/A5) so H002 n.15 cannot bite.
A51: Exclusions & qualifications carried per 01_SCOPE_MATRIX: roofing/DPs above ground (4.3 / 3.3), landscape irrigation (demarcation = the capped E-type flange, L13), plumbing approval lodgement (X2 - RRC plumbing applications; the FRW Private Works lodgement is Principal Contractor as written in ITT s16), trade waste application (X3 = EBC-2), shop drawings (X1 - EBC in the tender control register), court trench drains (TCS, L1), sewer pump station (Addendum 2, L6), design liability (construct-only; seismic = layout drafting only, CL C7).
