Workbook
Name aa: #REF!
Name aa: #REF!
Name aa: #REF!
Name aa: #REF!
Name aa: 'MISC & SITEWIDE'!#REF!
Name aa: #REF!
Name aa: #REF!
Name aa: #REF!
Name aa: #REF!
Name aa: #REF!
Name aa: #REF!
Name aa: #REF!
Name aa: #REF!
Name aa: #REF!
Name aa: #REF!
Name bh: #REF!
Name Civil4: #REF!
Name Civil4: #REF!
Name Civil4: #REF!
Name Civil4: #REF!
Name Civil4: 'MISC & SITEWIDE'!#REF!
Name Civil4: #REF!
Name Civil4: #REF!
Name Civil4: #REF!
Name Civil4: #REF!
Name Civil4: #REF!
Name Civil4: #REF!
Name Civil4: #REF!
Name Civil4: #REF!
Name Civil4: #REF!
Name Civil4: #REF!
Name d: #REF!
Name d: #REF!
Name d: #REF!
Name d: #REF!
Name d: 'MISC & SITEWIDE'!#REF!
Name d: #REF!
Name d: #REF!
Name d: #REF!
Name d: #REF!
Name d: #REF!
Name d: #REF!
Name d: #REF!
Name d: #REF!
Name d: #REF!
Name d: #REF!
Name date: #REF!
Name date: #REF!
Name date: #REF!
Name date: #REF!
Name date: 'MISC & SITEWIDE'!#REF!
Name date: #REF!
Name date: #REF!
Name date: #REF!
Name date: #REF!
Name date: #REF!
Name date: #REF!
Name date: #REF!
Name date: #REF!
Name date: #REF!

Sheet TCS $ Sched
B6: SUMMARY | V6: BIG TICKET ITEMS
B8: JOB DESCRIPTION: | N8: DATE: | V8: ROK 092
B9: SITE ADDRESS: | I9: CQU ROK | N9: TCS Quote #: **
R10: Cost | S10: (Cost + O/H) + Profit | V10: TRADE WASTE HOLDING TANK HOL(1) | Y10: ROK 092 - Sanitary Drainage Pump Station SDPS | AB10: ROK 092 - OIL/WATER SEPARATOR (OWS 2)
N11: TOTALS | V11: Purchase Cost Total | W11: 18000 | Y11: Purchase Cost Total | Z11: 35563 | AB11: Purchase Cost Total | AC11: 15932
V13: TPS Markup | W13: 1.15 | Y13: TPS Markup | Z13: 1.15 | AB13: TPS Markup | AC13: 1.15
B14: ROK092 | V14: Qty | W14: 1 | Y14: Qty | Z14: 1 | AB14: Qty | AC14: 1
V15: Freight | W15: 121 | Y15: Freight | Z15: 8965 | AB15: Freight | AC15: 2000
B16: A | C16: . | D16: 1 | I16: ROK 092 _ Hydraulic & Fire Services Complete | N16: =S16+Z17+W17+AC17+AC27+Z27+W26+W54+AC36+AC44+Z44+W44 -> 1103268.3 | R16: ='ROK092'!F908 -> 651013.36 | S16: =((R16/$R$64)*($R$74-$R$64))+R16 -> 967108.98 | V16: Installation_MH | W16: 1850 | Y16: Installation_MH | Z16: 1250 | AB16: Installation_MH | AC16: 2500
B17: A | C17: . | D17: 1 | E17: . | F17: 1 | J17: Ground Floor - InGround Services (Drainage, Water, Fire) | M17: 0 | V17: TOTAL | W17: =W11*W13*W14+W15+W16 -> 22671 | Y17: TOTAL | Z17: =Z11*Z13*Z14+Z15+Z16 -> 51112.45 | AB17: TOTAL | AC17: =AC11*AC13*AC14+AC15+AC16 -> 22821.8
B18: A | C18: . | D18: 1 | E18: . | F18: 2 | J18: Temps_ Plumbing Services and Connections for 'Typical' Construction temps | M18: 8620
B19: A | C19: . | D19: 1 | E19: . | F19: 3 | J19: Supply Hydraulic Fixtures | M19: 0 | V19: ROK 092 - Rainwater Pump 1(Dave KRB4 )
V20: Purchase Cost Total | W20: 2092 | Y20: ROK 092 - Rainwater Harvesting Filters - RWF (1) | AB20: RAIN WATER HARVESTING TANK RWHT (1)
B21: ROK021A | Y21: Purchase Cost Total | Z21: 4135 | AB21: Purchase Cost Total | AC21: 13200
V22: TPS Markup | W22: 1.15
B23: B | C23: . | D23: 1 | I23: ROK021A_ Hydraulic & Fire Services Complete | N23: =S23+W65 -> 81951.779 | R23: =ROK21A!F853 -> 54039.91 | S23: =((R23/$R$64)*($R$74-$R$64))+R23 -> 80278.664 | V23: Qty | W23: 1 | Y23: TPS Markup | Z23: 1.15 | AB23: TPS Markup | AC23: 1.15
B24: B | C24: . | D24: 1 | E24: . | F24: 1 | J24: Temps_ Plumbing Services and Connections for 'Typical' Construction temps | M24: 500 | V24: Freight | W24: 121 | Y24: Qty | Z24: 1 | AB24: Qty | AC24: 1
B25: B | C25: . | D25: 1 | E25: . | F25: 2 | J25: Supply Hydraulic Fixtures | M25: 0 | V25: Installation_MH | W25: 1000 | Y25: Freight | Z25: 121 | AB25: Freight
V26: TOTAL | W26: =W20*W22*W23+W24+W25 -> 3526.8 | Y26: Installation_MH | Z26: 1000 | AB26: Installation_MH | AC26: 1000
B27: ROK019 | Y27: TOTAL | Z27: =Z21*Z23*Z24+Z25+Z26 -> 5876.25 | AB27: TOTAL | AC27: =AC21*AC23*AC24+AC25+AC26 -> 16180
B29: C | C29: . | D29: 1 | I29: ROK019_ Hydraulic & Fire Services Complete | N29: =S29+W77+Z77 -> 210148.67 | R29: ='ROK019'!F854 -> 137986.01 | S29: =((R29/$R$64)*($R$74-$R$64))+R29 -> 204984.29
B30: C | C30: . | D30: 1 | E30: . | F30: 1 | J30: Temps_ Plumbing Services and Connections for 'Typical' Construction temps | M30: 3840 | V30: ROK 092 - Boiling/ Chilled /Hot Water Unit BCHWU (1) | Y30: ROK 092 - Boiling Chilled water unit BCWU (1) | AB30: ROK 092 - HWU 4 DHE27
B31: C | C31: . | D31: 1 | E31: . | F31: 2 | J31: Supply Hydraulic Fixtures | M31: 0 | V31: Purchase Cost Total | W31: 6930.1 | Y31: Purchase Cost Total | Z31: 4056.3 | AB31: Purchase Cost Total | AC31: 1432.3
Y32: FONT KID | Z32: 415.3
B33: ROK033 | V33: TPS Markup | W33: 1.15 | Y33: TPS Markup | Z33: 1.15 | AB33: TPS Markup | AC33: 1.15
V34: Qty | W34: 1 | Y34: Qty | Z34: 1 | AB34: Qty | AC34: 1
B35: D | C35: . | D35: 1 | I35: ROK033_ Hydraulic & Fire Services Complete | N35: =S35+W88+Z88+AC88 -> 405932.81 | R35: ='ROK033'!F860 -> 264906.62 | S35: =((R35/$R$64)*($R$74-$R$64))+R35 -> 393530.44 | V35: Installation_MH | Y35: Installation_MH | AB35: Installation_MH | AC35: 500
B36: D | C36: . | D36: 1 | E36: . | F36: 1 | J36: Temps_ Plumbing Services and Connections for 'Typical' Construction temps | M36: 3840 | V36: TOTAL | W36: =W31*W33*W34+W35 -> 7969.615 | Y36: TOTAL | Z36: =Z31*Z33*Z34+Z32+Z35 -> 5080.045 | AB36: TOTAL | AC36: =AC31*AC33*AC34+AC35 -> 2147.145
B37: D | C37: . | D37: 1 | E37: . | F37: 2 | J37: Supply Hydraulic Fixtures | M37: 0
V38: ROK 092 - HWU 5 DEL 27 PLUS | Y38: ROK 092 - HWU 6 DEL 18 | AB38: ROK 092 - HWU 7 DHB-E 13 LCD
B39: ROK034 | V39: Purchase Cost Total | W39: 1302.1 | Y39: Purchase Cost Total | Z39: 1240.1 | AB39: Purchase Cost Total | AC39: 1020.1
B41: E | C41: . | D41: 1 | I41: ROK034_ Hydraulic & Fire Services Complete | N41: =S41 -> 71587.708 | R41: ='ROK034'!F852 -> 48189.558 | S41: =((R41/$R$64)*($R$74-$R$64))+R41 -> 71587.708 | V41: TPS Markup | W41: 1.15 | Y41: TPS Markup | Z41: 1.15 | AB41: TPS Markup | AC41: 1.15
B42: E | C42: . | D42: 1 | E42: . | F42: 1 | J42: Temps_ Plumbing Services and Connections for 'Typical' Construction temps | M42: 500 | V42: Qty | W42: 1 | Y42: Qty | Z42: 3 | AB42: Qty | AC42: 1
B43: E | C43: . | D43: 1 | E43: . | F43: 2 | J43: Supply Hydraulic Fixtures | M43: 0 | V43: Installation_MH | W43: 500 | Y43: Installation_MH | Z43: 500 | AB43: Installation_MH | AC43: 500
V44: TOTAL | W44: =W39*W41*W42+W43 -> 1997.415 | Y44: TOTAL | Z44: =Z39*Z41*Z42+Z43 -> 4778.345 | AB44: TOTAL | AC44: =AC39*AC41*AC42+AC43 -> 1673.115
B45: ROK036
B47: F | C47: . | D47: 1 | I47: ROK036_ Hydraulic & Fire Services Complete | N47: =S47+W110+AC110+Z120+W120 -> 1094184.6 | R47: ='ROK036'!F938 -> 717701.26 | S47: =((R47/$R$64)*($R$74-$R$64))+R47 -> 1066176.8
B48: F | C48: . | D48: 1 | E48: . | F48: 1 | J48: Temps_ Plumbing Services and Connections for 'Typical' Construction temps | M48: 3840 | V48: ROK 092 - Lift Pump Sump
B49: F | C49: . | D49: 1 | E49: . | F49: 2 | J49: Supply Hydraulic Fixtures | M49: 0 | V49: Purchase Cost Total | W49: 2500
B51: ROK076 | V51: TPS Markup | W51: 1.15
V52: Qty | W52: 1
B53: G | C53: . | D53: 1 | I53: ROK076_ Hydraulic & Fire Services Complete | N53: =S53+W131+Z131+AC131+Z140+W140 -> 250631.28 | R53: ='ROK076'!F883 -> 141799.9 | S53: =((R53/$R$64)*($R$74-$R$64))+R53 -> 210649.99 | V53: Installation_MH | W53: 500
B54: G | C54: . | D54: 1 | E54: . | F54: 1 | J54: Temps_ Plumbing Services and Connections for 'Typical' Construction temps | M54: 500 | V54: TOTAL | W54: =W49*W51*W52+W53 -> 3375
B55: G | C55: . | D55: 1 | E55: . | F55: 2 | J55: Supply Hydraulic Fixtures | M55: 0
B57: Misc | V57: ROK 21 A
B59: H | C59: . | D59: 1 | I59: Hydraulic Services Design | N59: =S59 -> 0 | R59: ='ROK076'!F887 -> 0 | S59: =((R59/$R$64)*($R$74-$R$64))+R59 -> 0 | V59: ROK 21A - HWU 7 DHB-E 13 LCD
B60: H | C60: . | D60: 1 | E60: . | F60: 1 | M60: 1 | V60: Purchase Cost Total | W60: 1020.1
B61: B | C61: . | D61: 1 | E61: . | F61: 2 | M61: 0
V62: TPS Markup | W62: 1.15
V63: Qty | W63: 1
M64: SUB-TOTAL | N64: =SUM(N16:N63) -> 3217705.1 | R64: =SUM(R13:R63) -> 2015636.6 | S64: =SUM(S13:S26) -> 1047387.6 | V64: Installation_MH | W64: 500
V65: TOTAL | W65: =W60*W62*W63+W64 -> 1673.115
M66: 10% GST | N66: =N64*0.1 -> 321770.51
P67: Prelim | Q67: =R67/R64 -> 0.080331961 | R67: ='00_ TCS Prelim & OH'!F89 -> 161920.04 | S67: of total cost
M68: GRAND TOTAL | N68: =N64+N66 -> 3539475.7 | P68: O/H | Q68: =R68/R64 -> 0.17860362 | R68: ='00_ TCS Prelim & OH'!F96 -> 360000 | S68: of total cost | V68: ROK 19
Q69: .
P70: Sub Total | R70: =SUM(R64:R69) -> 2537556.7 | S70: total cost + Prelim + O/H
V71: ROK 19 - HWU 2 RHEEM 315 Liter 7.2kw | Y71: ROK 19 - HWU 3 RHEEM 50 LITTER 10.8KW | AB71: ROK 19 - Boiling Chilled water unit BCWU (1)
P72: Profit | Q72: 0.18 | R72: =R70*Q72 -> 456760.2 | S72: Gross | V72: Purchase Cost Total | W72: 1889 | Y72: Purchase Cost Total | Z72: 1732.2 | AB72: Purchase Cost Total | AC72: 4056.3
P73: Total Markup | Q73: =SUM(Q67:Q72) -> 0.43893558 | AB73: FONT KID | AC73: 415.3
P74: Grand Total | R74: =SUM(R70:R72) -> 2994316.9 | V74: TPS Markup | W74: 1.15 | Y74: TPS Markup | Z74: 1.15 | AB74: TPS Markup | AC74: 1.15
V75: Qty | W75: 1 | Y75: Qty | Z75: 1 | AB75: Qty | AC75: 1
V76: Installation_MH | W76: 500 | Y76: Installation_MH | Z76: 500 | AB76: Installation_MH
V77: TOTAL | W77: =W72*W74*W75+W76 -> 2672.35 | Y77: TOTAL | Z77: =Z72*Z74*Z75+Z76 -> 2492.03 | AB77: TOTAL | AC77: =AC72*AC74*AC75+AC76 -> 4664.745
V80: ROK 33
V82: ROK 33 - HWCP 2 Grundfos circulator Model UPS 20-60N pumps | Y82: ROK 33 - HWU 1 RHEEM 10.8KW | AB82: ROK 033 - Lift Pump Sump
V83: Purchase Cost Total | W83: 4545 | Y83: Purchase Cost Total | Z83: 3150.1 | AB83: Purchase Cost Total | AC83: 1600
V84: Friehgt | W84: 213
V85: TPS Markup | W85: 1.15 | Y85: TPS Markup | Z85: 1.15 | AB85: TPS Markup | AC85: 1.15
V86: Qty | W86: 1 | Y86: Qty | Z86: 1 | AB86: Qty | AC86: 1
V87: Installation_MH | W87: 500 | Y87: Installation_MH | Z87: 500 | AB87: Installation_MH | AC87: 500
V88: TOTAL | W88: =W83*W85*W86+W87+W84 -> 5939.75 | Y88: TOTAL | Z88: =Z83*Z85*Z86+Z87 -> 4122.615 | AB88: TOTAL | AC88: =AC83*AC85*AC86+AC87 -> 2340
V91: ROK 34
V93: ROK 34 - Boiling Chilled water unit BCWU (1)
V94: Purchase Cost Total | W94: 4056.3
V95: FONT KID | W95: 415.3
V96: TPS Markup | W96: 1.15
V97: Qty | W97: 2
V98: Installation_MH
V99: TOTAL | W99: =W94*W96*W97+W98 -> 9329.49
V102: ROK 36
V104: ROK 36 - GIT(1)GREASE INTERCEPTOR TRAP | Y104: ROK 36 - Boiling Chilled water unit BCWU (1) | AB104: ROK 36 - HWCP 1 HOT WATER CIRCULATION PUMPS GRUNDFOS UPS 20-60N
V105: Purchase Cost Total | W105: 11650 | Y105: Purchase Cost Total | Z105: 4056.3 | AB105: Purchase Cost Total | AC105: 4845
Y106: FONT KID | Z106: 415.3 | AB106: FRIEGHT | AC106: 213
V107: TPS Markup | W107: 1.15 | Y107: TPS Markup | Z107: 1.15 | AB107: TPS Markup | AC107: 1.15
V108: Qty | W108: 1 | Y108: Qty | Z108: 1 | AB108: Qty | AC108: 1
V109: Installation_MH | W109: 2200 | Y109: Installation_MH | AB109: Installation_MH | AC109: 500
V110: TOTAL | W110: =W105*W107*W108+W109 -> 15597.5 | Y110: TOTAL | Z110: =Z105*Z107*Z108+Z109 -> 4664.745 | AB110: TOTAL | AC110: =AC105*AC107*AC108+AC106+AC109 -> 6284.75
V114: ROK 36 - HWU 1 RHEEM 613-315 | Y114: ROK 036 - Lift Pump Sump
V115: Purchase Cost Total | W115: 2857 | Y115: Purchase Cost Total | Z115: 1600
V116: FONT KID
V117: TPS Markup | W117: 1.15 | Y117: TPS Markup | Z117: 1.15
V118: Qty | W118: 1 | Y118: Qty | Z118: 1
V119: Installation_MH | W119: 500 | Y119: Installation_MH | Z119: 500
V120: TOTAL | W120: =W115*W117*W118+W119 -> 3785.55 | Y120: TOTAL | Z120: =Z115*Z117*Z118+Z119 -> 2340
V123: ROK 76
V125: ROK 76 - RWHT2 BUSHMAN TANKS 15,000 EACH | Y125: ROK 76 -RWP 2 | AB125: ROK 76 -RWF 2
V126: Purchase Cost Total | W126: 11500 | Y126: Purchase Cost Total | Z126: 2092 | AB126: Purchase Cost Total | AC126: 4135.88
Y127: FRIGHT | Z127: 120 | AB127: FRIGHT | AC127: 150
V128: TPS Markup | W128: 1.15 | Y128: TPS Markup | Z128: 1.15 | AB128: TPS Markup | AC128: 1.15
...

Sheet 00_ TCS Prelim & OH
B1: Project:
B2: Tricore -
B3: Stage 1 Version 1
A4: Item
A7: A | B7: PRELIMINARIES
B8: SUMMARY (Not added in prelim$)
C9: =[1]Program_MASTER!$B$102 -> TOTAL Days Mobilized On Site
C10: =[1]Program_MASTER!B103 -> Months Mobilized
C11: =[1]Program_MASTER!B104 -> Work Weeks' Mobilized On Site
C12: =[1]Program_MASTER!B105 -> Work Days
C13: Breakdown as per program
B14: ='LabourProject Rates_Master'!$B$14 -> TRADESMAN_LEADING HAND | C14: Day | E14: =E36 -> 1231.1429 | F14: =D14*E14 -> 0
B15: ='LabourProject Rates_Master'!$B$23 -> TRADESMAN_PLUMBER_OPERATOR | C15: Day | E15: =E37 -> 941.16473 | F15: =D15*E15 -> 0
B16: ='LabourProject Rates_Master'!$B$30 -> T/A & Apprentice | C16: Day | E16: =E38 -> 768.06508 | F16: =D16*E16 -> 0
B17: ='LabourProject Rates_Master'!$B$36 -> Crew #1 - InGround Drainage | C17: Day | E17: =E39 -> 2650.3945 | F17: =D17*E17 -> 0
B18: ='LabourProject Rates_Master'!$B$43 -> Crew #2 - InGround Water/Fire | C18: Day | E18: =E40 -> 2650.3945 | F18: =D18*E18 -> 0
E19: Total Labour | F19: =SUM(F14:F18) -> 0
C20: Total as per stage boq
E21: Total Part A Labour | F21: 0
E22: Total Stage 1 Labour | F22: 0
E23: Total Stage 2 Labour | F23: 0
E24: Total Stage 3 Labour | F24: 0
E25: Total Stage 4 Labour | F25: 0
F26: =SUM(F21:F25) -> 0
E27: Difference | F27: =F26-F19 -> 0
C29: Unit | D29: REQ | E29: Cost ex GST | F29: Total ex GST
B30: Labour
B33: Contingencies; Wet Weather ?
B35: Superviser; Return Trip, 2 day stay - Inclusive | C35: item | D35: 4 | E35: 2423.831 | F35: =D35*E35 -> 9695.324
B36: ='LabourProject Rates_Master'!$B$14 -> TRADESMAN_LEADING HAND | C36: Day | D36: 14 | E36: ='LabourProject Rates_Master'!$E$15 -> 1231.1429 | F36: =E36*D36 -> 17236
B37: ='LabourProject Rates_Master'!$B$23 -> TRADESMAN_PLUMBER_OPERATOR | C37: Day | D37: 14 | E37: ='LabourProject Rates_Master'!$E$22 -> 941.16473 | F37: =E37*D37 -> 13176.306
B38: ='LabourProject Rates_Master'!$B$30 -> T/A & Apprentice | C38: Day | D38: 7 | E38: ='LabourProject Rates_Master'!$E$29 -> 768.06508 | F38: =E38*D38 -> 5376.4556
B39: ='LabourProject Rates_Master'!$B$36 -> Crew #1 - InGround Drainage | C39: Day | D39: 5 | E39: ='LabourProject Rates_Master'!$E$37 -> 2650.3945 | F39: =E39*D39 -> 13251.973
B40: ='LabourProject Rates_Master'!$B$43 -> Crew #2 - InGround Water/Fire | C40: Day | D40: 0 | E40: ='LabourProject Rates_Master'!$E$44 -> 2650.3945 | F40: =E40*D40 -> 0
B42: Management Labour
B44: ='LabourProject Rates_Master'!$B$14 -> TRADESMAN_LEADING HAND | C44: Day | D44: 5 | E44: ='LabourProject Rates_Master'!$E$15 -> 1231.1429 | F44: =E44*D44 -> 6155.7143 | G44: Included within stages?
B45: MH / DQ | C45: Day | D45: =[1]Program_MASTER!$C$144 -> 44 | E45: 120 | F45: =E45*D45 -> 5280 | G45: Refer Program for approx attendance on site. Technically covered in overheads. E/O for meals etc?
B46: MH / DQ - FLIGHTS | C46: ea | D46: 20 | E46: 200 | F46: =E46*D46 -> 4000
B51: ACCOMODATION (Refer Program)
B52: Per Month - Full Project (6 Persons)
B53: ='LabourProject Rates_Master'!B100 -> Full Apartment / TownHouse / Unit - VIA AGENT | C53: Month | D53: 12 | E53: ='LabourProject Rates_Master'!E103 -> 4606.0606 | F53: =D53*E53 -> 55272.727 | G53: ** 1 x 4Bed House (@650/Wk) fully kitted, +Consumable, +Cleaner etc
B54: ='LabourProject Rates_Master'!B100 -> Full Apartment / TownHouse / Unit - VIA AGENT | C54: Month | D54: 0 | E54: ='LabourProject Rates_Master'!E103 -> 4606.0606 | F54: =D54*E54 -> 0 | G54: ** 1 x 4Bed House (@650/Wk) fully kitted, +Consumable, +Cleaner etc
B56: Individual Night Stay - Private Room/Suite | H56: Avrg Nightly Book (LONG STAY)
B57: ='LabourProject Rates_Master'!$B$14 -> TRADESMAN_LEADING HAND | G57: =D14 -> 0 | H57: ='LabourProject Rates_Master'!$E$109 -> 103.24675 | I57: =H57*G57 -> 0
B58: ='LabourProject Rates_Master'!$B$23 -> TRADESMAN_PLUMBER_OPERATOR | G58: =D15 -> 0 | H58: ='LabourProject Rates_Master'!$E$109 -> 103.24675 | I58: =H58*G58 -> 0
B59: ='LabourProject Rates_Master'!$B$30 -> T/A & Apprentice | G59: =D16 -> 0 | H59: ='LabourProject Rates_Master'!$E$109 -> 103.24675 | I59: =H59*G59 -> 0
B60: ='LabourProject Rates_Master'!$B$36 -> Crew #1 - InGround Drainage | G60: =D17*3 -> 0 | H60: ='LabourProject Rates_Master'!$E$109 -> 103.24675 | I60: =H60*G60 -> 0
B62: Per Night - Extra-Over, Per Person.
B63: ='LabourProject Rates_Master'!B110 -> TCS Cost Per Person - Private Unit - NO SHARE - Nightly Booking (average allowance) | C63: item | D63: 20 | E63: =Accomodation_Master!$F$343 -> 112.85714 | F63: =D63*E63 -> 2257.1429
B65: MH / DQ | C65: item | D65: 20 | E65: 140 | F65: =D65*E65 -> 2800 | G65: TOTAL ACCOM ALLOWANCE
G66: =SUM(F53:F66) -> 60329.87 | I66: =SUM(I57:I65) -> 0
B68: Equipment, Hire, Subbies
B70: Vehicle - UTE - SUPERVISER | C70: Day | D70: =D14 -> 0 | E70: 90 | F70: =D70*E70 -> 0
B71: Vehicle - UTE - TRADESMAN | C71: Day | D71: =D15 -> 0 | E71: 60 | F71: =D71*E71 -> 0
B72: Vehicle - UTE - TRADESMAN / TA | C72: Day | D72: =D16 -> 0 | E72: 40 | F72: =D72*E72 -> 0
B74: Site Vehicle - Ute/Buggy | C74: Day | D74: 40 | E74: 90 | F74: =D74*E74 -> 3600
B77: ='Equip&HIRE_Master'!A40 -> Porta Loo_No Tank | C77: Day | D77: 40 | E77: ='Equip&HIRE_Master'!D40 -> 5.46 | F77: =D77*E77 -> 218.4
B78: ='Equip&HIRE_Master'!A41 -> 6*3m Demantable Lunchroom - COMPLETE | C78: Day | D78: =D9 -> 0 | E78: ='Equip&HIRE_Master'!D41 -> 23 | F78: =D78*E78 -> 0
B79: ='Equip&HIRE_Master'!A42 -> 6*3m Demantable Office - COMPLETE | C79: Day | D79: =D9 -> 0 | E79: ='Equip&HIRE_Master'!D42 -> 23 | F79: =D79*E79 -> 0
B80: ='Equip&HIRE_Master'!A43 -> 20Ft Shipping Container | C80: BUY | D80: 2 | E80: 1800 | F80: =D80*E80 -> 3600
B81: Skip Bin | C81: Changeover | D81: =D10 -> 0 | E81: ='Equip&HIRE_Master'!D59 -> 239.8 | F81: =D81*E81 -> 0
B85: Misc.
B87: INSURANCE | C87: item | D87: 1 | E87: 20000 | F87: =D87*E87 -> 20000
E89: Total TCS Prelims | F89: =SUM(F32:F88) -> 161920.04
A92: A | B92: OverHeads
C93: Unit | D93: REQ | E93: Cost ex GST | F93: Total ex GST | G93: Percentage across Project COST
B94: TriCore Overheads - COMPLETE…PER MONTH | C94: item | D94: 9 | E94: 40000 | F94: =D94*E94 -> 360000 | G94: ='TCS $ Sched'!$Q$68 -> 0.17860362
E96: Total TCS O/H | F96: =SUM(F94:F95) -> 360000

Sheet MISC & SITEWIDE
B1: Project:
B2: Tricore -
B3: Stage 1 Version 1
A4: Item
A9: 1 | B9: Complete -
B12: Labour
B14: DAY | J14: april 2026 direct impact Increase % (not contigency)
B15: ='LabourProject Rates_Master'!$B$14 -> TRADESMAN_LEADING HAND | C15: Day | E15: ='LabourProject Rates_Master'!$E$15 -> 1231.1429 | F15: =E15*D15 -> 0
B16: ='LabourProject Rates_Master'!$B$23 -> TRADESMAN_PLUMBER_OPERATOR | C16: Day | E16: ='LabourProject Rates_Master'!$E$22 -> 941.16473 | F16: =E16*D16 -> 0 | K16: PE Pipe & Fitting | L16: 0.38 | M16: 1.38
B17: ='LabourProject Rates_Master'!$B$30 -> T/A & Apprentice | C17: Day | E17: ='LabourProject Rates_Master'!$E$29 -> 768.06508 | F17: =E17*D17 -> 0 | K17: PVC Pipe & Fittings | L17: 0.38 | M17: 1.38
B18: ='LabourProject Rates_Master'!$B$36 -> Crew #1 - InGround Drainage | C18: Day | E18: ='LabourProject Rates_Master'!$E$37 -> 2650.3945 | F18: =E18*D18 -> 0 | K18: Subby Rates | L18: 0.15 | M18: 1.15
B19: ='LabourProject Rates_Master'!$B$43 -> Crew #2 - InGround Water/Fire | C19: Day | E19: ='LabourProject Rates_Master'!$E$44 -> 2650.3945 | F19: =E19*D19 -> 0 | K19: Delivey Rate | L19: 0.2 | M19: 1.2
B21: HOUR
B22: ='LabourProject Rates_Master'!$B$14 -> TRADESMAN_LEADING HAND | C22: HR | D22: 0 | E22: ='LabourProject Rates_Master'!$E$14 -> 123.11429 | F22: =E22*D22 -> 0
B23: ='LabourProject Rates_Master'!$B$23 -> TRADESMAN_PLUMBER_OPERATOR | C23: HR | D23: 0 | E23: ='LabourProject Rates_Master'!$E$21 -> 94.116473 | F23: =E23*D23 -> 0
B24: ='LabourProject Rates_Master'!$B$30 -> T/A & Apprentice | C24: HR | D24: 0 | E24: ='LabourProject Rates_Master'!$E$28 -> 76.806508 | F24: =E24*D24 -> 0
B25: ='LabourProject Rates_Master'!$B$36 -> Crew #1 - InGround Drainage | C25: HR | D25: 0 | E25: ='LabourProject Rates_Master'!$E$36 -> 265.03945 | F25: =E25*D25 -> 0
B26: ='LabourProject Rates_Master'!$B$43 -> Crew #2 - InGround Water/Fire | C26: HR | D26: 0 | E26: ='LabourProject Rates_Master'!$E$43 -> 265.03945 | F26: =E26*D26 -> 0
B29: Demolition & Reinstatement
B30: DEMO
B31: ='Misc Subbie Rates_Master'!A49 -> Asphalt Cutting | C31: m | E31: ='Misc Subbie Rates_Master'!D49+('Misc Subbie Rates_Master'!D49*$L$18) -> 15.525 | F31: =E31*D31 -> 0
B32: ='Misc Subbie Rates_Master'!A50 -> Concrete Cutting | C32: m | E32: ='Misc Subbie Rates_Master'!D50+('Misc Subbie Rates_Master'!D50*$L$18) -> 18.4 | F32: =E32*D32 -> 0
B33: Con Cut Establishemnt Fee | C33: ea | E33: ='Misc Subbie Rates_Master'!D51+('Misc Subbie Rates_Master'!D51*$L$18) -> 92 | F33: =E33*D33 -> 0
B34: REINSTATE - CONCRETE
B35: ='Misc Subbie Rates_Master'!A56 -> Road/Drveway Reinstate; 1mW x 150 Thck, N25/20/80, Incl Reinforcement | C35: m | E35: ='Misc Subbie Rates_Master'!D56 -> 145 | F35: =E35*D35 -> 0
B36: ='Misc Subbie Rates_Master'!A57 -> Kerb & Channel - 1m Wide | C36: ea | E36: ='Misc Subbie Rates_Master'!D57 -> 155 | F36: =E36*D36 -> 0
B37: ='Misc Subbie Rates_Master'!A58 -> Footpath - 1.5mW, N25/20/80, Incl Reinforcement | C37: lm | E37: ='Misc Subbie Rates_Master'!D58 -> 180 | F37: =E37*D37 -> 0
B38: ='Misc Subbie Rates_Master'!A59 -> Footpath - 1.5mW, EXPOSED AGG, N25/20/80, Incl Reinforcement | C38: lm | E38: ='Misc Subbie Rates_Master'!D59 -> 185 | F38: =E38*D38 -> 0
B39: REINSTATE - ASPHALT
B40: ='Misc Subbie Rates_Master'!A64 -> 50mm Thck - Trench Reinstatement Through Road/Driveway | C40: m2 | E40: ='Misc Subbie Rates_Master'!D64 -> 97 | F40: =E40*D40 -> 0
B41: ='Misc Subbie Rates_Master'!A65 -> 50mm Thck - 1.5-2m Wide Footpath reinstatements | C41: m2 | E41: ='Misc Subbie Rates_Master'!D65 -> 97 | F41: =E41*D41 -> 0
B42: ='Misc Subbie Rates_Master'!A66 -> Establishment Fee (1 per stage) | C42: Ea | E42: ='Misc Subbie Rates_Master'!D66 -> 5500 | F42: =E42*D42 -> 0
B44: Equipment & Hire - INCL WET PLANT HIRE
B46: PLANT HIRE - WET
B47: 1.8T Excavator | C47: Hr | E47: ='Misc Subbie Rates_Master'!D10 -> 100 | F47: =E47*D47 -> 0
B48: 3-5 ton Excavator | C48: Hr | E48: ='Misc Subbie Rates_Master'!D11 -> 115 | F48: =E48*D48 -> 0
B49: 3-5T Combo | C49: Hr | E49: ='Misc Subbie Rates_Master'!D12 -> 154 | F49: =E49*D49 -> 0
B50: Hammer attachment 3.5-4T | C50: Hr | E50: ='Misc Subbie Rates_Master'!D13 -> 21 | F50: =E50*D50 -> 0
B51: Ripper 3.5-4T | C51: Hr | E51: ='Misc Subbie Rates_Master'!D14 -> 10 | F51: =E51*D51 -> 0
B52: 5t Excavator | C52: Hr | E52: ='Misc Subbie Rates_Master'!D15 -> 150 | F52: =E52*D52 -> 0
B53: Hammer attachment 5T | C53: Hr | E53: ='Misc Subbie Rates_Master'!D16 -> 50 | F53: =E53*D53 -> 0
B54: Skid steer | C54: Hr | E54: ='Misc Subbie Rates_Master'!D17 -> 140 | F54: =E54*D54 -> 0
B55: 8T Excavator | C55: Hr | E55: ='Misc Subbie Rates_Master'!D18 -> 128 | F55: =E55*D55 -> 0
B56: Hammer attachment 8T | C56: Hr | E56: ='Misc Subbie Rates_Master'!D19 -> 26 | F56: =E56*D56 -> 0
B57: Ripper 8T | C57: Hr | E57: ='Misc Subbie Rates_Master'!D20 -> 10 | F57: =E57*D57 -> 0
B58: 13-15T Excavator | C58: Hr | E58: ='Misc Subbie Rates_Master'!D21 -> 153 | F58: =E58*D58 -> 0
... B65: 12t Body Truck Tipper | C65: Hr | E65: ='Misc Subbie Rates_Master'!D28 -> 110 | F65: =E65*D65 -> 0
B67: HIRE - DRY
B68: Skid Steer Loader_Tracked (CAT249+) | C68: Day | E68: ='Equip&HIRE_Master'!D4 -> 225.43333 | F68: =E68*D68 -> 0
B69: Skid Steer Loader_Wheeled (CAT226+) | C69: Day | E69: ='Equip&HIRE_Master'!D5 -> 163.96667 | F69: =E69*D69 -> 0
B70: Mini Loader, Stand-on Type | C70: Day | E70: ='Equip&HIRE_Master'!D6 -> 180 | F70: =E70*D70 -> 0
E71: ='Equip&HIRE_Master'!D7 -> 0 | F71: =E71*D71 -> 0
B72: 1.5-1.8 Ton_Excavator | C72: Day | E72: ='Equip&HIRE_Master'!D8 -> 137.14286 | F72: =E72*D72 -> 0
B73: 1.7-2Ton_Excavator | C73: Day | E73: ='Equip&HIRE_Master'!D9 -> 0 | F73: =E73*D73 -> 0
B74: 3-5Ton_Excavator | C74: Day | E74: ='Equip&HIRE_Master'!D10 -> 238.66667 | F74: =E74*D74 -> 0
B75: 8Ton_Excavator | C75: Day | E75: ='Equip&HIRE_Master'!D11 -> 261.16667 | F75: =E75*D75 -> 0
B76: 10-12Ton_Excavator | C76: Day | E76: ='Equip&HIRE_Master'!D12 -> 0 | F76: =E76*D76 -> 0
B77: 13-16Ton_Excavator | C77: Day | E77: ='Equip&HIRE_Master'!D13 -> 317.2 | F77: =E77*D77 -> 0
B78: 20-24Ton_Excavator | C78: Day | E78: ='Equip&HIRE_Master'!D14 -> 314.28571 | F78: =E78*D78 -> 0
E79: ='Equip&HIRE_Master'!D15 -> 0 | F79: =E79*D79 -> 0
B80: Ripper_1.7-2T | C80: Day | E80: ='Equip&HIRE_Master'!D16 -> 0 | F80: =E80*D80 -> 0
B81: Ripper_1.5-4T | C81: Day | E81: ='Equip&HIRE_Master'!D17 -> 32.74 | F81: =E81*D81 -> 0
B82: Ripper_3-5T | C82: Day | E82: ='Equip&HIRE_Master'!D18 -> 0 | F82: =E82*D82 -> 0
B83: Ripper_8T | C83: Day | E83: ='Equip&HIRE_Master'!D19 -> 40.38 | F83: =E83*D83 -> 0
B84: Breaker_1.7-2T | C84: Day | E84: ='Equip&HIRE_Master'!D20 -> 123.33 | F84: =E84*D84 -> 0
B85: Breaker_3-5T | C85: Day | E85: ='Equip&HIRE_Master'!D21 -> 165.89 | F85: =E85*D85 -> 0
B86: Breaker_8T | C86: Day | E86: ='Equip&HIRE_Master'!D22 -> 165.89 | F86: =E86*D86 -> 0
B87: Breaker_10-12T | C87: Day | E87: ='Equip&HIRE_Master'!D23 -> 0 | F87: =E87*D87 -> 0
B88: Breaker_13-15T | C88: Day | E88: ='Equip&HIRE_Master'!D24 -> 203 | F88: =E88*D88 -> 0
B89: Auger Drive_10-12T | E89: ='Equip&HIRE_Master'!D25 -> 0 | F89: =E89*D89 -> 0
B90: 300Dia Auger Drill | E90: ='Equip&HIRE_Master'!D26 -> 0 | F90: =E90*D90 -> 0
E91: ='Equip&HIRE_Master'!D27 -> 0 | F91: =E91*D91 -> 0
B92: 1.25T_Tipper Truck | C92: Day | E92: ='Equip&HIRE_Master'!D28 -> 205 | F92: =E92*D92 -> 0
B93: 2-4T_Tipper Truck | C93: Day | E93: ='Equip&HIRE_Master'!D29 -> 166.98 | F93: =E93*D93 -> 0
B94: <6T_Tipper Truck | C94: Day | E94: ='Equip&HIRE_Master'!D30 -> 171.42857 | F94: =E94*D94 -> 0
E95: ='Equip&HIRE_Master'!D31 -> 0 | F95: =E95*D95 -> 0
B96: <10T_Articulated Site Tipper | C96: Day | E96: ='Equip&HIRE_Master'!D32 -> 0 | F96: =E96*D96 -> 0
B97: Upright Rammer_Wacker | C97: Day | E97: ='Equip&HIRE_Master'!D33 -> 34.285714 | F97: =E97*D97 -> 0
B98: Trench Roller_Dbl Drum_Remote | C98: Day | E98: ='Equip&HIRE_Master'!D34 -> 165 | F98: =E98*D98 -> 0
B99: <26Ft_Scissor Lift - Diesel | C99: Day | E99: ='Equip&HIRE_Master'!D35 -> 0 | F99: =E99*D99 -> 0
B100: <26Ft_Scissor Lift - Elec | C100: Day | E100: ='Equip&HIRE_Master'!D36 -> 0 | F100: =E100*D100 -> 0
B101: <34Ft_Boom Lift - Diesel | C101: Day | E101: ='Equip&HIRE_Master'!D37 -> 0 | F101: =E101*D101 -> 0
B102: <34Ft_Boom Lift - Elec | C102: Day | E102: ='Equip&HIRE_Master'!D38 -> 0 | F102: =E102*D102 -> 0
E103: ='Equip&HIRE_Master'!D39 -> 0 | F103: =E103*D103 -> 0
B104: Porta Loo_No Tank | C104: Day | E104: ='Equip&HIRE_Master'!D40 -> 5.46 | F104: =E104*D104 -> 0
B105: 6*3m Demantable Lunchroom - COMPLETE | C105: Day | E105: ='Equip&HIRE_Master'!D41 -> 23 | F105: =E105*D105 -> 0
B106: 6*3m Demantable Office - COMPLETE | C106: Day | E106: ='Equip&HIRE_Master'!D42 -> 23 | F106: =E106*D106 -> 0
B107: 20Ft Shipping Container | C107: Day | E107: ='Equip&HIRE_Master'!D43 -> 0 | F107: =E107*D107 -> 0
B108: Quick Cut Demo Saw | C108: Day | E108: ='Equip&HIRE_Master'!D44 -> 0 | F108: =E108*D108 -> 0
B109: Sngl Ph_6KVA Genset | C109: Day | E109: ='Equip&HIRE_Master'!D45 -> 0 | F109: =E109*D109 -> 0
B110: Diesel Air Compressor_Trailer | C110: Day | E110: ='Equip&HIRE_Master'!D46 -> 0 | F110: =E110*D110 -> 0
B111: Air Breaker - Heavy | C111: Day | E111: ='Equip&HIRE_Master'!D47 -> 0 | F111: =E111*D111 -> 0
B112: Air Hose <10m | C112: Day | E112: ='Equip&HIRE_Master'!D48 -> 0 | F112: =E112*D112 -> 0
B113: Elec Breaker/Jachammer | C113: Day | E113: ='Equip&HIRE_Master'!D49 -> 0 | F113: =E113*D113 -> 0
B114: Flexdrive Motor Unit | C114: Day | E114: ='Equip&HIRE_Master'!D50 -> 0 | F114: =E114*D114 -> 0
B115: Flexdrive_Pump Shaft | C115: Day | E115: ='Equip&HIRE_Master'!D51 -> 0 | F115: =E115*D115 -> 0
B116: Temporary Power Board | C116: Day | E116: ='Equip&HIRE_Master'!D52 -> 0 | F116: =E116*D116 -> 0
E117: ='Equip&HIRE_Master'!D53 -> 0 | F117: =E117*D117 -> 0
B118: Dual CabUte | C118: Day | E118: ='Equip&HIRE_Master'!D54 -> 0 | F118: =E118*D118 -> 0
B119: 3m3 Skip Bbin | C119: per serive | E119: ='Equip&HIRE_Master'!D55 -> 230 | F119: =E119*D119 -> 0
...

Sheet ROK092
B1: Project:
B2: Tricore -
B3: Stage 1 Version 1
A4: Item
A9: 1 | B9: Complete -
B12: Labour
B14: DAY | J14: april 2026 direct impact Increase % (not contigency)
B15: ='LabourProject Rates_Master'!$B$14 -> TRADESMAN_LEADING HAND | C15: Day | E15: ='LabourProject Rates_Master'!$E$15 -> 1231.1429 | F15: =E15*D15 -> 0
B16: ='LabourProject Rates_Master'!$B$23 -> TRADESMAN_PLUMBER_OPERATOR | C16: Day | E16: ='LabourProject Rates_Master'!$E$22 -> 941.16473 | F16: =E16*D16 -> 0 | K16: PE Pipe & Fitting | L16: 0.38 | M16: 1.38
B17: ='LabourProject Rates_Master'!$B$30 -> T/A & Apprentice | C17: Day | E17: ='LabourProject Rates_Master'!$E$29 -> 768.06508 | F17: =E17*D17 -> 0 | K17: PVC Pipe & Fittings | L17: 0.38 | M17: 1.38
B18: ='LabourProject Rates_Master'!$B$36 -> Crew #1 - InGround Drainage | C18: Day | D18: 47 | E18: ='LabourProject Rates_Master'!$E$37 -> 2650.3945 | F18: =E18*D18 -> 124568.54 | K18: Subby Rates | L18: 0.15 | M18: 1.15
B19: ='LabourProject Rates_Master'!$B$43 -> Crew #2 - InGround Water/Fire | C19: Day | D19: 20 | E19: ='LabourProject Rates_Master'!$E$44 -> 2650.3945 | F19: =E19*D19 -> 53007.891 | K19: Delivey Rate | L19: 0.2 | M19: 1.2
B20: ='LabourProject Rates_Master'!B51 -> Crew #3 - Above Ground Drainage | C20: Day | D20: 17 | E20: ='LabourProject Rates_Master'!E52 -> 2650.3945 | F20: =E20*D20 -> 45056.707
B21: ='LabourProject Rates_Master'!B59 -> Crew #4 - Above Ground WATER/FIRE | C21: Day | D21: 49 | E21: ='LabourProject Rates_Master'!E60 -> 2650.3945 | F21: =E21*D21 -> 129869.33
B22: ='LabourProject Rates_Master'!B67 -> Crew #5 - Above Ground FitOff / Misc | C22: Day | D22: 15 | E22: ='LabourProject Rates_Master'!E68 -> 2650.3945 | F22: =E22*D22 -> 39755.918
B23: ='LabourProject Rates_Master'!B75 -> Crew #6 - DEMO | C23: Day | E23: ='LabourProject Rates_Master'!E76 -> 1709.2298 | F23: =E23*D23 -> 0
B27: HOUR
B28: ='LabourProject Rates_Master'!$B$14 -> TRADESMAN_LEADING HAND | C28: HR | D28: 0 | E28: ='LabourProject Rates_Master'!$E$14 -> 123.11429 | F28: =E28*D28 -> 0
B29: ='LabourProject Rates_Master'!$B$23 -> TRADESMAN_PLUMBER_OPERATOR | C29: HR | D29: 0 | E29: ='LabourProject Rates_Master'!$E$21 -> 94.116473 | F29: =E29*D29 -> 0
B30: ='LabourProject Rates_Master'!$B$30 -> T/A & Apprentice | C30: HR | D30: 0 | E30: ='LabourProject Rates_Master'!$E$28 -> 76.806508 | F30: =E30*D30 -> 0
B31: ='LabourProject Rates_Master'!$B$36 -> Crew #1 - InGround Drainage | C31: HR | D31: 0 | E31: ='LabourProject Rates_Master'!$E$36 -> 265.03945 | F31: =E31*D31 -> 0
B32: ='LabourProject Rates_Master'!$B$43 -> Crew #2 - InGround Water/Fire | C32: HR | D32: 0 | E32: ='LabourProject Rates_Master'!$E$43 -> 265.03945 | F32: =E32*D32 -> 0
B35: Demolition & Reinstatement
B36: DEMO
B37: ='Misc Subbie Rates_Master'!A49 -> Asphalt Cutting | C37: m | E37: ='Misc Subbie Rates_Master'!D49+('Misc Subbie Rates_Master'!D49*$L$18) -> 15.525 | F37: =E37*D37 -> 0
B38: ='Misc Subbie Rates_Master'!A50 -> Concrete Cutting | C38: m | E38: ='Misc Subbie Rates_Master'!D50+('Misc Subbie Rates_Master'!D50*$L$18) -> 18.4 | F38: =E38*D38 -> 0
B39: Con Cut Establishemnt Fee | C39: ea | E39: ='Misc Subbie Rates_Master'!D51+('Misc Subbie Rates_Master'!D51*$L$18) -> 92 | F39: =E39*D39 -> 0
B40: REINSTATE - CONCRETE
B41: ='Misc Subbie Rates_Master'!A56 -> Road/Drveway Reinstate; 1mW x 150 Thck, N25/20/80, Incl Reinforcement | C41: m | E41: ='Misc Subbie Rates_Master'!D56 -> 145 | F41: =E41*D41 -> 0
B42: ='Misc Subbie Rates_Master'!A57 -> Kerb & Channel - 1m Wide | C42: ea | E42: ='Misc Subbie Rates_Master'!D57 -> 155 | F42: =E42*D42 -> 0
B43: ='Misc Subbie Rates_Master'!A58 -> Footpath - 1.5mW, N25/20/80, Incl Reinforcement | C43: lm | E43: ='Misc Subbie Rates_Master'!D58 -> 180 | F43: =E43*D43 -> 0
B44: ='Misc Subbie Rates_Master'!A59 -> Footpath - 1.5mW, EXPOSED AGG, N25/20/80, Incl Reinforcement | C44: lm | E44: ='Misc Subbie Rates_Master'!D59 -> 185 | F44: =E44*D44 -> 0
B45: REINSTATE - ASPHALT
B46: ='Misc Subbie Rates_Master'!A64 -> 50mm Thck - Trench Reinstatement Through Road/Driveway | C46: m2 | E46: ='Misc Subbie Rates_Master'!D64 -> 97 | F46: =E46*D46 -> 0
B47: ='Misc Subbie Rates_Master'!A65 -> 50mm Thck - 1.5-2m Wide Footpath reinstatements | C47: m2 | E47: ='Misc Subbie Rates_Master'!D65 -> 97 | F47: =E47*D47 -> 0
B48: ='Misc Subbie Rates_Master'!A66 -> Establishment Fee (1 per stage) | C48: Ea | E48: ='Misc Subbie Rates_Master'!D66 -> 5500 | F48: =E48*D48 -> 0
B50: Equipment & Hire - INCL WET PLANT HIRE
A52: HIDDEN | B52: PLANT HIRE - WET
B53: 1.8T Excavator | C53: Hr | E53: ='Misc Subbie Rates_Master'!D10 -> 100 | F53: =E53*D53 -> 0
B54: 3-5 ton Excavator | C54: Hr | E54: ='Misc Subbie Rates_Master'!D11 -> 115 | F54: =E54*D54 -> 0
B55: 3-5T Combo | C55: Hr | E55: ='Misc Subbie Rates_Master'!D12 -> 154 | F55: =E55*D55 -> 0
B56: Hammer attachment 3.5-4T | C56: Hr | E56: ='Misc Subbie Rates_Master'!D13 -> 21 | F56: =E56*D56 -> 0
B57: Ripper 3.5-4T | C57: Hr | E57: ='Misc Subbie Rates_Master'!D14 -> 10 | F57: =E57*D57 -> 0
B58: 5t Excavator | C58: Hr | E58: ='Misc Subbie Rates_Master'!D15 -> 150 | F58: =E58*D58 -> 0
B59: Hammer attachment 5T | C59: Hr | E59: ='Misc Subbie Rates_Master'!D16 -> 50 | F59: =E59*D59 -> 0
B60: Skid steer | C60: Hr | E60: ='Misc Subbie Rates_Master'!D17 -> 140 | F60: =E60*D60 -> 0
B61: 8T Excavator | C61: Hr | E61: ='Misc Subbie Rates_Master'!D18 -> 128 | F61: =E61*D61 -> 0
B62: Hammer attachment 8T | C62: Hr | E62: ='Misc Subbie Rates_Master'!D19 -> 26 | F62: =E62*D62 -> 0
B63: Ripper 8T | C63: Hr | E63: ='Misc Subbie Rates_Master'!D20 -> 10 | F63: =E63*D63 -> 0
B64: 13-15T Excavator | C64: Hr | E64: ='Misc Subbie Rates_Master'!D21 -> 153 | F64: =E64*D64 -> 0
... B71: 12t Body Truck Tipper | C71: Hr | E71: ='Misc Subbie Rates_Master'!D28 -> 110 | F71: =E71*D71 -> 0
B73: HIRE - DRY
B74: Skid Steer Loader_Tracked (CAT249+) | C74: Day | D74: 35 | E74: ='Equip&HIRE_Master'!D4 -> 225.43333 | F74: =E74*D74 -> 7890.1667
B75: Skid Steer Loader_Wheeled (CAT226+) | C75: Day | E75: ='Equip&HIRE_Master'!D5 -> 163.96667 | F75: =E75*D75 -> 0
B76: Mini Loader, Stand-on Type | C76: Day | E76: ='Equip&HIRE_Master'!D6 -> 180 | F76: =E76*D76 -> 0
E77: ='Equip&HIRE_Master'!D7 -> 0 | F77: =E77*D77 -> 0
B78: 1.5-1.8 Ton_Excavator | C78: Day | D78: 35 | E78: ='Equip&HIRE_Master'!D8 -> 137.14286 | F78: =E78*D78 -> 4800
B79: 1.7-2Ton_Excavator | C79: Day | E79: ='Equip&HIRE_Master'!D9 -> 0 | F79: =E79*D79 -> 0
B80: 3-5Ton_Excavator | C80: Day | E80: ='Equip&HIRE_Master'!D10 -> 238.66667 | F80: =E80*D80 -> 0
B81: 8Ton_Excavator | C81: Day | D81: 35 | E81: ='Equip&HIRE_Master'!D11 -> 261.16667 | F81: =E81*D81 -> 9140.8333
B82: 10-12Ton_Excavator | C82: Day | E82: ='Equip&HIRE_Master'!D12 -> 0 | F82: =E82*D82 -> 0
B83: 13-16Ton_Excavator | C83: Day | E83: ='Equip&HIRE_Master'!D13 -> 317.2 | F83: =E83*D83 -> 0
B84: 20-24Ton_Excavator | C84: Day | E84: ='Equip&HIRE_Master'!D14 -> 314.28571 | F84: =E84*D84 -> 0
E85: ='Equip&HIRE_Master'!D15 -> 0 | F85: =E85*D85 -> 0
B86: Ripper_1.7-2T | C86: Day | E86: ='Equip&HIRE_Master'!D16 -> 0 | F86: =E86*D86 -> 0
B87: Ripper_1.5-4T | C87: Day | E87: ='Equip&HIRE_Master'!D17 -> 32.74 | F87: =E87*D87 -> 0
B88: Ripper_3-5T | C88: Day | E88: ='Equip&HIRE_Master'!D18 -> 0 | F88: =E88*D88 -> 0
B89: Ripper_8T | C89: Day | E89: ='Equip&HIRE_Master'!D19 -> 40.38 | F89: =E89*D89 -> 0
B90: Breaker_1.7-2T | C90: Day | E90: ='Equip&HIRE_Master'!D20 -> 123.33 | F90: =E90*D90 -> 0
B91: Breaker_3-5T | C91: Day | E91: ='Equip&HIRE_Master'!D21 -> 165.89 | F91: =E91*D91 -> 0
B92: Breaker_8T | C92: Day | E92: ='Equip&HIRE_Master'!D22 -> 165.89 | F92: =E92*D92 -> 0
B93: Breaker_10-12T | C93: Day | E93: ='Equip&HIRE_Master'!D23 -> 0 | F93: =E93*D93 -> 0
B94: Breaker_13-15T | C94: Day | E94: ='Equip&HIRE_Master'!D24 -> 203 | F94: =E94*D94 -> 0
B95: Auger Drive_10-12T | E95: ='Equip&HIRE_Master'!D25 -> 0 | F95: =E95*D95 -> 0
B96: 300Dia Auger Drill | E96: ='Equip&HIRE_Master'!D26 -> 0 | F96: =E96*D96 -> 0
E97: ='Equip&HIRE_Master'!D27 -> 0 | F97: =E97*D97 -> 0
B98: 1.25T_Tipper Truck | C98: Day | D98: 35 | E98: ='Equip&HIRE_Master'!D28 -> 205 | F98: =E98*D98 -> 7175
B99: 2-4T_Tipper Truck | C99: Day | E99: ='Equip&HIRE_Master'!D29 -> 166.98 | F99: =E99*D99 -> 0
B100: <6T_Tipper Truck | C100: Day | E100: ='Equip&HIRE_Master'!D30 -> 171.42857 | F100: =E100*D100 -> 0
E101: ='Equip&HIRE_Master'!D31 -> 0 | F101: =E101*D101 -> 0
B102: <10T_Articulated Site Tipper | C102: Day | E102: ='Equip&HIRE_Master'!D32 -> 0 | F102: =E102*D102 -> 0
B103: Upright Rammer_Wacker | C103: Day | D103: 0 | E103: ='Equip&HIRE_Master'!D33 -> 34.285714 | F103: =E103*D103 -> 0
B104: Trench Roller_Dbl Drum_Remote | C104: Day | D104: 35 | E104: ='Equip&HIRE_Master'!D34 -> 165 | F104: =E104*D104 -> 5775
B105: <26Ft_Scissor Lift - Diesel | C105: Day | D105: 18 | E105: 300 | F105: =E105*D105 -> 5400
B106: <26Ft_Scissor Lift - Elec | C106: Day | E106: ='Equip&HIRE_Master'!D36 -> 0 | F106: =E106*D106 -> 0
B107: <34Ft_Boom Lift - Diesel | C107: Day | E107: ='Equip&HIRE_Master'!D37 -> 0 | F107: =E107*D107 -> 0
B108: <34Ft_Boom Lift - Elec | C108: Day | E108: ='Equip&HIRE_Master'!D38 -> 0 | F108: =E108*D108 -> 0
E109: ='Equip&HIRE_Master'!D39 -> 0 | F109: =E109*D109 -> 0
B110: Porta Loo_No Tank | C110: Day | E110: ='Equip&HIRE_Master'!D40 -> 5.46 | F110: =E110*D110 -> 0
B111: 6*3m Demantable Lunchroom - COMPLETE | C111: Day | E111: ='Equip&HIRE_Master'!D41 -> 23 | F111: =E111*D111 -> 0
B112: 6*3m Demantable Office - COMPLETE | C112: Day | E112: ='Equip&HIRE_Master'!D42 -> 23 | F112: =E112*D112 -> 0
B113: 20Ft Shipping Container | C113: Day | E113: ='Equip&HIRE_Master'!D43 -> 0 | F113: =E113*D113 -> 0
B114: Quick Cut Demo Saw | C114: Day | E114: ='Equip&HIRE_Master'!D44 -> 0 | F114: =E114*D114 -> 0
B115: Sngl Ph_6KVA Genset | C115: Day | E115: ='Equip&HIRE_Master'!D45 -> 0 | F115: =E115*D115 -> 0
B116: Diesel Air Compressor_Trailer | C116: Day | E116: ='Equip&HIRE_Master'!D46 -> 0 | F116: =E116*D116 -> 0
B117: Air Breaker - Heavy | C117: Day | E117: ='Equip&HIRE_Master'!D47 -> 0 | F117: =E117*D117 -> 0
B118: Air Hose <10m | C118: Day | E118: ='Equip&HIRE_Master'!D48 -> 0 | F118: =E118*D118 -> 0
B119: Elec Breaker/Jachammer | C119: Day | E119: ='Equip&HIRE_Master'!D49 -> 0 | F119: =E119*D119 -> 0
B120: Flexdrive Motor Unit | C120: Day | E120: ='Equip&HIRE_Master'!D50 -> 0 | F120: =E120*D120 -> 0
B121: Flexdrive_Pump Shaft | C121: Day | E121: ='Equip&HIRE_Master'!D51 -> 0 | F121: =E121*D121 -> 0
...

Sheet ROK21A
B1: Project:
B2: Tricore -
B3: Stage 1 Version 1
A4: Item
A9: 1 | B9: Complete -
B12: Labour
B14: DAY | J14: april 2026 direct impact Increase % (not contigency)
B15: ='LabourProject Rates_Master'!$B$14 -> TRADESMAN_LEADING HAND | C15: Day | E15: ='LabourProject Rates_Master'!$E$15 -> 1231.1429 | F15: =E15*D15 -> 0
B16: ='LabourProject Rates_Master'!$B$23 -> TRADESMAN_PLUMBER_OPERATOR | C16: Day | E16: ='LabourProject Rates_Master'!$E$22 -> 941.16473 | F16: =E16*D16 -> 0 | K16: PE Pipe & Fitting | L16: 0.38 | M16: 1.38
B17: ='LabourProject Rates_Master'!$B$30 -> T/A & Apprentice | C17: Day | E17: ='LabourProject Rates_Master'!$E$29 -> 768.06508 | F17: =E17*D17 -> 0 | K17: PVC Pipe & Fittings | L17: 0.38 | M17: 1.38
B18: ='LabourProject Rates_Master'!$B$36 -> Crew #1 - InGround Drainage | C18: Day | D18: 3 | E18: ='LabourProject Rates_Master'!$E$37 -> 2650.3945 | F18: =E18*D18 -> 7951.1836 | K18: Subby Rates | L18: 0.15 | M18: 1.15
B19: ='LabourProject Rates_Master'!$B$43 -> Crew #2 - InGround Water/Fire | C19: Day | D19: 3 | E19: ='LabourProject Rates_Master'!$E$44 -> 2650.3945 | F19: =E19*D19 -> 7951.1836 | K19: Delivey Rate | L19: 0.2 | M19: 1.2
B20: ='LabourProject Rates_Master'!B51 -> Crew #3 - Above Ground Drainage | C20: Day | D20: 2 | E20: ='LabourProject Rates_Master'!E52 -> 2650.3945 | F20: =E20*D20 -> 5300.7891
B21: ='LabourProject Rates_Master'!B59 -> Crew #4 - Above Ground WATER/FIRE | C21: Day | D21: 2 | E21: ='LabourProject Rates_Master'!E60 -> 2650.3945 | F21: =E21*D21 -> 5300.7891
B22: ='LabourProject Rates_Master'!B67 -> Crew #5 - Above Ground FitOff / Misc | C22: Day | D22: 2 | E22: ='LabourProject Rates_Master'!E68 -> 2650.3945 | F22: =E22*D22 -> 5300.7891
B23: ='LabourProject Rates_Master'!B75 -> Crew #6 - DEMO | C23: Day | D23: 2 | E23: ='LabourProject Rates_Master'!E76 -> 1709.2298 | F23: =E23*D23 -> 3418.4596
B25: HOUR
B26: ='LabourProject Rates_Master'!$B$14 -> TRADESMAN_LEADING HAND | C26: HR | D26: 0 | E26: ='LabourProject Rates_Master'!$E$14 -> 123.11429 | F26: =E26*D26 -> 0
B27: ='LabourProject Rates_Master'!$B$23 -> TRADESMAN_PLUMBER_OPERATOR | C27: HR | D27: 0 | E27: ='LabourProject Rates_Master'!$E$21 -> 94.116473 | F27: =E27*D27 -> 0
B28: ='LabourProject Rates_Master'!$B$30 -> T/A & Apprentice | C28: HR | D28: 0 | E28: ='LabourProject Rates_Master'!$E$28 -> 76.806508 | F28: =E28*D28 -> 0
B29: ='LabourProject Rates_Master'!$B$36 -> Crew #1 - InGround Drainage | C29: HR | D29: 0 | E29: ='LabourProject Rates_Master'!$E$36 -> 265.03945 | F29: =E29*D29 -> 0
B30: ='LabourProject Rates_Master'!$B$43 -> Crew #2 - InGround Water/Fire | C30: HR | D30: 0 | E30: ='LabourProject Rates_Master'!$E$43 -> 265.03945 | F30: =E30*D30 -> 0
B33: Demolition & Reinstatement
B34: DEMO
B35: ='Misc Subbie Rates_Master'!A49 -> Asphalt Cutting | C35: m | E35: ='Misc Subbie Rates_Master'!D49+('Misc Subbie Rates_Master'!D49*$L$18) -> 15.525 | F35: =E35*D35 -> 0
B36: ='Misc Subbie Rates_Master'!A50 -> Concrete Cutting | C36: m | E36: ='Misc Subbie Rates_Master'!D50+('Misc Subbie Rates_Master'!D50*$L$18) -> 18.4 | F36: =E36*D36 -> 0
B37: Con Cut Establishemnt Fee | C37: ea | E37: ='Misc Subbie Rates_Master'!D51+('Misc Subbie Rates_Master'!D51*$L$18) -> 92 | F37: =E37*D37 -> 0
B38: REINSTATE - CONCRETE
B39: ='Misc Subbie Rates_Master'!A56 -> Road/Drveway Reinstate; 1mW x 150 Thck, N25/20/80, Incl Reinforcement | C39: m | E39: ='Misc Subbie Rates_Master'!D56 -> 145 | F39: =E39*D39 -> 0
B40: ='Misc Subbie Rates_Master'!A57 -> Kerb & Channel - 1m Wide | C40: ea | E40: ='Misc Subbie Rates_Master'!D57 -> 155 | F40: =E40*D40 -> 0
B41: ='Misc Subbie Rates_Master'!A58 -> Footpath - 1.5mW, N25/20/80, Incl Reinforcement | C41: lm | E41: ='Misc Subbie Rates_Master'!D58 -> 180 | F41: =E41*D41 -> 0
B42: ='Misc Subbie Rates_Master'!A59 -> Footpath - 1.5mW, EXPOSED AGG, N25/20/80, Incl Reinforcement | C42: lm | E42: ='Misc Subbie Rates_Master'!D59 -> 185 | F42: =E42*D42 -> 0
B43: REINSTATE - ASPHALT
B44: ='Misc Subbie Rates_Master'!A64 -> 50mm Thck - Trench Reinstatement Through Road/Driveway | C44: m2 | E44: ='Misc Subbie Rates_Master'!D64 -> 97 | F44: =E44*D44 -> 0
B45: ='Misc Subbie Rates_Master'!A65 -> 50mm Thck - 1.5-2m Wide Footpath reinstatements | C45: m2 | E45: ='Misc Subbie Rates_Master'!D65 -> 97 | F45: =E45*D45 -> 0
B46: ='Misc Subbie Rates_Master'!A66 -> Establishment Fee (1 per stage) | C46: Ea | E46: ='Misc Subbie Rates_Master'!D66 -> 5500 | F46: =E46*D46 -> 0
B48: Equipment & Hire - INCL WET PLANT HIRE
B50: PLANT HIRE - WET
B51: 1.8T Excavator | C51: Hr | E51: ='Misc Subbie Rates_Master'!D10 -> 100 | F51: =E51*D51 -> 0
B52: 3-5 ton Excavator | C52: Hr | E52: ='Misc Subbie Rates_Master'!D11 -> 115 | F52: =E52*D52 -> 0
B53: 3-5T Combo | C53: Hr | E53: ='Misc Subbie Rates_Master'!D12 -> 154 | F53: =E53*D53 -> 0
B54: Hammer attachment 3.5-4T | C54: Hr | E54: ='Misc Subbie Rates_Master'!D13 -> 21 | F54: =E54*D54 -> 0
B55: Ripper 3.5-4T | C55: Hr | E55: ='Misc Subbie Rates_Master'!D14 -> 10 | F55: =E55*D55 -> 0
B56: 5t Excavator | C56: Hr | E56: ='Misc Subbie Rates_Master'!D15 -> 150 | F56: =E56*D56 -> 0
B57: Hammer attachment 5T | C57: Hr | E57: ='Misc Subbie Rates_Master'!D16 -> 50 | F57: =E57*D57 -> 0
B58: Skid steer | C58: Hr | E58: ='Misc Subbie Rates_Master'!D17 -> 140 | F58: =E58*D58 -> 0
B59: 8T Excavator | C59: Hr | E59: ='Misc Subbie Rates_Master'!D18 -> 128 | F59: =E59*D59 -> 0
B60: Hammer attachment 8T | C60: Hr | E60: ='Misc Subbie Rates_Master'!D19 -> 26 | F60: =E60*D60 -> 0
B61: Ripper 8T | C61: Hr | E61: ='Misc Subbie Rates_Master'!D20 -> 10 | F61: =E61*D61 -> 0
B62: 13-15T Excavator | C62: Hr | E62: ='Misc Subbie Rates_Master'!D21 -> 153 | F62: =E62*D62 -> 0
... B69: 12t Body Truck Tipper | C69: Hr | E69: ='Misc Subbie Rates_Master'!D28 -> 110 | F69: =E69*D69 -> 0
B71: HIRE - DRY
B72: Skid Steer Loader_Tracked (CAT249+) | C72: Day | D72: 3 | E72: ='Equip&HIRE_Master'!D4 -> 225.43333 | F72: =E72*D72 -> 676.3
B73: Skid Steer Loader_Wheeled (CAT226+) | C73: Day | E73: ='Equip&HIRE_Master'!D5 -> 163.96667 | F73: =E73*D73 -> 0
B74: Mini Loader, Stand-on Type | C74: Day | E74: ='Equip&HIRE_Master'!D6 -> 180 | F74: =E74*D74 -> 0
E75: ='Equip&HIRE_Master'!D7 -> 0 | F75: =E75*D75 -> 0
B76: 1.5-1.8 Ton_Excavator | C76: Day | D76: 3 | E76: ='Equip&HIRE_Master'!D8 -> 137.14286 | F76: =E76*D76 -> 411.42857
B77: 1.7-2Ton_Excavator | C77: Day | E77: ='Equip&HIRE_Master'!D9 -> 0 | F77: =E77*D77 -> 0
B78: 3-5Ton_Excavator | C78: Day | E78: ='Equip&HIRE_Master'!D10 -> 238.66667 | F78: =E78*D78 -> 0
B79: 8Ton_Excavator | C79: Day | E79: ='Equip&HIRE_Master'!D11 -> 261.16667 | F79: =E79*D79 -> 0
B80: 10-12Ton_Excavator | C80: Day | E80: ='Equip&HIRE_Master'!D12 -> 0 | F80: =E80*D80 -> 0
B81: 13-16Ton_Excavator | C81: Day | E81: ='Equip&HIRE_Master'!D13 -> 317.2 | F81: =E81*D81 -> 0
B82: 20-24Ton_Excavator | C82: Day | E82: ='Equip&HIRE_Master'!D14 -> 314.28571 | F82: =E82*D82 -> 0
E83: ='Equip&HIRE_Master'!D15 -> 0 | F83: =E83*D83 -> 0
B84: Ripper_1.7-2T | C84: Day | E84: ='Equip&HIRE_Master'!D16 -> 0 | F84: =E84*D84 -> 0
B85: Ripper_1.5-4T | C85: Day | E85: ='Equip&HIRE_Master'!D17 -> 32.74 | F85: =E85*D85 -> 0
B86: Ripper_3-5T | C86: Day | E86: ='Equip&HIRE_Master'!D18 -> 0 | F86: =E86*D86 -> 0
B87: Ripper_8T | C87: Day | E87: ='Equip&HIRE_Master'!D19 -> 40.38 | F87: =E87*D87 -> 0
B88: Breaker_1.7-2T | C88: Day | E88: ='Equip&HIRE_Master'!D20 -> 123.33 | F88: =E88*D88 -> 0
B89: Breaker_3-5T | C89: Day | E89: ='Equip&HIRE_Master'!D21 -> 165.89 | F89: =E89*D89 -> 0
B90: Breaker_8T | C90: Day | E90: ='Equip&HIRE_Master'!D22 -> 165.89 | F90: =E90*D90 -> 0
B91: Breaker_10-12T | C91: Day | E91: ='Equip&HIRE_Master'!D23 -> 0 | F91: =E91*D91 -> 0
B92: Breaker_13-15T | C92: Day | E92: ='Equip&HIRE_Master'!D24 -> 203 | F92: =E92*D92 -> 0
B93: Auger Drive_10-12T | E93: ='Equip&HIRE_Master'!D25 -> 0 | F93: =E93*D93 -> 0
B94: 300Dia Auger Drill | E94: ='Equip&HIRE_Master'!D26 -> 0 | F94: =E94*D94 -> 0
E95: ='Equip&HIRE_Master'!D27 -> 0 | F95: =E95*D95 -> 0
B96: 1.25T_Tipper Truck | C96: Day | E96: ='Equip&HIRE_Master'!D28 -> 205 | F96: =E96*D96 -> 0
B97: 2-4T_Tipper Truck | C97: Day | E97: ='Equip&HIRE_Master'!D29 -> 166.98 | F97: =E97*D97 -> 0
B98: <6T_Tipper Truck | C98: Day | E98: ='Equip&HIRE_Master'!D30 -> 171.42857 | F98: =E98*D98 -> 0
E99: ='Equip&HIRE_Master'!D31 -> 0 | F99: =E99*D99 -> 0
B100: <10T_Articulated Site Tipper | C100: Day | E100: ='Equip&HIRE_Master'!D32 -> 0 | F100: =E100*D100 -> 0
B101: Upright Rammer_Wacker | C101: Day | D101: 3 | E101: ='Equip&HIRE_Master'!D33 -> 34.285714 | F101: =E101*D101 -> 102.85714
B102: Trench Roller_Dbl Drum_Remote | C102: Day | E102: ='Equip&HIRE_Master'!D34 -> 165 | F102: =E102*D102 -> 0
B103: <26Ft_Scissor Lift - Diesel | C103: Day | E103: ='Equip&HIRE_Master'!D35 -> 0 | F103: =E103*D103 -> 0
B104: <26Ft_Scissor Lift - Elec | C104: Day | E104: ='Equip&HIRE_Master'!D36 -> 0 | F104: =E104*D104 -> 0
B105: <34Ft_Boom Lift - Diesel | C105: Day | E105: ='Equip&HIRE_Master'!D37 -> 0 | F105: =E105*D105 -> 0
B106: <34Ft_Boom Lift - Elec | C106: Day | E106: ='Equip&HIRE_Master'!D38 -> 0 | F106: =E106*D106 -> 0
E107: ='Equip&HIRE_Master'!D39 -> 0 | F107: =E107*D107 -> 0
B108: Porta Loo_No Tank | C108: Day | E108: ='Equip&HIRE_Master'!D40 -> 5.46 | F108: =E108*D108 -> 0
B109: 6*3m Demantable Lunchroom - COMPLETE | C109: Day | E109: ='Equip&HIRE_Master'!D41 -> 23 | F109: =E109*D109 -> 0
B110: 6*3m Demantable Office - COMPLETE | C110: Day | E110: ='Equip&HIRE_Master'!D42 -> 23 | F110: =E110*D110 -> 0
B111: 20Ft Shipping Container | C111: Day | E111: ='Equip&HIRE_Master'!D43 -> 0 | F111: =E111*D111 -> 0
B112: Quick Cut Demo Saw | C112: Day | E112: ='Equip&HIRE_Master'!D44 -> 0 | F112: =E112*D112 -> 0
B113: Sngl Ph_6KVA Genset | C113: Day | E113: ='Equip&HIRE_Master'!D45 -> 0 | F113: =E113*D113 -> 0
B114: Diesel Air Compressor_Trailer | C114: Day | E114: ='Equip&HIRE_Master'!D46 -> 0 | F114: =E114*D114 -> 0
B115: Air Breaker - Heavy | C115: Day | E115: ='Equip&HIRE_Master'!D47 -> 0 | F115: =E115*D115 -> 0
B116: Air Hose <10m | C116: Day | E116: ='Equip&HIRE_Master'!D48 -> 0 | F116: =E116*D116 -> 0
B117: Elec Breaker/Jachammer | C117: Day | E117: ='Equip&HIRE_Master'!D49 -> 0 | F117: =E117*D117 -> 0
B118: Flexdrive Motor Unit | C118: Day | E118: ='Equip&HIRE_Master'!D50 -> 0 | F118: =E118*D118 -> 0
B119: Flexdrive_Pump Shaft | C119: Day | E119: ='Equip&HIRE_Master'!D51 -> 0 | F119: =E119*D119 -> 0
...

Sheet ROK019
B1: Project:
B2: Tricore -
B3: Stage 1 Version 1
A4: Item
A9: 1 | B9: Complete -
B12: Labour
B14: DAY | J14: april 2026 direct impact Increase % (not contigency)
B15: ='LabourProject Rates_Master'!$B$14 -> TRADESMAN_LEADING HAND | C15: Day | E15: ='LabourProject Rates_Master'!$E$15 -> 1231.1429 | F15: =E15*D15 -> 0
B16: ='LabourProject Rates_Master'!$B$23 -> TRADESMAN_PLUMBER_OPERATOR | C16: Day | E16: ='LabourProject Rates_Master'!$E$22 -> 941.16473 | F16: =E16*D16 -> 0 | K16: PE Pipe & Fitting | L16: 0.38 | M16: 1.38
B17: ='LabourProject Rates_Master'!$B$30 -> T/A & Apprentice | C17: Day | E17: ='LabourProject Rates_Master'!$E$29 -> 768.06508 | F17: =E17*D17 -> 0 | K17: PVC Pipe & Fittings | L17: 0.38 | M17: 1.38
B18: ='LabourProject Rates_Master'!$B$36 -> Crew #1 - InGround Drainage | C18: Day | E18: ='LabourProject Rates_Master'!$E$37 -> 2650.3945 | F18: =E18*D18 -> 0 | K18: Subby Rates | L18: 0.15 | M18: 1.15
B19: ='LabourProject Rates_Master'!$B$43 -> Crew #2 - InGround Water/Fire | C19: Day | E19: ='LabourProject Rates_Master'!$E$44 -> 2650.3945 | F19: =E19*D19 -> 0 | K19: Delivey Rate | L19: 0.2 | M19: 1.2
B20: ='LabourProject Rates_Master'!B51 -> Crew #3 - Above Ground Drainage | C20: Day | D20: 9 | E20: ='LabourProject Rates_Master'!E52 -> 2650.3945 | F20: =E20*D20 -> 23853.551
B21: ='LabourProject Rates_Master'!B59 -> Crew #4 - Above Ground WATER/FIRE | C21: Day | D21: 13 | E21: ='LabourProject Rates_Master'!E60 -> 2650.3945 | F21: =E21*D21 -> 34455.129
B22: ='LabourProject Rates_Master'!B67 -> Crew #5 - Above Ground FitOff / Misc | C22: Day | D22: 8 | E22: ='LabourProject Rates_Master'!E68 -> 2650.3945 | F22: =E22*D22 -> 21203.156
B23: ='LabourProject Rates_Master'!B75 -> Crew #6 - DEMO | C23: Day | D23: 9 | E23: ='LabourProject Rates_Master'!E76 -> 1709.2298 | F23: =E23*D23 -> 15383.068
B25: HOUR
B26: ='LabourProject Rates_Master'!$B$14 -> TRADESMAN_LEADING HAND | C26: HR | D26: 0 | E26: ='LabourProject Rates_Master'!$E$14 -> 123.11429 | F26: =E26*D26 -> 0
B27: ='LabourProject Rates_Master'!$B$23 -> TRADESMAN_PLUMBER_OPERATOR | C27: HR | D27: 0 | E27: ='LabourProject Rates_Master'!$E$21 -> 94.116473 | F27: =E27*D27 -> 0
B28: ='LabourProject Rates_Master'!$B$30 -> T/A & Apprentice | C28: HR | D28: 0 | E28: ='LabourProject Rates_Master'!$E$28 -> 76.806508 | F28: =E28*D28 -> 0
B29: ='LabourProject Rates_Master'!$B$36 -> Crew #1 - InGround Drainage | C29: HR | D29: 0 | E29: ='LabourProject Rates_Master'!$E$36 -> 265.03945 | F29: =E29*D29 -> 0
B30: ='LabourProject Rates_Master'!$B$43 -> Crew #2 - InGround Water/Fire | C30: HR | D30: 0 | E30: ='LabourProject Rates_Master'!$E$43 -> 265.03945 | F30: =E30*D30 -> 0
B33: Demolition & Reinstatement
B34: DEMO
B35: ='Misc Subbie Rates_Master'!A49 -> Asphalt Cutting | C35: m | E35: ='Misc Subbie Rates_Master'!D49+('Misc Subbie Rates_Master'!D49*$L$18) -> 15.525 | F35: =E35*D35 -> 0
B36: ='Misc Subbie Rates_Master'!A50 -> Concrete Cutting | C36: m | E36: ='Misc Subbie Rates_Master'!D50+('Misc Subbie Rates_Master'!D50*$L$18) -> 18.4 | F36: =E36*D36 -> 0
B37: Con Cut Establishemnt Fee | C37: ea | E37: ='Misc Subbie Rates_Master'!D51+('Misc Subbie Rates_Master'!D51*$L$18) -> 92 | F37: =E37*D37 -> 0
B38: REINSTATE - CONCRETE
B39: ='Misc Subbie Rates_Master'!A56 -> Road/Drveway Reinstate; 1mW x 150 Thck, N25/20/80, Incl Reinforcement | C39: m | E39: ='Misc Subbie Rates_Master'!D56 -> 145 | F39: =E39*D39 -> 0
B40: ='Misc Subbie Rates_Master'!A57 -> Kerb & Channel - 1m Wide | C40: ea | E40: ='Misc Subbie Rates_Master'!D57 -> 155 | F40: =E40*D40 -> 0
B41: ='Misc Subbie Rates_Master'!A58 -> Footpath - 1.5mW, N25/20/80, Incl Reinforcement | C41: lm | E41: ='Misc Subbie Rates_Master'!D58 -> 180 | F41: =E41*D41 -> 0
B42: ='Misc Subbie Rates_Master'!A59 -> Footpath - 1.5mW, EXPOSED AGG, N25/20/80, Incl Reinforcement | C42: lm | E42: ='Misc Subbie Rates_Master'!D59 -> 185 | F42: =E42*D42 -> 0
B43: REINSTATE - ASPHALT
B44: ='Misc Subbie Rates_Master'!A64 -> 50mm Thck - Trench Reinstatement Through Road/Driveway | C44: m2 | E44: ='Misc Subbie Rates_Master'!D64 -> 97 | F44: =E44*D44 -> 0
B45: ='Misc Subbie Rates_Master'!A65 -> 50mm Thck - 1.5-2m Wide Footpath reinstatements | C45: m2 | E45: ='Misc Subbie Rates_Master'!D65 -> 97 | F45: =E45*D45 -> 0
B46: ='Misc Subbie Rates_Master'!A66 -> Establishment Fee (1 per stage) | C46: Ea | E46: ='Misc Subbie Rates_Master'!D66 -> 5500 | F46: =E46*D46 -> 0
B48: Equipment & Hire - INCL WET PLANT HIRE
B50: PLANT HIRE - WET
B51: 1.8T Excavator | C51: Hr | E51: ='Misc Subbie Rates_Master'!D10 -> 100 | F51: =E51*D51 -> 0
B52: 3-5 ton Excavator | C52: Hr | E52: ='Misc Subbie Rates_Master'!D11 -> 115 | F52: =E52*D52 -> 0
B53: 3-5T Combo | C53: Hr | E53: ='Misc Subbie Rates_Master'!D12 -> 154 | F53: =E53*D53 -> 0
B54: Hammer attachment 3.5-4T | C54: Hr | E54: ='Misc Subbie Rates_Master'!D13 -> 21 | F54: =E54*D54 -> 0
B55: Ripper 3.5-4T | C55: Hr | E55: ='Misc Subbie Rates_Master'!D14 -> 10 | F55: =E55*D55 -> 0
B56: 5t Excavator | C56: Hr | E56: ='Misc Subbie Rates_Master'!D15 -> 150 | F56: =E56*D56 -> 0
B57: Hammer attachment 5T | C57: Hr | E57: ='Misc Subbie Rates_Master'!D16 -> 50 | F57: =E57*D57 -> 0
B58: Skid steer | C58: Hr | E58: ='Misc Subbie Rates_Master'!D17 -> 140 | F58: =E58*D58 -> 0
B59: 8T Excavator | C59: Hr | E59: ='Misc Subbie Rates_Master'!D18 -> 128 | F59: =E59*D59 -> 0
B60: Hammer attachment 8T | C60: Hr | E60: ='Misc Subbie Rates_Master'!D19 -> 26 | F60: =E60*D60 -> 0
B61: Ripper 8T | C61: Hr | E61: ='Misc Subbie Rates_Master'!D20 -> 10 | F61: =E61*D61 -> 0
B62: 13-15T Excavator | C62: Hr | E62: ='Misc Subbie Rates_Master'!D21 -> 153 | F62: =E62*D62 -> 0
... B69: 12t Body Truck Tipper | C69: Hr | E69: ='Misc Subbie Rates_Master'!D28 -> 110 | F69: =E69*D69 -> 0
B71: HIRE - DRY
B72: Skid Steer Loader_Tracked (CAT249+) | C72: Day | E72: ='Equip&HIRE_Master'!D4 -> 225.43333 | F72: =E72*D72 -> 0
B73: Skid Steer Loader_Wheeled (CAT226+) | C73: Day | E73: ='Equip&HIRE_Master'!D5 -> 163.96667 | F73: =E73*D73 -> 0
B74: Mini Loader, Stand-on Type | C74: Day | E74: ='Equip&HIRE_Master'!D6 -> 180 | F74: =E74*D74 -> 0
E75: ='Equip&HIRE_Master'!D7 -> 0 | F75: =E75*D75 -> 0
B76: 1.5-1.8 Ton_Excavator | C76: Day | E76: ='Equip&HIRE_Master'!D8 -> 137.14286 | F76: =E76*D76 -> 0
B77: 1.7-2Ton_Excavator | C77: Day | E77: ='Equip&HIRE_Master'!D9 -> 0 | F77: =E77*D77 -> 0
B78: 3-5Ton_Excavator | C78: Day | E78: ='Equip&HIRE_Master'!D10 -> 238.66667 | F78: =E78*D78 -> 0
B79: 8Ton_Excavator | C79: Day | E79: ='Equip&HIRE_Master'!D11 -> 261.16667 | F79: =E79*D79 -> 0
B80: 10-12Ton_Excavator | C80: Day | E80: ='Equip&HIRE_Master'!D12 -> 0 | F80: =E80*D80 -> 0
B81: 13-16Ton_Excavator | C81: Day | E81: ='Equip&HIRE_Master'!D13 -> 317.2 | F81: =E81*D81 -> 0
B82: 20-24Ton_Excavator | C82: Day | E82: ='Equip&HIRE_Master'!D14 -> 314.28571 | F82: =E82*D82 -> 0
E83: ='Equip&HIRE_Master'!D15 -> 0 | F83: =E83*D83 -> 0
B84: Ripper_1.7-2T | C84: Day | E84: ='Equip&HIRE_Master'!D16 -> 0 | F84: =E84*D84 -> 0
B85: Ripper_1.5-4T | C85: Day | E85: ='Equip&HIRE_Master'!D17 -> 32.74 | F85: =E85*D85 -> 0
B86: Ripper_3-5T | C86: Day | E86: ='Equip&HIRE_Master'!D18 -> 0 | F86: =E86*D86 -> 0
B87: Ripper_8T | C87: Day | E87: ='Equip&HIRE_Master'!D19 -> 40.38 | F87: =E87*D87 -> 0
B88: Breaker_1.7-2T | C88: Day | E88: ='Equip&HIRE_Master'!D20 -> 123.33 | F88: =E88*D88 -> 0
B89: Breaker_3-5T | C89: Day | E89: ='Equip&HIRE_Master'!D21 -> 165.89 | F89: =E89*D89 -> 0
B90: Breaker_8T | C90: Day | E90: ='Equip&HIRE_Master'!D22 -> 165.89 | F90: =E90*D90 -> 0
B91: Breaker_10-12T | C91: Day | E91: ='Equip&HIRE_Master'!D23 -> 0 | F91: =E91*D91 -> 0
B92: Breaker_13-15T | C92: Day | E92: ='Equip&HIRE_Master'!D24 -> 203 | F92: =E92*D92 -> 0
B93: Auger Drive_10-12T | E93: ='Equip&HIRE_Master'!D25 -> 0 | F93: =E93*D93 -> 0
B94: 300Dia Auger Drill | E94: ='Equip&HIRE_Master'!D26 -> 0 | F94: =E94*D94 -> 0
E95: ='Equip&HIRE_Master'!D27 -> 0 | F95: =E95*D95 -> 0
B96: 1.25T_Tipper Truck | C96: Day | E96: ='Equip&HIRE_Master'!D28 -> 205 | F96: =E96*D96 -> 0
B97: 2-4T_Tipper Truck | C97: Day | E97: ='Equip&HIRE_Master'!D29 -> 166.98 | F97: =E97*D97 -> 0
B98: <6T_Tipper Truck | C98: Day | E98: ='Equip&HIRE_Master'!D30 -> 171.42857 | F98: =E98*D98 -> 0
E99: ='Equip&HIRE_Master'!D31 -> 0 | F99: =E99*D99 -> 0
B100: <10T_Articulated Site Tipper | C100: Day | E100: ='Equip&HIRE_Master'!D32 -> 0 | F100: =E100*D100 -> 0
B101: Upright Rammer_Wacker | C101: Day | E101: ='Equip&HIRE_Master'!D33 -> 34.285714 | F101: =E101*D101 -> 0
B102: Trench Roller_Dbl Drum_Remote | C102: Day | E102: ='Equip&HIRE_Master'!D34 -> 165 | F102: =E102*D102 -> 0
B103: <26Ft_Scissor Lift - Diesel | C103: Day | E103: ='Equip&HIRE_Master'!D35 -> 0 | F103: =E103*D103 -> 0
B104: <26Ft_Scissor Lift - Elec | C104: Day | D104: 20 | E104: 300 | F104: =E104*D104 -> 6000
B105: <34Ft_Boom Lift - Diesel | C105: Day | E105: ='Equip&HIRE_Master'!D37 -> 0 | F105: =E105*D105 -> 0
B106: <34Ft_Boom Lift - Elec | C106: Day | E106: ='Equip&HIRE_Master'!D38 -> 0 | F106: =E106*D106 -> 0
E107: ='Equip&HIRE_Master'!D39 -> 0 | F107: =E107*D107 -> 0
B108: Porta Loo_No Tank | C108: Day | E108: ='Equip&HIRE_Master'!D40 -> 5.46 | F108: =E108*D108 -> 0
B109: 6*3m Demantable Lunchroom - COMPLETE | C109: Day | E109: ='Equip&HIRE_Master'!D41 -> 23 | F109: =E109*D109 -> 0
B110: 6*3m Demantable Office - COMPLETE | C110: Day | E110: ='Equip&HIRE_Master'!D42 -> 23 | F110: =E110*D110 -> 0
B111: 20Ft Shipping Container | C111: Day | E111: ='Equip&HIRE_Master'!D43 -> 0 | F111: =E111*D111 -> 0
B112: Quick Cut Demo Saw | C112: Day | E112: ='Equip&HIRE_Master'!D44 -> 0 | F112: =E112*D112 -> 0
B113: Sngl Ph_6KVA Genset | C113: Day | E113: ='Equip&HIRE_Master'!D45 -> 0 | F113: =E113*D113 -> 0
B114: Diesel Air Compressor_Trailer | C114: Day | E114: ='Equip&HIRE_Master'!D46 -> 0 | F114: =E114*D114 -> 0
B115: Air Breaker - Heavy | C115: Day | E115: ='Equip&HIRE_Master'!D47 -> 0 | F115: =E115*D115 -> 0
B116: Air Hose <10m | C116: Day | E116: ='Equip&HIRE_Master'!D48 -> 0 | F116: =E116*D116 -> 0
B117: Elec Breaker/Jachammer | C117: Day | E117: ='Equip&HIRE_Master'!D49 -> 0 | F117: =E117*D117 -> 0
B118: Flexdrive Motor Unit | C118: Day | E118: ='Equip&HIRE_Master'!D50 -> 0 | F118: =E118*D118 -> 0
B119: Flexdrive_Pump Shaft | C119: Day | E119: ='Equip&HIRE_Master'!D51 -> 0 | F119: =E119*D119 -> 0
...

Sheet ROK033
B1: Project:
B2: Tricore -
B3: Stage 1 Version 1
A4: Item
A9: 1 | B9: Complete -
B12: Labour
B14: DAY | J14: april 2026 direct impact Increase % (not contigency)
B15: ='LabourProject Rates_Master'!$B$14 -> TRADESMAN_LEADING HAND | C15: Day | E15: ='LabourProject Rates_Master'!$E$15 -> 1231.1429 | F15: =E15*D15 -> 0
B16: ='LabourProject Rates_Master'!$B$23 -> TRADESMAN_PLUMBER_OPERATOR | C16: Day | E16: ='LabourProject Rates_Master'!$E$22 -> 941.16473 | F16: =E16*D16 -> 0 | K16: PE Pipe & Fitting | L16: 0.38 | M16: 1.38
B17: ='LabourProject Rates_Master'!$B$30 -> T/A & Apprentice | C17: Day | E17: ='LabourProject Rates_Master'!$E$29 -> 768.06508 | F17: =E17*D17 -> 0 | K17: PVC Pipe & Fittings | L17: 0.38 | M17: 1.38
B18: ='LabourProject Rates_Master'!$B$36 -> Crew #1 - InGround Drainage | C18: Day | E18: ='LabourProject Rates_Master'!$E$37 -> 2650.3945 | F18: =E18*D18 -> 0 | K18: Subby Rates | L18: 0.15 | M18: 1.15
B19: ='LabourProject Rates_Master'!$B$43 -> Crew #2 - InGround Water/Fire | C19: Day | D19: 8 | E19: ='LabourProject Rates_Master'!$E$44 -> 2650.3945 | F19: =E19*D19 -> 21203.156 | K19: Delivey Rate | L19: 0.2 | M19: 1.2
B20: ='LabourProject Rates_Master'!B51 -> Crew #3 - Above Ground Drainage | C20: Day | D20: 0 | E20: ='LabourProject Rates_Master'!E52 -> 2650.3945 | F20: =E20*D20 -> 0
B21: ='LabourProject Rates_Master'!B59 -> Crew #4 - Above Ground WATER/FIRE | C21: Day | D21: 30 | E21: ='LabourProject Rates_Master'!E60 -> 2650.3945 | F21: =E21*D21 -> 79511.836
B22: ='LabourProject Rates_Master'!B67 -> Crew #5 - Above Ground FitOff / Misc | C22: Day | D22: 21 | E22: ='LabourProject Rates_Master'!E68 -> 2650.3945 | F22: =E22*D22 -> 55658.285
B23: ='LabourProject Rates_Master'!B75 -> Crew #6 - DEMO | C23: Day | D23: 16 | E23: ='LabourProject Rates_Master'!E76 -> 1709.2298 | F23: =E23*D23 -> 27347.677
B25: HOUR
B26: ='LabourProject Rates_Master'!$B$14 -> TRADESMAN_LEADING HAND | C26: HR | D26: 0 | E26: ='LabourProject Rates_Master'!$E$14 -> 123.11429 | F26: =E26*D26 -> 0
B27: ='LabourProject Rates_Master'!$B$23 -> TRADESMAN_PLUMBER_OPERATOR | C27: HR | D27: 0 | E27: ='LabourProject Rates_Master'!$E$21 -> 94.116473 | F27: =E27*D27 -> 0
B28: ='LabourProject Rates_Master'!$B$30 -> T/A & Apprentice | C28: HR | D28: 0 | E28: ='LabourProject Rates_Master'!$E$28 -> 76.806508 | F28: =E28*D28 -> 0
B29: ='LabourProject Rates_Master'!$B$36 -> Crew #1 - InGround Drainage | C29: HR | D29: 0 | E29: ='LabourProject Rates_Master'!$E$36 -> 265.03945 | F29: =E29*D29 -> 0
B30: ='LabourProject Rates_Master'!$B$43 -> Crew #2 - InGround Water/Fire | C30: HR | D30: 0 | E30: ='LabourProject Rates_Master'!$E$43 -> 265.03945 | F30: =E30*D30 -> 0
B33: Demolition & Reinstatement
B34: DEMO
B35: ='Misc Subbie Rates_Master'!A49 -> Asphalt Cutting | C35: m | E35: ='Misc Subbie Rates_Master'!D49+('Misc Subbie Rates_Master'!D49*$L$18) -> 15.525 | F35: =E35*D35 -> 0
B36: ='Misc Subbie Rates_Master'!A50 -> Concrete Cutting | C36: m | E36: ='Misc Subbie Rates_Master'!D50+('Misc Subbie Rates_Master'!D50*$L$18) -> 18.4 | F36: =E36*D36 -> 0
B37: Con Cut Establishemnt Fee | C37: ea | E37: ='Misc Subbie Rates_Master'!D51+('Misc Subbie Rates_Master'!D51*$L$18) -> 92 | F37: =E37*D37 -> 0
B38: REINSTATE - CONCRETE
B39: ='Misc Subbie Rates_Master'!A56 -> Road/Drveway Reinstate; 1mW x 150 Thck, N25/20/80, Incl Reinforcement | C39: m | E39: ='Misc Subbie Rates_Master'!D56 -> 145 | F39: =E39*D39 -> 0
B40: ='Misc Subbie Rates_Master'!A57 -> Kerb & Channel - 1m Wide | C40: ea | E40: ='Misc Subbie Rates_Master'!D57 -> 155 | F40: =E40*D40 -> 0
B41: ='Misc Subbie Rates_Master'!A58 -> Footpath - 1.5mW, N25/20/80, Incl Reinforcement | C41: lm | E41: ='Misc Subbie Rates_Master'!D58 -> 180 | F41: =E41*D41 -> 0
B42: ='Misc Subbie Rates_Master'!A59 -> Footpath - 1.5mW, EXPOSED AGG, N25/20/80, Incl Reinforcement | C42: lm | E42: ='Misc Subbie Rates_Master'!D59 -> 185 | F42: =E42*D42 -> 0
B43: REINSTATE - ASPHALT
B44: ='Misc Subbie Rates_Master'!A64 -> 50mm Thck - Trench Reinstatement Through Road/Driveway | C44: m2 | E44: ='Misc Subbie Rates_Master'!D64 -> 97 | F44: =E44*D44 -> 0
B45: ='Misc Subbie Rates_Master'!A65 -> 50mm Thck - 1.5-2m Wide Footpath reinstatements | C45: m2 | E45: ='Misc Subbie Rates_Master'!D65 -> 97 | F45: =E45*D45 -> 0
B46: ='Misc Subbie Rates_Master'!A66 -> Establishment Fee (1 per stage) | C46: Ea | E46: ='Misc Subbie Rates_Master'!D66 -> 5500 | F46: =E46*D46 -> 0
B48: Equipment & Hire - INCL WET PLANT HIRE
B50: PLANT HIRE - WET
B51: 1.8T Excavator | C51: Hr | E51: ='Misc Subbie Rates_Master'!D10 -> 100 | F51: =E51*D51 -> 0
B52: 3-5 ton Excavator | C52: Hr | E52: ='Misc Subbie Rates_Master'!D11 -> 115 | F52: =E52*D52 -> 0
B53: 3-5T Combo | C53: Hr | E53: ='Misc Subbie Rates_Master'!D12 -> 154 | F53: =E53*D53 -> 0
B54: Hammer attachment 3.5-4T | C54: Hr | E54: ='Misc Subbie Rates_Master'!D13 -> 21 | F54: =E54*D54 -> 0
B55: Ripper 3.5-4T | C55: Hr | E55: ='Misc Subbie Rates_Master'!D14 -> 10 | F55: =E55*D55 -> 0
B56: 5t Excavator | C56: Hr | E56: ='Misc Subbie Rates_Master'!D15 -> 150 | F56: =E56*D56 -> 0
B57: Hammer attachment 5T | C57: Hr | E57: ='Misc Subbie Rates_Master'!D16 -> 50 | F57: =E57*D57 -> 0
B58: Skid steer | C58: Hr | E58: ='Misc Subbie Rates_Master'!D17 -> 140 | F58: =E58*D58 -> 0
B59: 8T Excavator | C59: Hr | E59: ='Misc Subbie Rates_Master'!D18 -> 128 | F59: =E59*D59 -> 0
B60: Hammer attachment 8T | C60: Hr | E60: ='Misc Subbie Rates_Master'!D19 -> 26 | F60: =E60*D60 -> 0
B61: Ripper 8T | C61: Hr | E61: ='Misc Subbie Rates_Master'!D20 -> 10 | F61: =E61*D61 -> 0
B62: 13-15T Excavator | C62: Hr | E62: ='Misc Subbie Rates_Master'!D21 -> 153 | F62: =E62*D62 -> 0
... B69: 12t Body Truck Tipper | C69: Hr | E69: ='Misc Subbie Rates_Master'!D28 -> 110 | F69: =E69*D69 -> 0
B71: HIRE - DRY
B72: Skid Steer Loader_Tracked (CAT249+) | C72: Day | D72: 5 | E72: ='Equip&HIRE_Master'!D4 -> 225.43333 | F72: =E72*D72 -> 1127.1667
B73: Skid Steer Loader_Wheeled (CAT226+) | C73: Day | E73: ='Equip&HIRE_Master'!D5 -> 163.96667 | F73: =E73*D73 -> 0
B74: Mini Loader, Stand-on Type | C74: Day | E74: ='Equip&HIRE_Master'!D6 -> 180 | F74: =E74*D74 -> 0
E75: ='Equip&HIRE_Master'!D7 -> 0 | F75: =E75*D75 -> 0
B76: 1.5-1.8 Ton_Excavator | C76: Day | E76: ='Equip&HIRE_Master'!D8 -> 137.14286 | F76: =E76*D76 -> 0
B77: 1.7-2Ton_Excavator | C77: Day | E77: ='Equip&HIRE_Master'!D9 -> 0 | F77: =E77*D77 -> 0
B78: 3-5Ton_Excavator | C78: Day | D78: 5 | E78: ='Equip&HIRE_Master'!D10 -> 238.66667 | F78: =E78*D78 -> 1193.3333
B79: 8Ton_Excavator | C79: Day | E79: ='Equip&HIRE_Master'!D11 -> 261.16667 | F79: =E79*D79 -> 0
B80: 10-12Ton_Excavator | C80: Day | D80: 0 | E80: ='Equip&HIRE_Master'!D12 -> 0 | F80: =E80*D80 -> 0
B81: 13-16Ton_Excavator | C81: Day | E81: ='Equip&HIRE_Master'!D13 -> 317.2 | F81: =E81*D81 -> 0
B82: 20-24Ton_Excavator | C82: Day | E82: ='Equip&HIRE_Master'!D14 -> 314.28571 | F82: =E82*D82 -> 0
E83: ='Equip&HIRE_Master'!D15 -> 0 | F83: =E83*D83 -> 0
B84: Ripper_1.7-2T | C84: Day | E84: ='Equip&HIRE_Master'!D16 -> 0 | F84: =E84*D84 -> 0
B85: Ripper_1.5-4T | C85: Day | E85: ='Equip&HIRE_Master'!D17 -> 32.74 | F85: =E85*D85 -> 0
B86: Ripper_3-5T | C86: Day | E86: ='Equip&HIRE_Master'!D18 -> 0 | F86: =E86*D86 -> 0
B87: Ripper_8T | C87: Day | E87: ='Equip&HIRE_Master'!D19 -> 40.38 | F87: =E87*D87 -> 0
B88: Breaker_1.7-2T | C88: Day | E88: ='Equip&HIRE_Master'!D20 -> 123.33 | F88: =E88*D88 -> 0
B89: Breaker_3-5T | C89: Day | E89: ='Equip&HIRE_Master'!D21 -> 165.89 | F89: =E89*D89 -> 0
B90: Breaker_8T | C90: Day | E90: ='Equip&HIRE_Master'!D22 -> 165.89 | F90: =E90*D90 -> 0
B91: Breaker_10-12T | C91: Day | E91: ='Equip&HIRE_Master'!D23 -> 0 | F91: =E91*D91 -> 0
B92: Breaker_13-15T | C92: Day | E92: ='Equip&HIRE_Master'!D24 -> 203 | F92: =E92*D92 -> 0
B93: Auger Drive_10-12T | E93: ='Equip&HIRE_Master'!D25 -> 0 | F93: =E93*D93 -> 0
B94: 300Dia Auger Drill | E94: ='Equip&HIRE_Master'!D26 -> 0 | F94: =E94*D94 -> 0
E95: ='Equip&HIRE_Master'!D27 -> 0 | F95: =E95*D95 -> 0
B96: 1.25T_Tipper Truck | C96: Day | E96: ='Equip&HIRE_Master'!D28 -> 205 | F96: =E96*D96 -> 0
B97: 2-4T_Tipper Truck | C97: Day | E97: ='Equip&HIRE_Master'!D29 -> 166.98 | F97: =E97*D97 -> 0
B98: <6T_Tipper Truck | C98: Day | E98: ='Equip&HIRE_Master'!D30 -> 171.42857 | F98: =E98*D98 -> 0
E99: ='Equip&HIRE_Master'!D31 -> 0 | F99: =E99*D99 -> 0
B100: <10T_Articulated Site Tipper | C100: Day | E100: ='Equip&HIRE_Master'!D32 -> 0 | F100: =E100*D100 -> 0
B101: Upright Rammer_Wacker | C101: Day | D101: 5 | E101: ='Equip&HIRE_Master'!D33 -> 34.285714 | F101: =E101*D101 -> 171.42857
B102: Trench Roller_Dbl Drum_Remote | C102: Day | E102: ='Equip&HIRE_Master'!D34 -> 165 | F102: =E102*D102 -> 0
B103: <26Ft_Scissor Lift - Diesel | C103: Day | E103: ='Equip&HIRE_Master'!D35 -> 0 | F103: =E103*D103 -> 0
B104: <26Ft_Scissor Lift - Elec | C104: Day | D104: 30 | E104: 250 | F104: =E104*D104 -> 7500
B105: <34Ft_Boom Lift - Diesel | C105: Day | E105: ='Equip&HIRE_Master'!D37 -> 0 | F105: =E105*D105 -> 0
B106: <34Ft_Boom Lift - Elec | C106: Day | E106: ='Equip&HIRE_Master'!D38 -> 0 | F106: =E106*D106 -> 0
E107: ='Equip&HIRE_Master'!D39 -> 0 | F107: =E107*D107 -> 0
B108: Porta Loo_No Tank | C108: Day | E108: ='Equip&HIRE_Master'!D40 -> 5.46 | F108: =E108*D108 -> 0
B109: 6*3m Demantable Lunchroom - COMPLETE | C109: Day | E109: ='Equip&HIRE_Master'!D41 -> 23 | F109: =E109*D109 -> 0
B110: 6*3m Demantable Office - COMPLETE | C110: Day | E110: ='Equip&HIRE_Master'!D42 -> 23 | F110: =E110*D110 -> 0
B111: 20Ft Shipping Container | C111: Day | E111: ='Equip&HIRE_Master'!D43 -> 0 | F111: =E111*D111 -> 0
B112: Quick Cut Demo Saw | C112: Day | E112: ='Equip&HIRE_Master'!D44 -> 0 | F112: =E112*D112 -> 0
B113: Sngl Ph_6KVA Genset | C113: Day | E113: ='Equip&HIRE_Master'!D45 -> 0 | F113: =E113*D113 -> 0
B114: Diesel Air Compressor_Trailer | C114: Day | E114: ='Equip&HIRE_Master'!D46 -> 0 | F114: =E114*D114 -> 0
B115: Air Breaker - Heavy | C115: Day | E115: ='Equip&HIRE_Master'!D47 -> 0 | F115: =E115*D115 -> 0
B116: Air Hose <10m | C116: Day | E116: ='Equip&HIRE_Master'!D48 -> 0 | F116: =E116*D116 -> 0
B117: Elec Breaker/Jachammer | C117: Day | E117: ='Equip&HIRE_Master'!D49 -> 0 | F117: =E117*D117 -> 0
B118: Flexdrive Motor Unit | C118: Day | E118: ='Equip&HIRE_Master'!D50 -> 0 | F118: =E118*D118 -> 0
B119: Flexdrive_Pump Shaft | C119: Day | E119: ='Equip&HIRE_Master'!D51 -> 0 | F119: =E119*D119 -> 0
...

Sheet ROK034
B1: Project:
B2: Tricore -
B3: Stage 1 Version 1
A4: Item
A9: 1 | B9: Complete -
B12: Labour
B14: DAY | J14: april 2026 direct impact Increase % (not contigency)
B15: ='LabourProject Rates_Master'!$B$14 -> TRADESMAN_LEADING HAND | C15: Day | E15: ='LabourProject Rates_Master'!$E$15 -> 1231.1429 | F15: =E15*D15 -> 0
B16: ='LabourProject Rates_Master'!$B$23 -> TRADESMAN_PLUMBER_OPERATOR | C16: Day | E16: ='LabourProject Rates_Master'!$E$22 -> 941.16473 | F16: =E16*D16 -> 0 | K16: PE Pipe & Fitting | L16: 0.38 | M16: 1.38
B17: ='LabourProject Rates_Master'!$B$30 -> T/A & Apprentice | C17: Day | E17: ='LabourProject Rates_Master'!$E$29 -> 768.06508 | F17: =E17*D17 -> 0 | K17: PVC Pipe & Fittings | L17: 0.38 | M17: 1.38
B18: ='LabourProject Rates_Master'!$B$36 -> Crew #1 - InGround Drainage | C18: Day | E18: ='LabourProject Rates_Master'!$E$37 -> 2650.3945 | F18: =E18*D18 -> 0 | K18: Subby Rates | L18: 0.15 | M18: 1.15
B19: ='LabourProject Rates_Master'!$B$43 -> Crew #2 - InGround Water/Fire | C19: Day | D19: 2 | E19: ='LabourProject Rates_Master'!$E$44 -> 2650.3945 | F19: =E19*D19 -> 5300.7891 | K19: Delivey Rate | L19: 0.2 | M19: 1.2
B20: ='LabourProject Rates_Master'!B51 -> Crew #3 - Above Ground Drainage | C20: Day | D20: 2 | E20: ='LabourProject Rates_Master'!E52 -> 2650.3945 | F20: =E20*D20 -> 5300.7891
B21: ='LabourProject Rates_Master'!B59 -> Crew #4 - Above Ground WATER/FIRE | C21: Day | D21: 4 | E21: ='LabourProject Rates_Master'!E60 -> 2650.3945 | F21: =E21*D21 -> 10601.578
B22: ='LabourProject Rates_Master'!B67 -> Crew #5 - Above Ground FitOff / Misc | C22: Day | D22: 5 | E22: ='LabourProject Rates_Master'!E68 -> 2650.3945 | F22: =E22*D22 -> 13251.973
B23: ='LabourProject Rates_Master'!B75 -> Crew #6 - DEMO | C23: Day | E23: ='LabourProject Rates_Master'!E76 -> 1709.2298 | F23: =E23*D23 -> 0
B25: HOUR
B26: ='LabourProject Rates_Master'!$B$14 -> TRADESMAN_LEADING HAND | C26: HR | D26: 0 | E26: ='LabourProject Rates_Master'!$E$14 -> 123.11429 | F26: =E26*D26 -> 0
B27: ='LabourProject Rates_Master'!$B$23 -> TRADESMAN_PLUMBER_OPERATOR | C27: HR | D27: 0 | E27: ='LabourProject Rates_Master'!$E$21 -> 94.116473 | F27: =E27*D27 -> 0
B28: ='LabourProject Rates_Master'!$B$30 -> T/A & Apprentice | C28: HR | D28: 0 | E28: ='LabourProject Rates_Master'!$E$28 -> 76.806508 | F28: =E28*D28 -> 0
B29: ='LabourProject Rates_Master'!$B$36 -> Crew #1 - InGround Drainage | C29: HR | D29: 0 | E29: ='LabourProject Rates_Master'!$E$36 -> 265.03945 | F29: =E29*D29 -> 0
B30: ='LabourProject Rates_Master'!$B$43 -> Crew #2 - InGround Water/Fire | C30: HR | D30: 0 | E30: ='LabourProject Rates_Master'!$E$43 -> 265.03945 | F30: =E30*D30 -> 0
B33: Demolition & Reinstatement
B34: DEMO
B35: ='Misc Subbie Rates_Master'!A49 -> Asphalt Cutting | C35: m | E35: ='Misc Subbie Rates_Master'!D49+('Misc Subbie Rates_Master'!D49*$L$18) -> 15.525 | F35: =E35*D35 -> 0
B36: ='Misc Subbie Rates_Master'!A50 -> Concrete Cutting | C36: m | E36: ='Misc Subbie Rates_Master'!D50+('Misc Subbie Rates_Master'!D50*$L$18) -> 18.4 | F36: =E36*D36 -> 0
B37: Con Cut Establishemnt Fee | C37: ea | E37: ='Misc Subbie Rates_Master'!D51+('Misc Subbie Rates_Master'!D51*$L$18) -> 92 | F37: =E37*D37 -> 0
B38: REINSTATE - CONCRETE
B39: ='Misc Subbie Rates_Master'!A56 -> Road/Drveway Reinstate; 1mW x 150 Thck, N25/20/80, Incl Reinforcement | C39: m | E39: ='Misc Subbie Rates_Master'!D56 -> 145 | F39: =E39*D39 -> 0
B40: ='Misc Subbie Rates_Master'!A57 -> Kerb & Channel - 1m Wide | C40: ea | E40: ='Misc Subbie Rates_Master'!D57 -> 155 | F40: =E40*D40 -> 0
B41: ='Misc Subbie Rates_Master'!A58 -> Footpath - 1.5mW, N25/20/80, Incl Reinforcement | C41: lm | E41: ='Misc Subbie Rates_Master'!D58 -> 180 | F41: =E41*D41 -> 0
B42: ='Misc Subbie Rates_Master'!A59 -> Footpath - 1.5mW, EXPOSED AGG, N25/20/80, Incl Reinforcement | C42: lm | E42: ='Misc Subbie Rates_Master'!D59 -> 185 | F42: =E42*D42 -> 0
B43: REINSTATE - ASPHALT
B44: ='Misc Subbie Rates_Master'!A64 -> 50mm Thck - Trench Reinstatement Through Road/Driveway | C44: m2 | E44: ='Misc Subbie Rates_Master'!D64 -> 97 | F44: =E44*D44 -> 0
B45: ='Misc Subbie Rates_Master'!A65 -> 50mm Thck - 1.5-2m Wide Footpath reinstatements | C45: m2 | E45: ='Misc Subbie Rates_Master'!D65 -> 97 | F45: =E45*D45 -> 0
B46: ='Misc Subbie Rates_Master'!A66 -> Establishment Fee (1 per stage) | C46: Ea | E46: ='Misc Subbie Rates_Master'!D66 -> 5500 | F46: =E46*D46 -> 0
B48: Equipment & Hire - INCL WET PLANT HIRE
B50: PLANT HIRE - WET
B51: 1.8T Excavator | C51: Hr | E51: ='Misc Subbie Rates_Master'!D10 -> 100 | F51: =E51*D51 -> 0
B52: 3-5 ton Excavator | C52: Hr | E52: ='Misc Subbie Rates_Master'!D11 -> 115 | F52: =E52*D52 -> 0
B53: 3-5T Combo | C53: Hr | E53: ='Misc Subbie Rates_Master'!D12 -> 154 | F53: =E53*D53 -> 0
B54: Hammer attachment 3.5-4T | C54: Hr | E54: ='Misc Subbie Rates_Master'!D13 -> 21 | F54: =E54*D54 -> 0
B55: Ripper 3.5-4T | C55: Hr | E55: ='Misc Subbie Rates_Master'!D14 -> 10 | F55: =E55*D55 -> 0
B56: 5t Excavator | C56: Hr | E56: ='Misc Subbie Rates_Master'!D15 -> 150 | F56: =E56*D56 -> 0
B57: Hammer attachment 5T | C57: Hr | E57: ='Misc Subbie Rates_Master'!D16 -> 50 | F57: =E57*D57 -> 0
B58: Skid steer | C58: Hr | E58: ='Misc Subbie Rates_Master'!D17 -> 140 | F58: =E58*D58 -> 0
B59: 8T Excavator | C59: Hr | E59: ='Misc Subbie Rates_Master'!D18 -> 128 | F59: =E59*D59 -> 0
B60: Hammer attachment 8T | C60: Hr | E60: ='Misc Subbie Rates_Master'!D19 -> 26 | F60: =E60*D60 -> 0
B61: Ripper 8T | C61: Hr | E61: ='Misc Subbie Rates_Master'!D20 -> 10 | F61: =E61*D61 -> 0
B62: 13-15T Excavator | C62: Hr | E62: ='Misc Subbie Rates_Master'!D21 -> 153 | F62: =E62*D62 -> 0
... B69: 12t Body Truck Tipper | C69: Hr | E69: ='Misc Subbie Rates_Master'!D28 -> 110 | F69: =E69*D69 -> 0
B71: HIRE - DRY
B72: Skid Steer Loader_Tracked (CAT249+) | C72: Day | D72: 2 | E72: ='Equip&HIRE_Master'!D4 -> 225.43333 | F72: =E72*D72 -> 450.86667
B73: Skid Steer Loader_Wheeled (CAT226+) | C73: Day | D73: 0 | E73: ='Equip&HIRE_Master'!D5 -> 163.96667 | F73: =E73*D73 -> 0
B74: Mini Loader, Stand-on Type | C74: Day | E74: ='Equip&HIRE_Master'!D6 -> 180 | F74: =E74*D74 -> 0
E75: ='Equip&HIRE_Master'!D7 -> 0 | F75: =E75*D75 -> 0
B76: 1.5-1.8 Ton_Excavator | C76: Day | E76: ='Equip&HIRE_Master'!D8 -> 137.14286 | F76: =E76*D76 -> 0
B77: 1.7-2Ton_Excavator | C77: Day | E77: ='Equip&HIRE_Master'!D9 -> 0 | F77: =E77*D77 -> 0
B78: 3-5Ton_Excavator | C78: Day | D78: 2 | E78: ='Equip&HIRE_Master'!D10 -> 238.66667 | F78: =E78*D78 -> 477.33333
B79: 8Ton_Excavator | C79: Day | E79: ='Equip&HIRE_Master'!D11 -> 261.16667 | F79: =E79*D79 -> 0
B80: 10-12Ton_Excavator | C80: Day | E80: ='Equip&HIRE_Master'!D12 -> 0 | F80: =E80*D80 -> 0
B81: 13-16Ton_Excavator | C81: Day | E81: ='Equip&HIRE_Master'!D13 -> 317.2 | F81: =E81*D81 -> 0
B82: 20-24Ton_Excavator | C82: Day | E82: ='Equip&HIRE_Master'!D14 -> 314.28571 | F82: =E82*D82 -> 0
E83: ='Equip&HIRE_Master'!D15 -> 0 | F83: =E83*D83 -> 0
B84: Ripper_1.7-2T | C84: Day | E84: ='Equip&HIRE_Master'!D16 -> 0 | F84: =E84*D84 -> 0
B85: Ripper_1.5-4T | C85: Day | E85: ='Equip&HIRE_Master'!D17 -> 32.74 | F85: =E85*D85 -> 0
B86: Ripper_3-5T | C86: Day | E86: ='Equip&HIRE_Master'!D18 -> 0 | F86: =E86*D86 -> 0
B87: Ripper_8T | C87: Day | E87: ='Equip&HIRE_Master'!D19 -> 40.38 | F87: =E87*D87 -> 0
B88: Breaker_1.7-2T | C88: Day | E88: ='Equip&HIRE_Master'!D20 -> 123.33 | F88: =E88*D88 -> 0
B89: Breaker_3-5T | C89: Day | E89: ='Equip&HIRE_Master'!D21 -> 165.89 | F89: =E89*D89 -> 0
B90: Breaker_8T | C90: Day | E90: ='Equip&HIRE_Master'!D22 -> 165.89 | F90: =E90*D90 -> 0
B91: Breaker_10-12T | C91: Day | E91: ='Equip&HIRE_Master'!D23 -> 0 | F91: =E91*D91 -> 0
B92: Breaker_13-15T | C92: Day | E92: ='Equip&HIRE_Master'!D24 -> 203 | F92: =E92*D92 -> 0
B93: Auger Drive_10-12T | E93: ='Equip&HIRE_Master'!D25 -> 0 | F93: =E93*D93 -> 0
B94: 300Dia Auger Drill | E94: ='Equip&HIRE_Master'!D26 -> 0 | F94: =E94*D94 -> 0
E95: ='Equip&HIRE_Master'!D27 -> 0 | F95: =E95*D95 -> 0
B96: 1.25T_Tipper Truck | C96: Day | E96: ='Equip&HIRE_Master'!D28 -> 205 | F96: =E96*D96 -> 0
B97: 2-4T_Tipper Truck | C97: Day | D97: 1 | E97: ='Equip&HIRE_Master'!D29 -> 166.98 | F97: =E97*D97 -> 166.98
B98: <6T_Tipper Truck | C98: Day | E98: ='Equip&HIRE_Master'!D30 -> 171.42857 | F98: =E98*D98 -> 0
E99: ='Equip&HIRE_Master'!D31 -> 0 | F99: =E99*D99 -> 0
B100: <10T_Articulated Site Tipper | C100: Day | D100: 0 | E100: ='Equip&HIRE_Master'!D32 -> 0 | F100: =E100*D100 -> 0
B101: Upright Rammer_Wacker | C101: Day | D101: 2 | E101: ='Equip&HIRE_Master'!D33 -> 34.285714 | F101: =E101*D101 -> 68.571429
B102: Trench Roller_Dbl Drum_Remote | C102: Day | E102: ='Equip&HIRE_Master'!D34 -> 165 | F102: =E102*D102 -> 0
B103: <26Ft_Scissor Lift - Diesel | C103: Day | E103: ='Equip&HIRE_Master'!D35 -> 0 | F103: =E103*D103 -> 0
B104: <26Ft_Scissor Lift - Elec | C104: Day | E104: ='Equip&HIRE_Master'!D36 -> 0 | F104: =E104*D104 -> 0
B105: <34Ft_Boom Lift - Diesel | C105: Day | E105: ='Equip&HIRE_Master'!D37 -> 0 | F105: =E105*D105 -> 0
B106: <34Ft_Boom Lift - Elec | C106: Day | E106: ='Equip&HIRE_Master'!D38 -> 0 | F106: =E106*D106 -> 0
E107: ='Equip&HIRE_Master'!D39 -> 0 | F107: =E107*D107 -> 0
B108: Porta Loo_No Tank | C108: Day | E108: ='Equip&HIRE_Master'!D40 -> 5.46 | F108: =E108*D108 -> 0
B109: 6*3m Demantable Lunchroom - COMPLETE | C109: Day | E109: ='Equip&HIRE_Master'!D41 -> 23 | F109: =E109*D109 -> 0
B110: 6*3m Demantable Office - COMPLETE | C110: Day | E110: ='Equip&HIRE_Master'!D42 -> 23 | F110: =E110*D110 -> 0
B111: 20Ft Shipping Container | C111: Day | E111: ='Equip&HIRE_Master'!D43 -> 0 | F111: =E111*D111 -> 0
B112: Quick Cut Demo Saw | C112: Day | E112: ='Equip&HIRE_Master'!D44 -> 0 | F112: =E112*D112 -> 0
B113: Sngl Ph_6KVA Genset | C113: Day | E113: ='Equip&HIRE_Master'!D45 -> 0 | F113: =E113*D113 -> 0
B114: Diesel Air Compressor_Trailer | C114: Day | E114: ='Equip&HIRE_Master'!D46 -> 0 | F114: =E114*D114 -> 0
B115: Air Breaker - Heavy | C115: Day | E115: ='Equip&HIRE_Master'!D47 -> 0 | F115: =E115*D115 -> 0
B116: Air Hose <10m | C116: Day | E116: ='Equip&HIRE_Master'!D48 -> 0 | F116: =E116*D116 -> 0
B117: Elec Breaker/Jachammer | C117: Day | E117: ='Equip&HIRE_Master'!D49 -> 0 | F117: =E117*D117 -> 0
B118: Flexdrive Motor Unit | C118: Day | E118: ='Equip&HIRE_Master'!D50 -> 0 | F118: =E118*D118 -> 0
B119: Flexdrive_Pump Shaft | C119: Day | E119: ='Equip&HIRE_Master'!D51 -> 0 | F119: =E119*D119 -> 0
...

Sheet ROK036
B1: Project:
B2: Tricore -
B3: Stage 1 Version 1
A4: Item
A9: 1 | B9: Complete -
B12: Labour
B14: DAY | J14: april 2026 direct impact Increase % (not contigency)
B15: ='LabourProject Rates_Master'!$B$14 -> TRADESMAN_LEADING HAND | C15: Day | E15: ='LabourProject Rates_Master'!$E$15 -> 1231.1429 | F15: =E15*D15 -> 0
B16: ='LabourProject Rates_Master'!$B$23 -> TRADESMAN_PLUMBER_OPERATOR | C16: Day | E16: ='LabourProject Rates_Master'!$E$22 -> 941.16473 | F16: =E16*D16 -> 0 | K16: PE Pipe & Fitting | L16: 0.38 | M16: 1.38
B17: ='LabourProject Rates_Master'!$B$30 -> T/A & Apprentice | C17: Day | E17: ='LabourProject Rates_Master'!$E$29 -> 768.06508 | F17: =E17*D17 -> 0 | K17: PVC Pipe & Fittings | L17: 0.38 | M17: 1.38
B18: ='LabourProject Rates_Master'!$B$36 -> Crew #1 - InGround Drainage | C18: Day | D18: 30 | E18: ='LabourProject Rates_Master'!$E$37 -> 2650.3945 | F18: =E18*D18 -> 79511.836 | K18: Subby Rates | L18: 0.15 | M18: 1.15
B19: ='LabourProject Rates_Master'!$B$43 -> Crew #2 - InGround Water/Fire | C19: Day | D19: 6 | E19: ='LabourProject Rates_Master'!$E$44 -> 2650.3945 | F19: =E19*D19 -> 15902.367 | K19: Delivey Rate | L19: 0.2 | M19: 1.2
B20: ='LabourProject Rates_Master'!B51 -> Crew #3 - Above Ground Drainage | C20: Day | D20: 31 | E20: ='LabourProject Rates_Master'!E52 -> 2650.3945 | F20: =E20*D20 -> 82162.231
B21: ='LabourProject Rates_Master'!B59 -> Crew #4 - Above Ground WATER/FIRE | C21: Day | D21: 63 | E21: ='LabourProject Rates_Master'!E60 -> 2650.3945 | F21: =E21*D21 -> 166974.86
B22: ='LabourProject Rates_Master'!B67 -> Crew #5 - Above Ground FitOff / Misc | C22: Day | D22: 50 | E22: ='LabourProject Rates_Master'!E68 -> 2650.3945 | F22: =E22*D22 -> 132519.73
B23: ='LabourProject Rates_Master'!B75 -> Crew #6 - DEMO | C23: Day | D23: 13 | E23: ='LabourProject Rates_Master'!E76 -> 1709.2298 | F23: =E23*D23 -> 22219.988
B25: HOUR
B26: ='LabourProject Rates_Master'!$B$14 -> TRADESMAN_LEADING HAND | C26: HR | D26: 0 | E26: ='LabourProject Rates_Master'!$E$14 -> 123.11429 | F26: =E26*D26 -> 0
B27: ='LabourProject Rates_Master'!$B$23 -> TRADESMAN_PLUMBER_OPERATOR | C27: HR | D27: 0 | E27: ='LabourProject Rates_Master'!$E$21 -> 94.116473 | F27: =E27*D27 -> 0
B28: ='LabourProject Rates_Master'!$B$30 -> T/A & Apprentice | C28: HR | D28: 0 | E28: ='LabourProject Rates_Master'!$E$28 -> 76.806508 | F28: =E28*D28 -> 0
B29: ='LabourProject Rates_Master'!$B$36 -> Crew #1 - InGround Drainage | C29: HR | D29: 0 | E29: ='LabourProject Rates_Master'!$E$36 -> 265.03945 | F29: =E29*D29 -> 0
B30: ='LabourProject Rates_Master'!$B$43 -> Crew #2 - InGround Water/Fire | C30: HR | D30: 0 | E30: ='LabourProject Rates_Master'!$E$43 -> 265.03945 | F30: =E30*D30 -> 0
B33: Demolition & Reinstatement
B34: DEMO
B35: ='Misc Subbie Rates_Master'!A49 -> Asphalt Cutting | C35: m | E35: ='Misc Subbie Rates_Master'!D49+('Misc Subbie Rates_Master'!D49*$L$18) -> 15.525 | F35: =E35*D35 -> 0
B36: ='Misc Subbie Rates_Master'!A50 -> Concrete Cutting | C36: m | E36: ='Misc Subbie Rates_Master'!D50+('Misc Subbie Rates_Master'!D50*$L$18) -> 18.4 | F36: =E36*D36 -> 0
B37: Con Cut Establishemnt Fee | C37: ea | E37: ='Misc Subbie Rates_Master'!D51+('Misc Subbie Rates_Master'!D51*$L$18) -> 92 | F37: =E37*D37 -> 0
B38: REINSTATE - CONCRETE
B39: ='Misc Subbie Rates_Master'!A56 -> Road/Drveway Reinstate; 1mW x 150 Thck, N25/20/80, Incl Reinforcement | C39: m | E39: ='Misc Subbie Rates_Master'!D56 -> 145 | F39: =E39*D39 -> 0
B40: ='Misc Subbie Rates_Master'!A57 -> Kerb & Channel - 1m Wide | C40: ea | E40: ='Misc Subbie Rates_Master'!D57 -> 155 | F40: =E40*D40 -> 0
B41: ='Misc Subbie Rates_Master'!A58 -> Footpath - 1.5mW, N25/20/80, Incl Reinforcement | C41: lm | E41: ='Misc Subbie Rates_Master'!D58 -> 180 | F41: =E41*D41 -> 0
B42: ='Misc Subbie Rates_Master'!A59 -> Footpath - 1.5mW, EXPOSED AGG, N25/20/80, Incl Reinforcement | C42: lm | E42: ='Misc Subbie Rates_Master'!D59 -> 185 | F42: =E42*D42 -> 0
B43: REINSTATE - ASPHALT
B44: ='Misc Subbie Rates_Master'!A64 -> 50mm Thck - Trench Reinstatement Through Road/Driveway | C44: m2 | E44: ='Misc Subbie Rates_Master'!D64 -> 97 | F44: =E44*D44 -> 0
B45: ='Misc Subbie Rates_Master'!A65 -> 50mm Thck - 1.5-2m Wide Footpath reinstatements | C45: m2 | E45: ='Misc Subbie Rates_Master'!D65 -> 97 | F45: =E45*D45 -> 0
B46: ='Misc Subbie Rates_Master'!A66 -> Establishment Fee (1 per stage) | C46: Ea | E46: ='Misc Subbie Rates_Master'!D66 -> 5500 | F46: =E46*D46 -> 0
B48: Equipment & Hire - INCL WET PLANT HIRE
B50: PLANT HIRE - WET
B51: 1.8T Excavator | C51: Hr | E51: ='Misc Subbie Rates_Master'!D10 -> 100 | F51: =E51*D51 -> 0
B52: 3-5 ton Excavator | C52: Hr | E52: ='Misc Subbie Rates_Master'!D11 -> 115 | F52: =E52*D52 -> 0
B53: 3-5T Combo | C53: Hr | E53: ='Misc Subbie Rates_Master'!D12 -> 154 | F53: =E53*D53 -> 0
B54: Hammer attachment 3.5-4T | C54: Hr | E54: ='Misc Subbie Rates_Master'!D13 -> 21 | F54: =E54*D54 -> 0
B55: Ripper 3.5-4T | C55: Hr | E55: ='Misc Subbie Rates_Master'!D14 -> 10 | F55: =E55*D55 -> 0
B56: 5t Excavator | C56: Hr | E56: ='Misc Subbie Rates_Master'!D15 -> 150 | F56: =E56*D56 -> 0
B57: Hammer attachment 5T | C57: Hr | E57: ='Misc Subbie Rates_Master'!D16 -> 50 | F57: =E57*D57 -> 0
B58: Skid steer | C58: Hr | E58: ='Misc Subbie Rates_Master'!D17 -> 140 | F58: =E58*D58 -> 0
B59: 8T Excavator | C59: Hr | E59: ='Misc Subbie Rates_Master'!D18 -> 128 | F59: =E59*D59 -> 0
B60: Hammer attachment 8T | C60: Hr | E60: ='Misc Subbie Rates_Master'!D19 -> 26 | F60: =E60*D60 -> 0
B61: Ripper 8T | C61: Hr | E61: ='Misc Subbie Rates_Master'!D20 -> 10 | F61: =E61*D61 -> 0
B62: 13-15T Excavator | C62: Hr | E62: ='Misc Subbie Rates_Master'!D21 -> 153 | F62: =E62*D62 -> 0
... B69: 12t Body Truck Tipper | C69: Hr | E69: ='Misc Subbie Rates_Master'!D28 -> 110 | F69: =E69*D69 -> 0
B71: HIRE - DRY
B72: Skid Steer Loader_Tracked (CAT249+) | C72: Day | D72: 30 | E72: ='Equip&HIRE_Master'!D4 -> 225.43333 | F72: =E72*D72 -> 6763
B73: Skid Steer Loader_Wheeled (CAT226+) | C73: Day | E73: ='Equip&HIRE_Master'!D5 -> 163.96667 | F73: =E73*D73 -> 0
B74: Mini Loader, Stand-on Type | C74: Day | E74: ='Equip&HIRE_Master'!D6 -> 180 | F74: =E74*D74 -> 0
E75: ='Equip&HIRE_Master'!D7 -> 0 | F75: =E75*D75 -> 0
B76: 1.5-1.8 Ton_Excavator | C76: Day | D76: 30 | E76: ='Equip&HIRE_Master'!D8 -> 137.14286 | F76: =E76*D76 -> 4114.2857
B77: 1.7-2Ton_Excavator | C77: Day | E77: ='Equip&HIRE_Master'!D9 -> 0 | F77: =E77*D77 -> 0
B78: 3-5Ton_Excavator | C78: Day | D78: 20 | E78: ='Equip&HIRE_Master'!D10 -> 238.66667 | F78: =E78*D78 -> 4773.3333
B79: 8Ton_Excavator | C79: Day | E79: ='Equip&HIRE_Master'!D11 -> 261.16667 | F79: =E79*D79 -> 0
B80: 10-12Ton_Excavator | C80: Day | E80: ='Equip&HIRE_Master'!D12 -> 0 | F80: =E80*D80 -> 0
B81: 13-16Ton_Excavator | C81: Day | E81: ='Equip&HIRE_Master'!D13 -> 317.2 | F81: =E81*D81 -> 0
B82: 20-24Ton_Excavator | C82: Day | E82: ='Equip&HIRE_Master'!D14 -> 314.28571 | F82: =E82*D82 -> 0
E83: ='Equip&HIRE_Master'!D15 -> 0 | F83: =E83*D83 -> 0
B84: Ripper_1.7-2T | C84: Day | E84: ='Equip&HIRE_Master'!D16 -> 0 | F84: =E84*D84 -> 0
B85: Ripper_1.5-4T | C85: Day | D85: 20 | E85: ='Equip&HIRE_Master'!D17 -> 32.74 | F85: =E85*D85 -> 654.8
B86: Ripper_3-5T | C86: Day | E86: ='Equip&HIRE_Master'!D18 -> 0 | F86: =E86*D86 -> 0
B87: Ripper_8T | C87: Day | E87: ='Equip&HIRE_Master'!D19 -> 40.38 | F87: =E87*D87 -> 0
B88: Breaker_1.7-2T | C88: Day | E88: ='Equip&HIRE_Master'!D20 -> 123.33 | F88: =E88*D88 -> 0
B89: Breaker_3-5T | C89: Day | E89: ='Equip&HIRE_Master'!D21 -> 165.89 | F89: =E89*D89 -> 0
B90: Breaker_8T | C90: Day | D90: 8 | E90: ='Equip&HIRE_Master'!D22 -> 165.89 | F90: =E90*D90 -> 1327.12
B91: Breaker_10-12T | C91: Day | E91: ='Equip&HIRE_Master'!D23 -> 0 | F91: =E91*D91 -> 0
B92: Breaker_13-15T | C92: Day | E92: ='Equip&HIRE_Master'!D24 -> 203 | F92: =E92*D92 -> 0
B93: Auger Drive_10-12T | E93: ='Equip&HIRE_Master'!D25 -> 0 | F93: =E93*D93 -> 0
B94: 300Dia Auger Drill | E94: ='Equip&HIRE_Master'!D26 -> 0 | F94: =E94*D94 -> 0
E95: ='Equip&HIRE_Master'!D27 -> 0 | F95: =E95*D95 -> 0
B96: 1.25T_Tipper Truck | C96: Day | D96: 20 | E96: ='Equip&HIRE_Master'!D28 -> 205 | F96: =E96*D96 -> 4100
B97: 2-4T_Tipper Truck | C97: Day | E97: ='Equip&HIRE_Master'!D29 -> 166.98 | F97: =E97*D97 -> 0
B98: <6T_Tipper Truck | C98: Day | E98: ='Equip&HIRE_Master'!D30 -> 171.42857 | F98: =E98*D98 -> 0
E99: ='Equip&HIRE_Master'!D31 -> 0 | F99: =E99*D99 -> 0
B100: <10T_Articulated Site Tipper | C100: Day | E100: ='Equip&HIRE_Master'!D32 -> 0 | F100: =E100*D100 -> 0
B101: Upright Rammer_Wacker | C101: Day | D101: 30 | E101: ='Equip&HIRE_Master'!D33 -> 34.285714 | F101: =E101*D101 -> 1028.5714
B102: Trench Roller_Dbl Drum_Remote | C102: Day | E102: ='Equip&HIRE_Master'!D34 -> 165 | F102: =E102*D102 -> 0
B103: <26Ft_Scissor Lift - Diesel | C103: Day | E103: ='Equip&HIRE_Master'!D35 -> 0 | F103: =E103*D103 -> 0
B104: <26Ft_Scissor Lift - Elec | C104: Day | D104: 20 | E104: 250 | F104: =E104*D104 -> 5000
B105: <34Ft_Boom Lift - Diesel | C105: Day | E105: ='Equip&HIRE_Master'!D37 -> 0 | F105: =E105*D105 -> 0
B106: <34Ft_Boom Lift - Elec | C106: Day | E106: ='Equip&HIRE_Master'!D38 -> 0 | F106: =E106*D106 -> 0
E107: ='Equip&HIRE_Master'!D39 -> 0 | F107: =E107*D107 -> 0
B108: Porta Loo_No Tank | C108: Day | E108: ='Equip&HIRE_Master'!D40 -> 5.46 | F108: =E108*D108 -> 0
B109: 6*3m Demantable Lunchroom - COMPLETE | C109: Day | E109: ='Equip&HIRE_Master'!D41 -> 23 | F109: =E109*D109 -> 0
B110: 6*3m Demantable Office - COMPLETE | C110: Day | E110: ='Equip&HIRE_Master'!D42 -> 23 | F110: =E110*D110 -> 0
B111: 20Ft Shipping Container | C111: Day | E111: ='Equip&HIRE_Master'!D43 -> 0 | F111: =E111*D111 -> 0
B112: Quick Cut Demo Saw | C112: Day | E112: ='Equip&HIRE_Master'!D44 -> 0 | F112: =E112*D112 -> 0
B113: Sngl Ph_6KVA Genset | C113: Day | E113: ='Equip&HIRE_Master'!D45 -> 0 | F113: =E113*D113 -> 0
B114: Diesel Air Compressor_Trailer | C114: Day | E114: ='Equip&HIRE_Master'!D46 -> 0 | F114: =E114*D114 -> 0
B115: Air Breaker - Heavy | C115: Day | E115: ='Equip&HIRE_Master'!D47 -> 0 | F115: =E115*D115 -> 0
B116: Air Hose <10m | C116: Day | E116: ='Equip&HIRE_Master'!D48 -> 0 | F116: =E116*D116 -> 0
B117: Elec Breaker/Jachammer | C117: Day | E117: ='Equip&HIRE_Master'!D49 -> 0 | F117: =E117*D117 -> 0
B118: Flexdrive Motor Unit | C118: Day | E118: ='Equip&HIRE_Master'!D50 -> 0 | F118: =E118*D118 -> 0
B119: Flexdrive_Pump Shaft | C119: Day | E119: ='Equip&HIRE_Master'!D51 -> 0 | F119: =E119*D119 -> 0
...

Sheet ROK076
B1: Project:
B2: Tricore -
B3: Stage 1 Version 1
A4: Item
A9: 1 | B9: Complete -
B12: Labour
B14: DAY | J14: april 2026 direct impact Increase % (not contigency)
B15: ='LabourProject Rates_Master'!$B$14 -> TRADESMAN_LEADING HAND | C15: Day | E15: ='LabourProject Rates_Master'!$E$15 -> 1231.1429 | F15: =E15*D15 -> 0
B16: ='LabourProject Rates_Master'!$B$23 -> TRADESMAN_PLUMBER_OPERATOR | C16: Day | E16: ='LabourProject Rates_Master'!$E$22 -> 941.16473 | F16: =E16*D16 -> 0 | K16: PE Pipe & Fitting | L16: 0.38 | M16: 1.38
B17: ='LabourProject Rates_Master'!$B$30 -> T/A & Apprentice | C17: Day | E17: ='LabourProject Rates_Master'!$E$29 -> 768.06508 | F17: =E17*D17 -> 0 | K17: PVC Pipe & Fittings | L17: 0.38 | M17: 1.38
B18: ='LabourProject Rates_Master'!$B$36 -> Crew #1 - InGround Drainage | C18: Day | D18: 7 | E18: ='LabourProject Rates_Master'!$E$37 -> 2650.3945 | F18: =E18*D18 -> 18552.762 | K18: Subby Rates | L18: 0.15 | M18: 1.15
B19: ='LabourProject Rates_Master'!$B$43 -> Crew #2 - InGround Water/Fire | C19: Day | D19: 4 | E19: ='LabourProject Rates_Master'!$E$44 -> 2650.3945 | F19: =E19*D19 -> 10601.578 | K19: Delivey Rate | L19: 0.2 | M19: 1.2
B20: ='LabourProject Rates_Master'!B51 -> Crew #3 - Above Ground Drainage | C20: Day | D20: 3 | E20: ='LabourProject Rates_Master'!E52 -> 2650.3945 | F20: =E20*D20 -> 7951.1836
B21: ='LabourProject Rates_Master'!B59 -> Crew #4 - Above Ground WATER/FIRE | C21: Day | D21: 14 | E21: ='LabourProject Rates_Master'!E60 -> 2650.3945 | F21: =E21*D21 -> 37105.524
B22: ='LabourProject Rates_Master'!B67 -> Crew #5 - Above Ground FitOff / Misc | C22: Day | D22: 4 | E22: ='LabourProject Rates_Master'!E68 -> 2650.3945 | F22: =E22*D22 -> 10601.578
B23: ='LabourProject Rates_Master'!B75 -> Crew #6 - DEMO | C23: Day | D23: 2 | E23: ='LabourProject Rates_Master'!E76 -> 1709.2298 | F23: =E23*D23 -> 3418.4596
B25: HOUR
B26: ='LabourProject Rates_Master'!$B$14 -> TRADESMAN_LEADING HAND | C26: HR | D26: 0 | E26: ='LabourProject Rates_Master'!$E$14 -> 123.11429 | F26: =E26*D26 -> 0
B27: ='LabourProject Rates_Master'!$B$23 -> TRADESMAN_PLUMBER_OPERATOR | C27: HR | D27: 0 | E27: ='LabourProject Rates_Master'!$E$21 -> 94.116473 | F27: =E27*D27 -> 0
B28: ='LabourProject Rates_Master'!$B$30 -> T/A & Apprentice | C28: HR | D28: 0 | E28: ='LabourProject Rates_Master'!$E$28 -> 76.806508 | F28: =E28*D28 -> 0
B29: ='LabourProject Rates_Master'!$B$36 -> Crew #1 - InGround Drainage | C29: HR | D29: 0 | E29: ='LabourProject Rates_Master'!$E$36 -> 265.03945 | F29: =E29*D29 -> 0
B30: ='LabourProject Rates_Master'!$B$43 -> Crew #2 - InGround Water/Fire | C30: HR | D30: 0 | E30: ='LabourProject Rates_Master'!$E$43 -> 265.03945 | F30: =E30*D30 -> 0
B33: Demolition & Reinstatement
B34: DEMO
B35: ='Misc Subbie Rates_Master'!A49 -> Asphalt Cutting | C35: m | E35: ='Misc Subbie Rates_Master'!D49+('Misc Subbie Rates_Master'!D49*$L$18) -> 15.525 | F35: =E35*D35 -> 0
B36: ='Misc Subbie Rates_Master'!A50 -> Concrete Cutting | C36: m | E36: ='Misc Subbie Rates_Master'!D50+('Misc Subbie Rates_Master'!D50*$L$18) -> 18.4 | F36: =E36*D36 -> 0
B37: Con Cut Establishemnt Fee | C37: ea | E37: ='Misc Subbie Rates_Master'!D51+('Misc Subbie Rates_Master'!D51*$L$18) -> 92 | F37: =E37*D37 -> 0
B38: REINSTATE - CONCRETE
B39: ='Misc Subbie Rates_Master'!A56 -> Road/Drveway Reinstate; 1mW x 150 Thck, N25/20/80, Incl Reinforcement | C39: m | E39: ='Misc Subbie Rates_Master'!D56 -> 145 | F39: =E39*D39 -> 0
B40: ='Misc Subbie Rates_Master'!A57 -> Kerb & Channel - 1m Wide | C40: ea | E40: ='Misc Subbie Rates_Master'!D57 -> 155 | F40: =E40*D40 -> 0
B41: ='Misc Subbie Rates_Master'!A58 -> Footpath - 1.5mW, N25/20/80, Incl Reinforcement | C41: lm | E41: ='Misc Subbie Rates_Master'!D58 -> 180 | F41: =E41*D41 -> 0
B42: ='Misc Subbie Rates_Master'!A59 -> Footpath - 1.5mW, EXPOSED AGG, N25/20/80, Incl Reinforcement | C42: lm | E42: ='Misc Subbie Rates_Master'!D59 -> 185 | F42: =E42*D42 -> 0
B43: REINSTATE - ASPHALT
B44: ='Misc Subbie Rates_Master'!A64 -> 50mm Thck - Trench Reinstatement Through Road/Driveway | C44: m2 | E44: ='Misc Subbie Rates_Master'!D64 -> 97 | F44: =E44*D44 -> 0
B45: ='Misc Subbie Rates_Master'!A65 -> 50mm Thck - 1.5-2m Wide Footpath reinstatements | C45: m2 | E45: ='Misc Subbie Rates_Master'!D65 -> 97 | F45: =E45*D45 -> 0
B46: ='Misc Subbie Rates_Master'!A66 -> Establishment Fee (1 per stage) | C46: Ea | E46: ='Misc Subbie Rates_Master'!D66 -> 5500 | F46: =E46*D46 -> 0
B48: Equipment & Hire - INCL WET PLANT HIRE
B50: PLANT HIRE - WET
B51: 1.8T Excavator | C51: Hr | E51: ='Misc Subbie Rates_Master'!D10 -> 100 | F51: =E51*D51 -> 0
B52: 3-5 ton Excavator | C52: Hr | E52: ='Misc Subbie Rates_Master'!D11 -> 115 | F52: =E52*D52 -> 0
B53: 3-5T Combo | C53: Hr | E53: ='Misc Subbie Rates_Master'!D12 -> 154 | F53: =E53*D53 -> 0
B54: Hammer attachment 3.5-4T | C54: Hr | E54: ='Misc Subbie Rates_Master'!D13 -> 21 | F54: =E54*D54 -> 0
B55: Ripper 3.5-4T | C55: Hr | E55: ='Misc Subbie Rates_Master'!D14 -> 10 | F55: =E55*D55 -> 0
B56: 5t Excavator | C56: Hr | E56: ='Misc Subbie Rates_Master'!D15 -> 150 | F56: =E56*D56 -> 0
B57: Hammer attachment 5T | C57: Hr | E57: ='Misc Subbie Rates_Master'!D16 -> 50 | F57: =E57*D57 -> 0
B58: Skid steer | C58: Hr | E58: ='Misc Subbie Rates_Master'!D17 -> 140 | F58: =E58*D58 -> 0
B59: 8T Excavator | C59: Hr | E59: ='Misc Subbie Rates_Master'!D18 -> 128 | F59: =E59*D59 -> 0
B60: Hammer attachment 8T | C60: Hr | E60: ='Misc Subbie Rates_Master'!D19 -> 26 | F60: =E60*D60 -> 0
B61: Ripper 8T | C61: Hr | E61: ='Misc Subbie Rates_Master'!D20 -> 10 | F61: =E61*D61 -> 0
B62: 13-15T Excavator | C62: Hr | E62: ='Misc Subbie Rates_Master'!D21 -> 153 | F62: =E62*D62 -> 0
... B69: 12t Body Truck Tipper | C69: Hr | E69: ='Misc Subbie Rates_Master'!D28 -> 110 | F69: =E69*D69 -> 0
B71: HIRE - DRY
B72: Skid Steer Loader_Tracked (CAT249+) | C72: Day | D72: 10 | E72: ='Equip&HIRE_Master'!D4 -> 225.43333 | F72: =E72*D72 -> 2254.3333
B73: Skid Steer Loader_Wheeled (CAT226+) | C73: Day | E73: ='Equip&HIRE_Master'!D5 -> 163.96667 | F73: =E73*D73 -> 0
B74: Mini Loader, Stand-on Type | C74: Day | E74: ='Equip&HIRE_Master'!D6 -> 180 | F74: =E74*D74 -> 0
E75: ='Equip&HIRE_Master'!D7 -> 0 | F75: =E75*D75 -> 0
B76: 1.5-1.8 Ton_Excavator | C76: Day | E76: ='Equip&HIRE_Master'!D8 -> 137.14286 | F76: =E76*D76 -> 0
B77: 1.7-2Ton_Excavator | C77: Day | E77: ='Equip&HIRE_Master'!D9 -> 0 | F77: =E77*D77 -> 0
B78: 3-5Ton_Excavator | C78: Day | D78: 7 | E78: ='Equip&HIRE_Master'!D10 -> 238.66667 | F78: =E78*D78 -> 1670.6667
B79: 8Ton_Excavator | C79: Day | E79: ='Equip&HIRE_Master'!D11 -> 261.16667 | F79: =E79*D79 -> 0
B80: 10-12Ton_Excavator | C80: Day | E80: ='Equip&HIRE_Master'!D12 -> 0 | F80: =E80*D80 -> 0
B81: 13-16Ton_Excavator | C81: Day | E81: ='Equip&HIRE_Master'!D13 -> 317.2 | F81: =E81*D81 -> 0
B82: 20-24Ton_Excavator | C82: Day | E82: ='Equip&HIRE_Master'!D14 -> 314.28571 | F82: =E82*D82 -> 0
E83: ='Equip&HIRE_Master'!D15 -> 0 | F83: =E83*D83 -> 0
B84: Ripper_1.7-2T | C84: Day | E84: ='Equip&HIRE_Master'!D16 -> 0 | F84: =E84*D84 -> 0
B85: Ripper_1.5-4T | C85: Day | E85: ='Equip&HIRE_Master'!D17 -> 32.74 | F85: =E85*D85 -> 0
B86: Ripper_3-5T | C86: Day | E86: ='Equip&HIRE_Master'!D18 -> 0 | F86: =E86*D86 -> 0
B87: Ripper_8T | C87: Day | E87: ='Equip&HIRE_Master'!D19 -> 40.38 | F87: =E87*D87 -> 0
B88: Breaker_1.7-2T | C88: Day | E88: ='Equip&HIRE_Master'!D20 -> 123.33 | F88: =E88*D88 -> 0
B89: Breaker_3-5T | C89: Day | E89: ='Equip&HIRE_Master'!D21 -> 165.89 | F89: =E89*D89 -> 0
B90: Breaker_8T | C90: Day | E90: ='Equip&HIRE_Master'!D22 -> 165.89 | F90: =E90*D90 -> 0
B91: Breaker_10-12T | C91: Day | E91: ='Equip&HIRE_Master'!D23 -> 0 | F91: =E91*D91 -> 0
B92: Breaker_13-15T | C92: Day | E92: ='Equip&HIRE_Master'!D24 -> 203 | F92: =E92*D92 -> 0
B93: Auger Drive_10-12T | E93: ='Equip&HIRE_Master'!D25 -> 0 | F93: =E93*D93 -> 0
B94: 300Dia Auger Drill | E94: ='Equip&HIRE_Master'!D26 -> 0 | F94: =E94*D94 -> 0
E95: ='Equip&HIRE_Master'!D27 -> 0 | F95: =E95*D95 -> 0
B96: 1.25T_Tipper Truck | C96: Day | D96: 7 | E96: ='Equip&HIRE_Master'!D28 -> 205 | F96: =E96*D96 -> 1435
B97: 2-4T_Tipper Truck | C97: Day | E97: ='Equip&HIRE_Master'!D29 -> 166.98 | F97: =E97*D97 -> 0
B98: <6T_Tipper Truck | C98: Day | E98: ='Equip&HIRE_Master'!D30 -> 171.42857 | F98: =E98*D98 -> 0
E99: ='Equip&HIRE_Master'!D31 -> 0 | F99: =E99*D99 -> 0
B100: <10T_Articulated Site Tipper | C100: Day | E100: ='Equip&HIRE_Master'!D32 -> 0 | F100: =E100*D100 -> 0
B101: Upright Rammer_Wacker | C101: Day | D101: 7 | E101: ='Equip&HIRE_Master'!D33 -> 34.285714 | F101: =E101*D101 -> 240
B102: Trench Roller_Dbl Drum_Remote | C102: Day | E102: ='Equip&HIRE_Master'!D34 -> 165 | F102: =E102*D102 -> 0
B103: <26Ft_Scissor Lift - Diesel | C103: Day | E103: ='Equip&HIRE_Master'!D35 -> 0 | F103: =E103*D103 -> 0
B104: <26Ft_Scissor Lift - Elec | C104: Day | E104: ='Equip&HIRE_Master'!D36 -> 0 | F104: =E104*D104 -> 0
B105: <34Ft_Boom Lift - Diesel | C105: Day | E105: ='Equip&HIRE_Master'!D37 -> 0 | F105: =E105*D105 -> 0
B106: <34Ft_Boom Lift - Elec | C106: Day | E106: ='Equip&HIRE_Master'!D38 -> 0 | F106: =E106*D106 -> 0
E107: ='Equip&HIRE_Master'!D39 -> 0 | F107: =E107*D107 -> 0
B108: Porta Loo_No Tank | C108: Day | E108: ='Equip&HIRE_Master'!D40 -> 5.46 | F108: =E108*D108 -> 0
B109: 6*3m Demantable Lunchroom - COMPLETE | C109: Day | E109: ='Equip&HIRE_Master'!D41 -> 23 | F109: =E109*D109 -> 0
B110: 6*3m Demantable Office - COMPLETE | C110: Day | E110: ='Equip&HIRE_Master'!D42 -> 23 | F110: =E110*D110 -> 0
B111: 20Ft Shipping Container | C111: Day | E111: ='Equip&HIRE_Master'!D43 -> 0 | F111: =E111*D111 -> 0
B112: Quick Cut Demo Saw | C112: Day | E112: ='Equip&HIRE_Master'!D44 -> 0 | F112: =E112*D112 -> 0
B113: Sngl Ph_6KVA Genset | C113: Day | E113: ='Equip&HIRE_Master'!D45 -> 0 | F113: =E113*D113 -> 0
B114: Diesel Air Compressor_Trailer | C114: Day | E114: ='Equip&HIRE_Master'!D46 -> 0 | F114: =E114*D114 -> 0
B115: Air Breaker - Heavy | C115: Day | E115: ='Equip&HIRE_Master'!D47 -> 0 | F115: =E115*D115 -> 0
B116: Air Hose <10m | C116: Day | E116: ='Equip&HIRE_Master'!D48 -> 0 | F116: =E116*D116 -> 0
B117: Elec Breaker/Jachammer | C117: Day | E117: ='Equip&HIRE_Master'!D49 -> 0 | F117: =E117*D117 -> 0
B118: Flexdrive Motor Unit | C118: Day | E118: ='Equip&HIRE_Master'!D50 -> 0 | F118: =E118*D118 -> 0
B119: Flexdrive_Pump Shaft | C119: Day | E119: ='Equip&HIRE_Master'!D51 -> 0 | F119: =E119*D119 -> 0
...

Sheet LabourProject Rates_Master
B1: Project:
B2: Tricore -
B3: Stage 1 Version 1
A4: Item
B6: BASED ON:
B7: ='[2]Staff Costs_Lead Hand'!$B$193 -> Work ROSTER Example #3 - 6-Day Week, 10Hr Days, Stay @ Rocky for W/E, Return Every 2nd W/E. (FLY)
B8: ='[2]Staff Costs_Lead Hand'!$E$212 -> Working Days/Month | C8: ='[2]Staff Costs_Lead Hand'!$F$212 -> 21
B9: ='[2]Staff Costs_Lead Hand'!$E$213 -> No-Work Days/Month | C9: ='[2]Staff Costs_Lead Hand'!$F$213 -> 7
B10: ='[2]Staff Costs_Lead Hand'!$E$214 -> Avrg Hours / Month | C10: ='[2]Staff Costs_Lead Hand'!$F$214 -> 210
B12: STAFF
C13: Unit | D13: REQ | E13: Cost ex GST | F13: Total ex GST
B14: ='[2]Staff Costs_Lead Hand'!$B$4 -> TRADESMAN_LEADING HAND | C14: HR | D14: 1 | E14: =E17/$C$10 -> 123.11429 | F14: =D14*E14 -> 123.11429
B15: ** for Roster Examples # 3 | C15: DAY | D15: 1 | E15: =E17/$C$8 -> 1231.1429 | F15: =D15*E15 -> 1231.1429
B16: =B14 -> TRADESMAN_LEADING HAND | C16: WEEK | D16: 1 | E16: =E17/4 -> 6463.5 | F16: =D16*E16 -> 6463.5
C17: MONTH | D17: 1 | E17: ='[2]Staff Costs_Lead Hand'!$F$211 -> 25854 | F17: =D17*E17 -> 25854
B19: QTY Staff in Crew | C19: =COUNTA(B16,B17,B18) -> 1
B21: ='[2]Staff Costs_Tradesman'!$B$4 -> TRADESMAN_PLUMBER_OPERATOR | C21: HR | D21: 1 | E21: =E24/$C$10 -> 94.116473 | F21: =D21*E21 -> 94.116473
B22: ** for Roster Examples # 3 | C22: DAY | D22: 1 | E22: =E24/$C$8 -> 941.16473 | F22: =D22*E22 -> 941.16473
B23: =B21 -> TRADESMAN_PLUMBER_OPERATOR | C23: WEEK | D23: 1 | E23: =E24/4 -> 4941.1148 | F23: =D23*E23 -> 4941.1148
C24: MONTH | D24: 1 | E24: ='[2]Staff Costs_Tradesman'!$F$121 -> 19764.459 | F24: =D24*E24 -> 19764.459
B26: QTY Staff in Crew | C26: =COUNTA(B23,B24,B25) -> 1
B28: ='[2]Staff Costs_TA'!$B$4 -> T/A & Apprentice | C28: HR | D28: 1 | E28: =E31/$C$10 -> 76.806508 | F28: =D28*E28 -> 76.806508
B29: ** for Roster Examples # 3 | C29: DAY | D29: 1 | E29: =E31/$C$8 -> 768.06508 | F29: =D29*E29 -> 768.06508
B30: =B28 -> T/A & Apprentice | C30: WEEK | D30: 1 | E30: =E31/4 -> 4032.3417 | F30: =D30*E30 -> 4032.3417
C31: MONTH | D31: 1 | E31: ='[2]Staff Costs_TA'!$F$122 -> 16129.367 | F31: =D31*E31 -> 16129.367
B33: QTY Staff in Crew | C33: =COUNTA(B30,B31,B32) -> 1
B36: Crew #1 - InGround Drainage | C36: HR | D36: 1 | E36: =E39/$C$10 -> 265.03945 | F36: =D36*E36 -> 265.03945
B37: ** for Roster Examples # 3 | C37: DAY | D37: 1 | E37: =E39/$C$8 -> 2650.3945 | F37: =D37*E37 -> 2650.3945
B38: =B21 -> TRADESMAN_PLUMBER_OPERATOR | C38: WEEK | D38: 1 | E38: =E39/4 -> 13914.571 | F38: =D38*E38 -> 13914.571
B39: =B21 -> TRADESMAN_PLUMBER_OPERATOR | C39: MONTH | D39: 1 | E39: =(E24*2)+E31 -> 55658.285 | F39: =D39*E39 -> 55658.285
B40: =B28 -> T/A & Apprentice
B41: QTY Staff in Crew | C41: =COUNTA(B38,B39,B40) -> 3
B43: Crew #2 - InGround Water/Fire | C43: HR | D43: 1 | E43: =E46/$C$10 -> 265.03945 | F43: =D43*E43 -> 265.03945
B44: ** for Roster Examples # 3 | C44: DAY | D44: 1 | E44: =E46/$C$8 -> 2650.3945 | F44: =D44*E44 -> 2650.3945
B45: =B21 -> TRADESMAN_PLUMBER_OPERATOR | C45: WEEK | D45: 1 | E45: =E46/4 -> 13914.571 | F45: =D45*E45 -> 13914.571
B46: =B21 -> TRADESMAN_PLUMBER_OPERATOR | C46: MONTH | D46: 1 | E46: =(E24*2)+E31 -> 55658.285 | F46: =D46*E46 -> 55658.285
B47: =B28 -> T/A & Apprentice
B48: QTY Staff in Crew | C48: =COUNTA(B45,B46,B47) -> 3
B51: Crew #3 - Above Ground Drainage | C51: HR | D51: 1 | E51: =E43 -> 265.03945 | F51: =D51*E51 -> 265.03945
B52: =B44 -> ** for Roster Examples # 3 | C52: DAY | D52: 1 | E52: =E44 -> 2650.3945 | F52: =D52*E52 -> 2650.3945
B53: =B45 -> TRADESMAN_PLUMBER_OPERATOR | C53: WEEK | D53: 1 | E53: =E45 -> 13914.571 | F53: =D53*E53 -> 13914.571
B54: =B46 -> TRADESMAN_PLUMBER_OPERATOR | C54: MONTH | D54: 1 | E54: =E46 -> 55658.285 | F54: =D54*E54 -> 55658.285
B55: =B47 -> T/A & Apprentice
B56: QTY Staff in Crew | C56: =COUNTA(B53,B54,B55) -> 3
B59: Crew #4 - Above Ground WATER/FIRE | C59: HR | D59: 1 | E59: =E51 -> 265.03945 | F59: =D59*E59 -> 265.03945
B60: =B52 -> ** for Roster Examples # 3 | C60: DAY | D60: 1 | E60: =E52 -> 2650.3945 | F60: =D60*E60 -> 2650.3945
B61: =B53 -> TRADESMAN_PLUMBER_OPERATOR | C61: WEEK | D61: 1 | E61: =E53 -> 13914.571 | F61: =D61*E61 -> 13914.571
B62: =B54 -> TRADESMAN_PLUMBER_OPERATOR | C62: MONTH | D62: 1 | E62: =E54 -> 55658.285 | F62: =D62*E62 -> 55658.285
B63: =B55 -> T/A & Apprentice
B64: QTY Staff in Crew | C64: =COUNTA(B61,B62,B63) -> 3
B67: Crew #5 - Above Ground FitOff / Misc | C67: HR | D67: 1 | E67: =E59 -> 265.03945 | F67: =D67*E67 -> 265.03945
B68: =B60 -> ** for Roster Examples # 3 | C68: DAY | D68: 1 | E68: =E60 -> 2650.3945 | F68: =D68*E68 -> 2650.3945
B69: =B61 -> TRADESMAN_PLUMBER_OPERATOR | C69: WEEK | D69: 1 | E69: =E61 -> 13914.571 | F69: =D69*E69 -> 13914.571
B70: =B62 -> TRADESMAN_PLUMBER_OPERATOR | C70: MONTH | D70: 1 | E70: =E62 -> 55658.285 | F70: =D70*E70 -> 55658.285
B71: =B63 -> T/A & Apprentice
B72: QTY Staff in Crew | C72: =COUNTA(B69,B70,B71) -> 3
B75: Crew #6 - DEMO | C75: HR | D75: 1 | E75: =E78/$C$10 -> 170.92298 | F75: =D75*E75 -> 170.92298
B76: =B68 -> ** for Roster Examples # 3 | C76: DAY | D76: 1 | E76: =E78/$C$8 -> 1709.2298 | F76: =D76*E76 -> 1709.2298
B77: =B69 -> TRADESMAN_PLUMBER_OPERATOR | C77: WEEK | D77: 1 | E77: =E78/4 -> 8973.4565 | F77: =D77*E77 -> 8973.4565
B78: =B71 -> T/A & Apprentice | C78: MONTH | D78: 1 | E78: =(E24)+E31 -> 35893.826 | F78: =D78*E78 -> 35893.826
B80: QTY Staff in Crew | C80: =COUNTA(B77,B78) -> 2
A85: `
B87: FULL team, FULL Duration, as per Program | C87: HR | D87: 0 | E87: =E90/$C$10 -> 653.19319 | F87: =D87*E87 -> 0
B88: ** for Roster Examples # 3 | C88: DAY | D88: 0 | E88: =E90/$C$8 -> 6531.9319 | F88: =D88*E88 -> 0
B89: =B36 -> Crew #1 - InGround Drainage | C89: WEEK | D89: 0 | E89: =E90/4 -> 34292.643 | F89: =D89*E89 -> 0
B90: =B43 -> Crew #2 - InGround Water/Fire | C90: MONTH | D90: 4 | E90: =E46+E39+E17 -> 137170.57 | F90: =D90*E90 -> 548682.28
B91: =B14 -> TRADESMAN_LEADING HAND
B92: QTY Staff in Crew | C92: =C48+C41+C19 -> 7
A94: `
B97: ACCOMODATION
C98: Unit | D98: REQ | E98: Cost | F98: Total EX GST
B100: =Accomodation_Master!B266 -> Full Apartment / TownHouse / Unit - VIA AGENT | E100: *Changed to ex GST | G100: 11
B101: ** for Roster Examples # 3 | C101: NIGHT | D101: 0 | E101: =E102/7 -> 164.50216 | F101: =D101*E101 -> 0
C102: WEEK | D102: 0 | E102: =E103/4 -> 1151.5152 | F102: =D102*E102 -> 0
B103: =B21 -> TRADESMAN_PLUMBER_OPERATOR | C103: MONTH | D103: 0 | E103: =(Accomodation_Master!E308)-(Accomodation_Master!E308/G100) -> 4606.0606 | F103: =D103*E103 -> 0
B104: =B21 -> TRADESMAN_PLUMBER_OPERATOR
B105: =B28 -> T/A & Apprentice
B106: QTY Staff in Crew | C106: =COUNTA(B103,B104,B105) -> 3
B108: Individual - PER PERSON | E108: *Changed to ex GST | G108: 11
B109: ** for Roster Examples # 3 | C109: NIGHT | D109: 0 | E109: =(Accomodation_Master!F364)-(Accomodation_Master!F364/G108) -> 103.24675 | F109: =D109*E109 -> 0
B110: =Accomodation_Master!$B$364 -> TCS Cost Per Person - Private Unit - NO SHARE - Nightly Booking (average allowance) | C110: WEEK | D110: 0 | E110: =E109*7 -> 722.72727 | F110: =D110*E110 -> 0
C111: MONTH | D111: 0 | E111: =E110*4 -> 2890.9091 | F111: =D111*E111 -> 0

Sheet Material Rates_Master
A3: FIRE SERVICES - IN GROUND
A4: Description | B4: Unit | D4: Rate | F4: Total | I4: Qty
A5: 200 HDPE PN16 SDR11 - REDLINE | B5: m | D5: ='[3]240522_Supplier RFQ'!F16 -> 33.920833 | F5: =I5*D5 -> 16282 | G5: COMPLETED don’t edit | I5: 480
A6: 180 HDPE PN16 SDR11 - REDLINE | B6: m | D6: ='[3]240522_Supplier RFQ'!F17 -> 25.466667 | F6: =I6*D6 -> 128657.6 | I6: 5052
A7: 125 HDPE PN16 SDR11 - REDLINE | B7: m | D7: ='[3]240522_Supplier RFQ'!F18 -> 12.314167 | F7: =I7*D7 -> 13151.53 | I7: 1068
A8: 32 HDPE PN16 SDR11 - BLUELINE | B8: m | D8: ='[3]240522_Supplier RFQ'!F19 -> 1.2159 | F8: =I8*D8 -> 121.59 | I8: 100
A10: 200 EF Coupler | B10: ea | D10: ='[3]240522_Supplier RFQ'!F21 -> 44.06 | F10: =I10*D10 -> 1321.8 | G10: COMPLETED don’t edit | I10: 30
A11: 180 EF Coupler | B11: ea | D11: ='[3]240522_Supplier RFQ'!F22 -> 25.72 | F11: =I11*D11 -> 5144 | I11: 200
A12: 125 EF Coupler | B12: ea | D12: ='[3]240522_Supplier RFQ'!F23 -> 14.11 | F12: =I12*D12 -> 1411 | I12: 100
A13: 200 EF 45DFeg Bend | B13: ea | D13: ='[3]240522_Supplier RFQ'!F24 -> 109.16 | F13: =I13*D13 -> 218.32 | I13: 2
A14: 180 EF 45DFeg Bend | B14: ea | D14: ='[3]240522_Supplier RFQ'!F25 -> 97.97 | F14: =I14*D14 -> 12736.1 | I14: 130
A15: 125 EF 45DFeg Bend | B15: ea | D15: ='[3]240522_Supplier RFQ'!F26 -> 44.69 | F15: =I15*D15 -> 1117.25 | G15: COMPLETED don’t edit | I15: 25
A16: 200 EF 90DFeg Bend | B16: ea | D16: ='[3]240522_Supplier RFQ'!F27 -> 109.16 | F16: =I16*D16 -> 654.96 | I16: 6
A17: 180 EF 90DFeg Bend | B17: ea | D17: ='[3]240522_Supplier RFQ'!F28 -> 97.81 | F17: =I17*D17 -> 7824.8 | I17: 80
A18: 125 EF 90DFeg Bend | B18: ea | D18: ='[3]240522_Supplier RFQ'!F29 -> 44.65 | F18: =I18*D18 -> 3572 | I18: 80
A19: 200 EF TEE | B19: ea | D19: ='[3]240522_Supplier RFQ'!F30 -> 109.75 | F19: =I19*D19 -> 329.25 | I19: 3
A20: 180 EF TEE | B20: ea | D20: ='[3]240522_Supplier RFQ'!F31 -> 114.28 | F20: =I20*D20 -> 4571.2 | G20: COMPLETED don’t edit | I20: 40
A21: 125 EF TEE | B21: ea | D21: ='[3]240522_Supplier RFQ'!F32 -> 49.25 | F21: =I21*D21 -> 49.25 | I21: 1
A22: 200*180 EF TEE | B22: ea | D22: ='[3]240522_Supplier RFQ'!F33 -> 209.47 | F22: =I22*D22 -> 418.94 | I22: 2
A23: 200*125 EF TEE | B23: ea | D23: ='[3]240522_Supplier RFQ'!F34 -> 218.42 | F23: =I23*D23 -> 436.84 | I23: 2
A24: 180*125 EF TEE | B24: ea | D24: ='[3]240522_Supplier RFQ'!F35 -> 122.13 | F24: =I24*D24 -> 4885.2 | I24: 40
A25: 200*180 EF Reducer | B25: ea | D25: ='[3]240522_Supplier RFQ'!F36 -> 125.62 | F25: =I25*D25 -> 502.48 | G25: COMPLETED don’t edit | I25: 4
A26: 180*125 EF Reducer | B26: ea | D26: ='[3]240522_Supplier RFQ'!F37 -> 60.1 | F26: =I26*D26 -> 1202 | I26: 20
A27: 200PE*8"(200m) - MaxiStub W/Backing Ring | B27: ea | D27: ='[3]240522_Supplier RFQ'!F38 -> 342.35 | F27: =I27*D27 -> 3423.5 | I27: 10
A28: 180PE*6"(150mm) - MaxiStub W/Backing Ring | B28: ea | D28: ='[3]240522_Supplier RFQ'!F39 -> 129.77 | F28: =I28*D28 -> 7786.2 | I28: 60
A29: 125PE*4" (100mm) - MaxiStub W/Backing Ring | B29: ea | D29: ='[3]240522_Supplier RFQ'!F40 -> 92.67 | F29: =I29*D29 -> 1853.4 | I29: 20
A30: 180mm PE x 150mm GALV ADAPTER - PLASSON Brand | B30: ea | D30: ='[3]240522_Supplier RFQ'!$L$41 -> 313.19 | F30: =I30*D30 -> 3131.9 | G30: COMPLETED don’t edit | I30: 10
A31: 125mm PE x 100mm GALV ADAPTER - PLASSON Brand | B31: ea | D31: ='[3]240522_Supplier RFQ'!$L$42 -> 204.11 | F31: =I31*D31 -> 10205.5 | I31: 50
A33: 180mm PE x 150mm GALV ADAPTER | B33: ea | D33: ='[3]240522_Supplier RFQ'!F44 -> 315.71 | F33: =I33*D33 -> 3157.1 | I33: 10
A34: 125mm PE x 100mm GALV ADAPTER | B34: ea | D34: ='[3]240522_Supplier RFQ'!F45 -> 201.43 | F34: =I34*D34 -> 10071.5 | I34: 50
A35: 200 Long SPIG 45DFeg Bend | B35: ea | D35: ='[3]240522_Supplier RFQ'!F46 -> 68.54 | F35: =I35*D35 -> 137.08 | G35: COMPLETED don’t edit | I35: 2
A36: 180 Long SPIG 45DFeg Bend | B36: ea | D36: ='[3]240522_Supplier RFQ'!F47 -> 64.46 | F36: =I36*D36 -> 8379.8 | I36: 130
A37: 125 Long SPIG 45DFeg Bend | B37: ea | D37: ='[3]240522_Supplier RFQ'!F48 -> 38.76 | F37: =I37*D37 -> 969 | I37: 25
A38: 200 Long SPIG 90DFeg Bend | B38: ea | D38: ='[3]240522_Supplier RFQ'!F49 -> 86.17 | F38: =I38*D38 -> 517.02 | I38: 6
A39: 180 Long SPIG 90DFeg Bend | B39: ea | D39: ='[3]240522_Supplier RFQ'!F50 -> 68.11 | F39: =I39*D39 -> 5448.8 | I39: 80
A40: 125 Long SPIG 90DFeg Bend | B40: ea | D40: ='[3]240522_Supplier RFQ'!F51 -> 31.65 | F40: =I40*D40 -> 2532 | G40: COMPLETED don’t edit | I40: 80
A41: 200 Long SPIG TEE | B41: ea | D41: ='[3]240522_Supplier RFQ'!F52 -> 127.64 | F41: =I41*D41 -> 382.92 | I41: 3
A42: 180 Long SPIG TEE | B42: ea | D42: ='[3]240522_Supplier RFQ'!F53 -> 114.22 | F42: =I42*D42 -> 4568.8 | I42: 40
A43: 125 Long SPIG TEE | B43: ea | D43: ='[3]240522_Supplier RFQ'!F54 -> 38.26 | F43: =I43*D43 -> 38.26 | I43: 1
A44: 200*180 Long SPIG TEE | B44: ea | D44: ='[3]240522_Supplier RFQ'!F55 -> 183.48 | F44: =I44*D44 -> 366.96 | I44: 2
A45: 200*125 Long SPIG TEE | B45: ea | D45: ='[3]240522_Supplier RFQ'!F56 -> 192.43 | F45: =I45*D45 -> 384.86 | G45: COMPLETED don’t edit | I45: 2
A46: 180*125 Long SPIG TEE | B46: ea | D46: ='[3]240522_Supplier RFQ'!F57 -> 185.71 | F46: =I46*D46 -> 7428.4 | I46: 40
A47: 200*180 Long SPIG Reducer | B47: ea | D47: ='[3]240522_Supplier RFQ'!F58 -> 55.84 | F47: =I47*D47 -> 223.36 | I47: 4
A48: 180*125 Long SPIG Reducer | B48: ea | D48: ='[3]240522_Supplier RFQ'!F59 -> 39.83 | F48: =I48*D48 -> 796.6 | I48: 20
D49: ='[3]240522_Supplier RFQ'!F60 -> 0
A50: 200 FL DICL Sluice Valve | B50: ea | D50: ='[3]240522_Supplier RFQ'!F61 -> 679.41 | F50: =I50*D50 -> 4076.46 | G50: COMPLETED don’t edit | I50: 6
A51: 150 FL DICL Sluice Valve | B51: ea | D51: ='[3]240522_Supplier RFQ'!F62 -> 323.53 | F51: =I51*D51 -> 19411.8 | I51: 60
A52: 100 FL DICL Sluice Valve | B52: ea | D52: ='[3]240522_Supplier RFQ'!F63 -> 202.94 | F52: =I52*D52 -> 6088.2 | I52: 30
A53: Valve Spindle Riser - 600Long | B53: ea | D53: ='[3]240522_Supplier RFQ'!F64 -> 136.94 | F53: =I53*D53 -> 13146.24 | I53: 96
A54: Valve Box - Cast Iron Trafficable - Rectangle Type "V" | B54: ea | D54: ='[3]240522_Supplier RFQ'!F65 -> 123.53 | F54: =I54*D54 -> 8647.1 | I54: 70
A55: Valve Box - Non-Trafficable - Plastic Surround with CI Drop In "V" | B55: ea | D55: ='[3]240522_Supplier RFQ'!F66 -> 98.82 | F55: =I55*D55 -> 2964.6 | G55: COMPLETED don’t edit | I55: 30
A57: 200*150mm DICL FL Reducer | B57: ea | D57: ='[3]240522_Supplier RFQ'!F68 -> 291.18 | F57: =I57*D57 -> 582.36 | I57: 2
A58: 200*100mm DICL FL Reducer | B58: ea | D58: ='[3]240522_Supplier RFQ'!F69 -> 330 | F58: =I58*D58 -> 660 | I58: 2
A59: 150*100mm DICL FL Reducer | B59: ea | D59: ='[3]240522_Supplier RFQ'!F70 -> 156 | F59: =I59*D59 -> 936 | I59: 6
A60: 150mm DICL FL * SP Adapter | B60: ea | D60: ='[3]240522_Supplier RFQ'!F71 -> 106.24 | F60: =I60*D60 -> 1274.88 | G60: COMPLETED don’t edit | I60: 12
A61: 100mm DICL FL * SP Adapter | B61: ea | D61: ='[3]240522_Supplier RFQ'!F72 -> 70.59 | F61: =I61*D61 -> 564.72 | I61: 8
A62: 200mm DICL FL 90Deg Bend | B62: ea | D62: ='[3]240522_Supplier RFQ'!F73 -> 516.35 | F62: =I62*D62 -> 1032.7 | I62: 2
A63: 150mm DICL FL 90Deg Bend | B63: ea | D63: ='[3]240522_Supplier RFQ'!F74 -> 198.88 | F63: =I63*D63 -> 1591.04 | I63: 8
A64: 100mm DICL FL 90Deg Bend | B64: ea | D64: ='[3]240522_Supplier RFQ'!F75 -> 108.71 | F64: =I64*D64 -> 434.84 | I64: 4
A65: 200mm DICL FL TEE | B65: ea | D65: ='[3]240522_Supplier RFQ'!F76 -> 672.65 | F65: =I65*D65 -> 1345.3 | G65: COMPLETED don’t edit | I65: 2
A66: 150mm DICL FL TEE | B66: ea | D66: ='[3]240522_Supplier RFQ'!F77 -> 228.24 | F66: =I66*D66 -> 3423.6 | I66: 15
A67: 100mm DICL FL TEE | B67: ea | D67: ='[3]240522_Supplier RFQ'!F78 -> 128.24 | F67: =I67*D67 -> 256.48 | I67: 2
A68: 200*150*200 DICL FL TEE | B68: ea | D68: ='[3]240522_Supplier RFQ'!F79 -> 536.76 | F68: =I68*D68 -> 1073.52 | I68: 2
A69: 200*100*200 DICL FL TEE | B69: ea | D69: ='[3]240522_Supplier RFQ'!F80 -> 576.47 | F69: =I69*D69 -> 576.47 | I69: 1
A70: 150-100-150 DICL FL TEE | B70: ea | D70: ='[3]240522_Supplier RFQ'!F81 -> 198.82 | F70: =I70*D70 -> 1192.92 | G70: COMPLETED don’t edit | I70: 6
A71: 200mm DICL FL Pipe @ 1000 | B71: ea | D71: ='[3]240522_Supplier RFQ'!F82 -> 898.82 | F71: =I71*D71 -> 898.82 | I71: 1
A72: 200mm DICL FL Pipe @ 600 | B72: ea | D72: ='[3]240522_Supplier RFQ'!F83 -> 640 | F72: =I72*D72 -> 640 | I72: 1
A73: 200mm DICL FL Pipe @ 300 | B73: ea | D73: ='[3]240522_Supplier RFQ'!F84 -> 355.29 | F73: =I73*D73 -> 355.29 | I73: 1
A74: 150mm DICL FL Pipe @ 1000 | B74: ea | D74: ='[3]240522_Supplier RFQ'!F85 -> 534.41 | F74: =I74*D74 -> 534.41 | I74: 1
A75: 150mm DICL FL Pipe @ 600 | B75: ea | D75: ='[3]240522_Supplier RFQ'!F86 -> 280 | F75: =I75*D75 -> 280 | G75: COMPLETED don’t edit | I75: 1
A76: 150mm DICL FL Pipe @ 450 | B76: ea | D76: ='[3]240522_Supplier RFQ'!F87 -> 236.47 | F76: =I76*D76 -> 236.47 | I76: 1
A77: 150mm DICL FL Pipe @ 300 | B77: ea | D77: ='[3]240522_Supplier RFQ'!F88 -> 178.8 | F77: =I77*D77 -> 1430.4 | I77: 8
A78: 100mm DICL FL Pipe @ 1000 | B78: ea | D78: ='[3]240522_Supplier RFQ'!F89 -> 362.35 | F78: =I78*D78 -> 362.35 | I78: 1
A79: 100mm DICL FL Pipe @ 600 | B79: ea | D79: ='[3]240522_Supplier RFQ'!F90 -> 144.71 | F79: =I79*D79 -> 144.71 | I79: 1
A80: 100mm DICL FL Pipe @ 450 | B80: ea | D80: ='[3]240522_Supplier RFQ'!F91 -> 135.88 | F80: =I80*D80 -> 135.88 | G80: COMPLETED don’t edit | I80: 1
A81: 100mm DICL FL Pipe @ 300 | B81: ea | D81: ='[3]240522_Supplier RFQ'!F92 -> 76.47 | F81: =I81*D81 -> 305.88 | I81: 4
A82: 150mm DICL FL Deadplate | B82: ea | D82: ='[3]240522_Supplier RFQ'!F93 -> 67.65 | F82: =I82*D82 -> 1691.25 | I82: 25
A83: 100mm DICL FL Deadplate | B83: ea | D83: ='[3]240522_Supplier RFQ'!F94 -> 43.53 | F83: =I83*D83 -> 1958.85 | I83: 45
A85: 200mm PE*DI Gasket Kit Complete | B85: ea | D85: ='[3]240522_Supplier RFQ'!F96 -> 67.06 | F85: =I85*D85 -> 804.72 | G85: COMPLETED don’t edit | I85: 12
A86: 200mm DI*DI Gasket Kit Complete | B86: ea | D86: ='[3]240522_Supplier RFQ'!F97 -> 46.71 | F86: =I86*D86 -> 560.52 | I86: 12
A87: 150mm PE*DI Gasket Kit Complete | B87: ea | D87: ='[3]240522_Supplier RFQ'!F98 -> 60 | F87: =I87*D87 -> 3600 | I87: 60
A88: 150mm DI*DI Gasket Kit Complete | B88: ea | D88: ='[3]240522_Supplier RFQ'!F99 -> 42.35 | F88: =I88*D88 -> 2541 | I88: 60
A89: 100mm PE*DI Gasket Kit Complete | B89: ea | D89: ='[3]240522_Supplier RFQ'!F100 -> 24.71 | F89: =I89*D89 -> 741.3 | I89: 30
A90: 100mm DI*DI Gasket Kit Complete | B90: ea | D90: ='[3]240522_Supplier RFQ'!F101 -> 20 | F90: =I90*D90 -> 600 | G90: COMPLETED don’t edit | I90: 30
A92: 150mm SS Gibault Adapter Coupling | B92: ea | D92: ='[3]240522_Supplier RFQ'!F103 -> 108.71 | F92: =I92*D92 -> 2174.2 | I92: 20
A93: 100mm SS Gibault Adapter Coupling | B93: ea | D93: ='[3]240522_Supplier RFQ'!F104 -> 87.06 | F93: =I93*D93 -> 1218.84 | I93: 14
A94: 180mm PE GRIPPER Adapter Coupling | B94: ea | D94: ='[3]240522_Supplier RFQ'!F105 -> 305.88 | F94: =I94*D94 -> 3670.56 | I94: 12
A95: 125mm PE GRIPPER Adapter Coupling | B95: ea | D95: ='[3]240522_Supplier RFQ'!F106 -> 182.35 | F95: =I95*D95 -> 1458.8 | G95: COMPLETED don’t edit | I95: 8
A96: 180mm PE GRIPPER * 150FL Adapter Coupling | B96: ea | D96: ='[3]240522_Supplier RFQ'!F107 -> 229.41 | F96: =I96*D96 -> 917.64 | I96: 4
A97: 125mm PE GRIPPER * 100FL Adapter Coupling | B97: ea | D97: ='[3]240522_Supplier RFQ'!F108 -> 152.94 | F97: =I97*D97 -> 611.76 | I97: 4
A98: 180mm PE GRIPPER Sluice Valve | B98: ea | D98: ='[3]240522_Supplier RFQ'!F109 -> 690 | F98: =I98*D98 -> 13800 | I98: 20
A99: 125mm PE GRIPPER Sluice Valve | B99: ea | D99: ='[3]240522_Supplier RFQ'!F110 -> 408.47 | F99: =I99*D99 -> 8169.4 | I99: 20
G100: COMPLETED don’t edit
A101: Detectable Tape - Fire x 250m | B101: ea | D101: ='[3]240522_Supplier RFQ'!F112 -> 90 | F101: =I101*D101 -> 2520 | I101: 28
A102: Alcohol Weld Wipes | B102: ea | D102: ='[3]240522_Supplier RFQ'!F113 -> 13.5 | F102: =I102*D102 -> 2025 | I102: 150
A103: Denzo Tape 100mm roll | B103: ea | D103: ='[3]240522_Supplier RFQ'!F114 -> 27.14 | F103: =I103*D103 -> 4071 | I103: 150
A104: Black over-wrap tape - roll | B104: ea | D104: ='[3]240522_Supplier RFQ'!F115 -> 27.14 | F104: =I104*D104 -> 4071 | I104: 150
A106: FIRE SERVICES - ABOVE GROUND
A107: Description | B107: Unit | D107: Rate | F107: Total | G107: COMPLETED don’t edit | I107: Qty
A108: 150mm MED DUTY Galv Pipe | B108: m | D108: ='[3]240522_Supplier RFQ'!$I$120 -> 43.846154 | F108: =I108*D108 -> 3946.1538 | I108: 90
...

Sheet Equip&HIRE_Master
B2: TCS PROJECT USE | F2: COMPLETED don’t edit
A3: DESCRIPTION | B3: Unit | C3: Qty | D3: WEEKLY (5 day)
A4: Skid Steer Loader_Tracked (CAT249+) | B4: Day | D4: ='[4]Hire Items_Dry'!$M$16 -> 225.43333
A5: Skid Steer Loader_Wheeled (CAT226+) | B5: Day | D5: ='[4]Hire Items_Dry'!$M$17 -> 163.96667
A6: Mini Loader, Stand-on Type | B6: Day | D6: ='[4]Hire Items_Dry'!$J$18 -> 180
F7: COMPLETED don’t edit
A8: 1.5-1.8 Ton_Excavator | B8: Day | D8: ='[4]Hire Items_Dry'!$P$20 -> 137.14286
A9: 1.7-2Ton_Excavator | B9: Day
A10: 3-5Ton_Excavator | B10: Day | D10: ='[4]Hire Items_Dry'!$M$22 -> 238.66667
A11: 8Ton_Excavator | B11: Day | D11: ='[4]Hire Items_Dry'!$M$23 -> 261.16667
A12: 10-12Ton_Excavator | B12: Day | F12: COMPLETED don’t edit
A13: 13-16Ton_Excavator | B13: Day | D13: ='[4]Hire Items_Dry'!$M$25 -> 317.2
A14: 20-24Ton_Excavator | B14: Day | D14: ='[4]Hire Items_Dry'!$P$26 -> 314.28571
A16: Ripper_1.7-2T | B16: Day
A17: Ripper_1.5-4T | B17: Day | D17: ='[4]Hire Items_Dry'!$G$29 -> 32.74 | F17: COMPLETED don’t edit
A18: Ripper_3-5T | B18: Day
A19: Ripper_8T | B19: Day | D19: ='[4]Hire Items_Dry'!G31 -> 40.38
A20: Breaker_1.7-2T | B20: Day | D20: ='[4]Hire Items_Dry'!G32 -> 123.33
A21: Breaker_3-5T | B21: Day | D21: ='[4]Hire Items_Dry'!G33 -> 165.89
A22: Breaker_8T | B22: Day | D22: ='[4]Hire Items_Dry'!G34 -> 165.89 | F22: COMPLETED don’t edit
A23: Breaker_10-12T | B23: Day
A24: Breaker_13-15T | B24: Day | D24: ='[4]Hire Items_Dry'!G36 -> 203
A25: Auger Drive_10-12T
A26: 300Dia Auger Drill
F27: COMPLETED don’t edit
A28: 1.25T_Tipper Truck | B28: Day | D28: ='[4]Hire Items_Dry'!$J$40 -> 205
A29: 2-4T_Tipper Truck | B29: Day | D29: ='[4]Hire Items_Dry'!$G$41 -> 166.98
A30: <6T_Tipper Truck | B30: Day | D30: ='[4]Hire Items_Dry'!$P$42 -> 171.42857
A32: <10T_Articulated Site Tipper | B32: Day | F32: COMPLETED don’t edit
A33: Upright Rammer_Wacker | B33: Day | D33: ='[4]Hire Items_Dry'!$P$45 -> 34.285714
A34: Trench Roller_Dbl Drum_Remote | B34: Day | D34: ='[4]Hire Items_Dry'!$J$46 -> 165
A35: <26Ft_Scissor Lift - Diesel | B35: Day
A36: <26Ft_Scissor Lift - Elec | B36: Day
A37: <34Ft_Boom Lift - Diesel | B37: Day | F37: COMPLETED don’t edit
A38: <34Ft_Boom Lift - Elec | B38: Day
A40: Porta Loo_No Tank | B40: Day | D40: ='[4]Hire Items_Dry'!$G$52 -> 5.46
A41: 6*3m Demantable Lunchroom - COMPLETE | B41: Day | D41: ='[4]Hire Items_Dry'!$J$53 -> 23
A42: 6*3m Demantable Office - COMPLETE | B42: Day | D42: ='[4]Hire Items_Dry'!$J$54 -> 23 | F42: COMPLETED don’t edit
A43: 20Ft Shipping Container | B43: Day
A44: Quick Cut Demo Saw | B44: Day
A45: Sngl Ph_6KVA Genset | B45: Day
A46: Diesel Air Compressor_Trailer | B46: Day
A47: Air Breaker - Heavy | B47: Day | F47: COMPLETED don’t edit
A48: Air Hose <10m | B48: Day
A49: Elec Breaker/Jachammer | B49: Day
A50: Flexdrive Motor Unit | B50: Day
A51: Flexdrive_Pump Shaft | B51: Day
A52: Temporary Power Board | B52: Day | F52: COMPLETED don’t edit
A54: Dual CabUte | B54: Day
A55: 3m3 Skip Bbin | B55: per serive | D55: ='[4]Hire Items_Dry'!V67 -> 230
A56: plus disposal | B56: Tonne | D56: ='[4]Hire Items_Dry'!V68 -> 309
A57: site fee | B57: Week | D57: ='[4]Hire Items_Dry'!V69 -> 35 | F57: COMPLETED don’t edit
A58: ~4m3_Skip Bin | B58: per change over | D58: ='[4]Hire Items_Dry'!$S$70 -> 229.9
A59: ~6m3_Skip Bin | B59: per change over | D59: ='[4]Hire Items_Dry'!$S$71 -> 239.8
A60: Plus disposal | B60: Tonne | D60: ='[4]Hire Items_Dry'!$V$72 -> 309
A61: Site fee | B61: Week | D61: ='[4]Hire Items_Dry'!$V$73 -> 35
A62: Vacuum Excavator - Vermeer VT250D | B62: Day | D62: ='[4]Hire Items_Dry'!$G$74 -> 295.77 | F62: COMPLETED don’t edit
A63: Vac Trailer – Dry Hire | B63: Day | D63: ='[4]Hire Items_Dry'!$S$75 -> 355
A65: TRANSPORT_Ex BRIS - Return | B65: Day
A66: TRANSPORT_Ex ROK - Return | B66: Hour | D66: ='[4]Hire Items_Dry'!$G$78 -> 180
A67: 0-4T Per Hour Delivery Rate | B67: Hour | D67: ='[4]Hire Items_Dry'!P79 -> 125 | F67: COMPLETED don’t edit
A68: 5 - 9t Transport Hourly Rate | B68: Hour | D68: ='[4]Hire Items_Dry'!P80 -> 160
A69: 10 - 19t Low Loader Hourly rate - Minimum 2 Hour Charge | B69: Hour | D69: ='[4]Hire Items_Dry'!P81 -> 200

Sheet Misc Subbie Rates_Master
A4: DENIS - Cells highlighted GREEN are complete (By Me).
A8: PLANT HIRE - WET | D8: TCS PROJECT USE | G8: COMPLETED don’t edit
A9: DESCRIPTION | B9: Unit | D9: Hr Rate | E9: Total
A10: 1.8T Excavator | B10: Hr | D10: ='[4]Plant Hire_WET'!R16 -> 100
A11: 3-5 ton Excavator | B11: Hr | D11: ='[4]Plant Hire_WET'!R17 -> 115
A12: 3-5T Combo | B12: Hr | D12: ='[4]Plant Hire_WET'!F18 -> 154
A13: Hammer attachment 3.5-4T | B13: Hr | D13: ='[4]Plant Hire_WET'!F19 -> 21 | G13: COMPLETED don’t edit
A14: Ripper 3.5-4T | B14: Hr | D14: ='[4]Plant Hire_WET'!F20 -> 10
A15: 5t Excavator | B15: Hr | D15: ='[4]Plant Hire_WET'!O21 -> 150
A16: Hammer attachment 5T | B16: Hr | D16: ='[4]Plant Hire_WET'!O22 -> 50
A17: Skid steer | B17: Hr | D17: ='[4]Plant Hire_WET'!O23 -> 140
A18: 8T Excavator | B18: Hr | D18: ='[4]Plant Hire_WET'!F24 -> 128 | G18: COMPLETED don’t edit
A19: Hammer attachment 8T | B19: Hr | D19: ='[4]Plant Hire_WET'!F25 -> 26
A20: Ripper 8T | B20: Hr | D20: ='[4]Plant Hire_WET'!F26 -> 10
A21: 13-15T Excavator | B21: Hr | D21: ='[4]Plant Hire_WET'!F27 -> 153
A22: Hammer attachment 14T | B22: Hr | D22: ='[4]Plant Hire_WET'!F28 -> 36
A23: Ripper 14T | B23: Hr | D23: ='[4]Plant Hire_WET'!F29 -> 10 | G23: COMPLETED don’t edit
A24: 3000L Hydro Excavation Truck | B24: Hr | D24: ='[4]Plant Hire_WET'!L30 -> 190
A25: 4500L Hydro Excavation Truck | B25: Hr | D25: ='[4]Plant Hire_WET'!L31 -> 220
A26: 6300L Hydro Excavation Truck | B26: Hr | D26: ='[4]Plant Hire_WET'!L32 -> 250
A27: Water Truck allow for water at cost | B27: Hr | D27: ='[4]Plant Hire_WET'!$R$33 -> 110
A28: 12t Body Truck Tipper | B28: Hr | D28: ='[4]Plant Hire_WET'!$R$34 -> 110 | G28: COMPLETED don’t edit
A33: SURVEYOR | D33: TCS PROJECT USE | G33: COMPLETED don’t edit
A34: DESCRIPTION | B34: QTY | D34: Hr Rate? | E34: Total
A35: Site Field Surveyor for all works preformed | B35: 0 | D35: =[4]Subbies_Misc!$F$16 -> 180 | E35: =B35*D35 -> 0
B36: 0 | D36: 0 | E36: =B36*D36 -> 0
B37: 0 | D37: 0 | E37: =B37*D37 -> 0
A40: SERVICES LOCATOR | D40: TCS PROJECT USE | G40: COMPLETED don’t edit
A41: DESCRIPTION | B41: QTY | D41: Hr Rate? | E41: Total
A42: Standard Rate (includes wand, GPR) | B42: 0 | D42: =[4]Subbies_Misc!$F$25 -> 130 | E42: =B42*D42 -> 0
B43: 0 | D43: 0 | E43: =B43*D43 -> 0
B44: 0 | D44: 0 | E44: =B44*D44 -> 0
A47: CONCRETE CUTTER | D47: TCS PROJECT USE | G47: COMPLETED don’t edit
A48: DESCRIPTION | B48: QTY | D48: Lm Rate | E48: Total
A49: Asphalt Cutting | B49: 0 | D49: =[4]Subbies_Misc!$F$31 -> 13.5 | E49: =B49*D49 -> 0
A50: Concrete Cutting | B50: 0 | D50: =[4]Subbies_Misc!$F$33 -> 16 | E50: =B50*D50 -> 0
A51: Site Establishment Fee (2 per stage) | B51: 0 | D51: =[4]Subbies_Misc!$F$38 -> 80 | E51: =B51*D51 -> 0
A54: CONCRETING SERVICES | D54: TCS PROJECT USE | G54: COMPLETED don’t edit
A55: DESCRIPTION | B55: QTY | D55: Rate | E55: Total
A56: =[4]Subbies_Misc!$A$44 -> Road/Drveway Reinstate; 1mW x 150 Thck, N25/20/80, Incl Reinforcement | B56: 0 | D56: =[4]Subbies_Misc!$F$44 -> 145 | E56: =B56*D56 -> 0
A57: =[4]Subbies_Misc!$A$45 -> Kerb & Channel - 1m Wide | B57: 0 | D57: =[4]Subbies_Misc!$F$45 -> 155 | E57: =B57*D57 -> 0
A58: =[4]Subbies_Misc!$A$46 -> Footpath - 1.5mW, N25/20/80, Incl Reinforcement | B58: 0 | D58: =[4]Subbies_Misc!$F$46 -> 180 | E58: =B58*D58 -> 0
A59: =[4]Subbies_Misc!$A$47 -> Footpath - 1.5mW, EXPOSED AGG, N25/20/80, Incl Reinforcement | B59: 0 | D59: =[4]Subbies_Misc!$F$47 -> 185 | E59: =B59*D59 -> 0
A62: ASPHALT SERVICES | D62: TCS PROJECT USE | G62: COMPLETED don’t edit
A63: DESCRIPTION | B63: QTY | D63: m2 | E63: Total
A64: =[4]Subbies_Misc!$A$52 -> 50mm Thck - Trench Reinstatement Through Road/Driveway | B64: 0 | D64: =[4]Subbies_Misc!$L$52 -> 97 | E64: =B64*D64 -> 0
A65: =[4]Subbies_Misc!$A$53 -> 50mm Thck - 1.5-2m Wide Footpath reinstatements | B65: 0 | D65: =[4]Subbies_Misc!$L$53 -> 97 | E65: =B65*D65 -> 0
A66: Establishment Fee (1 per stage) | B66: 0 | D66: 5500 | E66: =B66*D66 -> 0
A70: SOIL TESTING & GEO | D70: TCS PROJECT USE | G70: COMPLETED don’t edit
A71: DESCRIPTION | B71: QTY | D71: Rate | E71: Total
A72: Compaction Testing | B72: 0 | D72: =[4]Subbies_Misc!$F$71 -> 115 | E72: =B72*D72 -> 0
A73: Site Establishment (3 per stage) | B73: 0 | D73: 90 | E73: =B73*D73 -> 0
B74: 0 | D74: =[4]Subbies_Misc!$F$55 -> 0 | E74: =B74*D74 -> 0
A78: FIRE TESTING / CERTIFICATION | D78: TCS PROJECT USE | G78: COMPLETED don’t edit
A79: DESCRIPTION | B79: QTY | D79: Rate | E79: Total
A80: Sprinkler Fitter | B80: 0 | D80: =[4]Subbies_Misc!F87 -> 130 | E80: =B80*D80 -> 0
A81: Sprinkler Apprentice | B81: 0 | D81: =[4]Subbies_Misc!F88 -> 100 | E81: =B81*D81 -> 0
A82: Hydrostatic Test Equip | B82: 0 | D82: =[4]Subbies_Misc!F89 -> 450 | E82: =B82*D82 -> 0
A83: Booster Pump Appliance | B83: 0 | D83: =[4]Subbies_Misc!F90 -> 800 | E83: =B83*D83 -> 0 | G83: COMPLETED don’t edit
A84: FULL Hydro Test - Per Test (6.5Hr 1 x fitter, 1 x apprentice, 1 day Test gear) | B84: 0 | D84: =[4]Subbies_Misc!F91 -> 1945 | E84: =B84*D84 -> 0
A85: FULL Boost Test - Per Test (8.5Hr - 2 x fitter, 1 x apprentice, 1 day Pump) | B85: 0 | D85: =[4]Subbies_Misc!F92 -> 3560 | E85: =B85*D85 -> 0
A86: Provision of Form 72 | B86: 0 | D86: =[4]Subbies_Misc!F93 -> 350 | E86: =B86*D86 -> 0
A95: Misc. Project Rates (ROCHAMPTON) - Master
B96: Unit | C96: REQ | D96: All EX GST | E96: Total EX GST
A97: Flight Costs; Qantas, 1-Way, No Check in Luggage | B97: Ea. | C97: 1 | D97: 220 | E97: =C97*D97 -> 220 | F97: Average $220 Incl GST per flight
A98: Hire Car; Budget, Airport Pick/Drop, NOT UTE, No Fuel | B98: Day | C98: 1 | D98: 190 | E98: =C98*D98 -> 190
A99: Transport (TCS Cost); Airport-Site/Accom, Cab/Staff Pickup | B99: Ea. | C99: 1 | D99: 65 | E99: =C99*D99 -> 65 | F99: Avg | G99: HD
A100: TCS Fuel; $/Km | B100: Km | C100: 1 | D100: 0.2 | E100: =C100*D100 -> 0.2 | G100: 0.16
A101: TCS Vehicle Running Costs; $/Km ($3,800/Yr, 35,000Kms/Yr) | B101: Km | C101: 1 | D101: 0.18 | E101: =C101*D101 -> 0.18 | G101: 0.11
B103: Ea. | C103: 1 | D103: 0 | E103: =C103*D103 -> 0
A104: Bris -> Rok - Courier - UTE | B104: Ea. | C104: 1 | D104: 0 | E104: =C104*D104 -> 0
A105: Bris -> Rok - Courier - Std Truck | B105: Ea. | C105: 1 | D105: 0 | E105: =C105*D105 -> 0
A106: Bris -> Rok - Courier - Flat Bed (Container/Machine) | B106: Ea. | C106: 1 | D106: 2500 | E106: =C106*D106 -> 2500

Sheet Accomodation_Master
B3: INCLUDING GST (UNLESS NOTED OTHERWISE)
B5: TCS Accomodation Rates & Costs
B6: Hotel / Motel | C6: Sngl Night | D6: Week | E6: Month | F6: Qtr
B7: 1 x Unit, 1 x Room | C7: Motel Unit | D7: Private Unit
A8: Hidden | B8: No. of persons stayng; | C8: 1
B9: Furnished | C9: YES
B10: *Serviced | C10: YES
B11: Individual/Private BATHROOM | C11: YES
B12: Individual/Private KITCHEN (Cooking) Faciliities Available - Microwave min. | C12: YES
B13: Individual/Private LAUNDRY Facilities Available | C13: YES
B14: Individual/Private LOUNGE ROOM Facilities Available | C14: YES
C16: Sngl Night | D16: Week | E16: Month | F16: Qtr
B17: Total Booking Cost | C17: =D17/7 -> 112.85714 | D17: 790 | E17: =D17*4 -> 3160 | F17: =E17*3 -> 9480
B19: TCS Housing Consumables; ….. | C19: =D19/7 -> 0 | D19: 0 | E19: =D19*4 -> 0 | F19: =E19*3 -> 0
B20: TCS Laundry Allowance..? | C20: =D20/7 -> 0 | D20: 0 | E20: =D20*4 -> 0 | F20: =E20*3 -> 0
B21: TCS Additional Meals Allowance (If no cooking Facilities?) | C21: =D21/7 -> 0 | D21: 0 | E21: =D21*4 -> 0 | F21: =E21*3 -> 0
B22: TCS Furnishings? | C22: =D22/7 -> 0 | D22: 0 | E22: =D22*4 -> 0 | F22: =E22*3 -> 0
B23: TCS Cleaning/Servincing Allowance? | C23: =D23/7 -> 0 | D23: 0 | E23: =D23*4 -> 0 | F23: =E23*3 -> 0
B25: Total TCS Cost | C25: =SUM(C17:C24) -> 112.85714 | D25: =SUM(D17:D24) -> 790 | E25: =SUM(E17:E24) -> 3160 | F25: =SUM(F17:F24) -> 9480
B26: Total Cost Per Person | C26: =D26/7 -> 112.85714 | D26: =D17/C8 -> 790 | E26: =D26*4 -> 3160 | F26: =E26*3 -> 9480
B28: 1 x Unit, 1 x Room | C28: Motel Unit | D28: Share Rooms
A29: Hidden | B29: No. of persons stayng; | C29: 2
B31: Furnished | C31: YES
B32: *Serviced | C32: YES
B33: Individual/Private BATHROOM | C33: NO | D33: Share with Unit
B34: Individual/Private KITCHEN (Cooking) Faciliities Available - Microwave min. | C34: NO | D34: Share with Unit
B35: Individual/Private LAUNDRY Facilities Available | C35: YES
B36: Individual/Private LOUNGE ROOM Facilities Available | C36: YES
C38: Sngl Night | D38: Week | E38: Month | F38: Qtr
B39: Total Booking Cost | C39: =D39/7 -> 101.42857 | D39: 710 | E39: =D39*4 -> 2840 | F39: =E39*3 -> 8520
B41: TCS Housing Consumables; ….. | C41: =D41/7 -> 0 | D41: 0 | E41: =D41*4 -> 0 | F41: =E41*3 -> 0
B42: TCS Laundry Allowance..? | C42: =D42/7 -> 0 | D42: 0 | E42: =D42*4 -> 0 | F42: =E42*3 -> 0
B43: TCS Additional Meals Allowance (If no cooking Facilities?) | C43: =D43/7 -> 0 | D43: 0 | E43: =D43*4 -> 0 | F43: =E43*3 -> 0
B44: TCS Furnishings? | C44: =D44/7 -> 0 | D44: 0 | E44: =D44*4 -> 0 | F44: =E44*3 -> 0
B45: TCS Cleaning/Servincing Allowance? | C45: =D45/7 -> 0 | D45: 0 | E45: =D45*4 -> 0 | F45: =E45*3 -> 0
B47: Total TCS Cost | C47: =SUM(C39:C46) -> 101.42857 | D47: =SUM(D39:D46) -> 710 | E47: =SUM(E39:E46) -> 2840 | F47: =SUM(F39:F46) -> 8520
B48: Total Cost Per Person | C48: =D48/7 -> 50.714286 | D48: =D39/C29 -> 355 | E48: =D48*4 -> 1420 | F48: =E48*3 -> 4260
B50: 1 x Unit, 1 x Room | C50: Motel Unit | D50: Share Rooms
A51: Hidden | B51: No. of persons stayng; | C51: 3
B53: Furnished | C53: YES
B54: *Serviced | C54: YES
B55: Individual/Private BATHROOM | C55: NO | D55: Share with Unit
B56: Individual/Private KITCHEN (Cooking) Faciliities Available - Microwave min. | C56: NO | D56: Share with Unit
B57: Individual/Private LAUNDRY Facilities Available | C57: YES
B58: Individual/Private LOUNGE ROOM Facilities Available | C58: YES
C60: Sngl Night | D60: Week | E60: Month | F60: Qtr
B61: Total Booking Cost | C61: =D61/7 -> 130.71429 | D61: 915 | E61: =D61*4 -> 3660 | F61: =E61*3 -> 10980
B63: TCS Housing Consumables; ….. | C63: =D63/7 -> 0 | D63: 0 | E63: =D63*4 -> 0 | F63: =E63*3 -> 0
B64: TCS Laundry Allowance..? | C64: =D64/7 -> 0 | D64: 0 | E64: =D64*4 -> 0 | F64: =E64*3 -> 0
B65: TCS Additional Meals Allowance (If no cooking Facilities?) | C65: =D65/7 -> 0 | D65: 0 | E65: =D65*4 -> 0 | F65: =E65*3 -> 0
B66: TCS Furnishings? | C66: =D66/7 -> 0 | D66: 0 | E66: =D66*4 -> 0 | F66: =E66*3 -> 0
B67: TCS Cleaning/Servincing Allowance? | C67: =D67/7 -> 0 | D67: 0 | E67: =D67*4 -> 0 | F67: =E67*3 -> 0
B69: Total TCS Cost | C69: =SUM(C61:C68) -> 130.71429 | D69: =SUM(D61:D68) -> 915 | E69: =SUM(E61:E68) -> 3660 | F69: =SUM(F61:F68) -> 10980
B70: Total Cost Per Person | C70: =D70/7 -> 43.571429 | D70: =D69/C51 -> 305 | E70: =D70*4 -> 1220 | F70: =E70*3 -> 3660
B72: 1 x Unit, 2 x Room | C72: Motel Unit | D72: Share House'
A73: Hidden | B73: No. of persons stayng; | C73: 2
B75: Furnished | C75: YES
B76: *Serviced | C76: YES
B77: Individual/Private BATHROOM | C77: NO | D77: Share with Unit
B78: Individual/Private KITCHEN (Cooking) Faciliities Available - Microwave min. | C78: NO | D78: Share with Unit
B79: Individual/Private LAUNDRY Facilities Available | C79: YES
B80: Individual/Private LOUNGE ROOM Facilities Available | C80: YES
C82: Sngl Night | D82: Week | E82: Month | F82: Qtr
B83: Total Booking Cost | C83: =D83/7 -> 254.28571 | D83: 1780 | E83: =D83*4 -> 7120 | F83: =E83*3 -> 21360
B85: TCS Housing Consumables; ….. | C85: =D85/7 -> 0 | D85: 0 | E85: =D85*4 -> 0 | F85: =E85*3 -> 0
B86: TCS Laundry Allowance..? | C86: =D86/7 -> 0 | D86: 0 | E86: =D86*4 -> 0 | F86: =E86*3 -> 0
B87: TCS Additional Meals Allowance (If no cooking Facilities?) | C87: =D87/7 -> 0 | D87: 0 | E87: =D87*4 -> 0 | F87: =E87*3 -> 0
B88: TCS Furnishings? | C88: =D88/7 -> 0 | D88: 0 | E88: =D88*4 -> 0 | F88: =E88*3 -> 0
B89: TCS Cleaning/Servincing Allowance? | C89: =D89/7 -> 0 | D89: 0 | E89: =D89*4 -> 0 | F89: =E89*3 -> 0
B91: Total TCS Cost | C91: =SUM(C83:C90) -> 254.28571 | D91: =SUM(D83:D90) -> 1780 | E91: =SUM(E83:E90) -> 7120 | F91: =SUM(F83:F90) -> 21360
B92: Total Cost Per Person | C92: =D92/7 -> 127.14286 | D92: =D91/C73 -> 890 | E92: =D92*4 -> 3560 | F92: =E92*3 -> 10680
B94: Full Apartment / Cabin / Villa (Tourist/Caravan Park) | C94: Sngl Night | D94: Week | E94: Month | F94: Qtr
B95: 1 x Unit, 1 x Room | C95: *CABIN | D95: Private Unit
A96: Hidden | B96: No. of persons stayng; | C96: 1
B97: Furnished | C97: YES
B98: *Serviced | C98: YES
B99: Individual/Private BATHROOM | C99: YES
B100: Individual/Private KITCHEN (Cooking) Faciliities Available - Microwave min. | C100: YES
B101: Individual/Private LAUNDRY Facilities Available | C101: YES
B102: Individual/Private LOUNGE ROOM Facilities Available | C102: YES
B103: ** Pool, BBQ, Games etc etc?
C104: Sngl Night | D104: Week | E104: Month | F104: Qtr
B105: Total Booking Cost | C105: =D105/7 -> 114.28571 | D105: 800 | E105: =D105*4 -> 3200 | F105: =E105*3 -> 9600
B107: TCS Housing Consumables; ….. | C107: =D107/7 -> 0 | D107: 0 | E107: =D107*4 -> 0 | F107: =E107*3 -> 0
B108: TCS Laundry Allowance..? | C108: =D108/7 -> 0 | D108: 0 | E108: =D108*4 -> 0 | F108: =E108*3 -> 0
B109: TCS Additional Meals Allowance (If no cooking Facilities?) | C109: =D109/7 -> 0 | D109: 0 | E109: =D109*4 -> 0 | F109: =E109*3 -> 0
B110: TCS Furnishings? | C110: =D110/7 -> 0 | D110: 0 | E110: =D110*4 -> 0 | F110: =E110*3 -> 0
B111: TCS Cleaning/Servincing Allowance? | C111: =D111/7 -> 0 | D111: 0 | E111: =D111*4 -> 0 | F111: =E111*3 -> 0
B113: Total TCS Cost | C113: =SUM(C105:C112) -> 114.28571 | D113: =SUM(D105:D112) -> 800 | E113: =SUM(E105:E112) -> 3200 | F113: =SUM(F105:F112) -> 9600
B114: Total Cost Per Person | C114: =D114/7 -> 114.28571 | D114: =D113/C96 -> 800 | E114: =D114*4 -> 3200 | F114: =E114*3 -> 9600
A116: Hidden | B116: 1 x Unit, 1 x Room | C116: *UNIT/VILLA | D116: Share Rooms
B117: No. of persons stayng; | C117: 2
B118: Furnished | C118: YES
B119: *Serviced | C119: YES
B120: Individual/Private BATHROOM | C120: NO | D120: Share with Unit
B121: Individual/Private KITCHEN (Cooking) Faciliities Available - Microwave min. | C121: NO | D121: Share with Unit
B122: Individual/Private LAUNDRY Facilities Available | C122: YES
B123: Individual/Private LOUNGE ROOM Facilities Available | C123: YES
B124: ** Pool, BBQ, Games etc etc?
C125: Sngl Night | D125: Week | E125: Month | F125: Qtr
...
