Workbook
Name aa: #REF!
Name aa: #REF!
Name aa: #REF!
Name aa: #REF!
Name aa: #REF!
Name aa: #REF!
Name aa: #REF!
Name aa: #REF!
Name bh: [1]Preliminaries!$J$1
Name bh: [1]Preliminaries!$J$1
Name bh: #REF!
Name Civil4: #REF!
Name Civil4: #REF!
Name Civil4: #REF!
Name Civil4: #REF!
Name Civil4: #REF!
Name Civil4: #REF!
Name Civil4: #REF!
Name d: #REF!
Name d: #REF!
Name d: #REF!
Name d: #REF!
Name d: #REF!
Name d: #REF!
Name d: #REF!
Name date: #REF!
Name date: #REF!
Name date: #REF!
Name date: #REF!
Name date: #REF!
Name date: #REF!
Name date: #REF!
Name date: #REF!
Name daz: #REF!
Name daz: #REF!
Name daz: #REF!
Name daz: #REF!
Name ddd: #REF!
Name ddd: #REF!
Name ddd: #REF!
Name ddd: #REF!
Name for: #REF!
Name for: #REF!
Name for: #REF!
Name for: #REF!
Name for: #REF!
Name job: #REF!
Name job: #REF!
Name job: #REF!
Name job: #REF!
Name job: #REF!
Name No: #REF!
Name No: #REF!
Name No: #REF!
Name No: #REF!
Name No: #REF!
Name qqq: #REF!
Name qqq: #REF!
Name qqq: #REF!
Name qqq: #REF!

Sheet V1
B6: SUMMARY | V6: WSUD FILTRATION SYSTEM
V7: Cost | W7: 88838 | Y7: Cost | Z7: 0
B8: JOB DESCRIPTION: | G8: Rockhampton Sport Precinct | K8: 46219 | V8: Markup | W8: 0.15 | Y8: Markup | Z8: 0.1
B9: SITE ADDRESS: | G9: 554-700 YAAMBA ROAD, NORMAN GARDEN | K9: TCS Quote #: 2372 | V9: Charge = | W9: =W7+(W7*W8) -> 102163.7 | Y9: Charge = | Z9: =Z7+(Z7*Z8) -> 0
R10: Cost | S10: (Cost + O/H) + Profit | V10: install estimate | W10: 6000
K11: TOTALS | V11: fuel levy estimate | W11: 2500
W12: =W9+W10+W11 -> 110663.7
B13: PART A | F13: Stormwater Drainage | K13: =S13+W12 -> 890849.95 | R13: ='SW Zone Sumry'!F70 -> 535364.2 | S13: =((R13/$R$26)*($R$36-$R$26))+R13 -> 780186.25
F15: Supply of
C24: .
J26: TOTAL ex GST | K26: =SUM(K13:K22) -> 890849.95 | R26: =SUM(R13:R18) -> 535364.2 | S26: =SUM(S13:S18) -> 780186.25
T28: Manual Calc
P29: Prelim | Q29: 0.055 | R29: =R26*Q29 -> 29445.031 | S29: of total cost | T29: ='Prelim_OH-Check'!F42 -> 0
P30: O/H | Q30: 0.18 | R30: =R26*Q30 -> 96365.556 | S30: of total cost | T30: ='Prelim_OH-Check'!F47 -> 0
P32: Sub Total | R32: =SUM(R26:R31) -> 661174.78 | S32: total cost + Prelim + O/H
P35: Gross Profit | Q35: 0.18 | R35: =R32*Q35 -> 119011.46 | S35: Exl equip & Fixt
P36: Grand Total | R36: =SUM(R32:R35) -> 780186.25
P38: Total Markup | Q38: =SUM(Q29:Q37) -> 0.415
P40: Net Profit Incl Equip | R40: =R35 -> 119011.46

Sheet Prelim_OH-Check
B1: Project:
B2: Tricore -
B3: Stage 1 Version 1
A4: Item
A7: A | B7: PRELIMINARIES
C8: Unit | D8: REQ | E8: Cost ex GST | F8: Total ex GST
B9: Labour
F10: 0
B11: Contingencies; Wet Weather ?
B13: TRADESMAN_LEADING HAND | C13: Day | D13: 0 | E13: ='Staff Rates'!E17 -> 822.5 | F13: =D13*E13 -> 0
B14: TRADESMAN_PLUMBER_OPERATOR | C14: Day | D14: 0 | E14: 400 | F14: =D14*E14 -> 0
B15: T/A & Apprentice | C15: Day | D15: 0 | E15: 597.62762 | F15: =D15*E15 -> 0
B16: Crew #1 | C16: Day | D16: 0 | E16: 1895.3002 | F16: =D16*E16 -> 0
B17: Crew #2 | C17: Day | D17: 0 | E17: 1511.9133 | F17: 0
B19: Equipment, Hire, Subbies
B21: Dual CabUte | C21: item | D21: 0 | E21: 0 | F21: =D21*E21 -> 0
B22: 10m3_Skip Bin | C22: item | D22: 0 | E22: 0 | F22: =D22*E22 -> 0
B23: TCS Container; Ecl Freight | C23: item | D23: 0 | E23: 0 | F23: =D23*E23 -> 0
B24: Fencing | C24: item | D24: 0 | E24: 0 | F24: =D24*E24 -> 0
C25: item | D25: 0 | E25: 0 | F25: =D25*E25 -> 0
B27: Misc.
B29: Site Admin, Stationary etc - GREENSTAR ADMINS | C29: item | D29: 0 | E29: 1600 | F29: =D29*E29 -> 0
B30: Site PPE | C30: item | D30: 0 | E30: 400 | F30: =D30*E30 -> 0
B31: Site Consumables- Paint, Tapes etc | C31: item | D31: 0 | E31: 180 | F31: =D31*E31 -> 0
B32: Site Management - Bollards, Pickets, Barrier Mesh etc | C32: item | D32: 0 | E32: 400 | F32: =D32*E32 -> 0
B33: Staff Refreshments - ONSITE | C33: item | D33: 0 | E33: 50 | F33: =D33*E33 -> 0
B34: Staff Refreshments - Offsite | C34: item | D34: 0 | E34: 50 | F34: =D34*E34 -> 0
B35: TOOLS - Roll Grover - S&M | C35: item | D35: 0 | E35: 320 | F35: =D35*E35 -> 0
B36: TOOLS - Poly Welder - S&M | C36: item | D36: 0 | E36: 320 | F36: =D36*E36 -> 0
B37: TOOLS - Wacker/Laser/Misc - S&M | C37: item | D37: 0 | E37: 580 | F37: =D37*E37 -> 0
B38: TOOLS - Demo Saw Trolley - PURCHASE | C38: item | D38: 0 | E38: 0 | F38: =D38*E38 -> 0
B39: TOOLS - Consumabls - Blades, etc | C39: item | D39: 0 | E39: 420 | F39: =D39*E39 -> 0
E42: Total TCS Prelims | F42: =SUM(F11:F41) -> 0
A45: A | B45: OverHeads
C46: Unit | D46: REQ | E46: Cost ex GST | F46: Total ex GST
B47: TriCore Overheads - COMPLETE…PER MONTH | C47: item | D47: 0 | E47: 20000 | F47: =D47*E47 -> 0
C48: item | D48: 0 | E48: 0 | F48: 0
C49: item | D49: 0 | E49: 0 | F49: 0
E53: Total TCS O/H | F53: =SUM(F47:F52) -> 0

Sheet SW Zone Sumry
B1: Project:
B2: Tricore -
B3: Stage 1 Version 1
A4: Item
A8: B | B8: Labour
H9: TOTAL Labour
B10: From Proposed Program
H11: =SUM(F13:F19) -> 0
B12: DAY
B13: TRADESMAN_LEADING HAND | C13: Day | E13: ='Staff Rates'!E17 -> 822.5 | F13: =E13*D13 -> 0
B14: CREW - Fire & WAT | C14: Day | E14: ='Staff Rates'!E24 -> 2152.5 | F14: =E14*D14 -> 0
B15: CREW - Drainage | C15: Day | E15: ='Staff Rates'!E24 -> 2152.5 | F15: =E15*D15 -> 0
B16: CREW #3 | C16: Day | E16: ='Staff Rates'!E31 -> 2152.5 | F16: =E16*D16 -> 0
B17: T/A & Apprentice | C17: Day | E17: ='Staff Rates'!E52 -> 612.5 | F17: =E17*D17 -> 0
B18: TRADESMAN.1 | C18: Day | E18: ='Staff Rates'!E45 -> 770 | F18: =E18*D18 -> 0
B19: TRADESMAN.2 | C19: Day | E19: ='Staff Rates'!E45 -> 770 | F19: =E19*D19 -> 0
B21: HOUR
B22: TRADESMAN_LEADING HAND | C22: HR | E22: 0 | F22: =E22*D22 -> 0
B23: TRADESMAN_PLUMBER_OPERATOR | C23: HR | E23: 0 | F23: =E23*D23 -> 0
B24: T/A & Apprentice | C24: HR | E24: 0 | F24: =E24*D24 -> 0
B25: Crew #1 | C25: HR | E25: 0 | F25: =E25*D25 -> 0
B26: Crew #2 | C26: HR | E26: 0 | F26: =E26*D26 -> 0
A28: C | B28: Equipment, Hire, Subbies | H28: TOTAL Equip
B30: Skid Steer Loader_Wheeled | C30: ea | E30: 300 | F30: =E30*D30 -> 0 | H30: =SUM(F30:F39) -> 0
B31: Skid Steer Loader_Wheeled | C31: ea | E31: 300 | F31: =E31*D31 -> 0
B32: 8Ton_Excavator | C32: ea | E32: 300 | F32: =E32*D32 -> 0
B33: 20-24Ton_Excavator | C33: ea | E33: 450 | F33: =E33*D33 -> 0
B34: 14-16Ton_Excavator | C34: ea | E34: 440 | F34: =E34*D34 -> 0
B35: 6-12T_Tipper Truck | C35: ea | E35: 400 | F35: =E35*D35 -> 0
B36: <10T_Articulated Site Tipper | C36: ea | E36: 341 | F36: =E36*D36 -> 0
B37: Trench Roller_Dbl Drum_Remote | C37: ea | E37: 180 | F37: =E37*D37 -> 0
B38: Trench Roller_Dbl Drum_Remote | C38: ea | E38: 180 | F38: =E38*D38 -> 0
B39: <26Ft_Scissor Lift - Diesel | C39: ea | E39: 150 | F39: =E39*D39 -> 0
B40: Compaction Testing | C40: ea | E40: 122 | F40: =E40*D40 -> 0
B41: CCTV | C41: ea | E41: 1680 | F41: =E41*D41 -> 0
B42: Misc Hire/Tooling | C42: ea | E42: 1680 | F42: =E42*D42 -> 0
... B48: Humesceptor Crane Hire | C48: ea | E48: 2677 | F48: =E48*D48 -> 0
B50: Fuel - Diesel_Machinery & Equip/WEEK (Average) | C50: ea | D50: 0 | E50: 2500 | F50: =E50*D50 -> 0
E51: **Mini tankers Avg 6,000/Mnth
A53: D | B53: Material
B55: Material; | C55: ea | D55: 1 | E55: =SW_Mataterial!F302 -> 502184.98 | F55: =E55*D55 -> 502184.98
B56: Inground Quarry Products; Complete | C56: ea | D56: 1 | E56: =SW_Mataterial!N343 -> 33179.213 | F56: =E56*D56 -> 33179.213
B57: MANHOLE Concrete | C57: ea | D57: 1 | E57: =SW_Mataterial!H337 -> 0 | F57: =E57*D57 -> 0
B58: FILTER Install Inc Gravels & Crane | C58: ea | D58: 0 | E58: 2120 | F58: =E58*D58 -> 0
B59: Lean mix stab sand etc - ROADS | C59: ea | D59: 0 | E59: 1650 | F59: =E59*D59 -> 0
A62: E | B62: Misc
C64: M3 | D64: 0 | E64: 0 | F64: =E64*D64 -> 0
B70: Total Taken forward to Summary | E70: Total | F70: =SUM(F12:F69) -> 535364.2

Sheet SW_Mataterial
B2: SECTION A
B3: STORMWATER DRAINAGE
B4: Description | C4: Qty | D4: Unit | E4: Rate | F4: Total
B6: rcp/frc
B7: PIPE 675MM - RCP_C3 | D7: m | E7: 270 | F7: =C7*E7 -> 0
B8: PIPE 600MM - RCP_C4 | D8: m | E8: =13169/60 -> 219.48333 | F8: =C8*E8 -> 0
B9: allow for 600 rubber ring | C9: 1 | D9: ea | E9: 24 | F9: =C9*E9 -> 24
B10: PIPE 600MM - RCP_C3 | C10: 5 | D10: m | E10: =896/5 -> 179.2 | F10: =C10*E10 -> 896
B11: PIPE 525MM - RCP_C4 | D11: m | E11: 187 | F11: =C11*E11 -> 0
B12: PIPE 525MM - RCP_C3 | D12: m | E12: 140.91 | F12: =C12*E12 -> 0
B13: PIPE 450MM - RCP_C4 | D13: m | E13: =7072.78/53 -> 133.44868 | F13: =C13*E13 -> 0
B14: allow for 450 rubber ring | D14: ea | E14: 14.68 | F14: =C14*E14 -> 0
B15: PIPE 375MM - RCP_C4 | C15: =31+696 -> 727 | D15: m | E15: =76604/727 -> 105.37001 | F15: =C15*E15 -> 76604
B16: allow for 375 rubber ring | C16: 1 | D16: ea | E16: 1435.2 | F16: =C16*E16 -> 1435.2
B17: PIPE 375MM - RCP_C3 | D17: m | E17: 87.11 | F17: =C17*E17 -> 0
B18: PIPE 375MM - RCP_C2 | D18: m | E18: 87.11 | F18: =C18*E18 -> 0
B19: SW_SN8 RIBBED (Blackmax or similar) | D19: m
B21: PIPE Ribbed RRJ 1050MM | D21: m | E21: =46246/111 -> 416.63063 | F21: =C21*E21 -> 0
B22: PIPE Ribbed RRJ 900MM | D22: m | E22: =39160/127 -> 308.34646 | F22: =C22*E22 -> 0
B23: PIPE Ribbed RRJ 825MM | D23: m | F23: =C23*E23 -> 0
B24: PIPE Ribbed RRJ 750MM | D24: m | E24: =21376/96 -> 222.66667 | F24: =C24*E24 -> 0
B25: PIPE Ribbed RRJ 675MM | D25: m | E25: 232 | F25: =C25*E25 -> 0
B26: PIPE Ribbed RRJ 600MM | C26: 39 | D26: m | E26: =5803/39 -> 148.79487 | F26: =C26*E26 -> 5803
B27: PIPE Ribbed RRJ 525MM | D27: m | E27: =9366/81 -> 115.62963 | F27: =C27*E27 -> 0
B28: PIPE Ribbed RRJ 450MM | C28: 42 | D28: m | E28: =3724/42 -> 88.666667 | F28: =C28*E28 -> 3724
B29: PIPE Ribbed RRJ 375MM | C29: 211 | D29: m | E29: =12708/211 -> 60.227488 | F29: =C29*E29 -> 12708
B30: PIPE Ribbed RRJ 300MM | C30: 59 | D30: m | E30: =2350/59 -> 39.830508 | F30: =C30*E30 -> 2350
B31: PIPE Ribbed RRJ 225MM | C31: 138 | D31: m | E31: =3473/138 -> 25.166667 | F31: =C31*E31 -> 3473
B32: PIPE Ribbed RRJ 150MM | D32: m | E32: 9.72 | F32: =C32*E32 -> 0
B33: Jointing Lubricant 1 liter | C33: 10 | D33: ea | E33: 17 | F33: =C33*E33 -> 170
B35: SW_SN8 PVC Pipeline
B36: PIPE DWV SN8 PVC S/WELD 375MM | D36: m | E36: 96.33 | F36: =C36*E36 -> 0
B37: PIPE DWV SN4 PVC S/WELD 300MM | D37: m | E37: 49.833333 | F37: =C37*E37 -> 0
B38: PIPE SW H/D PVC S/WELD 300MM | D38: m | E38: 40 | F38: =C38*E38 -> 0
B39: PIPE DWV SN8 PVC S/WELD 225MM | C39: 181 | D39: m | E39: =12816/181 -> 70.80663 | F39: =C39*E39 -> 12816
B40: PIPE DWV SN4 PVC S/WELD 225MM | D40: m | E40: 31 | F40: =C40*E40 -> 0
B41: 50mm PVC Class 12 | D41: m | E41: 18 | F41: =C41*E41 -> 0
B42: PIPE DWV SN8 PVC S/WELD 150MM | C42: 63 | D42: m | E42: 25.5 | F42: =C42*E42 -> 1606.5
B43: PIPE DWV SN4 PVC S/WELD 150MM | D43: m | E43: 11.666667 | F43: =C43*E43 -> 0
B44: PIPE DWV SN4 PVC S/WELD 100MM | C44: 284 | D44: m | E44: 15 | F44: =C44*E44 -> 4260
B45: SW Grade Option
B46: 300MM * 45D PVC SW JUNCTION | D46: ea | E46: 159 | F46: =C46*E46 -> 0
B47: 300X225X45D PVC SW JUNCTION | D47: ea | E47: 141.5 | F47: =C47*E47 -> 0
B48: 300MM X 225MM SW Reducer | D48: ea | E48: 45 | F48: =C48*E48 -> 0
B49: 300MM X 90Deg SW Bend (stud) | D49: ea | E49: 49 | F49: =C49*E49 -> 0
B50: 300MM X 45Deg SW Bend | D50: ea | E50: 44 | F50: =C50*E50 -> 0
B51: 225MM * 45D PVC SW JUNCTION | C51: 1 | D51: ea | E51: 60.1 | F51: =C51*E51 -> 60.1
B52: 225X150X45D PVC SW JUNCTION | D52: ea | E52: 37 | F52: =C52*E52 -> 0
B53: 225X100X45D PVC SW JUNCTION | C53: 11 | D53: ea | E53: 38.55 | F53: =C53*E53 -> 424.05
B54: 225MM X 90Deg SW Bend | C54: 1 | D54: ea | E54: 23.5 | F54: =C54*E54 -> 23.5
B55: 225MM X 45Deg SW Bend | D55: ea | E55: 15 | F55: =C55*E55 -> 0
B56: 150 PVC SW 45Deg Junct | D56: ea | E56: 12.5 | F56: =C56*E56 -> 0
B57: 150MM X 90Deg SW Bend | D57: ea | E57: 5.5 | F57: =C57*E57 -> 0
B58: 150MM X 45Deg SW Bend | D58: ea | E58: 5.5 | F58: =C58*E58 -> 0
B59: 100X45D PVC JUNCTION | C59: 26 | D59: ea | E59: 10 | F59: =C59*E59 -> 260
B60: 100MM X 90Deg Bend | C60: 17 | D60: ea | E60: 3.5 | F60: =C60*E60 -> 59.5
B61: 100MM X 45Deg Bend | C61: 9 | D61: ea | E61: 3.5 | F61: =C61*E61 -> 31.5
B63: Material for INSPECTION OPENING WITH GALVANISED COVER FLUSH WITH SURFACE | C63: 3 | D63: ea | E63: 150 | F63: =C63*E63 -> 450
B65: Pipe to Pipe /Culvert Connection ) price guess using Google AI
B66: PIPE TO PIPE CONNECTION ( 225 HDPE , 150 PVC ) | C66: 4 | D66: ea | E66: 150 | F66: =C66*E66 -> 600
B67: PIPE TO PIPE CONNECTION ( 300 HDPE , 150 PVC ) | C67: 1 | D67: ea | E67: 350 | F67: =C67*E67 -> 350
B68: PIPE TO PIPE CONNECTION ( 375 HDPE , 150 PVC ) | C68: 9 | D68: ea | E68: 310 | F68: =C68*E68 -> 2790
B69: PIPE TO PIPE CONNECTION ( 450 HDPE , 150 PVC ) | C69: 2 | D69: ea | E69: 400 | F69: =C69*E69 -> 800
B70: PIPE TO PIPE CONNECTION ( 600 HDPE , 150 PVC ) | C70: 1 | D70: ea | E70: 600 | F70: =C70*E70 -> 600
B71: PIPE TO PIPE CONNECTION ( 375 RPC , 100 PVC ) | C71: 1 | D71: ea | E71: 260 | F71: =C71*E71 -> 260
B72: PIPE TO CULVERT CONNECTION ( 375MM RCP /RCBC 1500 X600) | C72: 1 | D72: ea | E72: 200 | F72: =C72*E72 -> 200
B75: DWV Grade Option
B77: 600*225 Ribbed Saddle | D77: ea | E77: 490 | F77: =C77*E77 -> 0
B78: 600*45Deg RIBBED Bend | D78: ea | E78: 650 | F78: =C78*E78 -> 0
B79: 600*450 Ribbed Reducer | D79: ea | E79: 1100 | F79: =C79*E79 -> 0
B80: 450*375 Ribbed*PVC Reducer | D80: ea | E80: 460 | F80: =C80*E80 -> 0
B81: 450 45 Deg ribbed Bend | D81: ea | E81: 580 | F81: =C81*E81 -> 0
B82: 450 * 225 Ribbed Saddle | D82: ea | E82: 320 | F82: =C82*E82 -> 0
B83: 375mm X 45Deg Junction | D83: ea | E83: 420 | F83: =C83*E83 -> 0
B84: 375X300X45D PVC JUNCTION | D84: ea | E84: 562.39 | F84: =C84*E84 -> 0
B85: 375X225X45D PVC JUNCTION | D85: ea | E85: 563.39 | F85: =C85*E85 -> 0
B86: 375MM X 300MM Reducer | D86: ea | E86: 380 | F86: =C86*E86 -> 0
B87: 375MM X 225MM Reducer | D87: ea | E87: 360 | F87: =C87*E87 -> 0
B88: 375MM X 90Deg Bend | D88: ea | E88: 540 | F88: =C88*E88 -> 0
... B94: 300MM X 45Deg Bend | D94: ea | E94: 190 | F94: =C94*E94 -> 0
B95: 300MM X 150 Junction
B96: 225MM * 45D PVC JUNCTION | D96: ea | E96: 85.25 | F96: =C96*E96 -> 0
B97: 225X150X45D PVC JUNCTION | D97: ea | E97: 210 | F97: =C97*E97 -> 0
B98: 225MM X 90Deg Bend | D98: ea | E98: 62 | F98: =C98*E98 -> 0
B99: 225MM X 45Deg Bend | D99: ea | E99: 61 | F99: =C99*E99 -> 0
B100: 225MM X 150MM Reducer | D100: ea | E100: 120 | F100: =C100*E100 -> 0
B101: 150MM X 100MM Reducer | D101: ea | E101: 85 | F101: =C101*E101 -> 0
B102: 150 PVC DWV 45Deg Junct | D102: ea | E102: 18 | F102: =C102*E102 -> 0
B103: 150MM X 90Deg Bend | D103: ea | E103: 16 | F103: =C103*E103 -> 0
B104: 150MM X 45Deg Bend | D104: ea | E104: 12 | F104: =C104*E104 -> 0
B105: 150X100X45D PVC JUNCTION | D105: ea | E105: 16 | F105: =C105*E105 -> 0
B106: 100X45D PVC JUNCTION | D106: ea | E106: 13 | F106: =C106*E106 -> 0
B107: 100MM X 90Deg Bend | D107: ea | E107: 12 | F107: =C107*E107 -> 0
... B113: 600*600 pits | D113: ea | E113: 990 | F113: =C113*E113 -> 0
B115: SW_Gully/Pit
B116: Concrete/GRC - Class D - 450SQ Pit w/base - 450H | D116: ea
B117: Concrete/GRC - Class D - 450SQ Pit w/base - 600H | D117: ea
B118: Concrete/GRC - Class D - 450SQ Riser - 300H | D118: ea
B119: Concrete/GRC - Class D - 450SQ Riser - 450H | D119: ea
B120: Concrete/GRC - Class D - 450SQ Riser - 600H | D120: ea
...

Sheet SW_Pit Takeoff
C1: 44918
G2: Total Qty
C3: 600 Grte/frm Height | E3: 0.055
C4: 600*900 Grte/frm Height | E4: 0.08
C5: 1.2*1.2 Grte/frm Height | E5: 0.14
C6: 1200*9*6 ASPRO Height | E6: 0.175
C7: 600 infl Height | E7: 0.055
C8: 600 V Grate Height | E8: 0.15
C9: 600 Pit Base Height | E9: 0.6
C10: 600 Pit Riser Height | E10: 0.15
C11: 600 Pit Riser Height | E11: 0.3
C12: 600 Pit Riser Height | E12: 0.6
C13: 600 Pit Riser Height | E13: 0.9
C14: 900*900 Pit Base Height | E14: 0.9
... C18: 600*900 Pit Riser Height | E18: 0.9
C19: 1050 Chmbr Base Height | E19: 1.2 | F19: 1200
C20: 1050 Chmbr Riser Height | E20: 0.15
C21: 1050 Chmbr Riser Height | E21: 0.3
C22: 1050 Chmbr Riser Height | E22: 0.6
C23: 1050 Chmbr Riser Height | E23: 0.9
C24: 1050 Chmbr Riser Height | E24: 1.2
D25: 1200*1200*200 | E25: 0.2 | AG25: 0.2for1.2
O26: Manual calc | AD26: V3 | AG26: Manual calc | AV26: V3 | AX26: Manual calc
C27: Pit Count | D27: PIT No. | E27: Grate RL | F27: Type | G27: Grate Size | H27: Chamber | I27: Outlet IL | J27: Depth | M27: Riser Height Req. w/ base | O27: 0.15 Riser | P27: 0.3 Riser | Q27: 0.6 Riser | R27: 0.9 Riser | T27: Pit riser difference | V27: Pit Count | W27: PIT No. | X27: Grate RL | Y27: Type | Z27: Grate Size | AA27: Chamber | AB27: Outlet IL | AC27: Depth | AE27: Riser Height Req. w/base | AG27: 0.15 Riser | AH27: 0.3 Riser | AI27: 0.6 Riser | AJ27: 0.9 Riser | AK27: Pit riser difference | AM27: Pit Count | AN27: PIT No. | AO27: Grate RL | AP27: Type | AQ27: Grate Size | AR27: Chamber | AS27: Outlet IL | AT27: Depth | AW27: Riser Height Req. w/ base | AX27: 0.15 Riser | AY27: 0.3 Riser | AZ27: 0.6 Riser | BA27: 0.9 Riser | BB27: Pit riser difference
J28: =E28-I28 -> 0 | M28: =J28-$E$14-$E$4 -> -0.98 | T28: =M28-(O28*$E$10)-(P28*$E$11)-(Q28*$E$12)-(R28*$E$13) -> -0.98 | V28: 21 | AC28: 0.89 | AD28: 1 | AE28: =AC28-$E$3-$E$9 -> 0.235 | AK28: =AE28-(AG28*$E$25)-(AH28*$E$11)-(AI28*$E$12)-(AJ28*$E$13) -> 0.235 | AM28: 40 | AN28: 46 | AT28: 1.41 | AV28: =AT28-$E$9-$E$8 -> 0.66 | AW28: =AT28-$E$5-$E$19 -> 0.07 | BB28: =AW28-(AX28*$E$25)-(AY28*$E$11)-(AZ28*$E$12)-(BA28*$E$13) -> 0.07
J29: =E29-I29 -> 0 | M29: =J29-$E$14-$E$4 -> -0.98 | T29: =M29-(O29*$E$10)-(P29*$E$11)-(Q29*$E$12)-(R29*$E$13) -> -0.98 | V29: 22 | AC29: 0.94 | AD29: =Y29-AC29 -> -0.94 | AE29: =AC29-0.045-$E$14 -> -0.005 | AK29: =AE29-(AG29*$E$10)-(AH29*$E$11)-(AI29*$E$12)-(AJ29*$E$13) -> -0.005 | AM29: 42 | AN29: 47 | AT29: 1.68 | AV29: =AT29-$E$9-$E$8 -> 0.93 | AW29: =AT29-$E$5-$E$19 -> 0.34 | BB29: =AW29-(AX29*$E$10)-(AY29*$E$11)-(AZ29*$E$12)-(BA29*$E$13) -> 0.34
J30: =E30-I30 -> 0 | M30: =J30-$E$4-$E$6-$E$19 -> -1.455 | T30: =M30-(O30*$E$10)-(P30*$E$11)-(Q30*$E$12)-(R30*$E$13) -> -1.455 | V30: 23 | AC30: 0.91 | AE30: =AC30-$E$4-$E$14 -> -0.07 | AK30: =AE30-(AG30*$E$10)-(AH30*$E$11)-(AI30*$E$12)-(AJ30*$E$13) -> -0.07 | AM30: 43 | AT30: =AO30-AS30 -> 0 | AV30: =AT30-$E$9-$E$8 -> -0.75 | AW30: =AT30-$E$4-$E$14 -> -0.98 | BB30: =AW30-(AX30*$E$10)-(AY30*$E$11)-(AZ30*$E$12)-(BA30*$E$13) -> -0.98
J31: =E31-I31 -> 0 | M31: =J31-$E$4-$E$6-$E$19 -> -1.455 | T31: =M31-(O31*$E$25)-(P31*$E$11)-(Q31*$E$12)-(R31*$E$13) -> -1.455 | V31: 24 | AC31: 0.92 | AD31: 2.1 | AE31: =AC31-$E$4-$E$14 -> -0.06 | AK31: =AE31-(AG31*$E$10)-(AH31*$E$11)-(AI31*$E$12)-(AJ31*$E$13) -> -0.06 | AM31: 44 | AT31: =AO31-AS31 -> 0 | AV31: =AT31-$E$9-$E$8 -> -0.75 | AW31: =AT31-$E$4-$E$14 -> -0.98 | BB31: =AW31-(AX31*$E$10)-(AY31*$E$11)-(AZ31*$E$12)-(BA31*$E$13) -> -0.98
J32: =E32-I32 -> 0 | M32: =J32-$E$4-$E$6-$E$19 -> -1.455 | T32: =M32-(O32*$E$25)-(P32*$E$11)-(Q32*$E$12)-(R32*$E$13) -> -1.455 | V32: 25 | AC32: 1.01 | AD32: 0.86 | AE32: =AC32-$E$4-$E$14 -> 0.03 | AK32: =AE32-(AG32*$E$25)-(AH32*$E$11)-(AI32*$E$12)-(AJ32*$E$13) -> 0.03 | AM32: 45 | AV32: =AT32-$E$9-$E$8 -> -0.75
J33: =E33-I33 -> 0 | M33: =J33-$E$4-$E$6-$E$19 -> -1.455 | T33: =M33-(O33*$E$10)-(P33*$E$11)-(Q33*$E$12)-(R33*$E$13) -> -1.455 | V33: 26 | AC33: 0.9 | AD33: 2.26 | AE33: =AC33-$E$4-$E$14 -> -0.08 | AK33: =AE33-(AG33*$E$25)-(AH33*$E$11)-(AI33*$E$12)-(AJ33*$E$13) -> -0.08 | AM33: 46 | AV33: =AT33-$E$9-$E$8 -> -0.75
J34: =E34-I34 -> 0 | M34: =J34-$E$4-$E$14 -> -0.98 | T34: =M34-(O34*$E$10)-(P34*$E$11)-(Q34*$E$12)-(R34*$E$13) -> -0.98 | V34: 27 | AC34: 1.05 | AD34: 1.96 | AE34: =AC34-$E$4-$E$14 -> 0.07 | AK34: =AE34-(AG34*$E$25)-(AH34*$E$11)-(AI34*$E$12)-(AJ34*$E$13) -> 0.07 | AM34: 47 | AV34: =AT34-$E$9-$E$8 -> -0.75
J35: =E35-I35 -> 0 | M35: =J35-$E$4-$E$14 -> -0.98 | T35: =M35-(O35*$E$25)-(P35*$E$11)-(Q35*$E$12)-(R35*$E$13) -> -0.98 | V35: 28 | AC35: 1.62 | AD35: 2.1 | AE35: =AC35-$E$4-$E$14 -> 0.64 | AK35: =AE35-(AG35*$E$25)-(AH35*$E$11)-(AI35*$E$12)-(AJ35*$E$13) -> 0.64 | AM35: 48 | AV35: =AT35-$E$9-$E$8 -> -0.75
J36: =E36-I36 -> 0 | M36: =J36-$E$4-$E$14 -> -0.98 | T36: =M36-(O36*$E$25)-(P36*$E$11)-(Q36*$E$12)-(R36*$E$13) -> -0.98 | V36: 29 | AC36: 0.86 | AD36: 2.1 | AE36: =AC36-$E$4-$E$14 -> -0.12 | AK36: =AE36-(AG36*$E$25)-(AH36*$E$11)-(AI36*$E$12)-(AJ36*$E$13) -> -0.12
J37: =E37-I37 -> 0 | M37: =J37-$E$4-$E$14 -> -0.98 | T37: =M37-(O37*$E$25)-(P37*$E$11)-(Q37*$E$12)-(R37*$E$13) -> -0.98 | V37: 30 | AC37: 0.86 | AD37: 2.1 | AE37: =AC37-$E$4-$E$14 -> -0.12 | AK37: =AE37-(AG37*$E$25)-(AH37*$E$11)-(AI37*$E$12)-(AJ37*$E$13) -> -0.12
J38: =E38-I38 -> 0 | M38: =J38-$E$4-$E$14 -> -0.98 | T38: =M38-(O38*$E$10)-(P38*$E$11)-(Q38*$E$12)-(R38*$E$13) -> -0.98 | V38: 31 | AC38: 0.95 | AD38: 2.1 | AE38: =AC38-$E$4-$E$14 -> -0.03 | AK38: =AE38-(AG38*$E$25)-(AH38*$E$11)-(AI38*$E$12)-(AJ38*$E$13) -> -0.03
J39: =E39-I39 -> 0 | M39: =J39-$E$4-$E$6-$E$19 -> -1.455 | T39: =M39-(O39*$E$10)-(P39*$E$11)-(Q39*$E$12)-(R39*$E$13) -> -1.455 | V39: 32 | AC39: 1.01 | AD39: 2.1 | AE39: =AC39-$E$4-$E$14 -> 0.03 | AK39: =AE39-(AG39*$E$25)-(AH39*$E$11)-(AI39*$E$12)-(AJ39*$E$13) -> 0.03
J40: =E40-I40 -> 0 | M40: =J40-$E$4-$E$6-$E$19 -> -1.455 | T40: =M40-(O40*$E$25)-(P40*$E$11)-(Q40*$E$12)-(R40*$E$13) -> -1.455 | V40: 33 | AC40: 1.05 | AD40: 2.1 | AE40: =AC40-$E$4-$E$14 -> 0.07 | AK40: =AE40-(AG40*$E$10)-(AH40*$E$11)-(AI40*$E$12)-(AJ40*$E$13) -> 0.07
J41: =E41-I41 -> 0 | M41: =J41-$E$4-$E$6-$E$19 -> -1.455 | T41: =M41-(O41*$E$10)-(P41*$E$11)-(Q41*$E$12)-(R41*$E$13) -> -1.455 | V41: 34 | AC41: 1.51 | AD41: 2.1 | AE41: =AC41-$E$4-$E$14 -> 0.53 | AK41: =AE41-(AG41*$E$25)-(AH41*$E$11)-(AI41*$E$12)-(AJ41*$E$13) -> 0.53
J42: =E42-I42 -> 0 | M42: =J42-$E$4-$E$14 -> -0.98 | T42: =M42-(O42*$E$10)-(P42*$E$11)-(Q42*$E$12)-(R42*$E$13) -> -0.98 | V42: 35 | AC42: 1.25 | AD42: 2.1 | AE42: =AC42-$E$4-$E$14 -> 0.27 | AK42: =AE42-(AG42*$E$10)-(AH42*$E$11)-(AI42*$E$12)-(AJ42*$E$13) -> 0.27
J43: =E43-I43 -> 0 | M43: =J43-$E$4-$E$6-$E$19 -> -1.455 | T43: =M43-(O43*$E$10)-(P43*$E$11)-(Q43*$E$12)-(R43*$E$13) -> -1.455 | V43: 36 | AC43: 1.28 | AD43: 2.1 | AE43: =AC43-$E$4-$E$14 -> 0.3 | AK43: =AE43-(AG43*$E$10)-(AH43*$E$11)-(AI43*$E$12)-(AJ43*$E$13) -> 0.3
J44: =E44-I44 -> 0 | M44: =J44-$E$14-$E$4 -> -0.98 | T44: =M44-(O44*$E$25)-(P44*$E$11)-(Q44*$E$12)-(R44*$E$13) -> -0.98 | V44: 37 | AC44: 1.43 | AD44: 2.1 | AE44: =AC44-$E$4-$E$14 -> 0.45 | AK44: =AE44-(AG44*$E$10)-(AH44*$E$11)-(AI44*$E$12)-(AJ44*$E$13) -> 0.45
J45: =E45-I45 -> 0 | M45: =J45-$E$4-$E$14 -> -0.98 | T45: =M45-(O45*$E$10)-(P45*$E$11)-(Q45*$E$12)-(R45*$E$13) -> -0.98 | AC45: 1.43 | AD45: 2.1 | AE45: =AC45-$E$4-$E$14 -> 0.45 | AK45: =AE45-(AG45*$E$10)-(AH45*$E$11)-(AI45*$E$12)-(AJ45*$E$13) -> 0.45
J46: =E46-I46 -> 0 | M46: =J46-$E$4-$E$14 -> -0.98 | T46: =M46-(O46*$E$10)-(P46*$E$11)-(Q46*$E$12)-(R46*$E$13) -> -0.98 | V46: 38 | AC46: 1.38 | AD46: 2.1 | AE46: =AC46-$E$4-$E$14 -> 0.4 | AK46: =AE46-(AG46*$E$10)-(AH46*$E$11)-(AI46*$E$12)-(AJ46*$E$13) -> 0.4
J47: =E47-I47 -> 0 | M47: =J47-$E$3-$E$9 -> -0.655 | T47: =M47-(O47*$E$10)-(P47*$E$11)-(Q47*$E$12)-(R47*$E$13) -> -0.655 | V47: 39 | AC47: 1.4 | AD47: 2.1 | AE47: =AC47-0.045-$E$14 -> 0.455 | AK47: =AE47-(AG47*$E$10)-(AH47*$E$11)-(AI47*$E$12)-(AJ47*$E$13) -> 0.455
L50: provide filter basket | M50: Pit Bases | O50: 0.15 Riser | P50: 0.3 Riser | Q50: 0.6 Riser | R50: 0.9 Riser | AE50: Pits | AG50: 0.15 Riser | AH50: 0.3 Riser | AI50: 0.6 Riser | AJ50: 0.9 Riser | AW50: Pits | AX50: 0.15 Riser | AY50: 0.3 Riser | AZ50: 0.6 Riser | BA50: 0.9 Riser
AB51: 900High | AC51: 900*600 | AG51: =SUM(AG47,AG31,AG40) -> 0 | AH51: =SUM(AH47,AH31,AH40) -> 0 | AI51: =SUM(AI47,AI31,AI40) -> 0 | AJ51: =SUM(AJ47,AJ31,AJ40) -> 0 | AT51: 900High | AU51: 900*600
J52: 600*600 | N52: 600High | AC52: 1050 | AG52: =SUM(AG41:AG44,AG32:AG37,AG28) -> 0 | AH52: =SUM(AH41:AH44,AH32:AH37,AH28) -> 0 | AI52: =SUM(AI41:AI44,AI32:AI37,AI28) -> 0 | AJ52: =SUM(AJ41:AJ44,AJ32:AJ37,AJ28) -> 0 | AU52: 1050 | AW52: =COUNTA(AR28:AR29) -> 0 | AX52: =SUM(AX28:AX29) -> 0 | AY52: =SUM(AY28:AY29) -> 0 | AZ52: =SUM(AZ28:AZ29) -> 0 | BA52: =SUM(BA28:BA29) -> 0
J53: 900*600 | M53: =COUNTA(H46) -> 0 | N53: 900High | AC53: 1200 | AG53: =COUNTA(AG38:AG39,AG45) -> 0 | AH53: =COUNTA(AH38:AH39,AH45) -> 0 | AI53: =COUNTA(AI38:AI39,AI45) -> 0 | AJ53: =COUNTA(AJ38:AJ39,AJ45) -> 0 | AU53: 1200
J54: 900*900 | M54: =COUNTA(H28,H29,H36,H37,H38,H44,H45) -> 0 | N54: 900High | O54: =COUNTA(O29,O36,O38) -> 0 | P54: =COUNTA(P36) -> 0 | Q54: =COUNTA(Q29,Q37,Q38,Q44) -> 0
J55: 900x1200 | N55: 1200High
J56: 1200 DIA | M56: =COUNTA(H30,H31,H32,H39,H40,H41) -> 0 | N56: 1200 High | P56: =COUNTA(P32,P39) -> 0 | Q56: =COUNTA(Q30,Q40) -> 0 | R56: =COUNTA(R31,R32,R41) -> 0
I57: 1st Order | J57: 1500 DIA | N57: 1200 High | AB57: 1st Order | AC57: 600*600 | AT57: 1st Order | AU57: 600*600
J58: 2100 | N58: 900 high | AC58: 900*600 | AU58: 900*600
J59: 2100 | N59: 600 High | AC59: 1050 | AU59: 1050
J60: 2100 | N60: 300 High
O63: 0.2R 1.2*1.2
M65: Pit Bases | O65: 0.15 Riser | P65: 0.3 Riser | Q65: 0.6 Riser | R65: 0.9 Riser
I66: TOTAL | J66: 900*600 | N66: 600High
J67: 900*600 | N67: 900High | O67: 0 | P67: 0 | Q67: 0 | R67: 0
J68: 1050Dia | O68: 0 | P68: 0 | Q68: =Q55+AI52+AZ52 -> 0 | R68: =R55+AJ52+BA52 -> 0
J69: 1200Dia | O69: 0 | P69: 0 | Q69: =Q56+AI53+AZ53 -> 0 | R69: =R56+AJ53+BA53 -> 0
J72: 1200 Pit | K72: In lieu of 1050&1200Ch | N72: 1200High
M76: Grates/Covers
I77: TOTAL | J77: 600x600 | M77: heel safe grate cover | O77: CL D, Hinged, Galv, Bolt Down.
J78: 600X600 | M78: Grate &Frame | O78: CL D, Cast Iron
J79: 600x900 | M79: heel safe grate cover | O79: CL D, Hinged, Galv, Bolt Down.
J80: 600x900 | M80: Grate &Frame | O80: CL D, Hinged, Galv, Bolt Down.
J81: 900X900 | L81: =COUNTA(G28,G29,G30,G31,G32,G33,G38,G39,G40,G41,G43,G45) -> 0 | M81: Grate &Frame | O81: CL D, Hinged, Galv, Bolt Down.
J82: 900X900 | L82: =COUNTA(G36,G37,G44) -> 0 | M82: heel safe grate cover | O82: CL D, Cast Iron
J83: 1200 aspro 9x9 | L83: =COUNTA(H30,H31,H32,H39,H40,H41) -> 0 | M83: Aspro | O83: 150Thick, 900*900 Opening
J84: 1500 aspro 9x9 | L84: =COUNTA(H33,H43) -> 0 | M84: Aspro | O84: 150Thick, 900*900 Opening
J85: 1200*1200 | M85: Grate & Frame | O85: CL D, Hinged, Galv, Bolt Down.
J86: atlan filter 900x900 | L86: =COUNTA(H28,H29,H30,H31,H33,H36,H37,H38,H40,H41,H43,H44) -> 0
M87: 2.4m lintel | O87: 3.6m SAG centre inlet, Kerb in line
M88: concrete head wall to suit 1050 pipe
M91: Head Wall | O91: Precast - 450RCP Inlet
M94: Pit Bases | O94: 0.15 Riser | P94: 0.3 Riser | Q94: 0.6 Riser | R94: 0.9 Riser
I95: 1st PIT Order | J95: 600*600 | N95: 600High
J96: 900*900 | N96: 900High
J97: 900*600 | N97: 600High
J98: 900*600 | N98: 900High
J99: 1050 | N99: 0High
M101: Grates/Covers
I102: 1St GRATE Order | J102: 600*600 | M102: Grate & Frame | O102: CL D, Galv, Bolt Down.
J103: 600*600 | M103: Grate & Frame | O103: CL B, Galv, Bolt Down.
J104: 600*600 | M104: Cover & Frm - INFILL | O104: CL B, Galv, Bolt Down.
J105: 600*600 | M105: V-Grate w/conc surround | O105: CL B, Galv
J106: 900*600 | M106: Grate & Frame | O106: CL D, Galv, Bolt Down.
J107: 900*600 | M107: Grate & Frame | O107: CL D, Galv, Bolt Down - HEEL GUARD
J108: 900*900 | M108: Grate & Frame | O108: CL D, Galv, Bolt Down - HEEL GUARD
J109: 1050*6*9 | M109: Aspro | O109: 150Thick, 900*600 Opening
M112: Grates/Covers
I113: 2nd GRATE Order | J113: 600*600 | M113: Grate & Frame | O113: CL D, Galv, Bolt Down.
J114: 600*600 | M114: Grate & Frame | O114: CL B, Galv, Bolt Down.
J115: 600*600 | M115: Cover & Frm - INFILL | O115: CL B, Galv, Bolt Down.
J116: 600*600 | M116: V-Grate w/conc surround | O116: CL B, Galv
J117: 900*600 | M117: Grate & Frame | O117: CL D, Galv, Bolt Down.
J118: 900*600 | M118: Grate & Frame | O118: CL D, Galv, Bolt Down - HEEL GUARD
J119: 900*900 | M119: Grate & Frame | O119: CL D, Galv, Bolt Down - HEEL GUARD
J120: 1050*6*9 | M120: Aspro | O120: 150Thick, 900*600 Opening

Sheet SW_insitu Takeoff
B2: PIT/MANHOLE TAKEOFF
A3: DESCRIPTION | B3: Design Depth | C3: Grate/Finish | D3: Aspro | E3: Total Chamber Height | F3: Chamber Concrete volume/m3 | G3: Base Concrete volume/m3 | H3: Total Concrete volume/m3 | J3: Dia | K3: Area of circle
A4: 1500 DIA | H4: =F4+G4 -> 0 | J4: 1.5 | K4: =PI()*(J4/2)^2 -> 1.7671459 | L4: m2
J5: 1.95 | K5: =PI()*(J5/2)^2 -> 2.9864765 | L5: m2
K6: =PI()*(J6/2)^2 -> 0 | L6: m2
K7: =PI()*(J7/2)^2 -> 0 | L7: m2
J10: 32 | K10: MPA | L10: 290 | M10: $/m3
L24: =H24-G24 -> 0
H27: =SUM(H4:H16) -> 0 | I27: m3 | J27: =H27*L10 -> 0

Sheet Staff Rates
B1: Project:
B2: Tricore -
B3: Stage 1 Version 1
A4: Item
B6: BASED ON:
B7: 6 - Day Week, 10Hr Day | F7: 2023 Staff Cost increase | G7: Project total cost | H7: Difference
B8: Working Days/Month | C8: 24 | F8: Current
B9: No-Work Days/Month | C9: 4 | F9: 0.025 | G9: =G8+(G8*F9) -> 0 | H9: =G9-G8 -> 0
B10: Avrg Hours / Day | C10: 8.75 | F10: 0.05 | G10: =G9+(G9*F10) -> 0 | H10: =G10-$G$8 -> 0
B11: Avrg Days / Week | C11: 6 | F11: 0.075 | G11: =G10+(G10*F11) -> 0 | H11: =G11-$G$8 -> 0
B12: Avrg Hours / Month | C12: =C10*C8 -> 210 | F12: 0.1 | G12: =G11+(G11*F12) -> 0 | H12: =G12-$G$8 -> 0
B14: STAFF | G14: Hourly Rate + 2.5% | H14: Hourly Rate + 5% | I14: Hourly Rate + 7.5% | J14: Hourly Rate + 10%
C15: Unit | D15: REQ | E15: Cost ex GST | F15: Total ex GST
B16: TRADESMAN_LEADING HAND | C16: HR | D16: 1 | E16: 94 | F16: =D16*E16 -> 94 | G16: =E16+(F16*$F$9) -> 96.35 | H16: =E16+(E16*$F$10) -> 98.7 | I16: =E16+(E16*$F$11) -> 101.05 | J16: =E16+(E16*$F$12) -> 103.4
C17: DAY | D17: 1 | E17: =E16*$C$10 -> 822.5 | F17: =D17*E17 -> 822.5 | G17: =G16*$C$10 -> 843.0625 | H17: =H16*$C$10 -> 863.625 | I17: =I16*$C$10 -> 884.1875 | J17: =J16*$C$10 -> 904.75
B18: =B16 -> TRADESMAN_LEADING HAND | C18: WEEK | D18: 1 | E18: =E17*$C$11 -> 4935 | F18: =D18*E18 -> 4935 | G18: =G17*$C$11 -> 5058.375 | H18: =H17*$C$11 -> 5181.75 | I18: =I17*$C$11 -> 5305.125 | J18: =J17*$C$11 -> 5428.5
C19: MONTH | D19: 1 | E19: =E17*$C$8 -> 19740 | F19: =D19*E19 -> 19740 | G19: =G17*$C$8 -> 20233.5 | H19: =H17*$C$8 -> 20727 | I19: =I17*$C$8 -> 21220.5 | J19: =J17*$C$8 -> 21714
B21: QTY Staff in Crew | C21: =COUNTA(B18,B19,B20) -> 1
B23: Crew #1 | C23: HR | D23: 1 | E23: =E44*2+E51 -> 246 | F23: =D23*E23 -> 246 | G23: =E23+(F23*$F$9) -> 252.15 | H23: =E23+(E23*$F$10) -> 258.3 | I23: =E23+(E23*$F$11) -> 264.45 | J23: =E23+(E23*$F$12) -> 270.6
C24: DAY | D24: 1 | E24: =E23*$C$10 -> 2152.5 | F24: =D24*E24 -> 2152.5 | G24: =G23*$C$10 -> 2206.3125 | H24: =H23*$C$10 -> 2260.125 | I24: =I23*$C$10 -> 2313.9375 | J24: =J23*$C$10 -> 2367.75
B25: =B44 -> TRADESMAN_PLUMBER_OPERATOR | C25: WEEK | D25: 1 | E25: =E24*$C$11 -> 12915 | F25: =D25*E25 -> 12915 | G25: =G24*$C$11 -> 13237.875 | H25: =H24*$C$11 -> 13560.75 | I25: =I24*$C$11 -> 13883.625 | J25: =J24*$C$11 -> 14206.5
B26: =B44 -> TRADESMAN_PLUMBER_OPERATOR | C26: MONTH | D26: 1 | E26: =E24*$C$8 -> 51660 | F26: =D26*E26 -> 51660 | G26: =G24*$C$8 -> 52951.5 | H26: =H24*$C$8 -> 54243 | I26: =I24*$C$8 -> 55534.5 | J26: =J24*$C$8 -> 56826
B27: =B51 -> T/A & Apprentice
B28: QTY Staff in Crew | C28: =COUNTA(B25,B26,B27) -> 3
B30: Crew #2 | C30: HR | D30: 1 | E30: =E44*2+E51 -> 246 | F30: =D30*E30 -> 246 | G30: =E30+(F30*$F$9) -> 252.15 | H30: =E30+(E30*$F$10) -> 258.3 | I30: =E30+(E30*$F$11) -> 264.45 | J30: =E30+(E30*$F$12) -> 270.6
C31: DAY | D31: 1 | E31: =E30*$C$10 -> 2152.5 | F31: =D31*E31 -> 2152.5 | G31: =G30*$C$10 -> 2206.3125 | H31: =H30*$C$10 -> 2260.125 | I31: =I30*$C$10 -> 2313.9375 | J31: =J30*$C$10 -> 2367.75
B32: =B44 -> TRADESMAN_PLUMBER_OPERATOR | C32: WEEK | D32: 1 | E32: =E31*$C$11 -> 12915 | F32: =D32*E32 -> 12915 | G32: =G31*$C$11 -> 13237.875 | H32: =H31*$C$11 -> 13560.75 | I32: =I31*$C$11 -> 13883.625 | J32: =J31*$C$11 -> 14206.5
B33: =B44 -> TRADESMAN_PLUMBER_OPERATOR | C33: MONTH | D33: 1 | E33: =E31*$C$8 -> 51660 | F33: =D33*E33 -> 51660 | G33: =G31*$C$8 -> 52951.5 | H33: =H31*$C$8 -> 54243 | I33: =I31*$C$8 -> 55534.5 | J33: =J31*$C$8 -> 56826
B34: =B51 -> T/A & Apprentice
B35: QTY Staff in Crew | C35: =COUNTA(B32,B33,B34) -> 3
B37: Crew #3 | C37: HR | D37: 1 | E37: =E44*2+E51 -> 246 | F37: =D37*E37 -> 246 | G37: =E37+(F37*$F$9) -> 252.15 | H37: =E37+(E37*$F$10) -> 258.3 | I37: =E37+(E37*$F$11) -> 264.45 | J37: =E37+(E37*$F$12) -> 270.6
C38: DAY | D38: 1 | E38: =E37*$C$10 -> 2152.5 | F38: =D38*E38 -> 2152.5 | G38: =G37*$C$10 -> 2206.3125 | H38: =H37*$C$10 -> 2260.125 | I38: =I37*$C$10 -> 2313.9375 | J38: =J37*$C$10 -> 2367.75
B39: =B44 -> TRADESMAN_PLUMBER_OPERATOR | C39: WEEK | D39: 1 | E39: =E38*$C$11 -> 12915 | F39: =D39*E39 -> 12915 | G39: =G38*$C$11 -> 13237.875 | H39: =H38*$C$11 -> 13560.75 | I39: =I38*$C$11 -> 13883.625 | J39: =J38*$C$11 -> 14206.5
B40: =B44 -> TRADESMAN_PLUMBER_OPERATOR | C40: MONTH | D40: 1 | E40: =E38*$C$8 -> 51660 | F40: =D40*E40 -> 51660 | G40: =G38*$C$8 -> 52951.5 | H40: =H38*$C$8 -> 54243 | I40: =I38*$C$8 -> 55534.5 | J40: =J38*$C$8 -> 56826
B41: =B51 -> T/A & Apprentice
B42: QTY Staff in Crew | C42: =COUNTA(B39,B40,B41) -> 3
B44: TRADESMAN_PLUMBER_OPERATOR | C44: HR | D44: 1 | E44: 88 | F44: =D44*E44 -> 88 | G44: =E44+(F44*$F$9) -> 90.2 | H44: =E44+(E44*$F$10) -> 92.4 | I44: =E44+(E44*$F$11) -> 94.6 | J44: =E44+(E44*$F$12) -> 96.8
C45: DAY | D45: 1 | E45: =E44*$C$10 -> 770 | F45: =D45*E45 -> 770 | G45: =G44*$C$10 -> 789.25 | H45: =H44*$C$10 -> 808.5 | I45: =I44*$C$10 -> 827.75 | J45: =J44*$C$10 -> 847
B46: =B44 -> TRADESMAN_PLUMBER_OPERATOR | C46: WEEK | D46: 1 | E46: =E45*$C$11 -> 4620 | F46: =D46*E46 -> 4620 | G46: =G45*$C$11 -> 4735.5 | H46: =H45*$C$11 -> 4851 | I46: =I45*$C$11 -> 4966.5 | J46: =J45*$C$11 -> 5082
C47: MONTH | D47: 1 | E47: =E45*$C$8 -> 18480 | F47: =D47*E47 -> 18480 | G47: =G45*$C$8 -> 18942 | H47: =H45*$C$8 -> 19404 | I47: =I45*$C$8 -> 19866 | J47: =J45*$C$8 -> 20328
B49: QTY Staff in Crew | C49: =COUNTA(B46,B47,B48) -> 1
B51: T/A & Apprentice | C51: HR | D51: 1 | E51: 70 | F51: =D51*E51 -> 70 | G51: =E51+(F51*$F$9) -> 71.75 | H51: =E51+(E51*$F$10) -> 73.5 | I51: =E51+(E51*$F$11) -> 75.25 | J51: =E51+(E51*$F$12) -> 77
C52: DAY | D52: 1 | E52: =E51*$C$10 -> 612.5 | F52: =D52*E52 -> 612.5 | G52: =G51*$C$10 -> 627.8125 | H52: =H51*$C$10 -> 643.125 | I52: =I51*$C$10 -> 658.4375 | J52: =J51*$C$10 -> 673.75
B53: =B51 -> T/A & Apprentice | C53: WEEK | D53: 1 | E53: =E52*$C$11 -> 3675 | F53: =D53*E53 -> 3675 | G53: =G52*$C$11 -> 3766.875 | H53: =H52*$C$11 -> 3858.75 | I53: =I52*$C$11 -> 3950.625 | J53: =J52*$C$11 -> 4042.5
C54: MONTH | D54: 1 | E54: =E52*$C$8 -> 14700 | F54: =D54*E54 -> 14700 | G54: =G52*$C$8 -> 15067.5 | H54: =H52*$C$8 -> 15435 | I54: =I52*$C$8 -> 15802.5 | J54: =J52*$C$8 -> 16170
B56: QTY Staff in Crew | C56: =COUNTA(B53,B54,B55) -> 1

Sheet Equip&HIRE
D2: TCS PROJECT USE | G2: CAT Rental (ROK) | J2: COATES (ROK) | M2: ONSITE
A3: DESCRIPTION | B3: QTY | D3: WEEKLY (5 day) | E3: COMMENTS | G3: WEEKLY (5 day) | H3: COMMENTS | J3: WEEKLY (5 day) | K3: COMMENTS | M3: DAILY | N3: WEEKLY (5 day) | O3: COMMENTS
A4: Skid Steer Loader_Tracked | B4: 0 | D4: 0 | G4: 0 | J4: 0 | M4: 0 | N4: 262
A5: Skid Steer Loader_Wheeled | B5: 0 | D5: 300 | E5: =B5*D5 -> 0 | G5: 250 | J5: 192 | M5: 0 | N5: 0
A7: 4.5-6Ton_Excavator | B7: 0 | D7: 200 | G7: 0 | J7: 0 | M7: 0 | N7: 0
A8: 8Ton_Excavator | B8: 0 | D8: 250 | E8: =B8*D8 -> 0 | G8: 0 | J8: 0 | M8: 0 | N8: 0
A9: 10-12Ton_Excavator | B9: 0 | D9: 310 | E9: =B9*D9 -> 0 | G9: 310 | H9: 13T | J9: 301 | K9: 12T | M9: 0 | N9: 300 | O9: 13T
A10: 14-16Ton_Excavator | B10: 0 | D10: 440 | E10: =B10*D10 -> 0 | G10: 370 | H10: 17T | J10: 375 | K10: 14T | M10: 0 | N10: 295 | O10: 14T
A11: 20-24Ton_Excavator | B11: 0 | D11: 450 | E11: =B11*D11 -> 0 | G11: 480 | H11: 25T | J11: 417 | K11: 20T | M11: 0 | N11: 444 | O11: 20T
A13: Ripper_10-12T | B13: 0 | D13: 26 | G13: 0 | J13: 25.7 | M13: 0 | N13: 0
A14: Ripper_14-16T | B14: 0 | D14: 26 | G14: 0 | J14: 25.7 | M14: 0 | N14: 21
A15: Ripper_20-24T | B15: 0 | D15: 30 | G15: 0 | J15: 30.1 | M15: 0 | N15: 23
A16: Breaker_10-12T | B16: 0 | D16: 0 | G16: 0 | J16: 0 | M16: 0 | N16: 0
A17: Auger Drive_10-12T | B17: 0 | D17: 115 | E17: =B17*D17 -> 0 | G17: 0 | J17: 0 | M17: 0 | N17: 0
A18: 300Dia Auger Drill | B18: 0 | D18: 50 | G18: 0 | J18: 0 | M18: 0 | N18: 0
A20: 2-4T_Tipper Truck | B20: 0 | D20: 180 | E20: =B20*D20 -> 0 | G20: 0 | J20: 180 | K20: 2-3T | M20: 0 | N20: 130 | O20: 2-3T
A21: 6-12T_Tipper Truck | B21: 0 | D21: 400 | E21: =B21*D21 -> 0 | G21: 0 | J21: 238 | K21: 6T | M21: 0 | N21: 0
A23: <10T_Articulated Site Tipper | B23: 0 | D23: 341 | E23: =B23*D23 -> 0 | G23: 0 | J23: 243 | K23: 9T | M23: 0 | N23: 0
A24: Upright Rammer_Wacker | B24: 0 | D24: 50 | E24: =B24*D24 -> 0 | G24: 0 | J24: 48 | M24: 0 | N24: 46
A25: Trench Roller_Dbl Drum_Remote | B25: 0 | D25: 180 | E25: =B25*D25 -> 0 | G25: 0 | J25: 121 | M25: 0 | N25: 98 | O25: Rller - padfot?
A26: <26Ft_Scissor Lift - Diesel | B26: 0 | D26: 150 | E26: =B26*D26 -> 0 | G26: 0 | J26: 89 | M26: 0 | N26: 112
A27: <26Ft_Scissor Lift - Elec | B27: 0 | D27: 0 | E27: =B27*D27 -> 0 | G27: 0 | J27: 0 | M27: 0 | N27: 0
A28: <34Ft_Boom Lift - Diesel | B28: 0 | D28: 150 | E28: =B28*D28 -> 0 | G28: 0 | J28: 96 | M28: 0 | N28: 140
A29: <34Ft_Boom Lift - Elec | B29: 0 | D29: 0 | E29: =B29*D29 -> 0 | G29: 0 | J29: 0 | M29: 0 | N29: 0
A31: Porta Loo_No Tank | B31: 0 | D31: 5 | E31: =B31*D31 -> 0 | G31: 0 | J31: 5 | M31: 0 | N31: 7.5
A32: 3.6*3m Demantable Office | B32: 0 | D32: 0 | E32: =B32*D32 -> 0 | G32: 0 | J32: 15 | K32: 42D Min. | M32: 0 | N32: 13
A33: 20Ft Shipping Container | B33: 0 | D33: 5 | E33: =B33*D33 -> 0 | G33: 0 | J33: 4 | K33: 42D Min. | M33: 0 | N33: 0
A34: Quick Cut Demo Saw | B34: 0 | D34: 0 | E34: =B34*D34 -> 0 | G34: 0 | J34: 100 | M34: 0 | N34: 50
A35: Sngl Ph_6KVA Genset | B35: 0 | D35: 50 | E35: =B35*D35 -> 0 | G35: 0 | J35: 45 | M35: 0 | N35: 35
A36: Diesel Air Compressor_Trailer | B36: 0 | D36: 0 | E36: =B36*D36 -> 0 | G36: 0 | J36: 73 | M36: 0 | N36: 68
A37: Air Breaker - Heavy | B37: 0 | D37: 0 | E37: =B37*D37 -> 0 | G37: 0 | J37: 34 | M37: 0 | N37: 0
A38: Air Hose <10m | B38: 0 | D38: 0 | E38: =B38*D38 -> 0 | G38: 0 | J38: 9 | M38: 0 | N38: 1.2
A39: Elec Breaker/Jachammer | B39: 0 | D39: 0 | E39: =B39*D39 -> 0 | G39: 0 | J39: 45 | M39: 0 | N39: 0
A40: Flexdrive Motor Unit | B40: 0 | D40: 0 | E40: =B40*D40 -> 0 | G40: 0 | J40: 25 | M40: 0 | N40: 27
A41: Flexdrive_Pump Shaft | B41: 0 | D41: 0 | E41: =B41*D41 -> 0 | G41: 0 | J41: 30 | M41: 0 | N41: 22
A42: Temporary Power Board | B42: 0 | D42: 25 | E42: =B42*D42 -> 0 | G42: 0 | J42: 30 | M42: 0 | N42: 17
A44: Dual CabUte | B44: 0 | D44: 125 | E44: =B44*D44 -> 0 | G44: 0 | J44: 0 | M44: 0 | N44: 0
A45: 10m3_Skip Bin | B45: 0 | D45: 40 | E45: =B45*D45 -> 0 | G45: 0 | J45: 0 | M45: 0 | N45: 0
A46: Vac Truck / HR | B46: 0 | D46: 200 | E46: =B46*D46 -> 0 | G46: 0 | J46: 0 | M46: 0 | N46: 0
B47: 0 | D47: 0 | G47: 0 | J47: 0 | M47: 0 | N47: 0
B48: 0 | D48: 0 | G48: 0 | J48: 0 | M48: 0 | N48: 0
A50: TRANSPORT_Ex BRIS - Return | B50: 0 | D50: 0 | G50: 0 | J50: 0 | M50: 0 | N50: 0
A51: TRANSPORT_Ex ROK - Return | B51: 0 | D51: 0 | G51: 0 | J51: 480 | K51: 22T | M51: 0 | N51: 0 | O51: 0
